Workbook

Sheet Dashboard
A1: SOFI - Hybrid Sum-of-the-Parts | Dashboard
A2: Segment contribution profit ($M, FY2025) x EV/CP multiple
A3: Lending - contribution profit ($M) | B3: 1016.9
A4: Financial Services - contribution profit ($M) | B4: 792.9
A5: Technology Platform - contribution profit ($M) | B5: 144.4
A6: Lending - EV/CP multiple | B6: 6.5
A7: Financial Services - EV/CP multiple | B7: 13
A8: Technology Platform - EV/CP multiple | B8: 14
A9: Corporate overhead Y0 ($M/yr) | B9: 1000
A10: Corporate growth (vs faster segments) | B10: 0.02
A11: Corporate DCF horizon (yrs) | B11: 10
A12: Corporate terminal multiple | B12: 2
A13: Cost of equity Ke (discount rate) | B13: 0.133
A14: Net corporate debt ($M) | B14: 0
... A16: Current price ($) | B16: 15.71
A18: OUTPUT
A19: SOTP equity value ($M) | B19: =Valuation!$B$9
A20: Value per share ($) | B20: =Valuation!$B$10
A21: Upside vs price | B21: =Valuation!$B$11
A22: Implied blended EV/CP | B22: =Valuation!$B$12

Sheet Segments
A1: SOFI - Segments (FY2025 actual, $M)
A2: Segment | B2: Net revenue | C2: Contribution profit | D2: CP margin
A3: Lending | B3: 1848.9 | C3: 1016.9 | D3: 0.5500027
A4: Financial Services | B4: 1542 | C4: 792.9 | D4: 0.51420233
A5: Technology Platform (Galileo) | B5: 450.2 | C5: 144.4 | D5: 0.32074633
A6: Reportable segments total | C6: 1954.2
A8: RECONCILIATION + DRIVERS (reference)
A9: Corporate/Other net revenue ($M) | B9: -227.8
A10: Adjusted EBITDA ($M, FY2025) | B10: 1050
A11: GAAP income before taxes ($M) | B11: 525.9
A12: Implied corporate/unallocated drag ($M) | B12: 1428.3
A13: Total deposits ($B, YE2025) | B13: 37.5
A14: Total members (M, YE2025) | B14: 13.7
A15: SoFi Invest AUM ($B) | B15: 3.4

Sheet Corporate
A1: SOFI - Corporate overhead (tapering DCF, $M)
A2: Corporate grows slower than the segments (operating leverage).
B4: Year | C4: 1 | D4: 2 | E4: 3 | F4: 4 | G4: 5 | H4: 6 | I4: 7 | J4: 8 | K4: 9 | L4: 10
B5: Corporate cost | C5: =Dashboard!$B$9*(1+Dashboard!$B$10)^C4 | D5: =Dashboard!$B$9*(1+Dashboard!$B$10)^D4 | E5: =Dashboard!$B$9*(1+Dashboard!$B$10)^E4 | F5: =Dashboard!$B$9*(1+Dashboard!$B$10)^F4 | G5: =Dashboard!$B$9*(1+Dashboard!$B$10)^G4 | H5: =Dashboard!$B$9*(1+Dashboard!$B$10)^H4 | I5: =Dashboard!$B$9*(1+Dashboard!$B$10)^I4 | J5: =Dashboard!$B$9*(1+Dashboard!$B$10)^J4 | ... L5: =Dashboard!$B$9*(1+Dashboard!$B$10)^L4
B6: Discount factor | C6: =1/(1+Dashboard!$B$13)^C4 | D6: =1/(1+Dashboard!$B$13)^D4 | E6: =1/(1+Dashboard!$B$13)^E4 | F6: =1/(1+Dashboard!$B$13)^F4 | G6: =1/(1+Dashboard!$B$13)^G4 | H6: =1/(1+Dashboard!$B$13)^H4 | I6: =1/(1+Dashboard!$B$13)^I4 | J6: =1/(1+Dashboard!$B$13)^J4 | ... L6: =1/(1+Dashboard!$B$13)^L4
B7: PV corporate | C7: =C5*C6 | D7: =D5*D6 | E7: =E5*E6 | F7: =F5*F6 | G7: =G5*G6 | H7: =H5*H6 | I7: =I5*I6 | J7: =J5*J6 | ... L7: =L5*L6
B9: PV corporate (yrs 1-N) | C9: =SUM(C7:L7)
B10: Terminal corporate PV | C10: =L5*Dashboard!$B$12*L6
B11: Total corporate drag | C11: =C9+C10

Sheet Valuation
A1: SOFI - Sum-of-the-Parts ($M)
A2: (1) Lending value | B2: =Dashboard!$B$3*Dashboard!$B$6
A3: (2) Financial Services value | B3: =Dashboard!$B$4*Dashboard!$B$7
A4: (3) Technology Platform value | B4: =Dashboard!$B$5*Dashboard!$B$8
A5: Segment value subtotal | B5: =B2+B3+B4
A6: (4) Corporate overhead (tapering DCF) | B6: =Corporate!C11
A7: (5) Net corporate debt | B7: =Dashboard!$B$14
A8: Total contribution profit | B8: =Dashboard!$B$3+Dashboard!$B$4+Dashboard!$B$5
A9: SOTP equity value (= subtotal - corp - debt) | B9: =B5-B6-B7
A10: Value per share ($) | B10: =B9/Dashboard!$B$15
A11: Upside vs price | B11: =B10/Dashboard!$B$16-1
A12: Implied blended EV/CP (segments) | B12: =B5/B8

Sheet Scenario
A1: Scenarios & reverse-solve
A2: Scenario | B2: Lending x | C2: FS x | D2: Tech x | E2: Value/share
A3: Bear | B3: 5 | C3: 9 | D3: 10 | E3: 5.54
A4: Base | B4: 6.5 | C4: 13 | D4: 14 | E4: 9.66
A5: Bull | B5: 9 | C5: 18 | D5: 18 | E5: 15.19
A7: REVERSE-SOLVE - what the market price implies
A8: Market equity value ($M) | B8: 20,125
A9: Model segment subtotal ($M) | B9: 18,939
A10: Implied segment value at price ($M) | B10: 26,694
A11: -> segment multiples must be higher by | B11: +41%
A12: -> implied blended EV/CP | B12: 13.7x (model 9.7x)
A13: ...or corporate must shrink faster than modeled (operating leverage)
