Workbook
Name a: #REF!
Name A283.: Daloopa!$A$587
Name EC_Pub_New: #REF!
Name EC_Pub_QTR: #REF!
Name EC_Pub_QTR_CV: #REF!
Name IQ_CH: 110000
Name IQ_CQ: 5000
Name IQ_CY: 10000
Name IQ_DAILY: 500000
Name IQ_FH: 100000
Name IQ_FQ: 500
Name IQ_FY: 1000
Name IQ_LTM: 2000
Name IQ_MONTH: 15000
Name IQ_NTM: 6000
Name IQ_WEEK: 50000
Name IQ_YTD: 3000

Sheet How to Use 
A1: Instructions
A2: Tab | B2: Details
A3: Color Code | B3: Just familiarize yourself with the color code conventions used in this file. I will maintain these color code conventions in every model.
A4: Model | B4: The most important worksheet in this file is the "Model" Worksheet.
B5: If you want to change the assumptions, just change the cells that are filled yellow. Since the rest of the cells are formula driven, they will automatically be changed.
B6: I have made a few comments here and there whenever I thought it might be helpful for subscribers
B7: Please let me know asap if you think there has been any error/mistake (conceptual or otherwise) in the model
A9: Financials | B9: All three statements are in this worksheet. Balance sheet and cash flow related assumptions are mostly on this worksheet.
A10: Valuation | B10: Just change the current stock price and choose your multiple to run your valuation estimates.
A11: Daloopa | B11: database from company filings. Feel free to sign up for this by clicking below link (not a paid promotion; I don't get paid if you do so but I do get complimentary access to it)
B12: https://daloopa.com/?utm_source=MBI&utm_medium=Organic&utm_campaign=SourceLink
A13: E-commerce data | B13: Worksheet copied from US census Bureau which was used in "Model" worksheet.

Sheet Color Code
A1: Color | B1: Meaning
A2: Black | B2: Formula driven (both historical and forecasts)
A3: Blue | B3: Hard coded numbers (Actual for Historical, estimated for forecasts)
A4: Yellow | B4: Indication that there has been explicit assumption made in these cells. Change the numbers in these cells to drive your narrative.

Sheet Model
B1: 2015 | C1: 2016 | D1: 2017 | E1: 2018 | F1: 2019 | G1: 2020 | H1: 2021 | I1: 2022 | J1: 2023 | K1: 2024 | L1: 2025 | M1: 2026 | N1: 2027 | O1: 2028 | P1: 2029 | Q1: 2030
A2: US e-commerce (Bn) | D2: 461.034 | E2: 498.363 | F2: 561.727 | G2: 798.487 | H2: 936.592 | I2: 997.477 | J2: 1087.017 | K2: 1170.03 | L2: =L6*L4 -> 1261.2506 | M2: =M6*M4 -> 1356.8914 | N2: =N6*N4 -> 1457.1356 | O2: =O6*O4 -> 1562.1732 | P2: =P6*P4 -> 1672.2016 | Q2: =Q6*Q4 -> 1787.4258
A3: Growth | E3: =E2/D2-1 -> 0.080967998 | F3: =F2/E2-1 -> 0.12714427 | G3: =G2/F2-1 -> 0.42148588 | H3: =H2/G2-1 -> 0.17295836 | I3: =I2/H2-1 -> 0.065006961 | J3: =J2/I2-1 -> 0.089766481 | K3: =K2/J2-1 -> 0.076367711 | L3: =L2/K2-1 -> 0.077964338 | ... Q3: =Q2/P2-1 -> 0.068905674
A4: US Retail Sales (Bn) | D4: 5046.021 | E4: 5161.163 | F4: 5307.334 | G4: 5467.268 | H4: 6399.684 | I4: 6916.099 | J4: 7073.37 | K4: 7264.688 | L4: =K4*(1+L5) -> 7482.6286 | M4: =L4*(1+M5) -> 7707.1075 | N4: =M4*(1+N5) -> 7938.3207 | O4: =N4*(1+O5) -> 8176.4703 | P4: =O4*(1+P5) -> 8421.7645 | Q4: =P4*(1+Q5) -> 8674.4174
A5: Growth | E5: =E4/D4-1 -> 0.022818375 | F5: =F4/E4-1 -> 0.02832133 | G5: =G4/F4-1 -> 0.030134527 | H5: =H4/G4-1 -> 0.17054514 | I5: =I4/H4-1 -> 0.080693828 | J5: =J4/I4-1 -> 0.022739842 | K5: =K4/J4-1 -> 0.027047645 | L5: 0.03 | M5: 0.03 | N5: 0.03 | O5: 0.03 | P5: 0.03 | Q5: 0.03
A6: Penetration | D6: =D2/D4 -> 0.09136585 | E6: =E2/E4 -> 0.096560213 | F6: =F2/F4 -> 0.10583977 | G6: =G2/G4 -> 0.14604863 | H6: =H2/H4 -> 0.14634973 | I6: =I2/I4 -> 0.14422538 | J6: =J2/J4 -> 0.15367738 | K6: =K2/K4 -> 0.16105716 | L6: =K6+L7/10000 -> 0.16855716 | M6: =L6+M7/10000 -> 0.17605716 | N6: =M6+N7/10000 -> 0.18355716 | O6: =N6+O7/10000 -> 0.19105716 | P6: =O6+P7/10000 -> 0.19855716 | Q6: =P6+Q7/10000 -> 0.20605716
A7: Increase | E7: =(E6-D6)*10000 -> 51.943628 | F7: =(F6-E6)*10000 -> 92.795549 | G7: =(G6-F6)*10000 -> 402.08862 | H7: =(H6-G6)*10000 -> 3.0109625 | I7: =(I6-H6)*10000 -> -21.243469 | J7: =(J6-I6)*10000 -> 94.520053 | K7: =(K6-J6)*10000 -> 73.797733 | L7: 75 | M7: 75 | N7: 75 | O7: 75 | P7: 75 | Q7: 75
A9: Online Stores | C9: =Financials!B9 -> 91431 | D9: =Financials!C9 -> 108354 | E9: =Financials!D9 -> 122987 | F9: =Financials!E9 -> 141247 | G9: =Financials!F9 -> 197346 | H9: =Financials!G9 -> 222075 | I9: =Financials!H9 -> 220004 | J9: =Financials!I9 -> 231872 | ... L9: =Financials!K9 -> 269287 | M9: =L9*(1+M11) -> 290829.96 | N9: =M9*(1+N11) -> 314096.36 | O9: =N9*(1+O11) -> 339224.07 | P9: =O9*(1+P11) -> 364665.87 | Q9: =P9*(1+Q11) -> 390192.48
A10: Growth $ | E10: =E9-D9 -> 14633 | F10: =F9-E9 -> 18260 | G10: =G9-F9 -> 56099 | H10: =H9-G9 -> 24729 | I10: =I9-H9 -> -2071 | J10: =J9-I9 -> 11868 | K10: =K9-J9 -> 15157 | L10: =L9-K9 -> 22258 | ... Q10: =Q9-P9 -> 25526.611
A11: Growth % | E11: =E9/D9-1 -> 0.13504808 | F11: =F9/E9-1 -> 0.14847098 | G11: =G9/F9-1 -> 0.3971695 | H11: =H9/G9-1 -> 0.12530783 | I11: =I9/H9-1 -> -0.0093256783 | J11: =J9/I9-1 -> 0.053944474 | K11: =K9/J9-1 -> 0.065367962 | L11: =L9/K9-1 -> 0.090102781 | M11: 0.08 | N11: 0.08 | O11: 0.08 | P11: 0.075 | Q11: 0.07
A13: 3P Seller Services | C13: =Financials!B17 -> 22993 | D13: =Financials!C17 -> 31881 | E13: =Financials!D17 -> 42745 | F13: =Financials!E17 -> 53762 | G13: =Financials!F17 -> 80461 | H13: =Financials!G17 -> 103366 | I13: =Financials!H17 -> 117716 | J13: =Financials!I17 -> 140053 | ... L13: =Financials!K17 -> 172162 | M13: =M17*M18 -> 186783.86 | N13: =N17*N18 -> 202113.47 | O13: =O17*O18 -> 218173.4 | P13: =P17*P18 -> 235520.22 | Q13: =Q17*Q18 -> 254299.08
A14: =A10 -> Growth $ | E14: =E13-D13 -> 10864 | F14: =F13-E13 -> 11017 | G14: =G13-F13 -> 26699 | H14: =H13-G13 -> 22905 | I14: =I13-H13 -> 14350 | J14: =J13-I13 -> 22337 | K14: =K13-J13 -> 16093 | L14: =L13-K13 -> 16016 | ... Q14: =Q13-P13 -> 18778.863
A15: =A11 -> Growth % | E15: =E13/D13-1 -> 0.34076723 | F15: =F13/E13-1 -> 0.25773775 | G15: =G13/F13-1 -> 0.49661471 | H15: =H13/G13-1 -> 0.28467208 | I15: =I13/H13-1 -> 0.13882708 | J15: =J13/I13-1 -> 0.1897533 | K15: =K13/J13-1 -> 0.1149065 | L15: =L13/K13-1 -> 0.10257067 | ... Q15: =Q13/P13-1 -> 0.079733547
A16: 3P mix | D16: 0.56 | E16: 0.58 | F16: =E16+1.5% -> 0.595 | G16: =F16+1.5% -> 0.61 | H16: =G16+1.5% -> 0.625 | I16: =H16+1.5% -> 0.64 | J16: =I16+1.5% -> 0.655 | K16: =J16+1.5% -> 0.67 | L16: =K16 -> 0.67 | M16: =M18/M24 -> 0.67100637 | N16: =N18/N24 -> 0.67142923 | O16: =O18/O24 -> 0.67131888 | P16: =P18/P24 -> 0.67224184 | Q16: =Q18/Q24 -> 0.67423398
A17: AMZN take rate | D17: =D13/D18 -> 0.23118073 | E17: =E13/E18 -> 0.25167925 | F17: =F13/F18 -> 0.25908021 | G17: =G13/G18 -> 0.26067049 | H17: =H13/H18 -> 0.27927322 | I17: =I13/I18 -> 0.30097294 | J17: =J13/J18 -> 0.31814266 | K17: =K13/K18 -> 0.31133078 | L17: =L13/L18 -> 0.31489158 | M17: =L17 -> 0.31489158 | N17: =M17 -> 0.31489158 | O17: =N17 -> 0.31489158 | P17: =O17 -> 0.31489158 | Q17: =P17 -> 0.31489158
A18: 3P GMV | D18: =D24-D9 -> 137905.09 | E18: =E24-E9 -> 169839.19 | F18: =F24-F9 -> 207511.02 | G18: =G24-G9 -> 308669.38 | H18: =H24-H9 -> 370125 | I18: =I24-I9 -> 391118.22 | J18: =J24-J9 -> 440220.75 | K18: =K24-K9 -> 501543.73 | ... Q18: =Q24-Q9 -> 807576.64
A20: North America revenue | D20: =Daloopa!BJ67 -> 106110 | E20: =Daloopa!BK67 -> 141366 | F20: =Daloopa!BL67 -> 170773 | G20: =Daloopa!BM67 -> 236282 | H20: =Daloopa!BN67 -> 279833 | I20: =Daloopa!BO67 -> 315880 | J20: =Daloopa!BP67 -> 352828 | K20: =Daloopa!BQ67 -> 387497 | L20: =Daloopa!BR67 -> 426305
A21: International revenue | D21: =Daloopa!BJ75 -> 54297 | E21: =Daloopa!BK75 -> 65866 | F21: =Daloopa!BL75 -> 74723 | G21: =Daloopa!BM75 -> 104412 | H21: =Daloopa!BN75 -> 127787 | I21: =Daloopa!BO75 -> 118007 | J21: =Daloopa!BP75 -> 131200 | K21: =Daloopa!BQ75 -> 142906 | L21: =Daloopa!BR75 -> 161894
A22: NA as % of AMZN ex AWS revenue | D22: =D20/(D20+D21) -> 0.6615048 | E22: =E20/(E20+E21) -> 0.68216299 | F22: =F20/(F20+F21) -> 0.69562437 | G22: =G20/(G20+G21) -> 0.69353144 | H22: =H20/(H20+H21) -> 0.68650459 | I22: =I20/(I20+I21) -> 0.72802366 | J22: =J20/(J20+J21) -> 0.7289413 | K22: =K20/(K20+K21) -> 0.73057091 | L22: =L20/(L20+L21) -> 0.72476322 | M22: =M153 -> 0.71976322 | N22: =N153 -> 0.71476322 | O22: =O153 -> 0.70976322 | P22: =P153 -> 0.70476322 | Q22: =Q153 -> 0.69976322
A24: AMZN GMV | D24: =D9/(1-D16) -> 246259.09 | E24: =E9/(1-E16) -> 292826.19 | F24: =F9/(1-F16) -> 348758.02 | G24: =G9/(1-G16) -> 506015.38 | H24: =H9/(1-H16) -> 592200 | I24: =I9/(1-I16) -> 611122.22 | J24: =J9/(1-J16) -> 672092.75 | K24: =K9/(1-K16) -> 748572.73 | L24: =L9/(1-L16) -> 816021.21 | M24: =M26/M22 -> 883998.76 | N24: =N26/N22 -> 955947.35 | O24: =O26/O22 -> 1032076.5 | P24: =P26/P22 -> 1112606.5 | Q24: =Q26/Q22 -> 1197769.1
A25: Growth | E25: =E24/D24-1 -> 0.18909799 | F25: =F24/E24-1 -> 0.19100694 | G25: =G24/F24-1 -> 0.45090679 | H25: =H24/G24-1 -> 0.17032015 | I25: =I24/H24-1 -> 0.031952418 | J25: =J24/I24-1 -> 0.099768147 | K25: =K24/J24-1 -> 0.11379378 | L25: =L24/K24-1 -> 0.090102781 | ... Q25: =Q24/P24-1 -> 0.076543298
A26: AMZN GMV (US) | D26: =D24*D22 -> 162901.57 | E26: =E24*E22 -> 199755.19 | F26: =F24*F22 -> 242604.58 | G26: =G24*G22 -> 350937.58 | H26: =H24*H22 -> 406548.02 | I26: =I24*I22 -> 444911.43 | J26: =J24*J22 -> 489916.17 | K26: =K24*K22 -> 546885.46 | L26: =L24*L22 -> 591422.16 | M26: =M28*M2*1000 -> 636269.79 | N26: =N28*N2*1000 -> 683276 | O26: =O28*O2*1000 -> 732529.94 | P26: =P28*P2*1000 -> 784124.17 | Q26: =Q28*Q2*1000 -> 838154.77
A27: Growth | E27: =E26/D26-1 -> 0.22623243 | F27: =F26/E26-1 -> 0.21450953 | G27: =G26/F26-1 -> 0.44654143 | H27: =H26/G26-1 -> 0.15846248 | I27: =I26/H26-1 -> 0.094363805 | J27: =J26/I26-1 -> 0.10115436 | K27: =K26/J26-1 -> 0.11628375 | L27: =L26/K26-1 -> 0.081436988 | ... Q27: =Q26/P26-1 -> 0.068905674
A28: AMZN US e-com market share | D28: =D26/(D2*1000) -> 0.3533396 | E28: =E26/(E2*1000) -> 0.40082267 | F28: =F26/(F2*1000) -> 0.43189055 | G28: =G26/(G2*1000) -> 0.43950318 | H28: =H26/(H2*1000) -> 0.43407163 | I28: =I26/(I2*1000) -> 0.44603679 | J28: =J26/(J2*1000) -> 0.4506978 | K28: =K26/(K2*1000) -> 0.46741148 | L28: =L26/(L2*1000) -> 0.46891724 | M28: =L28 -> 0.46891724 | N28: =M28 -> 0.46891724 | O28: =N28 -> 0.46891724 | P28: =O28 -> 0.46891724 | Q28: =P28 -> 0.46891724
A29: AMZN International GMV | D29: =D24-D26 -> 83357.521 | E29: =E24-E26 -> 93071.002 | F29: =F24-F26 -> 106153.44 | G29: =G24-G26 -> 155077.81 | H29: =H24-H26 -> 185651.98 | I29: =I24-I26 -> 166210.79 | J29: =J24-J26 -> 182176.59 | K29: =K24-K26 -> 201687.27 | ... Q29: =Q24-Q26 -> 359614.35
A30: Growth | E30: =E29/D29-1 -> 0.11652795 | F30: =F29/E29-1 -> 0.14056411 | G30: =G29/F29-1 -> 0.46088343 | H30: =H29/G29-1 -> 0.19715378 | I30: =I29/H29-1 -> -0.10471849 | J30: =J29/I29-1 -> 0.096057542 | K30: =K29/J29-1 -> 0.10709765 | L30: =L29/K29-1 -> 0.11360053 | ... Q30: =Q29/P29-1 -> 0.094775161
A32: Physical stores | C32: =Financials!B13 -> 0 | D32: =Financials!C13 -> 5798 | E32: =Financials!D13 -> 17224 | F32: =Financials!E13 -> 17192 | G32: =Financials!F13 -> 16227 | H32: =Financials!G13 -> 17075 | I32: =Financials!H13 -> 18963 | J32: =Financials!I13 -> 20030 | ... L32: =Financials!K13 -> 22561 | M32: =L32*(1+M34) -> 23914.66 | N32: =M32*(1+N34) -> 25349.54 | O32: =N32*(1+O34) -> 26870.512 | P32: =O32*(1+P34) -> 28482.743 | Q32: =P32*(1+Q34) -> 30191.707
A33: Growth $ | E33: =E32-D32 -> 11426 | F33: =F32-E32 -> -32 | G33: =G32-F32 -> -965 | H33: =H32-G32 -> 848 | I33: =I32-H32 -> 1888 | J33: =J32-I32 -> 1067 | K33: =K32-J32 -> 1185 | L33: =L32-K32 -> 1346 | ... Q33: =Q32-P32 -> 1708.9646
A34: Growth % | E34: =E32/D32-1 -> 1.9706795 | F34: =F32/E32-1 -> -0.0018578727 | G34: =G32/F32-1 -> -0.056130758 | H34: =H32/G32-1 -> 0.052258581 | I34: =I32/H32-1 -> 0.11057101 | J34: =J32/I32-1 -> 0.056267468 | K34: =K32/J32-1 -> 0.059161258 | L34: =L32/K32-1 -> 0.063445675 | M34: 0.06 | N34: 0.06 | O34: 0.06 | P34: 0.06 | Q34: 0.06
A36: Subscription services | C36: =Financials!B21 -> 6394 | D36: =Financials!C21 -> 9721 | E36: =Financials!D21 -> 14168 | F36: =Financials!E21 -> 19210 | G36: =Financials!F21 -> 25207 | H36: =Financials!G21 -> 31768 | I36: =Financials!H21 -> 35218 | J36: =Financials!I21 -> 40209 | ... L36: =Financials!K21 -> 49619 | M36: =M50+M52+M54 -> 54854.401 | N36: =N50+N52+N54 -> 59420.961 | O36: =O50+O52+O54 -> 63440.099 | P36: =P50+P52+P54 -> 67259.897 | Q36: =Q50+Q52+Q54 -> 71204.078
A37: Growth $ | E37: =E36-D36 -> 4447 | F37: =F36-E36 -> 5042 | G37: =G36-F36 -> 5997 | H37: =H36-G36 -> 6561 | I37: =I36-H36 -> 3450 | J37: =J36-I36 -> 4991 | K37: =K36-J36 -> 4165 | L37: =L36-K36 -> 5245 | ... Q37: =Q36-P36 -> 3944.1809
A38: Growth % | E38: =E36/D36-1 -> 0.45746322 | F38: =F36/E36-1 -> 0.35587239 | G38: =G36/F36-1 -> 0.31218116 | H38: =H36/G36-1 -> 0.26028484 | I38: =I36/H36-1 -> 0.10859985 | J38: =J36/I36-1 -> 0.1417173 | K38: =K36/J36-1 -> 0.10358377 | L38: =L36/K36-1 -> 0.11819985 | ... Q38: =Q36/P36-1 -> 0.0586409
A40: AMZN Prime Members (US) | D40: 92 | E40: 101 | F40: 112 | G40: 142 | H40: 172 | I40: 173 | J40: 175 | K40: 185 | L40: 195 | M40: =L40+M41 -> 203 | N40: =M40+N41 -> 209 | O40: =N40+O41 -> 213 | P40: =O40+P41 -> 217 | Q40: =P40+Q41 -> 221
A41: Increase YoY | E41: =E40-D40 -> 9 | F41: =F40-E40 -> 11 | G41: =G40-F40 -> 30 | H41: =H40-G40 -> 30 | I41: =I40-H40 -> 1 | J41: =J40-I40 -> 2 | K41: =K40-J40 -> 10 | L41: =L40-K40 -> 10 | M41: =L41-2 -> 8 | N41: =M41-2 -> 6 | O41: =N41-2 -> 4 | P41: =O41 -> 4 | Q41: =P41 -> 4
A42: AMZN Prime Members (Global) | D42: 100 | E42: 125 | F42: 150 | G42: 200 | H42: =H43+H40 -> 245 | I42: =I43+I40 -> 256 | J42: =J43+J40 -> 268 | K42: =K43+K40 -> 293 | L42: =L43+L40 -> 323 | M42: =M43+M40 -> 346 | N42: =N43+N40 -> 364 | O42: =O43+O40 -> 378 | ... Q42: =Q43+Q40 -> 406
A43: AMZN international | D43: =D42-D40 -> 8 | E43: =E42-E40 -> 24 | F43: =F42-F40 -> 38 | G43: =G42-G40 -> 58 | H43: =G43+H44 -> 73 | I43: =H43+I44 -> 83 | J43: =I43+J44 -> 93 | K43: =J43+K44 -> 108 | L43: =K43+L44 -> 128 | M43: =L43+M44 -> 143 | N43: =M43+N44 -> 155 | O43: =N43+O44 -> 165 | ... Q43: =P43+Q44 -> 185
A44: Increase YoY | E44: =E43-D43 -> 16 | F44: =F43-E43 -> 14 | G44: =G43-F43 -> 20 | H44: 15 | I44: 10 | J44: 10 | K44: 15 | L44: 20 | M44: 15 | N44: 12 | O44: 10 | P44: 10 | Q44: 10
A46: Subscription Revenue per Global Prime member | E46: =E36/AVERAGE(D42:E42) -> 125.93778 | F46: =F36/AVERAGE(E42:F42) -> 139.70909 | G46: =G36/AVERAGE(F42:G42) -> 144.04 | H46: =H36/AVERAGE(G42:H42) -> 142.77753 | I46: =I36/AVERAGE(H42:I42) -> 140.59082 | J46: =J36/AVERAGE(I42:J42) -> 153.46947 | K46: =K36/AVERAGE(J42:K42) -> 158.19608 | L46: =L36/AVERAGE(K42:L42) -> 161.10065 | ... Q46: =Q36/AVERAGE(P42:Q42) -> 178.45634
A47: Growth | F47: =F46/E46-1 -> 0.10935014 | G47: =G46/F46-1 -> 0.030999479 | H47: =H46/G46-1 -> -0.0087647314 | I47: =I46/H46-1 -> -0.015315503 | J47: =J46/I46-1 -> 0.091603758 | K47: =K46/J46-1 -> 0.030798392 | L47: =L46/K46-1 -> 0.018360575 | M47: =M46/L46-1 -> 0.017930353 | ... Q47: =Q46/P46-1 -> 0.021495606
A49: US Prime Price Per Member | D49: 99 | E49: 119 | F49: 119 | G49: 119 | H49: 119 | I49: 129 | J49: 139 | K49: 139 | L49: =K49*1.03 -> 143.17 | M49: =L49*1.03 -> 147.4651 | N49: =M49*1.03 -> 151.88905 | O49: =N49*1.03 -> 156.44572 | P49: =O49*1.03 -> 161.1391 | Q49: =P49*1.03 -> 165.97327
A50: US Prime Subscription Revenue | E50: =E49*AVERAGE(D40:E40) -> 11483.5 | F50: =F49*AVERAGE(E40:F40) -> 12673.5 | G50: =G49*AVERAGE(F40:G40) -> 15113 | H50: =H49*AVERAGE(G40:H40) -> 18683 | I50: =I49*AVERAGE(H40:I40) -> 22252.5 | J50: =J49*AVERAGE(I40:J40) -> 24186 | K50: =K49*AVERAGE(J40:K40) -> 25020 | L50: =L49*AVERAGE(K40:L40) -> 27202.3 | ... Q50: =Q49*AVERAGE(P40:Q40) -> 36348.146
A51: US non-Prime subscription revenue per member | E51: 15 | F51: 35 | G51: 45 | H51: 50 | I51: 40 | J51: 45 | K51: 45 | L51: =K51+2 -> 47 | M51: =L51+2 -> 49 | N51: =M51+2 -> 51 | O51: =N51+2 -> 53 | P51: =O51+2 -> 55 | Q51: =P51+2 -> 57
A52: US Non-Prime Subscription Revenue | E52: =E51*AVERAGE(D40:E40) -> 1447.5 | F52: =F51*AVERAGE(E40:F40) -> 3727.5 | G52: =G51*AVERAGE(F40:G40) -> 5715 | H52: =H51*AVERAGE(G40:H40) -> 7850 | I52: =I51*AVERAGE(H40:I40) -> 6900 | J52: =J51*AVERAGE(I40:J40) -> 7830 | K52: =K51*AVERAGE(J40:K40) -> 8100 | L52: =L51*AVERAGE(K40:L40) -> 8930 | ... Q52: =Q51*AVERAGE(P40:Q40) -> 12483
A54: International Prime+Misc. Revenue | E54: =E36-E50-E52 -> 1237 | F54: =F36-F50-F52 -> 2809 | G54: =G36-G50-G52 -> 4379 | H54: =H36-H50-H52 -> 5235 | I54: =I36-I50-I52 -> 6065.5 | J54: =J36-J50-J52 -> 8193 | K54: =K36-K50-K52 -> 11254 | L54: =L36-L50-L52 -> 13486.7 | M54: =M55*AVERAGE(L43:M43) -> 15757.846 | N54: =N55*AVERAGE(M43:N43) -> 17625.816 | O54: =O55*AVERAGE(N43:O43) -> 19247.051 | P54: =P55*AVERAGE(O43:P43) -> 20789.992 | Q54: =Q55*AVERAGE(P43:Q43) -> 22372.932
A55: Revenue per international member | E55: =E54/AVERAGE(D43:E43) -> 77.3125 | F55: =F54/AVERAGE(E43:F43) -> 90.612903 | G55: =G54/AVERAGE(F43:G43) -> 91.229167 | H55: =H54/AVERAGE(G43:H43) -> 79.923664 | I55: =I54/AVERAGE(H43:I43) -> 77.762821 | J55: =J54/AVERAGE(I43:J43) -> 93.102273 | K55: =K54/AVERAGE(J43:K43) -> 111.9801 | L55: =L54/AVERAGE(K43:L43) -> 114.29407 | M55: =L55+2 -> 116.29407 | N55: =M55+2 -> 118.29407 | O55: =N55+2 -> 120.29407 | P55: =O55+2 -> 122.29407 | Q55: =P55+2 -> 124.29407
A57: Advertising Services | C57: =Financials!B25 -> 2802.5 | D57: =Financials!C25 -> 4420.35 | E57: =Financials!D25 -> 9602.6 | F57: =Financials!E25 -> 13380.75 | G57: =Financials!F25 -> 20380.35 | H57: =Financials!G25 -> 31160 | I57: =Financials!H25 -> 37739 | J57: =Financials!I25 -> 46906 | ... L57: =Financials!K25 -> 68635 | M57: =M62+M67 -> 78593.036 | N57: =N62+N67 -> 88506.222 | O57: =O62+O67 -> 98704.89 | P57: =P62+P67 -> 109204.08 | Q57: =Q62+Q67 -> 120019.62
A58: Growth $ | E58: =E57-D57 -> 5182.25 | F58: =F57-E57 -> 3778.15 | G58: =G57-F57 -> 6999.6 | H58: =H57-G57 -> 10779.65 | I58: =I57-H57 -> 6579 | J58: =J57-I57 -> 9167 | K58: =K57-J57 -> 9308 | L58: =L57-K57 -> 12421 | ... Q58: =Q57-P57 -> 10815.536
A59: Growth % | E59: =E57/D57-1 -> 1.1723619 | F59: =F57/E57-1 -> 0.39345073 | G59: =G57/F57-1 -> 0.52310969 | H59: =H57/G57-1 -> 0.52892369 | I59: =I57/H57-1 -> 0.21113607 | J59: =J57/I57-1 -> 0.24290522 | K59: =K57/J57-1 -> 0.19843943 | L59: =L57/K57-1 -> 0.22095919 | ... Q59: =Q57/P57-1 -> 0.099039672
A61: Ads mix from marketplace | D61: 0.9 | E61: =D61-1% -> 0.89 | F61: =E61-1% -> 0.88 | G61: =F61-1% -> 0.87 | H61: =G61-1% -> 0.86 | I61: =H61-1% -> 0.85 | J61: =I61-1% -> 0.84 | K61: =J61-2% -> 0.82 | L61: =K61-2% -> 0.8
A62: Ad revenue from marketplace | D62: =D61*D57 -> 3978.315 | E62: =E61*E57 -> 8546.314 | F62: =F61*F57 -> 11775.06 | G62: =G61*G57 -> 17730.904 | H62: =H61*H57 -> 26797.6 | I62: =I61*I57 -> 32078.15 | J62: =J61*J57 -> 39401.04 | K62: =K61*K57 -> 46095.48 | L62: =L61*L57 -> 54908 | M62: =M63*M24 -> 60366.036 | N62: =N63*N24 -> 65279.222 | O62: =O63*O24 -> 70477.89 | P62: =P63*P24 -> 75977.082 | Q62: =Q63*Q24 -> 81792.619
A63: As % of GMV | D63: =D62/D24 -> 0.016154998 | E63: =E62/E24 -> 0.02918562 | F63: =F62/F24 -> 0.033762836 | G63: =G62/G24 -> 0.035040248 | H63: =H62/H24 -> 0.045250929 | I63: =I62/I24 -> 0.052490564 | J63: =J62/J24 -> 0.058624408 | K63: =K62/K24 -> 0.061577824 | L63: =L62/L24 -> 0.067287467 | M63: =L63+(M64/10000) -> 0.068287467 | N63: =M63+(N64/10000) -> 0.068287467 | O63: =N63+(O64/10000) -> 0.068287467 | P63: =O63+(P64/10000) -> 0.068287467 | Q63: =P63+(Q64/10000) -> 0.068287467
A64: Increase in bps | E64: =(E63-D63)*10000 -> 130.30623 | F64: =(F63-E63)*10000 -> 45.772158 | G64: =(G63-F63)*10000 -> 12.774118 | H64: =(H63-G63)*10000 -> 102.10681 | I64: =(I63-H63)*10000 -> 72.396351 | J64: =(J63-I63)*10000 -> 61.338445 | K64: =(K63-J63)*10000 -> 29.534162 | L64: =(L63-K63)*10000 -> 57.096421 | M64: 10 | N64: 0 | O64: 0 | P64: 0 | Q64: 0
A65: Revenue growth YoY | E65: =E62/D62-1 -> 1.1482246 | F65: =F62/E62-1 -> 0.37779398 | G65: =G62/F62-1 -> 0.50580163 | H65: =H62/G62-1 -> 0.51134986 | I65: =I62/H62-1 -> 0.19705309 | J65: =J62/I62-1 -> 0.2282828 | K65: =K62/J62-1 -> 0.16990516 | L65: =L62/K62-1 -> 0.1911797 | ... Q65: =Q62/P62-1 -> 0.076543298
A67: Ads from outside of marketplace | D67: =D57-D62 -> 442.035 | E67: =E57-E62 -> 1056.286 | F67: =F57-F62 -> 1605.69 | G67: =G57-G62 -> 2649.4455 | H67: =H57-H62 -> 4362.4 | I67: =I57-I62 -> 5660.85 | J67: =J57-J62 -> 7504.96 | K67: =K57-K62 -> 10118.52 | L67: =L57-L62 -> 13727 | M67: =L67+M68 -> 18227 | N67: =M67+N68 -> 23227 | O67: =N67+O68 -> 28227 | P67: =O67+P68 -> 33227 | Q67: =P67+Q68 -> 38227
A68: Growth $ | E68: =E67-D67 -> 614.251 | F68: =F67-E67 -> 549.404 | G68: =G67-F67 -> 1043.7555 | H68: =H67-G67 -> 1712.9545 | I68: =I67-H67 -> 1298.45 | J68: =J67-I67 -> 1844.11 | K68: =K67-J67 -> 2613.56 | L68: =L67-K67 -> 3608.48 | M68: 4500 | N68: 5000 | O68: 5000 | P68: 5000 | Q68: 5000
A69: Growth % | E69: =E67/D67-1 -> 1.3895981 | F69: =F67/E67-1 -> 0.52012807 | G69: =G67/F67-1 -> 0.6500355 | H69: =H67/G67-1 -> 0.64653321 | I69: =I67/H67-1 -> 0.29764579 | J69: =J67/I67-1 -> 0.32576557 | K69: =K67/J67-1 -> 0.34824436 | L69: =L67/K67-1 -> 0.35662132 | ... Q69: =Q67/P67-1 -> 0.15048003
A71: AWS | B71: =Daloopa!BH59 -> 7880 | C71: =Daloopa!BI59 -> 12219 | D71: =Daloopa!BJ59 -> 17459 | E71: =Daloopa!BK59 -> 25655 | F71: =Daloopa!BL59 -> 35026 | G71: =Daloopa!BM59 -> 45370 | H71: =Daloopa!BN59 -> 62202 | I71: =Daloopa!BO59 -> 80096 | ... L71: =Daloopa!BR59 -> 128725 | M71: =L71+M185 -> 170327.68 | N71: =M71+N185 -> 233582.53 | O71: =N71+O185 -> 291413.12 | P71: =O71+P185 -> 335125.09 | Q71: =P71+Q185 -> 376345.48
A72: Growth $ | C72: =C71-B71 -> 4339 | D72: =D71-C71 -> 5240 | E72: =E71-D71 -> 8196 | F72: =F71-E71 -> 9371 | G72: =G71-F71 -> 10344 | H72: =H71-G71 -> 16832 | I72: =I71-H71 -> 17894 | J72: =J71-I71 -> 10661 | ... Q72: =Q71-P71 -> 41220.386
A73: Growth % | C73: =C71/B71-1 -> 0.55063452 | D73: =D71/C71-1 -> 0.42884033 | E73: =E71/D71-1 -> 0.46944269 | F73: =F71/E71-1 -> 0.36526993 | G73: =G71/F71-1 -> 0.29532347 | H73: =H71/G71-1 -> 0.37099405 | I73: =I71/H71-1 -> 0.28767564 | J73: =J71/I71-1 -> 0.13310278 | ... Q73: =Q71/P71-1 -> 0.123
A74: Consensus | L74: 127700 | M74: 151100
A76: Other revenues/Other Bets | C76: =Financials!B30 -> 147.5 | D76: =Financials!C30 -> 232.65 | E76: =Financials!D30 -> 505.4 | F76: =Financials!E30 -> 704.25 | G76: =Financials!F30 -> 1072.65 | H76: =Financials!G30 -> 2176 | I76: =Financials!H30 -> 4247 | J76: =Financials!I30 -> 4958 | ... L76: =Financials!K30 -> 5935 | M76: =L76+M77 -> 6935 | N76: =M76+N77 -> 8435 | O76: =N76+O77 -> 9935 | P76: =O76+P77 -> 11435 | Q76: =P76+Q77 -> 12935
A77: Growth $ | E77: =E76-D76 -> 272.75 | F77: =F76-E76 -> 198.85 | G77: =G76-F76 -> 368.4 | H77: =H76-G76 -> 1103.35 | I77: =I76-H76 -> 2071 | J77: =J76-I76 -> 711 | K77: =K76-J76 -> 467 | L77: =L76-K76 -> 510 | M77: 1000 | N77: 1500 | O77: 1500 | P77: 1500 | Q77: 1500
A78: Growth % | E78: =E76/D76-1 -> 1.1723619 | F78: =F76/E76-1 -> 0.39345073 | G78: =G76/F76-1 -> 0.52310969 | H78: =H76/G76-1 -> 1.0286207 | I78: =I76/H76-1 -> 0.95174632 | J78: =J76/I76-1 -> 0.16741229 | K78: =K76/J76-1 -> 0.094191206 | L78: =L76/K76-1 -> 0.094009217 | ... Q78: =Q76/P76-1 -> 0.13117621
A80: Total Revenues | C80: =C71+C76+C57+C36+C32+C13+C9 -> 135987 | D80: =D71+D76+D57+D36+D32+D13+D9 -> 177866 | E80: =E71+E76+E57+E36+E32+E13+E9 -> 232887 | F80: =F71+F76+F57+F36+F32+F13+F9 -> 280522 | G80: =G71+G76+G57+G36+G32+G13+G9 -> 386064 | H80: =H71+H76+H57+H36+H32+H13+H9 -> 469822 | I80: =I71+I76+I57+I36+I32+I13+I9 -> 513983 | J80: =J71+J76+J57+J36+J32+J13+J9 -> 574785 | ... Q80: =Q71+Q76+Q57+Q36+Q32+Q13+Q9 -> 1255187.4
F81: =(F80-F71)/(E80-E71)-1 -> 0.1846433 | G81: =(G80-G71)/(F80-F71)-1 -> 0.38777821 | H81: =(H80-H71)/(G80-G71)-1 -> 0.19644021 | I81: =(I80-I71)/(H80-H71)-1 -> 0.06443992 | J81: =(J80-J71)/(I80-I71)-1 -> 0.11556235 | K81: =(K80-K71)/(J80-J71)-1 -> 0.095810573 | L81: =(L80-L71)/(K80-K71)-1 -> 0.1089662 | M81: =(M80-M71)/(L80-L71)-1 -> 0.091315893 | ... Q81: =(Q80-Q71)/(P80-P71)-1 -> 0.076263299
A82: Cost of Sales | C82: =Daloopa!BI349 -> 88265 | D82: =Daloopa!BJ349 -> 111934 | E82: =Daloopa!BK349 -> 139156 | F82: =Daloopa!BL349 -> 165536 | G82: =Daloopa!BM349 -> 233307 | H82: =Daloopa!BN349 -> 272344 | I82: =Daloopa!BO349 -> 288831 | J82: =Daloopa!BP349 -> 304739 | ... L82: =Daloopa!BR349 -> 356414 | M82: =M85+M88+M91 -> 382950.83 | N82: =N85+N88+N91 -> 410035.82 | O82: =O85+O88+O91 -> 437673.09 | P82: =P85+P88+P91 -> 465580.1 | Q82: =Q85+Q88+Q91 -> 493814.42
A83: As % of revenue ex AWS | D83: =D82/(D80-D71) -> 0.69781244 | E83: =E82/(E80-E71) -> 0.67149861 | F83: =F82/(F80-F71) -> 0.67429205 | G83: =G82/(G80-G71) -> 0.68479926 | H83: =H82/(H80-H71) -> 0.66813208 | I83: =I82/(I80-I71) -> 0.66568254 | J83: =J82/(J80-J71) -> 0.62958961 | K83: =K82/(K80-K71) -> 0.61516997 | ... Q83: =Q82/(Q80-Q71) -> 0.56189217
A85: Shipping fees | D85: =Daloopa!BJ196 -> 21720 | E85: =Daloopa!BK196 -> 27668 | F85: =Daloopa!BL196 -> 37946 | G85: =Daloopa!BM196 -> 61116 | H85: =Daloopa!BN196 -> 76673 | I85: =Daloopa!BO196 -> 83520 | J85: =Daloopa!BP196 -> 89500 | K85: =Daloopa!BQ196 -> 95800 | L85: =Daloopa!BR196 -> 102741 | M85: =M86*M24 -> 107763.71 | N85: =N86*N24 -> 112710.8 | O85: =O86*O24 -> 117558.48 | P85: =P86*P24 -> 122280.82 | Q85: =Q86*Q24 -> 126849.52
A86: As % of est. GMV | D86: =D85/D24 -> 0.08819979 | E86: =E85/E24 -> 0.094486084 | F86: =F85/F24 -> 0.10880323 | G86: =G85/G24 -> 0.12077894 | H86: =H85/H24 -> 0.12947146 | I86: =I85/I24 -> 0.13666661 | J86: =J85/J24 -> 0.13316614 | K86: =K85/K24 -> 0.12797688 | L86: =L85/L24 -> 0.12590482 | M86: =L86-0.4% -> 0.12190482 | N86: =M86-0.4% -> 0.11790482 | O86: =N86-0.4% -> 0.11390482 | P86: =O86-0.4% -> 0.10990482 | Q86: =P86-0.4% -> 0.10590482
A88: Video and music expense | D88: N/A | E88: 6700 | F88: 7800 | G88: 11000 | H88: 13000 | I88: 16600 | J88: 18900 | K88: 20400 | L88: 22400 | M88: =L88+M89 -> 24400 | N88: =M88+N89 -> 26400 | O88: =N88+O89 -> 28400 | P88: =O88+P89 -> 30400 | Q88: =P88+Q89 -> 32400
A89: Increase | F89: =F88-E88 -> 1100 | G89: =G88-F88 -> 3200 | H89: =H88-G88 -> 2000 | I89: =I88-H88 -> 3600 | J89: =J88-I88 -> 2300 | K89: =K88-J88 -> 1500 | L89: =L88-K88 -> 2000 | M89: 2000 | N89: 2000 | O89: 2000 | P89: 2000 | Q89: 2000
A91: Cost of sales, ex Shipping and Prime content | E91: =E82-E85-E88 -> 104788 | F91: =F82-F85-F88 -> 119790 | G91: =G82-G85-G88 -> 161191 | H91: =H82-H85-H88 -> 182671 | I91: =I82-I85-I88 -> 188711 | J91: =J82-J85-J88 -> 196339 | K91: =K82-K85-K88 -> 210088 | L91: =L82-L85-L88 -> 231273 | M91: =M92*(M80-M71) -> 250787.12 | N91: =N92*(N80-N71) -> 270925.02 | O91: =O92*(O80-O71) -> 291714.61 | P91: =P92*(P80-P71) -> 312899.28 | Q91: =Q92*(Q80-Q71) -> 334564.91
A92: As % of revenue ex AWS | E92: =E91/(E80-E71) -> 0.5056555 | F92: =F91/(F80-F71) -> 0.48795092 | G92: =G91/(G80-G71) -> 0.47312544 | H92: =H91/(H80-H71) -> 0.44814042 | I92: =I91/(I80-I71) -> 0.43493121 | J92: =J91/(J80-J71) -> 0.40563562 | K92: =K91/(K80-K71) -> 0.39609127 | L92: =L91/(L80-L71) -> 0.39318836 | M92: =L92-0.25% -> 0.39068836 | N92: =M92-0.25% -> 0.38818836 | O92: =N92-0.25% -> 0.38568836 | P92: =O92-0.25% -> 0.38318836 | Q92: =P92-0.25% -> 0.38068836
A94: Fulfilment | C94: =Daloopa!BI350 -> 17619 | D94: =Daloopa!BJ350 -> 25249 | E94: =Daloopa!BK350 -> 34027 | F94: =Daloopa!BL350 -> 40232 | G94: =Daloopa!BM350 -> 58517 | H94: =Daloopa!BN350 -> 75111 | I94: =Daloopa!BO350 -> 84299 | J94: =Daloopa!BP350 -> 90619 | ... L94: =Daloopa!BR350 -> 109074 | M94: =M99+M97 -> 118069.38 | N94: =N99+N97 -> 125108.61 | O94: =O99+O97 -> 132250.91 | P94: =P99+P97 -> 142260.53 | Q94: =Q99+Q97 -> 152764.86
A95: As % of GMV | D95: =D94/D24 -> 0.10253023 | E95: =E94/E24 -> 0.11620204 | F95: =F94/F24 -> 0.11535792 | G95: =G94/G24 -> 0.11564273 | H95: =H94/H24 -> 0.12683384 | I95: =I94/I24 -> 0.13794131 | J95: =J94/J24 -> 0.13483109 | K95: =K94/K24 -> 0.13159042 | ... Q95: =Q94/Q24 -> 0.12754116
A96: As % of related revenue i.e. 1P+3P | D96: =D94/(D9+D13) -> 0.18004778 | E96: =E94/(E9+E13) -> 0.2053134 | F96: =F94/(F9+F13) -> 0.20630843 | G96: =G94/(G9+G13) -> 0.21063904 | H96: =H94/(H9+H13) -> 0.23079759 | I96: =I94/(I9+I13) -> 0.2496121 | J96: =J94/(J9+J13) -> 0.24364859 | K96: =K94/(K9+K13) -> 0.24432318 | ... Q96: =Q94/(Q9+Q13) -> 0.2370316
A97: Depreciation | D97: =D160+D174 -> 4307 | E97: =E160+E174 -> 6043 | F97: =F160+F174 -> 6992 | G97: =G160+G174 -> 8636 | H97: =H160+H174 -> 12256 | I97: =I160+I174 -> 15048 | J97: =J160+J174 -> 17694 | K97: =K160+K174 -> 18747 | ... Q97: =Q160+Q174 -> 31605.681
A98: As % of revenue 1P+3P revenue | D98: =D97/(D9+D13) -> 0.030712732 | E98: =E97/(E9+E13) -> 0.036462482 | F98: =F97/(F9+F13) -> 0.035854755 | G98: =G97/(G9+G13) -> 0.03108633 | H98: =H97/(H9+H13) -> 0.037659668 | I98: =I97/(I9+I13) -> 0.044557622 | J98: =J97/(J9+J13) -> 0.047574108 | K98: =K97/(K9+K13) -> 0.046498419 | ... Q98: =Q97/(Q9+Q13) -> 0.049039713
A99: Fulfillment ex depreciation | D99: =D94-D97 -> 20942 | E99: =E94-E97 -> 27984 | F99: =F94-F97 -> 33240 | G99: =G94-G97 -> 49881 | H99: =H94-H97 -> 62855 | I99: =I94-I97 -> 69251 | J99: =J94-J97 -> 72925 | K99: =K94-K97 -> 79758 | L99: =L94-L97 -> 88664 | M99: =M100*M24 -> 93840.038 | N99: =N100*N24 -> 99087.803 | O99: =O100*O24 -> 104398.71 | P99: =P100*P24 -> 112544.64 | Q99: =Q100*Q24 -> 121159.18
A100: As % of GMV | D100: =D99/D24 -> 0.085040515 | E100: =E99/E24 -> 0.095565222 | F100: =F99/F24 -> 0.095309635 | G100: =G99/G24 -> 0.098576054 | H100: =H99/H24 -> 0.10613813 | I100: =I99/I24 -> 0.11331776 | J100: =J99/J24 -> 0.10850437 | K100: =K99/K24 -> 0.10654676 | L100: =L99/L24 -> 0.10865404 | M100: =L100-0.25% -> 0.10615404 | N100: =M100-0.25% -> 0.10365404 | O100: =N100-0.25% -> 0.10115404 | P100: =O100 -> 0.10115404 | Q100: =P100 -> 0.10115404
A102: Shipping+fulfillment as % of GMV | D102: =(D95+D86) -> 0.19073001 | E102: =(E95+E86) -> 0.21068812 | F102: =(F95+F86) -> 0.22416115 | G102: =(G95+G86) -> 0.23642167 | H102: =(H95+H86) -> 0.2563053 | I102: =(I95+I86) -> 0.27460792 | J102: =(J95+J86) -> 0.26799724 | K102: =(K95+K86) -> 0.2595673 | ... Q102: =(Q95+Q86) -> 0.23344598
A104: Sales and Marketing | C104: =Daloopa!BI351 -> 7233 | D104: =Daloopa!BJ351 -> 10069 | E104: =Daloopa!BK351 -> 13814 | F104: =Daloopa!BL351 -> 18878 | G104: =Daloopa!BM351 -> 22008 | H104: =Daloopa!BN351 -> 32551 | I104: =Daloopa!BO351 -> 42238 | J104: =Daloopa!BP351 -> 44370 | ... L104: =Daloopa!BR351 -> 47129
A105: As % of revenue | D105: =D104/D80 -> 0.056610032 | E105: =E104/E80 -> 0.059316321 | F105: =F104/F80 -> 0.06729597 | G105: =G104/G80 -> 0.057006092 | H105: =H104/H80 -> 0.069283686 | I105: =I104/I80 -> 0.082177815 | J105: =J104/J80 -> 0.077194081 | K105: =K104/K80 -> 0.068824172 | L105: =L104/L80 -> 0.065737791
A106: Return on S&M | D106: =Daloopa!BJ348 -> 1.8085212 | E106: =Daloopa!BK348 -> 2.0123787 | F106: =Daloopa!BL348 -> 1.1259138 | G106: =Daloopa!BM348 -> 1.7162395 | H106: =Daloopa!BN348 -> 1.3738748 | I106: =Daloopa!BO348 -> 0.65519201 | J106: =Daloopa!BP348 -> 1.0118098 | K106: =Daloopa!BQ348 -> 0.94802651 | L106: =Daloopa!BR348 -> 0
A108: Technology and Content | C108: =Daloopa!BI352 -> 16085 | D108: =Daloopa!BJ352 -> 22620 | E108: =Daloopa!BK352 -> 28837 | F108: =Daloopa!BL352 -> 35931 | G108: =Daloopa!BM352 -> 42740 | H108: =Daloopa!BN352 -> 56052 | I108: =Daloopa!BO352 -> 73213 | J108: =Daloopa!BP352 -> 85622 | ... L108: =Daloopa!BR352 -> 108521
A109: As % of revenue | D109: =D108/D80 -> 0.12717439 | E109: =E108/E80 -> 0.123824 | F109: =F108/F80 -> 0.12808621 | G109: =G108/G80 -> 0.11070703 | H109: =H108/H80 -> 0.11930476 | I109: =I108/I80 -> 0.14244245 | J109: =J108/J80 -> 0.14896353 | K109: =K108/K80 -> 0.13879262 | L109: =L108/L80 -> 0.1513703
A111: General and Administrative | C111: =Daloopa!BI353 -> 2432 | D111: =Daloopa!BJ353 -> 3674 | E111: =Daloopa!BK353 -> 4336 | F111: =Daloopa!BL353 -> 5203 | G111: =Daloopa!BM353 -> 6668 | H111: =Daloopa!BN353 -> 8823 | I111: =Daloopa!BO353 -> 11891 | J111: =Daloopa!BP353 -> 11816 | ... L111: =Daloopa!BR353 -> 11172
A112: As % of revenue | D112: =D111/D80 -> 0.020655999 | E112: =E111/E80 -> 0.018618472 | F112: =F111/F80 -> 0.018547565 | G112: =G111/G80 -> 0.017271748 | H112: =H111/H80 -> 0.018779453 | I112: =I111/I80 -> 0.023135006 | J112: =J111/J80 -> 0.020557252 | K112: =K111/K80 -> 0.017805219 | L112: =L111/L80 -> 0.015583242
A114: Other operating expense (income) | C114: =Daloopa!BI354 -> 167 | D114: =Daloopa!BJ354 -> 214 | E114: =Daloopa!BK354 -> 296 | F114: =Daloopa!BL354 -> 201 | G114: =Daloopa!BM354 -> -75 | H114: =Daloopa!BN354 -> 62 | I114: =Daloopa!BO354 -> 1263 | J114: =Daloopa!BP354 -> 767 | ... L114: =Daloopa!BR354 -> 4639
A116: AWS Opex | B116: =B71-B140 -> 6016 | C116: =C71-C140 -> 9110 | D116: =D71-D140 -> 13128 | E116: =E71-E140 -> 18359 | F116: =F71-F140 -> 25825 | G116: =G71-G140 -> 31839 | H116: =H71-H140 -> 43670 | I116: =I71-I140 -> 57255 | ... L116: =L71-L140 -> 83119 | M116: =M118+M120 -> 116728.58 | N116: =N118+N120 -> 166634.18 | O116: =O118+O120 -> 205917.24 | P116: =P118+P120 -> 235888.83 | Q116: =Q118+Q120 -> 252509.86
A117: As % of AWS revenue | B117: =B116/B71 -> 0.76345178 | C117: =C116/C71 -> 0.74556019 | D117: =D116/D71 -> 0.7519331 | E117: =E116/E71 -> 0.71561099 | F117: =F116/F71 -> 0.73730943 | G117: =G116/G71 -> 0.70176328 | H117: =H116/H71 -> 0.70206746 | I117: =I116/I71 -> 0.7148297 | ... Q117: =Q116/Q71 -> 0.67095229
A118: AWS depreciation | B118: =B180 -> 2576 | C118: =C180 -> 3461 | D118: =D180 -> 4524 | E118: =E180 -> 6095 | F118: =F180 -> 8158 | G118: =G180 -> 7603 | H118: =H180 -> 10653 | I118: =I180 -> 9876 | ... Q118: =Q180 -> 91029.22
A119: As % of AWS revenue | E119: =E118/E116 -> 0.33198976 | F119: =F118/F116 -> 0.31589545 | G119: =G118/G116 -> 0.23879519 | H119: =H118/H116 -> 0.24394321 | I119: =I118/I116 -> 0.17249149 | J119: =J118/J116 -> 0.18950186 | K119: =K118/K116 -> 0.19668645 | L119: =L118/L116 -> 0.25806374 | ... Q119: =Q118/Q116 -> 0.36049768
A120: AWS Opex ex depreciation | B120: =B116-B118 -> 3440 | C120: =C116-C118 -> 5649 | D120: =D116-D118 -> 8604 | E120: =E116-E118 -> 12264 | F120: =F116-F118 -> 17667 | G120: =G116-G118 -> 24236 | H120: =H116-H118 -> 33017 | I120: =I116-I118 -> 47379 | ... L120: =L116-L118 -> 61669 | M120: =M121*M71 -> 79896.552 | N120: =N121*N71 -> 107232.03 | O120: =O121*O71 -> 130866.51 | P120: =P121*P71 -> 147145.23 | Q120: =Q121*Q71 -> 161480.64
A121: As % of AWS revenue | B121: =B120/B71 -> 0.43654822 | C121: =C120/C71 -> 0.46231279 | D121: =D120/D71 -> 0.49281173 | E121: =E120/E71 -> 0.47803547 | F121: =F120/F71 -> 0.50439673 | G121: =G120/G71 -> 0.53418559 | H121: =H120/H71 -> 0.53080287 | I121: =I120/I71 -> 0.59152767 | ... L121: =L120/L71 -> 0.47907555 | M121: =L121-1% -> 0.46907555 | N121: =M121-1% -> 0.45907555 | O121: =N121-1% -> 0.44907555 | P121: =O121-1% -> 0.43907555 | Q121: =P121-1% -> 0.42907555
A123: AMZN ex AWS Opex | C123: =C104+C108+C111-C116 -> 16640 | D123: =D104+D108+D111-D116 -> 23235 | E123: =E104+E108+E111-E116 -> 28628 | F123: =F104+F108+F111-F116 -> 34187 | G123: =G104+G108+G111-G116 -> 39577 | H123: =H104+H108+H111-H116 -> 53756 | I123: =I104+I108+I111-I116 -> 70087 | J123: =J104+J108+J111-J116 -> 75682 | ... L123: =L104+L108+L111-L116 -> 83703 | M123: =M124*(M80-M71) -> 89741.637 | N123: =N124*(N80-N71) -> 95827.337 | O123: =O124*(O80-O71) -> 101958.64 | P123: =P124*(P80-P71) -> 108035.09 | Q123: =Q124*(Q80-Q71) -> 114077.1
A124: As % of AMZN ex AWS revenue | C124: =C123/(C80-C71) -> 0.13444509 | D124: =D123/(D80-D71) -> 0.14485029 | E124: =E123/(E80-E71) -> 0.13814469 | F124: =F123/(F80-F71) -> 0.13925685 | G124: =G123/(G80-G71) -> 0.11616583 | H124: =H123/(H80-H71) -> 0.13187773 | I124: =I123/(I80-I71) -> 0.16153284 | J124: =J123/(J80-J71) -> 0.15635872 | ... L124: =L123/(L80-L71) -> 0.14230388 | M124: =L124-0.25% -> 0.13980388 | N124: =M124-0.25% -> 0.13730388 | O124: =N124-0.25% -> 0.13480388 | P124: =O124-0.25% -> 0.13230388 | Q124: =P124-0.25% -> 0.12980388
A125: AMZN, ex AWS and "Other Bets" | D125: =D126*(D80-D71) -> 22456.98 | E125: =E126*(E80-E71) -> 27458.24 | F125: =F126*(F80-F71) -> 30687 | G125: =G126*(G80-G71) -> 35772.87 | H125: =H126*(H80-H71) -> 48914.4 | I125: =I126*(I80-I71) -> 56405.31 | J125: =J126*(J80-J71) -> 60503.5 | K125: =K126*(K80-K71) -> 60996.345 | ... Q125: =Q126*(Q80-Q71) -> 87884.197
A126: As % of AMZN ex AWS revenue | D126: 0.14 | E126: =D126-0.75% -> 0.1325 | F126: =E126-0.75% -> 0.125 | G126: =10.5% -> 0.105 | H126: 0.12 | I126: 0.13 | J126: 0.125 | K126: 0.115 | L126: =K126-0.25% -> 0.1125 | M126: =L126-0.25% -> 0.11 | N126: =M126-0.25% -> 0.1075 | O126: =N126-0.25% -> 0.105 | P126: =O126-0.25% -> 0.1025 | Q126: =P126-0.25% -> 0.1
A127: Implied "Other Bets" opex | D127: =D123-D125 -> 778.02 | E127: =E123-E125 -> 1169.76 | F127: =F123-F125 -> 3500 | G127: =G123-G125 -> 3804.13 | H127: =H123-H125 -> 4841.6 | I127: =I123-I125 -> 13681.69 | J127: =J123-J125 -> 15178.5 | K127: =K123-K125 -> 15091.655 | ... Q127: =Q123-Q125 -> 26192.901
...

Sheet Financials
B1: 2016 | C1: 2017 | D1: 2018 | E1: 2019 | F1: 2020 | G1: 2021 | H1: 2022 | I1: 2023 | J1: 2024 | K1: 2025 | L1: 2026 | M1: 2027 | N1: 2028 | O1: 2029 | P1: 2030
A2: Revenue | B2: =Daloopa!BI62 -> 135987 | C2: =Daloopa!BJ62 -> 177866 | D2: =Daloopa!BK62 -> 232887 | E2: =Daloopa!BL62 -> 280522 | F2: =Daloopa!BM62 -> 386064 | G2: =Daloopa!BN62 -> 469822 | H2: =Daloopa!BO62 -> 513983 | I2: =I38 -> 574785 | J2: =J38 -> 637959 | K2: =K38 -> 716924 | L2: =L38 -> 812238.6 | M2: =M38 -> 931504.08 | N2: =N38 -> 1047761.1 | O2: =O38 -> 1151692.9 | P2: =P38 -> 1255187.4
A3: Growth $ | C3: =C2-B2 -> 41879 | D3: =D2-C2 -> 55021 | E3: =E2-D2 -> 47635 | F3: =F2-E2 -> 105542 | G3: =G2-F2 -> 83758 | H3: =H2-G2 -> 44161 | I3: =I2-H2 -> 60802 | J3: =J2-I2 -> 63174 | ... P3: =P2-O2 -> 103494.54
A4: Growth % | C4: =C2/B2-1 -> 0.30796326 | D4: =D2/C2-1 -> 0.30933962 | E4: =E2/D2-1 -> 0.20454126 | F4: =F2/E2-1 -> 0.37623431 | G4: =G2/F2-1 -> 0.21695367 | H4: =H2/G2-1 -> 0.093995173 | I4: =I2/H2-1 -> 0.11829574 | J4: =J2/I2-1 -> 0.10990892 | ... P4: =P2/O2-1 -> 0.089862967
A5: Consensus (as of Feb 08, 2026) | L5: 805040 | M5: 895471 | N5: 1008977 | O5: 1103636 | P5: 1215335
A7: Segments
A9: Online Stores | B9: =Daloopa!BI54 -> 91431 | C9: =Daloopa!BJ54 -> 108354 | D9: =Daloopa!BK54 -> 122987 | E9: =Daloopa!BL54 -> 141247 | F9: =Daloopa!BM54 -> 197346 | G9: =Daloopa!BN54 -> 222075 | H9: =Daloopa!BO54 -> 220004 | I9: =Daloopa!BP54 -> 231872 | ... K9: =Daloopa!BR54 -> 269287 | L9: =Model!M9 -> 290829.96 | M9: =Model!N9 -> 314096.36 | N9: =Model!O9 -> 339224.07 | O9: =Model!P9 -> 364665.87 | P9: =Model!Q9 -> 390192.48
A10: Growth | C10: =C9-B9 -> 16923 | D10: =D9-C9 -> 14633 | E10: =E9-D9 -> 18260 | F10: =F9-E9 -> 56099 | G10: =G9-F9 -> 24729 | H10: =H9-G9 -> -2071 | I10: =I9-H9 -> 11868 | J10: =J9-I9 -> 15157 | ... P10: =P9-O9 -> 25526.611
A11: Growth % | C11: =C9/B9-1 -> 0.1850904 | D11: =D9/C9-1 -> 0.13504808 | E11: =E9/D9-1 -> 0.14847098 | F11: =F9/E9-1 -> 0.3971695 | G11: =G9/F9-1 -> 0.12530783 | H11: =H9/G9-1 -> -0.0093256783 | I11: =I9/H9-1 -> 0.053944474 | J11: =J9/I9-1 -> 0.065367962 | ... P11: =P9/O9-1 -> 0.07
A13: Physical Stores | B13: =Daloopa!BI55 -> 0 | C13: =Daloopa!BJ55 -> 5798 | D13: =Daloopa!BK55 -> 17224 | E13: =Daloopa!BL55 -> 17192 | F13: =Daloopa!BM55 -> 16227 | G13: =Daloopa!BN55 -> 17075 | H13: =Daloopa!BO55 -> 18963 | I13: =Daloopa!BP55 -> 20030 | ... K13: =Daloopa!BR55 -> 22561 | L13: =Model!M32 -> 23914.66 | M13: =Model!N32 -> 25349.54 | N13: =Model!O32 -> 26870.512 | O13: =Model!P32 -> 28482.743 | P13: =Model!Q32 -> 30191.707
A14: =A10 -> Growth | D14: =D13-C13 -> 11426 | E14: =E13-D13 -> -32 | F14: =F13-E13 -> -965 | G14: =G13-F13 -> 848 | H14: =H13-G13 -> 1888 | I14: =I13-H13 -> 1067 | J14: =J13-I13 -> 1185 | K14: =K13-J13 -> 1346 | ... P14: =P13-O13 -> 1708.9646
A15: =A11 -> Growth % | D15: =D13/C13-1 -> 1.9706795 | E15: =E13/D13-1 -> -0.0018578727 | F15: =F13/E13-1 -> -0.056130758 | G15: =G13/F13-1 -> 0.052258581 | H15: =H13/G13-1 -> 0.11057101 | I15: =I13/H13-1 -> 0.056267468 | J15: =J13/I13-1 -> 0.059161258 | K15: =K13/J13-1 -> 0.063445675 | ... P15: =P13/O13-1 -> 0.06
A17: 3P Seller Services | B17: =Daloopa!BI56 -> 22993 | C17: =Daloopa!BJ56 -> 31881 | D17: =Daloopa!BK56 -> 42745 | E17: =Daloopa!BL56 -> 53762 | F17: =Daloopa!BM56 -> 80461 | G17: =Daloopa!BN56 -> 103366 | H17: =Daloopa!BO56 -> 117716 | I17: =Daloopa!BP56 -> 140053 | ... K17: =Daloopa!BR56 -> 172162 | L17: =Model!M13 -> 186783.86 | M17: =Model!N13 -> 202113.47 | N17: =Model!O13 -> 218173.4 | O17: =Model!P13 -> 235520.22 | P17: =Model!Q13 -> 254299.08
A18: =A14 -> Growth | C18: =C17-B17 -> 8888 | D18: =D17-C17 -> 10864 | E18: =E17-D17 -> 11017 | F18: =F17-E17 -> 26699 | G18: =G17-F17 -> 22905 | H18: =H17-G17 -> 14350 | I18: =I17-H17 -> 22337 | J18: =J17-I17 -> 16093 | ... P18: =P17-O17 -> 18778.863
A19: =A15 -> Growth % | C19: =C17/B17-1 -> 0.38655243 | D19: =D17/C17-1 -> 0.34076723 | E19: =E17/D17-1 -> 0.25773775 | F19: =F17/E17-1 -> 0.49661471 | G19: =G17/F17-1 -> 0.28467208 | H19: =H17/G17-1 -> 0.13882708 | I19: =I17/H17-1 -> 0.1897533 | J19: =J17/I17-1 -> 0.1149065 | ... P19: =P17/O17-1 -> 0.079733547
A21: Subscription Services | B21: =Daloopa!BI57 -> 6394 | C21: =Daloopa!BJ57 -> 9721 | D21: =Daloopa!BK57 -> 14168 | E21: =Daloopa!BL57 -> 19210 | F21: =Daloopa!BM57 -> 25207 | G21: =Daloopa!BN57 -> 31768 | H21: =Daloopa!BO57 -> 35218 | I21: =Daloopa!BP57 -> 40209 | ... K21: =Daloopa!BR57 -> 49619 | L21: =Model!M36 -> 54854.401 | M21: =Model!N36 -> 59420.961 | N21: =Model!O36 -> 63440.099 | O21: =Model!P36 -> 67259.897 | P21: =Model!Q36 -> 71204.078
A22: =A18 -> Growth | C22: =C21-B21 -> 3327 | D22: =D21-C21 -> 4447 | E22: =E21-D21 -> 5042 | F22: =F21-E21 -> 5997 | G22: =G21-F21 -> 6561 | H22: =H21-G21 -> 3450 | I22: =I21-H21 -> 4991 | J22: =J21-I21 -> 4165 | ... P22: =P21-O21 -> 3944.1809
A23: =A19 -> Growth % | D23: =D21/C21-1 -> 0.45746322 | E23: =E21/D21-1 -> 0.35587239 | F23: =F21/E21-1 -> 0.31218116 | G23: =G21/F21-1 -> 0.26028484 | H23: =H21/G21-1 -> 0.10859985 | I23: =I21/H21-1 -> 0.1417173 | J23: =J21/I21-1 -> 0.10358377 | K23: =K21/J21-1 -> 0.11819985 | ... P23: =P21/O21-1 -> 0.0586409
A25: Advertising Services | B25: =B29*95% -> 2802.5 | C25: =C29*95% -> 4420.35 | D25: =D29*95% -> 9602.6 | E25: =E29*95% -> 13380.75 | F25: =F29*95% -> 20380.35 | G25: =Daloopa!BN58 -> 31160 | H25: =Daloopa!BO58 -> 37739 | I25: =Daloopa!BP58 -> 46906 | J25: =Daloopa!BQ58 -> 56214 | K25: =Daloopa!BR58 -> 68635 | L25: =Model!M57 -> 78593.036 | M25: =Model!N57 -> 88506.222 | N25: =Model!O57 -> 98704.89 | O25: =Model!P57 -> 109204.08 | P25: =Model!Q57 -> 120019.62
A26: =A22 -> Growth | C26: =C25-B25 -> 1617.85 | D26: =D25-C25 -> 5182.25 | E26: =E25-D25 -> 3778.15 | F26: =F25-E25 -> 6999.6 | G26: =G25-F25 -> 10779.65 | H26: =H25-G25 -> 6579 | I26: =I25-H25 -> 9167 | J26: =J25-I25 -> 9308 | ... P26: =P25-O25 -> 10815.536
A27: =A23 -> Growth % | C27: =C25/B25-1 -> 0.57728814 | D27: =D25/C25-1 -> 1.1723619 | E27: =E25/D25-1 -> 0.39345073 | F27: =F25/E25-1 -> 0.52310969 | G27: =G25/F25-1 -> 0.52892369 | H27: =H25/G25-1 -> 0.21113607 | I27: =I25/H25-1 -> 0.24290522 | J27: =J25/I25-1 -> 0.19843943 | ... P27: =P25/O25-1 -> 0.099039672
A29: Others | B29: =Daloopa!BI60 -> 2950 | C29: =Daloopa!BJ60 -> 4653 | D29: =Daloopa!BK60 -> 10108 | E29: =Daloopa!BL60 -> 14085 | F29: =Daloopa!BM60 -> 21453 | G29: =Daloopa!BN61 -> 2176 | H29: =Daloopa!BO61 -> 4247 | I29: =Daloopa!BP61 -> 4958 | J29: =Daloopa!BQ61 -> 5425 | K29: =Daloopa!BR61 -> 5935
A30: Others, excludind ads | B30: =B29-B25 -> 147.5 | C30: =C29-C25 -> 232.65 | D30: =D29-D25 -> 505.4 | E30: =E29-E25 -> 704.25 | F30: =F29-F25 -> 1072.65 | G30: =G29 -> 2176 | H30: =H29 -> 4247 | I30: =I29 -> 4958 | J30: =J29 -> 5425 | K30: =K29 -> 5935 | L30: =Model!M76 -> 6935 | M30: =Model!N76 -> 8435 | N30: =Model!O76 -> 9935 | O30: =Model!P76 -> 11435 | P30: =Model!Q76 -> 12935
A31: =A26 -> Growth | C31: =C30-B30 -> 85.15 | D31: =D30-C30 -> 272.75 | E31: =E30-D30 -> 198.85 | F31: =F30-E30 -> 368.4 | G31: =G30-F30 -> 1103.35 | H31: =H30-G30 -> 2071 | I31: =I30-H30 -> 711 | J31: =J30-I30 -> 467 | ... P31: =P30-O30 -> 1500
A32: =A27 -> Growth % | C32: =C30/B30-1 -> 0.57728814 | D32: =D30/C30-1 -> 1.1723619 | E32: =E30/D30-1 -> 0.39345073 | F32: =F30/E30-1 -> 0.52310969 | G32: =G30/F30-1 -> 1.0286207 | H32: =H30/G30-1 -> 0.95174632 | I32: =I30/H30-1 -> 0.16741229 | J32: =J30/I30-1 -> 0.094191206 | ... P32: =P30/O30-1 -> 0.13117621
A34: AWS | B34: =Daloopa!BI59 -> 12219 | C34: =Daloopa!BJ59 -> 17459 | D34: =Daloopa!BK59 -> 25655 | E34: =Daloopa!BL59 -> 35026 | F34: =Daloopa!BM59 -> 45370 | G34: =Daloopa!BN59 -> 62202 | H34: =Daloopa!BO59 -> 80096 | I34: =Daloopa!BP59 -> 90757 | ... K34: =Daloopa!BR59 -> 128725 | L34: =Model!M71 -> 170327.68 | M34: =Model!N71 -> 233582.53 | N34: =Model!O71 -> 291413.12 | O34: =Model!P71 -> 335125.09 | P34: =Model!Q71 -> 376345.48
A35: =A31 -> Growth | C35: =C34-B34 -> 5240 | D35: =D34-C34 -> 8196 | E35: =E34-D34 -> 9371 | F35: =F34-E34 -> 10344 | G35: =G34-F34 -> 16832 | H35: =H34-G34 -> 17894 | I35: =I34-H34 -> 10661 | J35: =J34-I34 -> 16799 | ... P35: =P34-O34 -> 41220.386
A36: =A32 -> Growth % | C36: =C34/B34-1 -> 0.42884033 | D36: =D34/C34-1 -> 0.46944269 | E36: =E34/D34-1 -> 0.36526993 | F36: =F34/E34-1 -> 0.29532347 | G36: =G34/F34-1 -> 0.37099405 | H36: =H34/G34-1 -> 0.28767564 | I36: =I34/H34-1 -> 0.13310278 | J36: =J34/I34-1 -> 0.18509867 | ... P36: =P34/O34-1 -> 0.123
A38: Total revenues | B38: =B34+B30+B25+B21+B17+B13+B9 -> 135987 | C38: =C34+C30+C25+C21+C17+C13+C9 -> 177866 | D38: =D34+D30+D25+D21+D17+D13+D9 -> 232887 | E38: =E34+E30+E25+E21+E17+E13+E9 -> 280522 | F38: =F34+F30+F25+F21+F17+F13+F9 -> 386064 | G38: =G34+G30+G25+G21+G17+G13+G9 -> 469822 | H38: =H34+H30+H25+H21+H17+H13+H9 -> 513983 | I38: =I34+I30+I25+I21+I17+I13+I9 -> 574785 | ... P38: =P34+P30+P25+P21+P17+P13+P9 -> 1255187.4
A39: Growth | C39: =C38-B38 -> 41879 | D39: =D38-C38 -> 55021 | E39: =E38-D38 -> 47635 | F39: =F38-E38 -> 105542 | G39: =G38-F38 -> 83758 | H39: =H38-G38 -> 44161 | I39: =I38-H38 -> 60802 | J39: =J38-I38 -> 63174 | ... P39: =P38-O38 -> 103494.54
A40: Growth % | C40: =C38/B38-1 -> 0.30796326 | D40: =D38/C38-1 -> 0.30933962 | E40: =E38/D38-1 -> 0.20454126 | F40: =F38/E38-1 -> 0.37623431 | G40: =G38/F38-1 -> 0.21695367 | H40: =H38/G38-1 -> 0.093995173 | I40: =I38/H38-1 -> 0.11829574 | J40: =J38/I38-1 -> 0.10990892 | ... P40: =P38/O38-1 -> 0.089862967
A42: Cost of Sales | C42: =Model!D82 -> 111934 | D42: =Model!E82 -> 139156 | E42: =Model!F82 -> 165536 | F42: =Model!G82 -> 233307 | G42: =Model!H82 -> 272344 | H42: =Model!I82 -> 288831 | I42: =Model!J82 -> 304739 | J42: =Model!K82 -> 326288 | ... P42: =Model!Q82 -> 493814.42
A43: As % of revenue | C43: =C42/(C2-C34) -> 0.69781244 | D43: =D42/(D2-D34) -> 0.67149861 | E43: =E42/(E2-E34) -> 0.67429205 | F43: =F42/(F2-F34) -> 0.68479926 | G43: =G42/(G2-G34) -> 0.66813208 | H43: =H42/(H2-H34) -> 0.66568254 | I43: =I42/(I2-I34) -> 0.62958961 | J43: =J42/(J2-J34) -> 0.61516997 | ... P43: =P42/(P2-P34) -> 0.56189217
A45: Fulfilment | C45: =Model!D94 -> 25249 | D45: =Model!E94 -> 34027 | E45: =Model!F94 -> 40232 | F45: =Model!G94 -> 58517 | G45: =Model!H94 -> 75111 | H45: =Model!I94 -> 84299 | I45: =Model!J94 -> 90619 | J45: =Model!K94 -> 98505 | ... P45: =Model!Q94 -> 152764.86
A46: As % of revenue | C46: =C45/C2 -> 0.14195518 | D46: =D45/D2 -> 0.14610949 | E46: =E45/E2 -> 0.14341834 | F46: =F45/F2 -> 0.15157331 | G46: =G45/G2 -> 0.15987119 | H46: =H45/H2 -> 0.16401126 | I46: =I45/I2 -> 0.15765721 | J46: =J45/J2 -> 0.15440647 | ... P46: =P45/P2 -> 0.12170681
A48: Sales & Marketing | C48: =Model!D104 -> 10069 | D48: =Model!E104 -> 13814 | E48: =Model!F104 -> 18878 | F48: =Model!G104 -> 22008 | G48: =Model!H104 -> 32551 | H48: =Model!I104 -> 42238 | I48: =Model!J104 -> 44370 | J48: =Model!K104 -> 43907 | K48: =Model!L104 -> 47129
A49: As % of revenue | C49: =C48/C2 -> 0.056610032 | D49: =D48/D2 -> 0.059316321 | E49: =E48/E2 -> 0.06729597 | F49: =F48/F2 -> 0.057006092 | G49: =G48/G2 -> 0.069283686 | H49: =H48/H2 -> 0.082177815 | I49: =I48/I2 -> 0.077194081 | J49: =J48/J2 -> 0.068824172 | K49: =K48/K2 -> 0.065737791
A51: Technology & Content | C51: =Model!D108 -> 22620 | D51: =Model!E108 -> 28837 | E51: =Model!F108 -> 35931 | F51: =Model!G108 -> 42740 | G51: =Model!H108 -> 56052 | H51: =Model!I108 -> 73213 | I51: =Model!J108 -> 85622 | J51: =Model!K108 -> 88544 | K51: =Model!L108 -> 108521
A52: As % of revenue | C52: =C51/C2 -> 0.12717439 | D52: =D51/D2 -> 0.123824 | E52: =E51/E2 -> 0.12808621 | F52: =F51/F2 -> 0.11070703 | G52: =G51/G2 -> 0.11930476 | H52: =H51/H2 -> 0.14244245 | I52: =I51/I2 -> 0.14896353 | J52: =J51/J2 -> 0.13879262 | K52: =K51/K2 -> 0.1513703
A54: General & Administrative | C54: =Model!D111 -> 3674 | D54: =Model!E111 -> 4336 | E54: =Model!F111 -> 5203 | F54: =Model!G111 -> 6668 | G54: =Model!H111 -> 8823 | H54: =Model!I111 -> 11891 | I54: =Model!J111 -> 11816 | J54: =Model!K111 -> 11359 | K54: =Model!L111 -> 11172
A55: As % of revenue | C55: =C54/C2 -> 0.020655999 | D55: =D54/D2 -> 0.018618472 | E55: =E54/E2 -> 0.018547565 | F55: =F54/F2 -> 0.017271748 | G55: =G54/G2 -> 0.018779453 | H55: =H54/H2 -> 0.023135006 | I55: =I54/I2 -> 0.020557252 | J55: =J54/J2 -> 0.017805219 | K55: =K54/K2 -> 0.015583242
A57: Other operating expense (income) | C57: =Model!D114 -> 214 | D57: =Model!E114 -> 296 | E57: =Model!F114 -> 201 | F57: =Model!G114 -> -75 | G57: =Model!H114 -> 62 | H57: =Model!I114 -> 1263 | I57: =Model!J114 -> 767 | J57: =Model!K114 -> 763 | K57: =Model!L114 -> 4639
A59: Total Opex | C59: =C45+C48+C51+C42+C54+C57 -> 173760 | D59: =D45+D48+D51+D42+D54+D57 -> 220466 | E59: =E45+E48+E51+E42+E54+E57 -> 265981 | F59: =F45+F48+F51+F42+F54+F57 -> 363165 | G59: =G45+G48+G51+G42+G54+G57 -> 444943 | H59: =H45+H48+H51+H42+H54+H57 -> 501735 | I59: =I45+I48+I51+I42+I54+I57 -> 537933 | J59: =J45+J48+J51+J42+J54+J57 -> 569366 | K59: =K45+K48+K51+K42+K54+K57 -> 636949 | L59: =Model!M116+Model!M123+Model!M94+Model!M82 -> 707490.43 | M59: =Model!N116+Model!N123+Model!N94+Model!N82 -> 797605.94 | N59: =Model!O116+Model!O123+Model!O94+Model!O82 -> 877799.87 | O59: =Model!P116+Model!P123+Model!P94+Model!P82 -> 951764.55 | P59: =Model!Q116+Model!Q123+Model!Q94+Model!Q82 -> 1013166.2
A60: Operating Income | C60: =C38-C59 -> 4106 | D60: =D38-D59 -> 12421 | E60: =E38-E59 -> 14541 | F60: =F38-F59 -> 22899 | G60: =G38-G59 -> 24879 | H60: =H38-H59 -> 12248 | I60: =I38-I59 -> 36852 | J60: =J38-J59 -> 68593 | ... P60: =P38-P59 -> 242021.2
A61: Operating margin | C61: =C60/C2 -> 0.023084794 | D61: =D60/D2 -> 0.053334879 | E61: =E60/E2 -> 0.051835507 | F61: =F60/F2 -> 0.059314 | G61: =G60/G2 -> 0.052954098 | H61: =H60/H2 -> 0.023829582 | I61: =I60/I2 -> 0.064114408 | J61: =J60/J2 -> 0.10751945 | ... P61: =P60/P2 -> 0.19281678
A62: Consensus EBIT | L62: 98334 | M62: 121403 | N62: 156321 | O62: 185889 | P62: 222680
A64: Interest income | C64: =Daloopa!BJ359 -> 202 | D64: =Daloopa!BK359 -> 440 | E64: =Daloopa!BL359 -> 832 | F64: =Daloopa!BM359 -> 555 | G64: =Daloopa!BN359 -> 448 | H64: =Daloopa!BO359 -> 989 | I64: =Daloopa!BP359 -> 2949 | J64: =Daloopa!BQ359 -> 4677 | K64: =Daloopa!BR359 -> 4381 | L64: =L65*(AVERAGE(K125:L125)+AVERAGE(K126:L126)) -> 4391.5025 | M64: =M65*(AVERAGE(L125:M125)+AVERAGE(L126:M126)) -> 4042.2356 | N64: =N65*(AVERAGE(M125:N125)+AVERAGE(M126:N126)) -> 4409.6985 | O64: =O65*(AVERAGE(N125:O125)+AVERAGE(N126:O126)) -> 4790.847 | P64: =P65*(AVERAGE(O125:P125)+AVERAGE(O126:P126)) -> 5185.5493
A65: As % of net cash and LT investments | D65: =D64/(AVERAGE(C125:D125)+AVERAGE(C126:D126)) -> 0.012182291 | E65: =E64/(AVERAGE(D125:E125)+AVERAGE(D126:E126)) -> 0.017284541 | F65: =F64/(AVERAGE(E125:F125)+AVERAGE(E126:F126)) -> 0.0079617263 | G65: =G64/(AVERAGE(F125:G125)+AVERAGE(F126:G126)) -> 0.004965502 | H65: =H64/(AVERAGE(G125:H125)+AVERAGE(G126:H126)) -> 0.011910281 | I65: =I64/(AVERAGE(H125:I125)+AVERAGE(H126:I126)) -> 0.037613357 | J65: =J64/(AVERAGE(I125:J125)+AVERAGE(I126:J126)) -> 0.049760083 | K65: =K64/(AVERAGE(J125:K125)+AVERAGE(J126:K126)) -> 0.039075775 | L65: 0.04 | M65: 0.04 | N65: 0.04 | O65: 0.04 | P65: 0.04
A67: Interest expense | C67: =Daloopa!BJ360 -> -848 | D67: =Daloopa!BK360 -> -1417 | E67: =Daloopa!BL360 -> -1600 | F67: =Daloopa!BM360 -> -1647 | G67: =Daloopa!BN360 -> -1809 | H67: =Daloopa!BO360 -> -2367 | I67: =Daloopa!BP360 -> -3182 | J67: =Daloopa!BQ360 -> -2406 | K67: =Daloopa!BR360 -> -2274 | L67: =-L68*(AVERAGE(K155:L155)+AVERAGE(K158:L158)) -> -2861.3259 | M67: =-M68*(AVERAGE(L155:M155)+AVERAGE(L158:M158)) -> -3418.6417 | N67: =-N68*(AVERAGE(M155:N155)+AVERAGE(M158:N158)) -> -4037.7894 | O67: =-O68*(AVERAGE(N155:O155)+AVERAGE(N158:O158)) -> -4714.7958 | P67: =-P68*(AVERAGE(O155:P155)+AVERAGE(O158:P158)) -> -5443.9213
A68: As % of LT debt+Lease liabilities | D68: =-D67/(AVERAGE(C155:D155)+AVERAGE(C158:D158)) -> 0.058750363 | E68: =-E67/(AVERAGE(D155:E155)+AVERAGE(D158:E158)) -> 0.036908881 | F68: =-F67/(AVERAGE(E155:F155)+AVERAGE(E158:F158)) -> 0.02231798 | G68: =-G67/(AVERAGE(F155:G155)+AVERAGE(F158:G158)) -> 0.018019364 | H68: =-H67/(AVERAGE(G155:H155)+AVERAGE(G158:H158)) -> 0.018455205 | I68: =-I67/(AVERAGE(H155:I155)+AVERAGE(H158:I158)) -> 0.023080634 | J68: =-J67/(AVERAGE(I155:J155)+AVERAGE(I158:J158)) -> 0.01805554 | K68: =-K67/(AVERAGE(J155:K155)+AVERAGE(J158:K158)) -> 0.016020459 | L68: =K68+0.2% -> 0.018020459 | M68: =L68+0.2% -> 0.020020459 | N68: =M68+0.2% -> 0.022020459 | O68: =N68+0.2% -> 0.024020459 | P68: =O68+0.2% -> 0.026020459
A69: Other income (expense), net | C69: =Daloopa!BJ361 -> 346 | D69: =Daloopa!BK361 -> -183 | E69: =Daloopa!BL361 -> 203 | F69: =Daloopa!BM361 -> 2371 | G69: =Daloopa!BN361 -> 14633 | H69: =Daloopa!BO361 -> -16806 | I69: =Daloopa!BP361 -> 938 | J69: =Daloopa!BQ361 -> -2250 | K69: =Daloopa!BR361 -> 15229
A70: Total non-operating income | C70: =C64+C67+C69 -> -300 | D70: =D64+D67+D69 -> -1160 | E70: =E64+E67+E69 -> -565 | F70: =F64+F67+F69 -> 1279 | G70: =G64+G67+G69 -> 13272 | H70: =H64+H67+H69 -> -18184 | I70: =I64+I67+I69 -> 705 | J70: =J64+J67+J69 -> 21 | ... P70: =P64+P67+P69 -> -258.37206
A72: Profit before tax | C72: =C60+C70 -> 3806 | D72: =D60+D70 -> 11261 | E72: =E60+E70 -> 13976 | F72: =F60+F70 -> 24178 | G72: =G60+G70 -> 38151 | H72: =H60+H70 -> -5936 | I72: =I60+I70 -> 37557 | J72: =J60+J70 -> 68614 | ... P72: =P60+P70 -> 241762.83
A73: Income taxes | C73: =Daloopa!BJ366 -> -769 | D73: =Daloopa!BK366 -> -1197 | E73: =Daloopa!BL366 -> -2374 | F73: =Daloopa!BM366 -> -2863 | G73: =Daloopa!BN366 -> -4791 | H73: =Daloopa!BO366 -> 3217 | I73: =Daloopa!BP366 -> -7120 | J73: =Daloopa!BQ366 -> -9265 | K73: =Daloopa!BR366 -> -19087 | L73: =-L74*L72 -> -22318.452 | M73: =-M74*M72 -> -28249.564 | N73: =-N74*N72 -> -35769.957 | O73: =-O74*O72 -> -42000.926 | P73: =-P74*P72 -> -50770.194
A74: Effective tax | C74: =-C73/C72 -> 0.2020494 | D74: =-D73/D72 -> 0.10629607 | E74: =-E73/E72 -> 0.16986262 | F74: =-F73/F72 -> 0.11841343 | G74: =-G73/G72 -> 0.12557993 | H74: =-H73/H72 -> 0.54194744 | I74: =-I73/I72 -> 0.18957851 | J74: =-J73/J72 -> 0.13503075 | K74: =-K73/K72 -> 0.19614432 | L74: 0.21 | M74: 0.21 | N74: 0.21 | O74: 0.21 | P74: 0.21
A75: Equity method investment activity | C75: =Daloopa!BJ367 -> -4 | D75: =Daloopa!BK367 -> 9 | E75: =Daloopa!BL367 -> -14 | F75: =Daloopa!BM367 -> 16 | G75: =Daloopa!BN367 -> 4 | H75: =Daloopa!BO367 -> -3 | I75: =Daloopa!BP367 -> -12 | J75: =Daloopa!BQ367 -> -101 | K75: =Daloopa!BR367 -> -554
A76: Net Income | C76: =C72+C73+C75 -> 3033 | D76: =D72+D73+D75 -> 10073 | E76: =E72+E73+E75 -> 11588 | F76: =F72+F73+F75 -> 21331 | G76: =G72+G73+G75 -> 33364 | H76: =H72+H73+H75 -> -2722 | I76: =I72+I73+I75 -> 30425 | J76: =J72+J73+J75 -> 59248 | ... P76: =P72+P73+P75 -> 190992.63
A77: EPS | E77: =E76/E178 -> 1.1496032 | F77: =F76/F178 -> 2.0912745 | G77: =G76/G178 -> 3.2392233 | H77: =H76/H178 -> -0.26715085 | I77: =I76/I178 -> 2.8998284 | J77: =J76/J178 -> 5.5263502 | K77: =K76/K178 -> 7.1737323 | L77: =L76/L178 -> 7.6864586 | ... P77: =P76/P178 -> 19.767467
A78: Cash Flow
A80: Net Income | C80: =C76 -> 3033 | D80: =D76 -> 10073 | E80: =E76 -> 11588 | F80: =F76 -> 21331 | G80: =G76 -> 33364 | H80: =H76 -> -2722 | I80: =I76 -> 30425 | J80: =J76 -> 59248 | ... P80: =P76 -> 190992.63
A81: D&A | C81: =Daloopa!BJ448 -> 11478 | D81: =Daloopa!BK448 -> 15341 | E81: =Daloopa!BL448 -> 21789 | F81: =Daloopa!BM448 -> 25251 | G81: =Daloopa!BN448 -> 34296 | H81: =Daloopa!BO448 -> 41921 | I81: =Daloopa!BP448 -> 48663 | J81: =Daloopa!BQ448 -> 52795 | K81: =Daloopa!BR448 -> 65756 | L81: =Model!M211 -> 85461.378 | M81: =Model!N211 -> 111822.96 | N81: =Model!O211 -> 131302.93 | O81: =Model!P211 -> 148859.48 | P81: =Model!Q211 -> 155034.9
A82: As % of revenue | C82: =C81/C2 -> 0.064531726 | D82: =D81/D2 -> 0.065873149 | E82: =E81/E2 -> 0.077673052 | F82: =F81/F2 -> 0.065406254 | G82: =G81/G2 -> 0.072997859 | H82: =H81/H2 -> 0.081561063 | I82: =I81/I2 -> 0.084662961 | J82: =J81/J2 -> 0.082756102 | ... P82: =P81/P2 -> 0.12351534
A83: SBC | C83: =Daloopa!BJ449 -> 4215 | D83: =Daloopa!BK449 -> 5418 | E83: =Daloopa!BL449 -> 6864 | F83: =Daloopa!BM449 -> 9208 | G83: =Daloopa!BN449 -> 12757 | H83: =Daloopa!BO449 -> 19621 | I83: =Daloopa!BP449 -> 24023 | J83: =Daloopa!BQ449 -> 22011 | K83: =Daloopa!BR449 -> 19467 | L83: =L84*L2 -> 22055.126 | M83: =M84*M2 -> 25293.601 | N83: =N84*N2 -> 28450.387 | O83: =O84*O2 -> 31272.5 | P83: =P84*P2 -> 34082.74
A84: As % of revenue | C84: =C83/C2 -> 0.023697615 | D84: =D83/D2 -> 0.023264502 | E84: =E83/E2 -> 0.024468669 | F84: =F83/F2 -> 0.023850968 | G84: =G83/G2 -> 0.027152837 | H84: =H83/H2 -> 0.038174414 | I84: =I83/I2 -> 0.041794758 | J84: =J83/J2 -> 0.034502217 | K84: =K83/K2 -> 0.027153506 | L84: =K84 -> 0.027153506 | M84: =L84 -> 0.027153506 | N84: =M84 -> 0.027153506 | O84: =N84 -> 0.027153506 | P84: =O84 -> 0.027153506
A85: Other operating expense (income), net | C85: =Daloopa!BJ450 -> 202 | D85: =Daloopa!BK450 -> 274 | E85: =Daloopa!BL450 -> 164 | F85: =Daloopa!BM450 -> -71 | G85: =Daloopa!BN450 -> 137 | H85: =Daloopa!BO450 -> 0 | I85: =Daloopa!BP450 -> 0 | J85: =Daloopa!BQ450 -> 0 | K85: =Daloopa!BR450 -> 0
A86: Losses (gains) on sales of marketable securities, net | C86: =Daloopa!BJ451 -> 0 | D86: =Daloopa!BK451 -> 0 | E86: =Daloopa!BL451 -> 0 | F86: =Daloopa!BM451 -> 0 | G86: =Daloopa!BN451 -> 0 | H86: =Daloopa!BO451 -> 0 | I86: =Daloopa!BP451 -> 0 | J86: =Daloopa!BQ451 -> 0 | K86: =Daloopa!BR451 -> 0
A87: Other expense (income), net | C87: =Daloopa!BJ452 -> -292 | D87: =Daloopa!BK452 -> 219 | E87: =Daloopa!BL452 -> -249 | F87: =Daloopa!BM452 -> -2582 | G87: =Daloopa!BN452 -> -14306 | H87: =Daloopa!BO452 -> 16966 | I87: =Daloopa!BP452 -> -748 | J87: =Daloopa!BQ452 -> 2012 | K87: =Daloopa!BR452 -> -14880
A88: Deferred income taxes | C88: =Daloopa!BJ453 -> -29 | D88: =Daloopa!BK453 -> 441 | E88: =Daloopa!BL453 -> 796 | F88: =Daloopa!BM453 -> -554 | G88: =Daloopa!BN453 -> -310 | H88: =Daloopa!BO453 -> -8148 | I88: =Daloopa!BP453 -> -5876 | J88: =Daloopa!BQ453 -> -4648 | K88: =Daloopa!BR453 -> 11470
A89: Excess tax benefits from stock-based compensation | C89: =Daloopa!BJ454 -> 0 | D89: =Daloopa!BK454 -> 0 | E89: =Daloopa!BL454 -> 0 | F89: =Daloopa!BM454 -> 0 | G89: =Daloopa!BN454 -> 0 | H89: =Daloopa!BO454 -> 0 | I89: =Daloopa!BP454 -> 0 | J89: =Daloopa!BQ454 -> 0 | K89: =Daloopa!BR454 -> 0
A90: NWC
A91: Inventories | C91: =Daloopa!BJ456 -> -3583 | D91: =Daloopa!BK456 -> -1314 | E91: =Daloopa!BL456 -> -3278 | F91: =Daloopa!BM456 -> -2849 | G91: =Daloopa!BN456 -> -9487 | H91: =Daloopa!BO456 -> -2592 | I91: =Daloopa!BP456 -> 1449 | J91: =Daloopa!BQ456 -> -1884 | K91: =Daloopa!BR456 -> -3002 | L91: =K130-L130 -> -644.9481 | M91: =L130-M130 -> -2756.2301 | N91: =M130-N130 -> -2812.4317 | O91: =N130-O130 -> -2839.8807 | P91: =O130-P130 -> -2873.1894
A92: Accounts receivable, net and other | C92: =Daloopa!BJ457 -> -4786 | D92: =Daloopa!BK457 -> -4615 | E92: =Daloopa!BL457 -> -7681 | F92: =Daloopa!BM457 -> -8169 | G92: =Daloopa!BN457 -> -18163 | H92: =Daloopa!BO457 -> -21897 | I92: =-8348-12265 -> -20613 | J92: =-3249-14483 -> -17732 | K92: =-3249-14483 -> -17732 | L92: =K127-L127+K139-L139-Model!M218 -> -32889.352 | M92: =L127-M127+L139-M139-Model!N218 -> -41045.941 | N92: =M127-N127+M139-N139-Model!O218 -> -42787.487 | O92: =N127-O127+N139-O139-Model!P218 -> -43728.646 | P92: =O127-P127+O139-P139-Model!Q218 -> -15847.415
A93: Accounts payable | C93: =Daloopa!BJ458 -> 7175 | D93: =Daloopa!BK458 -> 3263 | E93: =Daloopa!BL458 -> 8193 | F93: =Daloopa!BM458 -> 17480 | G93: =Daloopa!BN458 -> 3602 | H93: =Daloopa!BO458 -> 2945 | I93: =Daloopa!BP458 -> 5473 | J93: =Daloopa!BQ458 -> 2972 | K93: =Daloopa!BR458 -> 11231 | L93: =L145-K145 -> -5721.7267 | M93: =M145-L145 -> 8217.5851 | N93: =N145-M145 -> 8385.1477 | O93: =O145-N145 -> 8466.9856 | P93: =P145-O145 -> 8065.044
A94: Accrued expenses and other | C94: =Daloopa!BJ459 -> 283 | D94: =Daloopa!BK459 -> 472 | E94: =Daloopa!BL459 -> -1383 | F94: =Daloopa!BM459 -> 5754 | G94: =Daloopa!BN459 -> 2123 | H94: =Daloopa!BO459 -> -1558 | I94: =Daloopa!BP459 -> -2428 | J94: =Daloopa!BQ459 -> -2904 | K94: =Daloopa!BR459 -> -5019 | L94: =L148-K148 -> 8363.7608 | M94: =M148-L148 -> 10684.565 | N94: =N148-M148 -> 9508.211 | O94: =O148-N148 -> 8769.6384 | P94: =P148-O148 -> 7280.1064
A95: Unearned revenue | C95: =Daloopa!BJ460 -> 738 | D95: =Daloopa!BK460 -> 1151 | E95: =Daloopa!BL460 -> 1711 | F95: =Daloopa!BM460 -> 1265 | G95: =Daloopa!BN460 -> 2314 | H95: =Daloopa!BO460 -> 2216 | I95: =Daloopa!BP460 -> 4578 | J95: =Daloopa!BQ460 -> 4007 | K95: =Daloopa!BR460 -> -214 | L95: =L150-K150 -> 2735.5665 | M95: =M150-L150 -> 3422.9661 | N95: =N150-M150 -> 3336.6217 | O95: =O150-N150 -> 2982.8839 | P95: =P150-O150 -> 2970.3339
A96: Change in NWC | C96: =C91+C92+C93+C94+C95 -> -173 | D96: =D91+D92+D93+D94+D95 -> -1043 | E96: =E91+E92+E93+E94+E95 -> -2438 | F96: =F91+F92+F93+F94+F95 -> 13481 | G96: =G91+G92+G93+G94+G95 -> -19611 | H96: =H91+H92+H93+H94+H95 -> -20886 | I96: =I91+I92+I93+I94+I95 -> -11541 | J96: =J91+J92+J93+J94+J95 -> -15541 | ... P96: =P91+P92+P93+P94+P95 -> -405.12016
A97: As % of revenue | C97: =C96/C2 -> -0.00097264233 | D97: =D96/D2 -> -0.0044785669 | E97: =E96/E2 -> -0.0086909405 | F97: =F96/F2 -> 0.034919081 | G97: =G96/G2 -> -0.04174134 | H97: =H96/H2 -> -0.040635585 | I97: =I96/I2 -> -0.020078812 | J97: =J96/J2 -> -0.0243605 | ... P97: =P96/P2 -> -0.0003227567
A98: Cash Flow from Operations | C98: =+C96+C85+C83+C81+C80+C86+C87+C88+C89 -> 18434 | D98: =+D96+D85+D83+D81+D80+D86+D87+D88+D89 -> 30723 | E98: =+E96+E85+E83+E81+E80+E86+E87+E88+E89 -> 38514 | F98: =+F96+F85+F83+F81+F80+F86+F87+F88+F89 -> 66064 | G98: =+G96+G85+G83+G81+G80+G86+G87+G88+G89 -> 46327 | H98: =+H96+H85+H83+H81+H80+H86+H87+H88+H89 -> 46752 | I98: =+I96+I85+I83+I81+I80+I86+I87+I88+I89 -> 84946 | J98: =+J96+J85+J83+J81+J80+J86+J87+J88+J89 -> 115877 | ... P98: =+P96+P85+P83+P81+P80+P86+P87+P88+P89 -> 379705.15
A99: OCF Margin | C99: =C98/C2 -> 0.10363982 | D99: =D98/D2 -> 0.13192235 | E99: =E98/E2 -> 0.13729404 | F99: =F98/F2 -> 0.17112189 | G99: =G98/G2 -> 0.098605429 | H99: =H98/H2 -> 0.090960207 | I99: =I98/I2 -> 0.14778743 | J99: =J98/J2 -> 0.18163706 | ... P99: =P98/P2 -> 0.30250872
A101: Capex | C101: =Daloopa!BJ465 -> -11955 | D101: =Daloopa!BK465 -> -13427 | E101: =Daloopa!BL465 -> -16861 | F101: =Daloopa!BM465 -> -40140 | G101: =Daloopa!BN465 -> -61053 | H101: =Daloopa!BO465 -> -63645 | I101: =Daloopa!BP465 -> -52729 | J101: =Daloopa!BQ465 -> -82999 | K101: =Daloopa!BR465 -> -131819 | L101: =-Model!M202 -> -189802.57 | M101: =-Model!N202 -> -178657.17 | N101: =-Model!O202 -> -186214.22 | O101: =-Model!P202 -> -143045.18 | P101: =-Model!Q202 -> -119815.2
A102: As % of sales | C102: =-C101/C2 -> 0.06721352 | D102: =-D101/D2 -> 0.057654571 | E102: =-E101/E2 -> 0.060105803 | F102: =-F101/F2 -> 0.1039724 | G102: =-G101/G2 -> 0.12994921 | H102: =-H101/H2 -> 0.12382705 | I102: =-I101/I2 -> 0.09173691 | J102: =-J101/J2 -> 0.13010084 | ... P102: =-P101/P2 -> 0.095456022
A103: Capex/D&A | C103: =-C101/(C81) -> 1.0415578 | D103: =-D101/(D81) -> 0.87523629 | E103: =-E101/(E81) -> 0.77383083 | F103: =-F101/(F81) -> 1.58964 | G103: =-G101/(G81) -> 1.7801784 | H103: =-H101/(H81) -> 1.5182128 | I103: =-I101/(I81) -> 1.0835542 | J103: =-J101/(J81) -> 1.5720996 | ... P103: =-P101/(P81) -> 0.77282728
A104: Proceeds from sale of property | C104: =Daloopa!BJ469 -> 1897 | D104: =Daloopa!BK469 -> 2104 | E104: =Daloopa!BL469 -> 4172 | F104: =Daloopa!BM469 -> 5096 | G104: =Daloopa!BN469 -> 5657 | H104: =Daloopa!BO469 -> 5324 | I104: =Daloopa!BP469 -> 4596 | J104: =Daloopa!BQ469 -> 5341 | K104: =Daloopa!BR469 -> 3499
A105: Acuisition | C105: =Daloopa!BJ466 -> -13972 | D105: =Daloopa!BK466 -> -2186 | E105: =Daloopa!BL466 -> -2461 | F105: =Daloopa!BM466 -> -2325 | G105: =Daloopa!BN466 -> -1985 | H105: =Daloopa!BO466 -> -8316 | I105: =Daloopa!BP466 -> -5839 | J105: =Daloopa!BQ466 -> -7082 | K105: =Daloopa!BR466 -> -3841
A106: Other investing activities | C106: =C108-C105-C101-C104 -> -3789 | D106: =D108-D105-D101-D104 -> 1140 | E106: =E108-E105-E101-E104 -> -9131 | F106: =F108-F105-F101-F104 -> -22242 | G106: =G108-G105-G101-G104 -> -773 | H106: =H108-H105-H101-H104 -> 29036 | I106: =I108-I105-I101-I104 -> 4139 | J106: =J108-J105-J101-J104 -> -9602 | K106: =K108-K105-K101-K104 -> -10384
A108: Cash Flow from Investing | C108: =Daloopa!BJ470 -> -27819 | D108: =Daloopa!BK470 -> -12369 | E108: =Daloopa!BL470 -> -24281 | F108: =Daloopa!BM470 -> -59611 | G108: =Daloopa!BN470 -> -58154 | H108: =Daloopa!BO470 -> -37601 | I108: =Daloopa!BP470 -> -49833 | J108: =Daloopa!BQ470 -> -94342 | K108: =Daloopa!BR470 -> -142545 | L108: =L106+L105+L101 -> -189802.57 | M108: =M106+M105+M101 -> -178657.17 | N108: =N106+N105+N101 -> -186214.22 | O108: =O106+O105+O101 -> -143045.18 | P108: =P106+P105+P101 -> -119815.2
A110: Repurchases of ordinary shares | C110: =Daloopa!BJ480 -> 0 | D110: =Daloopa!BK480 -> 0 | E110: =Daloopa!BL480 -> 0 | F110: =Daloopa!BM480 -> 0 | G110: =Daloopa!BN480 -> 0 | H110: =Daloopa!BO480 -> -6000 | I110: =Daloopa!BP480 -> 0 | J110: =Daloopa!BQ480 -> 0 | K110: =Daloopa!BR480 -> 0 | M110: =-M121-M105-M113 -> -34234.976 | N110: =-N121-N105-N113 -> -74378.706 | O110: =-O121-O105-O113 -> -159037.46 | P110: =-P121-P105-P113 -> -249858.64
A111: Proceeds/repayment of short-term debt | C111: =Daloopa!BJ473+Daloopa!BJ474 -> 0 | D111: =Daloopa!BK473+Daloopa!BK474 -> 0 | E111: =Daloopa!BL473+Daloopa!BL474 -> 0 | F111: =Daloopa!BM473+Daloopa!BM474 -> 619 | G111: =Daloopa!BN473+Daloopa!BN474 -> 203 | H111: =Daloopa!BO473+Daloopa!BO474 -> 3999 | I111: =Daloopa!BP473+Daloopa!BP474 -> -7548 | J111: =Daloopa!BQ473+Daloopa!BQ474 -> 82 | K111: =Daloopa!BR473+Daloopa!BR474 -> 894
A112: Proceeds/repayment of long term debt | C112: =Daloopa!BJ475+Daloopa!BJ476+Daloopa!BJ481 -> 16231 | D112: =Daloopa!BK475+Daloopa!BK476+Daloopa!BK481 -> 768 | E112: =Daloopa!BL475+Daloopa!BL476+Daloopa!BL481 -> 2273 | F112: =Daloopa!BM475+Daloopa!BM476+Daloopa!BM481 -> 8972 | G112: =Daloopa!BN475+Daloopa!BN476+Daloopa!BN481 -> 17413 | H112: =Daloopa!BO475+Daloopa!BO476+Daloopa!BO481 -> 19908 | I112: =Daloopa!BP475+Daloopa!BP476+Daloopa!BP481 -> -3676 | J112: =Daloopa!BQ475+Daloopa!BQ476+Daloopa!BQ481 -> -9182 | K112: =Daloopa!BR475+Daloopa!BR476+Daloopa!BR481 -> 10652 | L112: =-L113 -> 8733.9 | M112: =-M113 -> 9019.5258 | N112: =-N113 -> 9353.6234 | O112: =-O113 -> 9703.8011 | P112: =-P113 -> 10031.31
A113: Proceeds/Repayment of leases/obligations | C113: =Daloopa!BJ477+Daloopa!BJ478+Daloopa!BJ482 -> -6371 | D113: =Daloopa!BK477+Daloopa!BK478+Daloopa!BK482 -> -8454 | E113: =Daloopa!BL477+Daloopa!BL478+Daloopa!BL482 -> -12339 | F113: =Daloopa!BM477+Daloopa!BM478+Daloopa!BM482 -> -10695 | G113: =Daloopa!BN477+Daloopa!BN478+Daloopa!BN482 -> -11325 | H113: =Daloopa!BO477+Daloopa!BO478+Daloopa!BO482 -> -8189 | I113: =Daloopa!BP477+Daloopa!BP478+Daloopa!BP482 -> -4655 | J113: =Daloopa!BQ477+Daloopa!BQ478+Daloopa!BQ482 -> -2712 | K113: =Daloopa!BR477+Daloopa!BR478+Daloopa!BR482 -> -1885 | L113: =L159 -> -8733.9 | M113: =M159 -> -9019.5258 | N113: =N159 -> -9353.6234 | O113: =O159 -> -9703.8011 | P113: =P159 -> -10031.31
A114: Cash Flow from Financing | C114: =+C110+C111+C112+C113 -> 9860 | D114: =+D110+D111+D112+D113 -> -7686 | E114: =+E110+E111+E112+E113 -> -10066 | F114: =+F110+F111+F112+F113 -> -1104 | G114: =+G110+G111+G112+G113 -> 6291 | H114: =+H110+H111+H112+H113 -> 9718 | I114: =+I110+I111+I112+I113 -> -15879 | J114: =+J110+J111+J112+J113 -> -11812 | ... P114: =+P110+P111+P112+P113 -> -249858.64
A115: Effect of exchange rates | C115: =Daloopa!BJ485 -> 713 | D115: =Daloopa!BK485 -> -351 | E115: =Daloopa!BL485 -> 70 | F115: =Daloopa!BM485 -> 618 | G115: =Daloopa!BN485 -> -364 | H115: =Daloopa!BO485 -> -1093 | I115: =Daloopa!BP485 -> 403 | J115: =Daloopa!BQ485 -> -1301 | K115: =Daloopa!BR485 -> 1164
A117: Change in Cash | C117: =C114+C115+C108+C98 -> 1188 | D117: =D114+D115+D108+D98 -> 10317 | E117: =E114+E115+E108+E98 -> 4237 | F117: =F114+F115+F108+F98 -> 5967 | G117: =G114+G115+G108+G98 -> -5900 | H117: =H114+H115+H108+H98 -> 17776 | I117: =I114+I115+I108+I98 -> 19637 | J117: =J114+J115+J108+J98 -> 8422 | ... P117: =P114+P115+P108+P98 -> 10031.31
A118: Beginning Cash | L118: =K119 -> 86810 | M118: =L119 -> 60327.126 | N118: =M119 -> 69346.652 | O118: =N119 -> 78700.275 | P118: =O119 -> 88404.077
A119: Ending Cash | K119: =K125 -> 86810 | L119: =L118+L117 -> 60327.126 | M119: =M118+M117 -> 69346.652 | N119: =N118+N117 -> 78700.275 | O119: =O118+O117 -> 88404.077 | P119: =P118+P117 -> 98435.386
A121: Free Cash Flow | C121: =C98+C101+C104 -> 8376 | D121: =D98+D101+D104 -> 19400 | E121: =E98+E101+E104 -> 25825 | F121: =F98+F101+F104 -> 31020 | G121: =G98+G101+G104 -> -9069 | H121: =H98+H101+H104 -> -11569 | I121: =I98+I101+I104 -> 36813 | J121: =J98+J101+J104 -> 38219 | ... P121: =P98+P101+P104 -> 259889.95
A122: FCF Margin | C122: =C121/C2 -> 0.047091631 | D122: =D121/D2 -> 0.083302202 | E122: =E121/E2 -> 0.092060516 | F122: =F121/F2 -> 0.080349372 | G122: =G121/G2 -> -0.019303055 | H122: =H121/H2 -> -0.022508527 | I122: =I121/I2 -> 0.064046557 | J122: =J121/J2 -> 0.059908239 | ... P122: =P121/P2 -> 0.2070527
A124: Balance Sheet
A125: Cash & Cash equivalents | C125: =Daloopa!BJ397 -> 20522 | D125: =Daloopa!BK397 -> 31750 | E125: =Daloopa!BL397 -> 36092 | F125: =Daloopa!BM397 -> 42122 | G125: =Daloopa!BN397 -> 36220 | H125: =Daloopa!BO397 -> 53888 | I125: =Daloopa!BP397 -> 73387 | J125: =Daloopa!BQ397 -> 78779 | K125: =Daloopa!BR397 -> 86810 | L125: =L119 -> 60327.126 | M125: =M119 -> 69346.652 | N125: =N119 -> 78700.275 | O125: =O119 -> 88404.077 | P125: =P119 -> 98435.386
A126: Marketable Securities | C126: =Daloopa!BJ398 -> 10464 | D126: =Daloopa!BK398 -> 9500 | E126: =Daloopa!BL398 -> 18929 | F126: =Daloopa!BM398 -> 42274 | G126: =Daloopa!BN398 -> 59829 | H126: =Daloopa!BO398 -> 16138 | I126: =Daloopa!BP398 -> 13393 | J126: =Daloopa!BQ398 -> 22423 | K126: =Daloopa!BR398 -> 36219 | L126: =K126 -> 36219 | M126: =L126 -> 36219 | N126: =M126 -> 36219 | O126: =N126 -> 36219 | P126: =O126 -> 36219
...

Sheet Valuation
A1: Items | C1: 2021 | D1: 2022 | E1: 2023 | F1: 2024 | G1: 2025 | H1: 2026 | I1: 2027 | J1: 2028 | K1: 2029 | L1: 2030
A2: FCF
A3: OCF | C3: =Financials!G98 -> 46327 | D3: =Financials!H98 -> 46752 | E3: =Financials!I98 -> 84946 | F3: =Financials!J98 -> 115877 | G3: =Financials!K98 -> 144747 | H3: =Financials!L98 -> 163319.7 | I3: =Financials!M98 -> 221911.67 | J3: =Financials!N98 -> 269946.55 | ... L3: =Financials!P98 -> 379705.15
A4: Capex | C4: =Financials!G101+Financials!G104 -> -55396 | D4: =Financials!H101+Financials!H104 -> -58321 | E4: =Financials!I101+Financials!I104 -> -48133 | F4: =Financials!J101+Financials!J104 -> -77658 | G4: =Financials!K101+Financials!K104 -> -128320 | H4: =Financials!L101+Financials!L104 -> -189802.57 | I4: =Financials!M101+Financials!M104 -> -178657.17 | J4: =Financials!N101+Financials!N104 -> -186214.22 | ... L4: =Financials!P101+Financials!P104 -> -119815.2 | Q4: Terminal Multiple
A5: FCF | C5: =C3+C4 -> -9069 | D5: =D3+D4 -> -11569 | E5: =E3+E4 -> 36813 | F5: =F3+F4 -> 38219 | G5: =G3+G4 -> 16427 | H5: =H3+H4 -> -26482.874 | I5: =I3+I4 -> 43254.502 | J5: =J3+J4 -> 83732.33 | K5: =K3+K4 -> 168741.26 | L5: =L3+L4-Financials!P83 -> 225807.21 | Q5: 10
A6: FCF/share | C6: =C5/C14 -> -0.88048544 | D6: =D5/D14 -> -1.1354402 | E6: =E5/E14 -> 3.5086733 | F6: =F5/F14 -> 3.5648727 | G6: =G5/G14 -> 1.5172255 | H6: =H5/H14 -> -2.4244852 | I6: =I5/I14 -> 3.9727945 | J6: =J5/J14 -> 7.8091754 | ... L6: =L5/L14 -> 23.370727 | Q6: =Q5+0.5 -> 10.5
A7: Terminal FCF multiple | L7: 14.5 | Q7: =Q6+0.5 -> 11
A8: Terminal Stock price | L8: =L7*L6 -> 338.87554 | Q8: =Q7+0.5 -> 11.5
A9: Current price* | B9: 210.32 | Q9: =Q8+0.5 -> 12
A10: Dividend/share | E10: 0 | F10: 0 | G10: 0 | H10: 0 | I10: 0 | J10: 0 | K10: 0 | L10: 0 | Q10: =Q9+0.5 -> 12.5
A11: Cash flow | G11: =-B9 -> -210.32 | H11: =H10+H8 -> 0 | I11: =I10+I8 -> 0 | J11: =J10+J8 -> 0 | K11: =K10+K8 -> 0 | L11: =L10+L8 -> 338.87554 | Q11: =Q10+0.5 -> 13
Q12: =Q11+0.5 -> 13.5
A13: IRR | B13: =IRR(F11:L11) -> 0.10009941 | Q13: =Q12+0.5 -> 14
A14: #diluted shares outstanding | C14: =Financials!G178 -> 10300 | D14: =Financials!H178 -> 10189 | E14: =Financials!I178 -> 10492 | F14: =Financials!J178 -> 10721 | G14: =Financials!K178 -> 10827 | H14: =Financials!L178 -> 10923.092 | I14: =Financials!M178 -> 10887.677 | J14: =Financials!N178 -> 10722.301 | ... L14: =Financials!P178 -> 9661.9678 | Q14: =Q13+0.5 -> 14.5
Q15: =Q14+0.5 -> 15
A16: *Closing price of February 06, 2026 | Q16: =Q15+0.5 -> 15.5
Q17: =Q16+0.5 -> 16
A18: Stock price | E18: =B9 -> 210.32 | F18: =B9 -> 210.32 | G18: =F18 -> 210.32 | H18: =G18*(1.1)^(11/12) -> 229.52176 | I18: =H18*1.1 -> 252.47394 | J18: =I18*1.1 -> 277.72133 | K18: =J18*1.1 -> 305.49346 | L18: =K18*1.1 -> 336.04281 | Q18: =Q17+0.5 -> 16.5
Q19: =Q18+0.5 -> 17
Q20: =Q19+0.5 -> 17.5
Q21: =Q20+0.5 -> 18
Q22: =Q21+0.5 -> 18.5
Q23: =Q22+0.5 -> 19
Q24: =Q23+0.5 -> 19.5
Q25: =Q24+0.5 -> 20
Q26: =Q25+0.5 -> 20.5
Q27: =Q26+0.5 -> 21
Q28: =Q27+0.5 -> 21.5
Q29: =Q28+0.5 -> 22
Q30: =Q29+0.5 -> 22.5
Q31: =Q30+0.5 -> 23
Q32: =Q31+1 -> 24
Q33: =Q32+1 -> 25
Q34: =Q33+1 -> 26
Q35: =Q34+1 -> 27
Q36: =Q35+1 -> 28
Q37: =Q36+1 -> 29
Q38: =Q37+1 -> 30
Q39: =Q38+1 -> 31
Q40: =Q39+1 -> 32

Sheet Daloopa
A1: Calendar | B1: Unit | C1: Source | D1: Tag Id | E1: 2013Q1 | F1: 2013Q2 | G1: 2013Q3 | H1: 2013Q4 | I1: 2014Q1 | J1: 2014Q2 | K1: 2014Q3 | L1: 2014Q4 | M1: 2015Q1 | N1: 2015Q2 | O1: 2015Q3 | P1: 2015Q4 | Q1: 2016Q1 | R1: 2016Q2 | S1: 2016Q3 | T1: 2016Q4 | U1: 2017Q1 | V1: 2017Q2 | W1: 2017Q3 | X1: 2017Q4 | Y1: 2018Q1 | Z1: 2018Q2 | AA1: 2018Q3 | AB1: 2018Q4 | AC1: 2019Q1 | AD1: 2019Q2 | AE1: 2019Q3 | AF1: 2019Q4 | AG1: 2020Q1 | AH1: 2020Q2 | AI1: 2020Q3 | AJ1: 2020Q4 | AK1: 2021Q1 | AL1: 2021Q2 | AM1: 2021Q3 | AN1: 2021Q4 | AO1: 2022Q1 | AP1: 2022Q2 | AQ1: 2022Q3 | AR1: 2022Q4 | AS1: 2023Q1 | AT1: 2023Q2 | AU1: 2023Q3 | AV1: 2023Q4 | AW1: 2024Q1 | AX1: 2024Q2 | AY1: 2024Q3 | AZ1: 2024Q4 | BA1: 2025Q1 | BB1: 2025Q2 | BC1: 2025Q3 | BD1: 2025Q4 | BF1: 2013FY | BG1: 2014FY | BH1: 2015FY | BI1: 2016FY | BJ1: 2017FY | BK1: 2018FY | BL1: 2019FY | BM1: 2020FY | BN1: 2021FY | BO1: 2022FY | BP1: 2023FY | BQ1: 2024FY | BR1: 2025FY
A2: Fiscal | E2: 2013Q1 | F2: 2013Q2 | G2: 2013Q3 | H2: 2013Q4 | I2: 2014Q1 | J2: 2014Q2 | K2: 2014Q3 | L2: 2014Q4 | M2: 2015Q1 | N2: 2015Q2 | O2: 2015Q3 | P2: 2015Q4 | Q2: 2016Q1 | R2: 2016Q2 | S2: 2016Q3 | T2: 2016Q4 | U2: 2017Q1 | V2: 2017Q2 | W2: 2017Q3 | X2: 2017Q4 | Y2: 2018Q1 | Z2: 2018Q2 | AA2: 2018Q3 | AB2: 2018Q4 | AC2: 2019Q1 | AD2: 2019Q2 | AE2: 2019Q3 | AF2: 2019Q4 | AG2: 2020Q1 | AH2: 2020Q2 | AI2: 2020Q3 | AJ2: 2020Q4 | AK2: 2021Q1 | AL2: 2021Q2 | AM2: 2021Q3 | AN2: 2021Q4 | AO2: 2022Q1 | AP2: 2022Q2 | AQ2: 2022Q3 | AR2: 2022Q4 | AS2: 2023Q1 | AT2: 2023Q2 | AU2: 2023Q3 | AV2: 2023Q4 | AW2: 2024Q1 | AX2: 2024Q2 | AY2: 2024Q3 | AZ2: 2024Q4 | BF2: 2013FY | BG2: 2014FY | BH2: 2015FY | BI2: 2016FY | BJ2: 2017FY | BK2: 2018FY | BL2: 2019FY | BM2: 2020FY | BN2: 2021FY | BO2: 2022FY | BP2: 2023FY | BQ2: 2024FY | BR2: 2025FY
A3: Fiscal Date | E3: 41364 | F3: 41455 | G3: 41547 | H3: 41639 | I3: 41729 | J3: 41820 | K3: 41912 | L3: 42004 | M3: 42094 | N3: 42185 | O3: 42277 | P3: 42369 | Q3: 42460 | R3: 42551 | S3: 42643 | T3: 42735 | U3: 42825 | V3: 42916 | W3: 43008 | X3: 43100 | Y3: 43190 | Z3: 43281 | AA3: 43373 | AB3: 43465 | AC3: 43555 | AD3: 43646 | AE3: 43738 | AF3: 43830 | AG3: 43921 | AH3: 44012 | AI3: 44104 | AJ3: 44196 | AK3: 44286 | AL3: 44377 | AM3: 44469 | AN3: 44561 | AO3: 44651 | AP3: 44742 | AQ3: 44834 | AR3: 44926
A4: Documents
A5: 10-Q/10-K | E5: 10-Q | F5: 10-Q | G5: 10-Q | H5: 10-K | I5: 10-Q | J5: 10-Q | K5: 10-Q | L5: 10-K | M5: 10-Q | N5: 10-Q | O5: 10-Q | P5: 10-K | Q5: 10-Q | R5: 10-Q | S5: 10-Q | T5: 10-K | U5: 10-Q | V5: 10-Q | W5: 10-Q | X5: 10-K | Y5: 10-Q | Z5: 10-Q | AA5: 10-Q | AB5: 10-K | AC5: 10-Q | AD5: 10-Q | AE5: 10-Q | AF5: 10-K | AG5: 10-Q | AH5: 10-Q | AI5: 10-Q | AJ5: 10-K | AK5: 10-Q | AL5: 10-Q | AM5: 10-Q | AN5: 10-K | AO5: 10-Q | AP5: 10-Q | AQ5: 10-Q | AR5: 10-K
A6: 8-K | E6: EX-99.1 | F6: EX-99.1 | G6: EX-99.1 | H6: EX-99.1 | I6: EX-99.1 | J6: EX-99.1 | K6: EX-99.1 | L6: EX-99.1 | M6: EX-99.1 | N6: EX-99.1 | O6: EX-99.1 | P6: EX-99.1 | Q6: EX-99.1 | R6: EX-99.1 | S6: EX-99.1 | T6: EX-99.1 | U6: EX-99.1 | V6: EX-99.1 | W6: EX-99.1 | X6: EX-99.1 | Y6: EX-99.1 | Z6: EX-99.1 | AA6: EX-99.1 | AB6: EX-99.1 | AC6: EX-99.1 | AD6: EX-99.1 | AE6: EX-99.1 | AF6: EX-99.1 | AG6: EX-99.1 | AH6: EX-99.1 | AI6: EX-99.1 | AJ6: EX-99.1 | AK6: EX-99.1 | AL6: EX-99.1 | AM6: EX-99.1 | AN6: EX-99.1 | AO6: EX-99.1 | AP6: EX-99.1 | AQ6: EX-99.1 | AR6: EX-99.1
A8: Guidance
A9: Quarterly
A10: Net sales - high | B10: Billion | C10: 8-K | D10: 85882 | E10: 16.2 | F10: 17.15 | G10: 26.5 | H10: 19.9 | I10: 19.8 | J10: 21.5 | K10: 30.3 | L10: 22.9 | M10: 22.8 | N10: 25.5 | O10: 36.75 | P10: 29 | Q10: 30.5 | R10: 33.5 | S10: 45.5 | T10: 35.75 | U10: 37.75 | V10: 41.75 | W10: 60.5 | X10: 50.75 | Y10: 54 | Z10: 57.5 | AA10: 72.5 | AB10: 60 | AC10: 63.5 | AD10: 70 | AE10: 86.5 | AF10: 73 | AG10: 81 | AH10: 93 | AI10: 121 | AJ10: 106 | AK10: 116 | AL10: 112 | AM10: 140 | AN10: 117 | AO10: 121 | AP10: 130 | AQ10: 148 | AR10: 126 | AS10: 133 | AT10: 143 | AU10: 167 | AV10: 143.5 | AW10: 149 | AX10: 158.5 | AY10: 188.5 | AZ10: 155.5 | BA10: 164 | BB10: 179.5 | BC10: 213 | BD10: 178.5 | BR10: 178.5
A11: Net sales - low | B11: Billion | C11: 8-K | D11: 85883 | E11: 14.5 | F11: 15.45 | G11: 23.5 | H11: 18.2 | I11: 18.1 | J11: 19.7 | K11: 27.3 | L11: 20.9 | M11: 20.6 | N11: 23.3 | O11: 33.5 | P11: 26.5 | Q11: 28 | R11: 31 | S11: 42 | T11: 33.25 | U11: 35.25 | V11: 39.25 | W11: 56 | X11: 47.75 | Y11: 51 | Z11: 54 | AA11: 66.5 | AB11: 56 | AC11: 59.5 | AD11: 66 | AE11: 80 | AF11: 69 | AG11: 75 | AH11: 87 | AI11: 112 | AJ11: 100 | AK11: 110 | AL11: 106 | AM11: 130 | AN11: 112 | AO11: 116 | AP11: 125 | AQ11: 140 | AR11: 121 | AS11: 127 | AT11: 138 | AU11: 160 | AV11: 138 | AW11: 144 | AX11: 154 | AY11: 181.5 | AZ11: 151 | BA11: 159 | BB11: 174 | BC11: 206 | BD11: 173.5 | BR11: 173.5
A12: Net sales percentage - high | B12: Percent | C12: 8-K | D12: 85884 | E12: 0.26 | F12: 0.24 | G12: 0.25 | H12: 0.24 | I12: 0.26 | J12: 0.26 | K12: 0.18 | L12: 0.16 | M12: 0.18 | N12: 0.24 | O12: 0.25 | P12: 0.28 | Q12: 0.32 | R12: 0.32 | S12: 0.27 | T12: 0.23 | U12: 0.24 | V12: 0.28 | W12: 0.38 | X12: 0.42 | Y12: 0.42 | Z12: 0.31 | AA12: 0.2 | AB12: 0.18 | AC12: 0.2 | AD12: 0.24 | AE12: 0.2 | AF12: 0.22 | AG12: 0.28 | AH12: 0.33 | AI12: 0.38 | AJ12: 0.4 | AK12: 0.3 | AL12: 0.16 | AM12: 0.12 | AN12: 0.08 | AO12: 0.07 | AP12: 0.17 | AQ12: 0.08 | AR12: 0.08 | AS12: 0.1 | AT12: 0.13 | AU12: 0.12 | AV12: 0.13 | AW12: 0.11 | AX12: 0.11 | AY12: 0.11 | AZ12: 0.09 | BA12: 0.11 | BB12: 0.13 | BC12: 0.13 | BD12: 0.15 | BR12: 0.15
A13: Net sales percentage - low | B13: Percent | C13: 8-K | D13: 85885 | E13: 0.13 | F13: 0.12 | G13: 0.1 | H13: 0.13 | I13: 0.15 | J13: 0.15 | K13: 0.07 | L13: 0.06 | M13: 0.07 | N13: 0.13 | O13: 0.14 | P13: 0.17 | Q13: 0.21 | R13: 0.22 | S13: 0.17 | T13: 0.14 | U13: 0.16 | V13: 0.2 | W13: 0.28 | X13: 0.34 | Y13: 0.34 | Z13: 0.23 | AA13: 0.1 | AB13: 0.1 | AC13: 0.13 | AD13: 0.17 | AE13: 0.11 | AF13: 0.16 | AG13: 0.18 | AH13: 0.24 | AI13: 0.28 | AJ13: 0.33 | AK13: 0.24 | AL13: 0.1 | AM13: 0.04 | AN13: 0.03 | AO13: 0.03 | AP13: 0.13 | AQ13: 0.02 | AR13: 0.04 | AS13: 0.05 | AT13: 0.09 | AU13: 0.07 | AV13: 0.08 | AW13: 0.07 | AX13: 0.08 | AY13: 0.07 | AZ13: 0.05 | BA13: 0.07 | BB13: 0.1 | BC13: 0.1 | BD13: 0.11 | BR13: 0.11
A14: Impact on sales from foreign exchange rates | B14: Billion | C14: 8-K | D14: 85886 | T14: -0.73 | U14: -0.72 | V14: -0.125 | W14: 1.2 | X14: 1.2 | Y14: 1.2 | AZ14: -2.1
A15: Impact on sales from foreign exchange rates (basis point) | B15: Actual | C15: 8-K | D15: 85887 | S15: 60 | T15: 250 | U15: 240 | V15: 40 | W15: 270 | X15: 330 | Y15: 320 | Z15: 30 | AA15: 80 | AB15: 210 | AC15: 150 | AD15: 30 | AE15: 80 | AF15: 5 | AG15: -70 | AH15: -20 | AI15: 90 | AJ15: 300 | AK15: 200 | AL15: 70 | AM15: -60 | AN15: -150 | AO15: -200 | AP15: -390 | AQ15: -460 | AR15: -210 | AS15: -30 | AT15: 120 | AU15: 40 | AV15: 40 | AW15: -60 | AX15: -90 | AY15: -10 | AZ15: -150 | BA15: -10 | BB15: 130 | BC15: 190 | BD15: 180 | BR15: 180
A16: Basis points of impact to YoY growth rate from whole foods market | B16: Actual | C16: 8-K | D16: 85888 | W16: 1000
A17: Operating income - high | B17: Billion | C17: 8-K | D17: 2636319 | E17: 0.01 | F17: -0.065 | G17: 0.5 | H17: 0.2 | I17: -0.055 | J17: -0.41 | K17: 0.43 | L17: 0.05 | M17: 0.05 | N17: 0.07 | O17: 1.28 | P17: 0.7 | Q17: 0.975 | R17: 0.65 | S17: 1.25 | T17: 0.9 | U17: 1.075 | V17: 0.3 | W17: 1.65 | X17: 1 | Y17: 1.9 | Z17: 2.4 | AA17: 3.6 | AB17: 3.3 | AC17: 3.6 | AD17: 3.1 | AE17: 2.9 | AF17: 4.2 | AG17: 1.5 | AH17: 5 | AI17: 4.5 | AJ17: 6.5 | AK17: 8 | AL17: 6 | AM17: 3 | AN17: 6 | AO17: 3 | AP17: 3.5 | AQ17: 4 | AR17: 4 | AS17: 5.5 | AT17: 8.5 | AU17: 11 | AV17: 12 | AW17: 14 | AX17: 15 | AY17: 20 | AZ17: 18 | BA17: 17.5 | BB17: 20.5 | BC17: 26 | BD17: 21.5 | BR17: 21.5
A18: Operating income - low | B18: Billion | C18: 8-K | D18: 2636320 | E18: -0.34 | F18: -0.44 | G18: -0.5 | H18: -0.2 | I18: -0.455 | J18: -0.81 | K18: -0.57 | L18: -0.45 | M18: -0.5 | N18: -0.48 | O18: 0.08 | P18: 0.1 | Q18: 0.375 | R18: 0.05 | S18: 0 | T18: 0.25 | U18: 0.425 | V18: -0.4 | W18: 0.3 | X18: 0.3 | Y18: 1.1 | Z18: 1.4 | AA18: 2.1 | AB18: 2.3 | AC18: 2.6 | AD18: 2.1 | AE18: 1.2 | AF18: 3 | AG18: -1.5 | AH18: 2 | AI18: 1 | AJ18: 3 | AK18: 4.5 | AL18: 2.5 | AM18: 0 | AN18: 3 | AO18: -1 | AP18: 0 | AQ18: 0 | AR18: 0 | AS18: 2 | AT18: 5.5 | AU18: 7 | AV18: 8 | AW18: 10 | AX18: 11.5 | AY18: 16 | AZ18: 14 | BA18: 13 | BB18: 15.5 | BC18: 21 | BD18: 16.5 | BR18: 16.5
A19: Cost related to COVID-19 | B19: Billion | C19: 8-K | D19: 142241 | AG19: 4 | AH19: 2 | AI19: 4 | AJ19: 2 | AK19: 1.5 | AL19: 1
A20: Stock-based compensation and other operating expense (income) | B20: Million | C20: 8-K | D20: 85891 | E20: 340 | F20: 340 | G20: 350 | H20: 350 | I20: 455 | J20: 410 | K20: 470 | L20: 450 | M20: 600 | N20: 580 | O20: 620 | P20: 600 | Q20: 825
A21: Depreciation expenses | B21: Million | C21: 8-K | D21: 85892 | AF21: -800 | AN21: -1000 | AV21: 900
A22: Investments over next year to help delivery service partners (DSP) | B22: Million | C22: 8-K | D22: 3516099 | AQ22: 450
A24: Long-term
A25: Investments over next 5 years to electrify its transport network in Europe (in Billions) | B25: Billion | C25: 8-K | D25: 3516100 | AQ25: 1
A27: KPIs
A28: Prime customers around the world | B28: Million | C28: 8-K | D28: 1182673 | Y28: 100 | Z28: 100 | AF28: 150 | AK28: 200 | AN28: 200
A29: Audible customers downloaded listening hours | B29: Million | C29: PRIVATE | D29: 1139137 | BF29: 600
A30: Smart home devices controllable by Alexa | B30: Actual | C30: 8-K | D30: 1139139 | X30: 4000 | Z30: 13000 | AA30: 20000 | AB30: 28000 | AD30: 60000 | AE30: 85000
A31: Unique brands compatible with Alexa | B31: Actual | C31: 8-K | D31: 1139140 | X31: 1200 | Z31: 2500 | AA31: 3500 | AB31: 4500 | AD31: 7400 | AE31: 9500
A32: Total unearned revenue | B32: Billion | C32: 10-K | D32: 2127453 | AF32: 10.2 | AJ32: 11.6 | AN32: 14 | AR32: 16.1 | AT32: 2.7 | AU32: 2.7 | AV32: 20.6 | AX32: 6.7 | AY32: 7 | AZ32: 24.6
A34: Segmental breakdown
A35: Net sales
A36: Online stores | B36: Million | C36: 8-K | D36: 2640310 | Q36: 19916 | R36: 20378 | S36: 21590 | T36: 29548 | U36: 22826 | V36: 23754 | W36: 26392 | X36: 35383 | Y36: 26939 | Z36: 27165 | AA36: 29061 | AB36: 39822 | AC36: 29498 | AD36: 31053 | AE36: 35039 | AF36: 45657 | AG36: 36652 | AH36: 45896 | AI36: 48350 | AJ36: 66451 | AK36: 52901 | AL36: 53157 | AM36: 49942 | AN36: 66075 | AO36: 51129 | AP36: 50855 | AQ36: 53489 | AR36: 64531 | AS36: 51096 | AT36: 52966 | AU36: 57267 | AV36: 70543 | AW36: 54670 | AX36: 55392 | AY36: 61411 | AZ36: 75556 | BA36: 57407 | BB36: 61485 | BC36: 67407 | BD36: 82988 | BI36: =SUM(Q36,R36,S36,T36) -> 91432 | BJ36: =SUM(U36,V36,W36,X36) -> 108355 | BK36: =SUM(Y36,Z36,AA36,AB36) -> 122987 | BL36: =SUM(AC36,AD36,AE36,AF36) -> 141247 | BM36: =SUM(AG36,AH36,AI36,AJ36) -> 197349 | BN36: =SUM(AK36,AL36,AM36,AN36) -> 222075 | BO36: =SUM(AO36,AP36,AQ36,AR36) -> 220004 | BP36: 231872 | BQ36: 247029 | BR36: 269287
A37: Online stores - Y/Y growth (decline), excluding F/X | B37: Percent | C37: 8-K | D37: 85896 | Q37: 0.21 | R37: 0.22 | S37: 0.2 | T37: 0.16 | U37: 0.16 | V37: 0.18 | W37: 0.22 | X37: 0.17 | Y37: 0.13 | Z37: 0.12 | AA37: 0.11 | AB37: 0.14 | AC37: 0.12 | AD37: 0.16 | AE37: 0.22 | AF37: 0.15 | AG37: 0.25 | AH37: 0.49 | AI37: 0.37 | AJ37: 0.43 | AK37: 0.41 | AL37: 0.13 | AM37: 0.03 | AN37: 0.01 | AO37: -0.01 | AP37: 0 | AQ37: 0.13 | AR37: 0.02 | AS37: 0.03 | AT37: 0.05 | AU37: 0.06 | AV37: 0.08 | AW37: 0.07 | AX37: 0.06 | AY37: 0.08 | AZ37: 0.08 | BA37: 0.06 | BB37: 0.1 | BC37: 0.08 | BD37: 0.08
A38: Physical stores | B38: Million | C38: 8-K | D38: 2640311 | U38: 0 | V38: 0 | W38: 1276 | X38: 4522 | Y38: 4263 | Z38: 4312 | AA38: 4248 | AB38: 4401 | AC38: 4307 | AD38: 4330 | AE38: 4192 | AF38: 4363 | AG38: 4640 | AH38: 3774 | AI38: 3788 | AJ38: 4022 | AK38: 3920 | AL38: 4198 | AM38: 4269 | AN38: 4688 | AO38: 4591 | AP38: 4721 | AQ38: 4694 | AR38: 4957 | AS38: 4895 | AT38: 5024 | AU38: 4959 | AV38: 5152 | AW38: 5202 | AX38: 5206 | AY38: 5228 | AZ38: 5579 | BA38: 5533 | BB38: 5595 | BC38: 5578 | BD38: 5855 | BJ38: =SUM(U38,V38,W38,X38) -> 5798 | BK38: =SUM(Y38,Z38,AA38,AB38) -> 17224 | BL38: =SUM(AC38,AD38,AE38,AF38) -> 17192 | BM38: =SUM(AG38,AH38,AI38,AJ38) -> 16224 | BN38: =SUM(AK38,AL38,AM38,AN38) -> 17075 | BO38: =SUM(AO38,AP38,AQ38,AR38) -> 18963 | BP38: 20030 | BQ38: 21215 | BR38: 22561
A39: Physical stores - Y/Y growth, excluding F/X | B39: Percent | C39: 8-K | D39: 85898 | Y39: 0 | Z39: 0 | AA39: 0 | AB39: -0.03 | AC39: 0.01 | AD39: 0.01 | AE39: -0.01 | AF39: -0.01 | AG39: 0.08 | AH39: -0.13 | AI39: -0.1 | AJ39: -0.07 | AK39: -0.16 | AL39: 0.1 | AM39: 0.12 | AN39: 0.16 | AO39: 0.16 | AP39: 0.13 | AQ39: 0.1 | AR39: 0.06 | AS39: 0.07 | AT39: 0.07 | AU39: 0.06 | AV39: 0.04 | AW39: 0.06 | AX39: 0.04 | AY39: 0.05 | AZ39: 0.08 | BA39: 0.06 | BB39: 0.07 | BC39: 0.07 | BD39: 0.05
A40: Third-party seller services | B40: Million | C40: 8-K | D40: 2640312 | Q40: 4801 | R40: 5083 | S40: 5652 | T40: 7456 | U40: 6438 | V40: 6991 | W40: 7928 | X40: 10523 | Y40: 9265 | Z40: 9702 | AA40: 10395 | AB40: 13383 | AC40: 11141 | AD40: 11962 | AE40: 13212 | AF40: 17446 | AG40: 14479 | AH40: 18195 | AI40: 20436 | AJ40: 27327 | AK40: 23709 | AL40: 25085 | AM40: 24252 | AN40: 30320 | AO40: 25335 | AP40: 27376 | AQ40: 28666 | AR40: 36339 | AS40: 29820 | AT40: 32332 | AU40: 34342 | AV40: 43559 | AW40: 34596 | AX40: 36201 | AY40: 37864 | AZ40: 47485 | BA40: 36512 | BB40: 40348 | BC40: 42486 | BD40: 52816 | BI40: =SUM(Q40,R40,S40,T40) -> 22992 | BJ40: =SUM(U40,V40,W40,X40) -> 31880 | BK40: =SUM(Y40,Z40,AA40,AB40) -> 42745 | BL40: =SUM(AC40,AD40,AE40,AF40) -> 53761 | BM40: =SUM(AG40,AH40,AI40,AJ40) -> 80437 | BN40: =SUM(AK40,AL40,AM40,AN40) -> 103366 | BO40: =SUM(AO40,AP40,AQ40,AR40) -> 117716 | BP40: 140053 | BQ40: 156146 | BR40: 172162
A41: Third-party seller services - Y/Y growth, excluding F/X | B41: Percent | C41: 8-K | D41: 85900 | Q41: 0.46 | R41: 0.48 | S41: 0.46 | T41: 0.39 | U41: 0.36 | V41: 0.4 | W41: 0.4 | X41: 0.38 | Y41: 0.39 | Z41: 0.36 | AA41: 0.32 | AB41: 0.28 | AC41: 0.23 | AD41: 0.25 | AE41: 0.28 | AF41: 0.31 | AG41: 0.31 | AH41: 0.53 | AI41: 0.53 | AJ41: 0.54 | AK41: 0.6 | AL41: 0.34 | AM41: 0.18 | AN41: 0.12 | AO41: 0.09 | AP41: 0.13 | AQ41: 0.23 | AR41: 0.24 | AS41: 0.2 | AT41: 0.18 | AU41: 0.18 | AV41: 0.19 | AW41: 0.16 | AX41: 0.13 | AY41: 0.1 | AZ41: 0.09 | BA41: 0.07 | BB41: 0.1 | BC41: 0.11 | BD41: 0.1
A42: Subscription services | B42: Million | C42: 8-K | D42: 2640313 | Q42: 1300 | R42: 1431 | S42: 1532 | T42: 2130 | U42: 1939 | V42: 2165 | W42: 2441 | X42: 3177 | Y42: 3102 | Z42: 3408 | AA42: 3698 | AB42: 3959 | AC42: 4342 | AD42: 4676 | AE42: 4957 | AF42: 5235 | AG42: 5556 | AH42: 6018 | AI42: 6572 | AJ42: 7061 | AK42: 7580 | AL42: 7917 | AM42: 8148 | AN42: 8123 | AO42: 8410 | AP42: 8716 | AQ42: 8903 | AR42: 9189 | AS42: 9657 | AT42: 9894 | AU42: 10170 | AV42: 10488 | AW42: 10722 | AX42: 10866 | AY42: 11278 | AZ42: 11508 | BA42: 11715 | BB42: 12208 | BC42: 12574 | BD42: 13122 | BI42: =SUM(Q42,R42,S42,T42) -> 6393 | BJ42: =SUM(U42,V42,W42,X42) -> 9722 | BK42: =SUM(Y42,Z42,AA42,AB42) -> 14167 | BL42: =SUM(AC42,AD42,AE42,AF42) -> 19210 | BM42: =SUM(AG42,AH42,AI42,AJ42) -> 25207 | BN42: =SUM(AK42,AL42,AM42,AN42) -> 31768 | BO42: =SUM(AO42,AP42,AQ42,AR42) -> 35218 | BP42: 40209 | BQ42: 44374 | BR42: 49619
A43: Subscription services - Y/Y growth, excluding F/X | B43: Percent | C43: 8-K | D43: 85902 | Q43: 0.56 | R43: 0.52 | S43: 0.47 | T43: 0.33 | U43: 0.52 | V43: 0.53 | W43: 0.59 | X43: 0.47 | Y43: 0.56 | Z43: 0.55 | AA43: 0.52 | AB43: 0.26 | AC43: 0.42 | AD43: 0.39 | AE43: 0.35 | AF43: 0.32 | AG43: 0.29 | AH43: 0.3 | AI43: 0.32 | AJ43: 0.34 | AK43: 0.34 | AL43: 0.28 | AM43: 0.23 | AN43: 0.16 | AO43: 0.13 | AP43: 0.14 | AQ43: 0.14 | AR43: 0.17 | AS43: 0.17 | AT43: 0.14 | AU43: 0.13 | AV43: 0.13 | AW43: 0.11 | AX43: 0.11 | AY43: 0.11 | AZ43: 0.1 | BA43: 0.11 | BB43: 0.11 | BC43: 0.1 | BD43: 0.12
A44: Advertising services | B44: Million | C44: 8-K | D44: 2489617 | AN44: 9716 | AO44: 7877 | AP44: 8757 | AQ44: 9548 | AR44: 11557 | AS44: 9509 | AT44: 10683 | AU44: 12060 | AV44: 14654 | AW44: 11824 | AX44: 12771 | AY44: 14331 | AZ44: 17288 | BA44: 13921 | BB44: 15694 | BC44: 17703 | BD44: 21317 | BO44: 37739 | BP44: 46906 | BQ44: 56214 | BR44: 68635
A45: Advertising services -- Y/Y growth, excluding F/X | B45: Percent | C45: 8-K | D45: 2489618 | AN45: 0.33 | AO45: 0.25 | AP45: 0.21 | AQ45: 0.3 | AR45: 0.23 | AS45: 0.23 | AT45: 0.22 | AU45: 0.25 | AV45: 0.26 | AW45: 0.24 | AX45: 0.2 | AY45: 0.19 | AZ45: 0.18 | BA45: 0.19 | BB45: 0.22 | BC45: 0.22 | BD45: 0.22
A46: AWS | B46: Million | C46: 8-K | D46: 2640314 | Q46: 2566 | R46: 2886 | S46: 3231 | T46: 3536 | U46: 3661 | V46: 4100 | W46: 4584 | X46: 5113 | Y46: 5442 | Z46: 6105 | AA46: 6679 | AB46: 7430 | AC46: 7696 | AD46: 8381 | AE46: 8995 | AF46: 9954 | AG46: 10219 | AH46: 10808 | AI46: 11601 | AJ46: 12742 | AK46: 13503 | AL46: 14809 | AM46: 16110 | AN46: 17780 | AO46: 18441 | AP46: 19739 | AQ46: 20538 | AR46: 21378 | AS46: 21354 | AT46: 22140 | AU46: 23059 | AV46: 24204 | AW46: 25037 | AX46: 26281 | AY46: 27452 | AZ46: 28786 | BA46: 29267 | BB46: 30873 | BC46: 33006 | BD46: 35579 | BI46: =SUM(Q46,R46,S46,T46) -> 12219 | BJ46: =SUM(U46,V46,W46,X46) -> 17458 | BK46: =SUM(Y46,Z46,AA46,AB46) -> 25656 | BL46: =SUM(AC46,AD46,AE46,AF46) -> 35026 | BM46: =SUM(AG46,AH46,AI46,AJ46) -> 45370 | BN46: =SUM(AK46,AL46,AM46,AN46) -> 62202 | BO46: 80096 | BP46: 90757 | BQ46: 107556 | BR46: 128725
A47: AWS - Y/Y growth, excluding F/X | B47: Percent | C47: 8-K | D47: 85904 | Q47: 0.64 | R47: 0.58 | S47: 0.55 | T47: 0.47 | U47: 0.43 | V47: 0.42 | W47: 0.42 | X47: 0.44 | Y47: 0.49 | Z47: 0.49 | AA47: 0.46 | AB47: 0.46 | AC47: 0.42 | AD47: 0.37 | AE47: 0.35 | AF47: 0.34 | AG47: 0.33 | AH47: 0.29 | AI47: 0.29 | AJ47: 0.28 | AK47: 0.32 | AL47: 0.37 | AM47: 0.39 | AN47: 0.4 | AO47: 0.37 | AP47: 0.33 | AQ47: 0.28 | AR47: 0.2 | AS47: 0.16 | AT47: 0.12 | AU47: 0.12 | AV47: 0.13 | AW47: 0.17 | AX47: 0.19 | AY47: 0.19 | AZ47: 0.19 | BA47: 0.17 | BB47: 0.17 | BC47: 0.2 | BD47: 0.24
A48: Other | B48: Million | C48: 8-K | D48: 2640315 | Q48: 545 | R48: 626 | S48: 709 | T48: 1071 | U48: 850 | V48: 945 | W48: 1123 | X48: 1735 | Y48: 2031 | Z48: 2194 | AA48: 2495 | AB48: 3388 | AC48: 2716 | AD48: 3002 | AE48: 3586 | AF48: 4782 | AG48: 3906 | AH48: 4221 | AI48: 5398 | AJ48: 7952 | AK48: 6905 | AL48: 7914 | AM48: 8091 | AN48: 710 | AO48: 661 | AP48: 1070 | AQ48: 1263 | AR48: 1253 | AS48: 1027 | AT48: 1344 | AU48: 1226 | AV48: 1361 | AW48: 1262 | AX48: 1260 | AY48: 1313 | AZ48: 1590 | BA48: 1312 | BB48: 1499 | BC48: 1415 | BD48: 1709 | BI48: =SUM(Q48,R48,S48,T48) -> 2951 | BJ48: =SUM(U48,V48,W48,X48) -> 4653 | BK48: =SUM(Y48,Z48,AA48,AB48) -> 10108 | BL48: =SUM(AC48,AD48,AE48,AF48) -> 14086 | BM48: =SUM(AG48,AH48,AI48,AJ48) -> 21477 | BN48: =SUM(AK48,AL48,AM48,AN48) -> 23620 | BO48: =SUM(AO48,AP48,AQ48,AR48) -> 4247 | BP48: 4958 | BQ48: 5425 | BR48: 5935
A49: Other - Y/Y growth, excluding F/X | B49: Percent | C49: 8-K | D49: 85906 | Q49: 0.46 | R49: 0.65 | S49: 0.74 | T49: 0.99 | U49: 0.58 | V49: 0.53 | W49: 0.58 | X49: 0.6 | Y49: 1.32 | Z49: 1.29 | AA49: 1.23 | AB49: 0.97 | AC49: 0.36 | AD49: 0.37 | AE49: 0.45 | AF49: 0.41 | AG49: 0.44 | AH49: 0.41 | AI49: 0.49 | AJ49: 0.64 | AK49: 0.73 | AL49: 0.83 | AM49: 0.49 | AN49: 0.19 | AO49: 0.28 | AP49: 1.35 | AQ49: 1.68 | AR49: 0.8 | AS49: 0.57 | AT49: 0.26 | AU49: -0.03 | AV49: 0.08 | AW49: 0.23 | AX49: -0.06 | AY49: 0.05 | AZ49: 0.17 | BA49: 0.04 | BB49: 0.18 | BC49: 0.07 | BD49: 0.07
A51: Net sales
A52: Media | B52: Million | C52: 10-Q | D52: 2640316 | E52: 5058 | F52: 4397 | G52: 5033 | H52: =BF52-SUM(E52,F52,G52) -> 7228 | I52: 5467 | J52: 4844 | K52: 5244 | L52: =BG52-SUM(I52,J52,K52) -> 6950 | M52: 5289 | N52: 4714 | O52: 5283 | P52: =BH52-SUM(M52,N52,O52) -> 7223 | Q52: 5688 | R52: 5211 | S52: 5728 | BF52: 21716 | BG52: 22505 | BH52: 22509
A53: Electronics and other general merchandise | B53: Million | C53: 10-Q | D53: 2640317 | E53: 10214 | F53: 10415 | G53: 11048 | H53: =BF53-SUM(E53,F53,G53) -> 17125 | I53: 13017 | J53: 13278 | K53: 13953 | L53: =BG53-SUM(I53,J53,K53) -> 20638 | M53: 15628 | N53: 16412 | O53: 17741 | P53: =BH53-SUM(M53,N53,O53) -> 25816 | Q53: 20545 | R53: 21963 | S53: 23383 | BF53: 48802 | BG53: 60886 | BH53: 75597
A54: Online stores | B54: Million | C54: 10-K | D54: 2640318 | U54: 22826 | V54: 23754 | W54: 26392 | X54: =BJ54-SUM(U54,V54,W54) -> 35382 | Y54: 26939 | Z54: 27165 | AA54: 29061 | AB54: =BK54-SUM(Y54,Z54,AA54) -> 39822 | AC54: 29498 | AD54: 31053 | AE54: 35039 | AF54: =BL54-SUM(AC54,AD54,AE54) -> 45657 | AG54: 36652 | AH54: 45896 | AI54: 48350 | AJ54: =BM54-SUM(AG54,AH54,AI54) -> 66448 | AK54: 52901 | AL54: 53157 | AM54: 49942 | AN54: =BN54-SUM(AK54,AL54,AM54) -> 66075 | AO54: 51129 | AP54: 50855 | AQ54: 53489 | AR54: =BO54-SUM(AO54,AP54,AQ54) -> 64531 | AS54: 51096 | AT54: 52966 | AU54: 57267 | AV54: 70543 | AW54: 54670 | AX54: 55392 | AY54: 61411 | AZ54: 75556 | BA54: 57407 | BB54: 61485 | BC54: 67407 | BI54: 91431 | BJ54: 108354 | BK54: 122987 | BL54: 141247 | BM54: 197346 | BN54: 222075 | BO54: 220004 | BP54: 231872 | BQ54: 247029 | BR54: =BR36 -> 269287
A55: Physical stores | B55: Million | C55: 10-K | D55: 2640319 | U55: 0 | V55: 0 | W55: 1276 | X55: =BJ55-SUM(U55,V55,W55) -> 4522 | Y55: 4263 | Z55: 4312 | AA55: 4248 | AB55: =BK55-SUM(Y55,Z55,AA55) -> 4401 | AC55: 4307 | AD55: 4330 | AE55: 4192 | AF55: =BL55-SUM(AC55,AD55,AE55) -> 4363 | AG55: 4640 | AH55: 3774 | AI55: 3788 | AJ55: =BM55-SUM(AG55,AH55,AI55) -> 4025 | AK55: 3920 | AL55: 4198 | AM55: 4269 | AN55: =BN55-SUM(AK55,AL55,AM55) -> 4688 | AO55: 4591 | AP55: 4721 | AQ55: 4694 | AR55: =BO55-SUM(AO55,AP55,AQ55) -> 4957 | AS55: 4895 | AT55: 5024 | AU55: 4959 | AV55: 5152 | AW55: 5202 | AX55: 5206 | AY55: 5228 | AZ55: 5579 | BA55: 5533 | BB55: 5595 | BC55: 5578 | BJ55: 5798 | BK55: 17224 | BL55: 17192 | BM55: 16227 | BN55: 17075 | BO55: 18963 | BP55: 20030 | BQ55: 21215 | BR55: =BR38 -> 22561
A56: Third-party seller services | B56: Million | C56: 10-K | D56: 2640320 | U56: 6438 | V56: 6991 | W56: 7928 | X56: =BJ56-SUM(U56,V56,W56) -> 10524 | Y56: 9265 | Z56: 9702 | AA56: 10395 | AB56: =BK56-SUM(Y56,Z56,AA56) -> 13383 | AC56: 11141 | AD56: 11962 | AE56: 13212 | AF56: =BL56-SUM(AC56,AD56,AE56) -> 17447 | AG56: 14479 | AH56: 18195 | AI56: 20436 | AJ56: =BM56-SUM(AG56,AH56,AI56) -> 27351 | AK56: 23709 | AL56: 25085 | AM56: 24252 | AN56: =BN56-SUM(AK56,AL56,AM56) -> 30320 | AO56: 25335 | AP56: 27376 | AQ56: 28666 | AR56: =BO56-SUM(AO56,AP56,AQ56) -> 36339 | AS56: 29820 | AT56: 32332 | AU56: 34342 | AV56: 43559 | AW56: 34596 | AX56: 36201 | AY56: 37864 | AZ56: 47485 | BA56: 36512 | BB56: 40348 | BC56: 42486 | BI56: 22993 | BJ56: 31881 | BK56: 42745 | BL56: 53762 | BM56: 80461 | BN56: 103366 | BO56: 117716 | BP56: 140053 | BQ56: 156146 | BR56: =BR40 -> 172162
A57: Subscription services | B57: Million | C57: 10-K | D57: 2640321 | U57: 1939 | V57: 2165 | W57: 2441 | X57: =BJ57-SUM(U57,V57,W57) -> 3176 | Y57: 3102 | Z57: 3408 | AA57: 3698 | AB57: =BK57-SUM(Y57,Z57,AA57) -> 3960 | AC57: 4342 | AD57: 4676 | AE57: 4957 | AF57: =BL57-SUM(AC57,AD57,AE57) -> 5235 | AG57: 5556 | AH57: 6018 | AI57: 6572 | AJ57: =BM57-SUM(AG57,AH57,AI57) -> 7061 | AK57: 7580 | AL57: 7917 | AM57: 8148 | AN57: =BN57-SUM(AK57,AL57,AM57) -> 8123 | AO57: 8410 | AP57: 8716 | AQ57: 8903 | AR57: =BO57-SUM(AO57,AP57,AQ57) -> 9189 | AS57: 9657 | AT57: 9894 | AU57: 10170 | AV57: 10488 | AW57: 10722 | AX57: 10866 | AY57: 11278 | AZ57: 11508 | BA57: 11715 | BB57: 12208 | BC57: 12574 | BD57: 13122 | BI57: 6394 | BJ57: 9721 | BK57: 14168 | BL57: 19210 | BM57: 25207 | BN57: 31768 | BO57: 35218 | BP57: 40209 | BQ57: 44374 | BR57: =BR42 -> 49619
A58: Advertising services | B58: Million | C58: 10-K | D58: 2492330 | AO58: 7877 | AP58: 8757 | AQ58: 9548 | AR58: =BO58-SUM(AO58,AP58,AQ58) -> 11557 | AS58: 9509 | AT58: 10683 | AU58: 12060 | AV58: 14654 | AW58: 11824 | AX58: 12771 | AY58: 14331 | AZ58: 17288 | BA58: 13921 | BB58: 15694 | BC58: 17703 | BD58: 21317 | BN58: 31160 | BO58: 37739 | BP58: 46906 | BQ58: 56214 | BR58: 68635
A59: AWS | B59: Million | C59: 10-K | D59: 2640322 | M59: 1566 | N59: 1824 | O59: 2085 | P59: =BH59-SUM(M59,N59,O59) -> 2405 | Q59: 2566 | R59: 2886 | S59: 3231 | T59: =BI59-SUM(Q59,R59,S59) -> 3536 | U59: 3661 | V59: 4100 | W59: 4584 | X59: =BJ59-SUM(U59,V59,W59) -> 5114 | Y59: 5442 | Z59: 6105 | AA59: 6679 | AB59: =BK59-SUM(Y59,Z59,AA59) -> 7429 | AC59: 7696 | AD59: 8381 | AE59: 8995 | AF59: =BL59-SUM(AC59,AD59,AE59) -> 9954 | AG59: 10219 | AH59: 10808 | AI59: 11601 | AJ59: =BM59-SUM(AG59,AH59,AI59) -> 12742 | AK59: 13503 | AL59: 14809 | AM59: 16110 | AN59: =BN59-SUM(AK59,AL59,AM59) -> 17780 | AO59: 18441 | AP59: 19739 | AQ59: 20538 | AR59: =BO59-SUM(AO59,AP59,AQ59) -> 21378 | AS59: 21354 | AT59: 22140 | AU59: 23059 | AV59: 24204 | AW59: 25037 | AX59: 26281 | AY59: 27452 | AZ59: 28786 | BA59: 29267 | BB59: 30873 | BC59: 33006 | BD59: 35579 | BH59: 7880 | BI59: 12219 | BJ59: 17459 | BK59: 25655 | BL59: 35026 | BM59: 45370 | BN59: 62202 | BO59: 80096 | BP59: 90757 | BQ59: 107556 | BR59: 128725
A60: Other (Including advertising service) | B60: Million | C60: 10-Q | D60: 3517107 | E60: 798 | F60: 892 | G60: 1011 | H60: =BF60-SUM(E60,F60,G60) -> 1233 | I60: 1257 | J60: 1218 | K60: 1382 | L60: =BG60-SUM(I60,J60,K60) -> 1740 | M60: 234 | N60: 235 | O60: 249 | P60: =BH60-SUM(M60,N60,O60) -> 302 | Q60: 329 | R60: 344 | S60: 372 | T60: =BI60-SUM(Q60,R60,S60) -> 1905 | U60: 850 | V60: 945 | W60: 1123 | X60: =BJ60-SUM(U60,V60,W60) -> 1735 | Y60: 2031 | Z60: 2194 | AA60: 2495 | AB60: =BK60-SUM(Y60,Z60,AA60) -> 3388 | AC60: 2716 | AD60: 3002 | AE60: 3586 | AF60: =BL60-SUM(AC60,AD60,AE60) -> 4781 | AG60: 3906 | AH60: 4221 | AI60: 5398 | AJ60: =BM60-SUM(AG60,AH60,AI60) -> 7928 | AK60: 6905 | AL60: 7914 | AM60: 8091 | BF60: 3934 | BG60: 5597 | BH60: 1020 | BI60: 2950 | BJ60: 4653 | BK60: 10108 | BL60: 14085 | BM60: 21453
A61: Other (excluding advertising service) | B61: Million | C61: 10-K | D61: 3517108 | AO61: 661 | AP61: 1070 | AQ61: 1263 | AR61: =BO61-SUM(AO61,AP61,AQ61) -> 1253 | AS61: 1027 | AT61: 1344 | AU61: 1226 | AV61: 1361 | AW61: 1262 | AX61: 1260 | AY61: 1313 | AZ61: 1590 | BA61: 1312 | BB61: 1499 | BC61: 1415 | BD61: 1709 | BN61: 2176 | BO61: 4247 | BP61: 4958 | BQ61: 5425 | BR61: =BR48 -> 5935
A62: Consolidated | B62: Million | C62: 10-K | D62: 2640324 | E62: =SUM(E52:E61) -> 16070 | F62: =SUM(F52:F61) -> 15704 | G62: =SUM(G52:G61) -> 17092 | H62: =BF62-SUM(E62,F62,G62) -> 25586 | I62: =SUM(I52:I61) -> 19741 | J62: =SUM(J52:J61) -> 19340 | K62: =SUM(K52:K61) -> 20579 | L62: =BG62-SUM(I62,J62,K62) -> 29328 | M62: =SUM(M52:M61) -> 22717 | N62: =SUM(N52:N61) -> 23185 | O62: =SUM(O52:O61) -> 25358 | P62: =BH62-SUM(M62,N62,O62) -> 35746 | Q62: =SUM(Q52:Q61) -> 29128 | R62: =SUM(R52:R61) -> 30404 | S62: =SUM(S52:S61) -> 32714 | T62: =BI62-SUM(Q62,R62,S62) -> 43741 | U62: =SUM(U52:U61) -> 35714 | V62: =SUM(V52:V61) -> 37955 | W62: =SUM(W52:W61) -> 43744 | X62: =BJ62-SUM(U62,V62,W62) -> 60453 | Y62: =SUM(Y52:Y61) -> 51042 | Z62: =SUM(Z52:Z61) -> 52886 | AA62: =SUM(AA52:AA61) -> 56576 | AB62: =BK62-SUM(Y62,Z62,AA62) -> 72383 | AC62: =SUM(AC52:AC61) -> 59700 | AD62: =SUM(AD52:AD61) -> 63404 | AE62: =SUM(AE52:AE61) -> 69981 | AF62: =BL62-SUM(AC62,AD62,AE62) -> 87437 | AG62: =SUM(AG52:AG61) -> 75452 | AH62: =SUM(AH52:AH61) -> 88912 | AI62: =SUM(AI52:AI61) -> 96145 | AJ62: =BM62-SUM(AG62,AH62,AI62) -> 125555 | AK62: =SUM(AK52:AK61) -> 108518 | AL62: =SUM(AL52:AL61) -> 113080 | AM62: =SUM(AM52:AM61) -> 110812 | AN62: =BN62-SUM(AK62,AL62,AM62) -> 137412 | AO62: =SUM(AO52:AO61) -> 116444 | AP62: =SUM(AP52:AP61) -> 121234 | AQ62: =SUM(AQ52:AQ61) -> 127101 | AR62: =BO62-SUM(AO62,AP62,AQ62) -> 149204 | AS62: 127358 | AT62: 134383 | AU62: 143083 | AV62: 169961 | AW62: 143313 | AX62: 147977 | AY62: 158877 | AZ62: 187792 | BA62: 155667 | BB62: 167702 | BC62: 180169 | BD62: 213386 | BF62: =SUM(BF52:BF61) -> 74452 | BG62: =SUM(BG52:BG61) -> 88988 | BH62: =SUM(BH52:BH61) -> 107006 | BI62: =SUM(BI52:BI61) -> 135987 | BJ62: =SUM(BJ52:BJ61) -> 177866 | BK62: =SUM(BK52:BK61) -> 232887 | BL62: =SUM(BL52:BL61) -> 280522 | BM62: =SUM(BM52:BM61) -> 386064 | BN62: =SUM(BN52:BN61) -> 469822 | BO62: 513983 | BP62: 574785 | BQ62: 637959 | BR62: 716924
A64: Geographical breakdown
A65: Segment information
A66: North America
A67: Net sales | B67: Million | C67: 8-K | D67: 85908 | E67: 9391 | F67: 9495 | G67: 10301 | H67: 15331 | I67: 11858 | J67: 11998 | K67: 12867 | L67: 18747 | M67: 13406 | N67: 13796 | O67: 15006 | P67: 21501 | Q67: 16996 | R67: 17674 | S67: 18874 | T67: 26240 | U67: 20992 | V67: 22370 | W67: 25446 | X67: 37302 | Y67: 30725 | Z67: 32169 | AA67: 34348 | AB67: 44124 | AC67: 35812 | AD67: 38653 | AE67: 42638 | AF67: 53670 | AG67: 46127 | AH67: 55436 | AI67: 59373 | AJ67: 75346 | AK67: 64366 | AL67: 67550 | AM67: 65557 | AN67: 82360 | AO67: 69244 | AP67: 74430 | AQ67: 78843 | AR67: 93363 | AS67: 76881 | AT67: 82546 | AU67: 87887 | AV67: 105514 | AW67: 86341 | AX67: 90033 | AY67: 95537 | AZ67: 115586 | BA67: 92887 | BB67: 100068 | BC67: 106267 | BD67: 127083 | BF67: 44517 | BG67: 55469 | BH67: 63708 | BI67: 79785 | BJ67: 106110 | BK67: 141366 | BL67: 170773 | BM67: 236282 | BN67: 279833 | BO67: 315880 | BP67: 352828 | BQ67: 387497 | BR67: 426305
A68: Segment operating expenses | B68: Million | C68: 8-K | D68: 85909 | E68: 8934 | F68: 9086 | G68: 10006 | H68: 14606 | I68: 11296 | J68: 11560 | K68: 12779 | L68: 17729 | M68: 12889 | N68: 13093 | O68: 14478 | P68: 20498 | Q68: 16072 | R68: 16517 | S68: 18180 | T68: 24916 | U68: 20396 | V68: 21934 | W68: 25334 | X68: 35610 | Y68: 29576 | Z68: 30334 | AA68: 32316 | AB68: 41873 | AC68: 33525 | AD68: 37089 | AE68: 41356 | AF68: 51770 | AG68: 44815 | AH68: 53295 | AI68: 57121 | AJ68: 72400 | AK68: 60916 | AL68: 64403 | AM68: 64677 | AN68: 82566 | AO68: 70812 | AP68: 75057 | AQ68: 79255 | AR68: 93603 | AS68: 75983 | AT68: 79335 | AU68: 83580 | AV68: 99053 | AW68: 81358 | AX68: 84968 | AY68: 89874 | AZ68: 106330 | BA68: 87046 | BB68: 92551 | BC68: 101478 | BD68: 115611 | BF68: 42631 | BG68: 53364 | BH68: 60957 | BI68: 75686 | BJ68: 103273 | BK68: 134099 | BL68: 163740 | BM68: 227631 | BN68: 272562 | BO68: 318727 | BP68: 337951 | BQ68: 362530 | BR68: 396686
A69: Segment operating income (loss) before stock-based compensation and other | B69: Million | C69: 8-K | D69: 85910 | Q69: =Q67-Q68 -> 924 | R69: =R67-R68 -> 1157 | S69: =S67-S68 -> 694 | T69: =T67-T68 -> 1324 | BI69: =BI67-BI68 -> 4099
A71: Stock-based compensation and other | B71: Million | C71: 8-K | D71: 85911 | Q71: 336 | R71: 455 | S71: 439 | T71: 508 | BI71: 1738
A72: Segment operating income (loss) | B72: Million | C72: 8-K | D72: 85912 | E72: =E67-E68-E71 -> 457 | F72: =F67-F68-F71 -> 409 | G72: =G67-G68-G71 -> 295 | H72: =H67-H68-H71 -> 725 | I72: =I67-I68-I71 -> 562 | J72: =J67-J68-J71 -> 438 | K72: =K67-K68-K71 -> 88 | L72: =L67-L68-L71 -> 1018 | ... AR72: =AR67-AR68-AR71 -> -240 | AS72: 898 | AT72: 3211 | AU72: 4307 | AV72: 6461 | AW72: 4983 | AX72: 5065 | AY72: 5663 | AZ72: 9256 | BA72: 5841 | BB72: 7517 | BC72: 4789 | BD72: 11472 | BF72: =BF67-BF68-BF71 -> 1886 | BG72: =BG67-BG68-BG71 -> 2105 | BH72: =BH67-BH68-BH71 -> 2751 | BI72: =BI67-BI68-BI71 -> 2361 | BJ72: =BJ67-BJ68-BJ71 -> 2837 | BK72: =BK67-BK68-BK71 -> 7267 | BL72: =BL67-BL68-BL71 -> 7033 | BM72: =BM67-BM68-BM71 -> 8651 | BN72: =BN67-BN68-BN71 -> 7271 | BO72: -2847 | BP72: 14877 | BQ72: 24967 | BR72: 29619
A74: International
A75: Net sales | B75: Million | C75: 8-K | D75: 85913 | E75: 6679 | F75: 6209 | G75: 6791 | H75: 10256 | I75: 7883 | J75: 7342 | K75: 7712 | L75: 10581 | M75: 7745 | N75: 7565 | O75: 8267 | P75: 11841 | Q75: 9566 | R75: 9844 | S75: 10609 | T75: 13965 | U75: 11061 | V75: 11485 | W75: 13714 | X75: 18038 | Y75: 14875 | Z75: 14612 | AA75: 15549 | AB75: 20829 | AC75: 16192 | AD75: 16370 | AE75: 18348 | AF75: 23813 | AG75: 19106 | AH75: 22668 | AI75: 25171 | AJ75: 37467 | AK75: 30649 | AL75: 30721 | AM75: 29145 | AN75: 37272 | AO75: 28759 | AP75: 27065 | AQ75: 27720 | AR75: 34463 | AS75: 29123 | AT75: 29697 | AU75: 32137 | AV75: 40243 | AW75: 31935 | AX75: 31663 | AY75: 35888 | AZ75: 43420 | BA75: 33513 | BB75: 36761 | BC75: 40896 | BD75: 50724 | BF75: 29935 | BG75: 33519 | BH75: 35418 | BI75: 43983 | BJ75: 54297 | BK75: 65866 | BL75: 74723 | BM75: 104412 | BN75: 127787 | BO75: 118007 | BP75: 131200 | BQ75: 142906 | BR75: 161894
A76: Segment operating expenses | B76: Million | C76: 8-K | D76: 85914 | E76: 6695 | F76: 6209 | G76: 6819 | H76: 10105 | I76: 7943 | J76: 7376 | K76: 7936 | L76: 10561 | M76: 7821 | N76: 7584 | O76: 8323 | P76: 11781 | Q76: 9546 | R76: 9756 | S76: 10941 | T76: 14219 | U76: 11542 | V76: 12209 | W76: 14650 | X76: 18957 | Y76: 15497 | Z76: 15106 | AA76: 15934 | AB76: 21471 | AC76: 16282 | AD76: 16971 | AE76: 18734 | AF76: 24430 | AG76: 19504 | AH76: 22323 | AI76: 24764 | AJ76: 37104 | AK76: 29397 | AL76: 30359 | AM76: 30056 | AN76: 38899 | AO76: 30040 | AP76: 28836 | AQ76: 30186 | AR76: 36691 | AS76: 30370 | AT76: 30592 | AU76: 32232 | AV76: 40662 | AW76: 31032 | AX76: 31390 | AY76: 34587 | AZ76: 42105 | BA76: 32496 | BB76: 35267 | BC76: 39697 | BD76: 49684 | BF76: 29828 | BG76: 33816 | BH76: 35509 | BI76: 44460 | BJ76: 57359 | BK76: 68008 | BL76: 76416 | BM76: 103695 | BN76: 128711 | BO76: 125753 | BP76: 133856 | BQ76: 139114 | BR76: 157144
A77: Segment operating income (loss) before stock-based compensation and other | B77: Million | C77: 8-K | D77: 85915 | Q77: =Q75-Q76 -> 20 | R77: =R75-R76 -> 88 | S77: =S75-S76 -> -332 | T77: =T75-T76 -> -254 | BI77: =BI75-BI76 -> -477
A79: Stock-based compensation and other | B79: Million | C79: 8-K | D79: 85916 | Q79: 141 | R79: 223 | S79: 209 | T79: 233 | BI79: 806
A80: Segment operating income (loss) | B80: Million | C80: 8-K | D80: 85917 | E80: =E75-E76-E79 -> -16 | F80: 0 | G80: =G75-G76-G79 -> -28 | H80: =H75-H76-H79 -> 151 | I80: =I75-I76-I79 -> -60 | J80: =J75-J76-J79 -> -34 | K80: =K75-K76-K79 -> -224 | L80: =L75-L76-L79 -> 20 | M80: =M75-M76-M79 -> -76 | N80: =N75-N76-N79 -> -19 | ... AR80: =AR75-AR76-AR79 -> -2228 | AS80: -1247 | AT80: -895 | AU80: -95 | AV80: -419 | AW80: 903 | AX80: 273 | AY80: 1301 | AZ80: 1315 | BA80: 1017 | BB80: 1494 | BC80: 1199 | BD80: 1040 | BF80: =BF75-BF76-BF79 -> 107 | BG80: =BG75-BG76-BG79 -> -297 | BH80: =BH75-BH76-BH79 -> -91 | BI80: =BI75-BI76-BI79 -> -1283 | BJ80: =BJ75-BJ76-BJ79 -> -3062 | BK80: =BK75-BK76-BK79 -> -2142 | BL80: =BL75-BL76-BL79 -> -1693 | BM80: =BM75-BM76-BM79 -> 717 | BN80: =BN75-BN76-BN79 -> -924 | BO80: -7746 | BP80: -2656 | BQ80: 3792 | BR80: 4750
A82: AWS
A83: Net sales | B83: Million | C83: 8-K | D83: 85918 | M83: 1566 | N83: 1824 | O83: 2085 | P83: 2405 | Q83: 2566 | R83: 2886 | S83: 3231 | T83: 3536 | U83: 3661 | V83: 4100 | W83: 4584 | X83: 5113 | Y83: 5442 | Z83: 6105 | AA83: 6679 | AB83: 7430 | AC83: 7696 | AD83: 8381 | AE83: 8995 | AF83: 9954 | AG83: 10219 | AH83: 10808 | AI83: 11601 | AJ83: 12742 | AK83: 13503 | AL83: 14809 | AM83: 16110 | AN83: 17780 | AO83: 18441 | AP83: 19739 | AQ83: 20538 | AR83: 21378 | AS83: 21354 | AT83: 22140 | AU83: 23059 | AV83: 24204 | AW83: 25037 | AX83: 26281 | AY83: 27452 | AZ83: 28786 | BA83: 29267 | BB83: 30873 | BC83: 33006 | BD83: 35579 | BH83: 7880 | BI83: 12219 | BJ83: 17459 | BK83: 25655 | BL83: 35026 | BM83: 45370 | BN83: 62202 | BO83: 80096 | BP83: 90757 | BQ83: 107556 | BR83: 128725
A84: Segment operating expenses | B84: Million | C84: 8-K | D84: 85919 | M84: 1301 | N84: 1433 | O84: 1564 | P84: 1718 | Q84: 1850 | R84: 2023 | S84: 2210 | T84: 2430 | U84: 2771 | V84: 3184 | W84: 3413 | X84: 3759 | Y84: 4042 | Z84: 4463 | AA84: 4602 | AB84: 5253 | AC84: 5473 | AD84: 6260 | AE84: 6734 | AF84: 7358 | AG84: 7144 | AH84: 7451 | AI84: 8066 | AJ84: 9178 | AK84: 9340 | AL84: 10616 | AM84: 11227 | AN84: 12487 | AO84: 11923 | AP84: 14024 | AQ84: 15135 | AR84: 16173 | AS84: 16231 | AT84: 16775 | AU84: 16083 | AV84: 17037 | AW84: 15616 | AX84: 16947 | AY84: 17005 | AZ84: 18154 | BA84: 17720 | BB84: 20713 | BC84: 21572 | BD84: 23114 | BH84: 6017 | BI84: 8513 | BJ84: 13128 | BK84: 18359 | BL84: 25825 | BM84: 31839 | BN84: 43670 | BO84: 57255 | BP84: 66126 | BQ84: 67722 | BR84: 83119
A85: Segment operating income (loss) before stock-based compensation and other | B85: Million | C85: 8-K | D85: 85920 | Q85: =Q83-Q84 -> 716 | R85: =R83-R84 -> 863 | S85: =S83-S84 -> 1021 | T85: =T83-T84 -> 1106 | BI85: =BI83-BI84 -> 3706
A87: Stock-based compensation and other | B87: Million | C87: 8-K | D87: 85921 | Q87: 112 | R87: 145 | S87: 160 | T87: 180 | BI87: 598
A88: Segment operating income (loss) | B88: Million | C88: 8-K | D88: 85922 | M88: =M83-M84-M87 -> 265 | N88: =N83-N84-N87 -> 391 | O88: =O83-O84-O87 -> 521 | P88: =P83-P84-P87 -> 687 | Q88: =Q83-Q84-Q87 -> 604 | R88: =R83-R84-R87 -> 718 | S88: =S83-S84-S87 -> 861 | T88: =T83-T84-T87 -> 926 | ... AR88: =AR83-AR84-AR87 -> 5205 | AS88: 5123 | AT88: 5365 | AU88: 6976 | AV88: 7167 | AW88: 9421 | AX88: 9334 | AY88: 10447 | AZ88: 10632 | BA88: 11547 | BB88: 10160 | BC88: 11434 | BD88: 12465 | BH88: =BH83-BH84-BH87 -> 1863 | BI88: =BI83-BI84-BI87 -> 3108 | BJ88: =BJ83-BJ84-BJ87 -> 4331 | BK88: =BK83-BK84-BK87 -> 7296 | BL88: =BL83-BL84-BL87 -> 9201 | BM88: =BM83-BM84-BM87 -> 13531 | BN88: =BN83-BN84-BN87 -> 18532 | BO88: 22841 | BP88: 24631 | BQ88: 39834 | BR88: 45606
A90: Consolidated
A91: Net sales | B91: Million | C91: 8-K | D91: 85923 | E91: 16070 | F91: 15704 | G91: 17092 | H91: 25587 | I91: 19741 | J91: 19340 | K91: 20579 | L91: 29328 | M91: 22717 | N91: 23185 | O91: 25358 | P91: 35747 | Q91: 29128 | R91: 30404 | S91: 32714 | T91: 43741 | U91: 35714 | V91: 37955 | W91: 43744 | X91: 60453 | Y91: 51042 | Z91: 52886 | AA91: 56576 | AB91: 72383 | AC91: 59700 | AD91: 63404 | AE91: 69981 | AF91: 87437 | AG91: 75452 | AH91: 88912 | AI91: 96145 | AJ91: 125555 | AK91: 108518 | AL91: 113080 | AM91: 110812 | AN91: 137412 | AO91: 116444 | AP91: 121234 | AQ91: 127101 | AR91: 149204 | AS91: 127358 | AT91: 134383 | AU91: 143083 | AV91: 169961 | AW91: 143313 | AX91: 147977 | AY91: 158877 | AZ91: 187792 | BA91: 155667 | BB91: 167702 | BC91: 180169 | BD91: 213386 | BF91: 74452 | BG91: 88988 | BH91: 107006 | BI91: 135987 | BJ91: 177866 | BK91: 232887 | BL91: 280522 | BM91: 386064 | BN91: 469822 | BO91: 513983 | BP91: 574785 | BQ91: 637959 | BR91: 716924
A92: Segment operating expenses | B92: Million | C92: 8-K | D92: 85924 | E92: 15629 | F92: 15295 | G92: 16825 | H92: 24711 | I92: 19239 | J92: 18936 | K92: 20715 | L92: 28290 | M92: 22011 | N92: 22110 | O92: 24365 | P92: 33997 | Q92: 27468 | R92: 28296 | S92: 31331 | T92: 41565 | U92: 34709 | V92: 37327 | W92: 43397 | X92: 58326 | Y92: 49115 | Z92: 49903 | AA92: 52852 | AB92: 68597 | AC92: 55280 | AD92: 60320 | AE92: 66824 | AF92: 83558 | AG92: 71463 | AH92: 83069 | AI92: 89951 | AJ92: 118682 | AK92: 99653 | AL92: 105378 | AM92: 105960 | AN92: 133952 | AO92: 112775 | AP92: 117917 | AQ92: 124576 | AR92: 146467 | AS92: 122584 | AT92: 126702 | AU92: 131895 | AV92: 156752 | AW92: 128006 | AX92: 133305 | AY92: 141466 | AZ92: 166589 | BA92: 137262 | BB92: 148531 | BC92: 162747 | BD92: 188409 | BF92: 72459 | BG92: 87180 | BH92: 102483 | BI92: 128659 | BJ92: 173760 | BK92: 220466 | BL92: 265981 | BM92: 363165 | BN92: 444943 | BO92: 501735 | BP92: 537933 | BQ92: 569366 | BR92: 636949
A93: Segment operating income (loss) before stock-based compensation and other | B93: Million | C93: 8-K | D93: 85925 | E93: =E91-E92 -> 441 | F93: =F91-F92 -> 409 | G93: =G91-G92 -> 267 | H93: =H91-H92 -> 876 | I93: =I91-I92 -> 502 | J93: =J91-J92 -> 404 | K93: =K91-K92 -> -136 | L93: =L91-L92 -> 1038 | ... T93: =T91-T92 -> 2176 | BF93: =BF91-BF92 -> 1993 | BG93: =BG91-BG92 -> 1808 | BH93: =BH91-BH92 -> 4523 | BI93: =BI91-BI92 -> 7328
A95: Stock-based compensation | B95: Million | C95: 8-K | D95: 85926 | E95: -229 | F95: -298 | G95: -281 | H95: -326 | I95: -321 | J95: -391 | K95: -377 | L95: -408 | M95: -407 | N95: -563 | O95: -544 | P95: -606 | Q95: -589 | R95: -823 | S95: -808 | T95: -921 | BF95: -1134 | BG95: -1497 | BH95: -2119 | BI95: -3142
A96: Other operating income (expense), net | B96: Million | C96: 8-K | D96: 85927 | E96: -31 | F96: -32 | G96: -11 | H96: -40 | I96: -35 | J96: -28 | K96: -31 | L96: -39 | M96: -44 | N96: -48 | O96: -43 | P96: -36 | AS96: 223 | AT96: 146 | AU96: 244 | AV96: 154 | AW96: 228 | AX96: 97 | AY96: 262 | AZ96: 176 | BA96: 308 | BB96: 199 | BC96: 2875 | BD96: 1257 | BF96: -114 | BG96: -133 | BH96: -171 | BO96: 1263 | BP96: 767 | BQ96: 763 | BR96: 4639
A97: Segment operating income (loss) | B97: Million | C97: 8-K | D97: 85928 | E97: =E91+E95+E96-(E92) -> 181 | F97: =F91+F95+F96-(F92) -> 79 | G97: =G91+G95+G96-(G92) -> -25 | H97: =H91+H95+H96-(H92) -> 510 | I97: =I91+I95+I96-(I92) -> 146 | J97: =J91+J95+J96-(J92) -> -15 | K97: =K91+K95+K96-(K92) -> -544 | L97: =L91+L95+L96-(L92) -> 591 | ... AR97: =AR91+AR95+AR96-(AR92) -> 2737 | AS97: 4774 | AT97: 7681 | AU97: 11188 | AV97: 13209 | AW97: 15307 | AX97: 14672 | AY97: 17411 | AZ97: 21203 | BA97: 18405 | BB97: 19171 | BC97: 17422 | BD97: 24977 | BF97: =BF91+BF95+BF96-(BF92) -> 745 | BG97: =BG91+BG95+BG96-(BG92) -> 178 | BH97: =BH91+BH95+BH96-(BH92) -> 2233 | BI97: =BI91+BI95+BI96-(BI92) -> 4186 | BJ97: =BJ91+BJ95+BJ96-(BJ92) -> 4106 | BK97: =BK91+BK95+BK96-(BK92) -> 12421 | BL97: =BL91+BL95+BL96-(BL92) -> 14541 | BM97: =BM91+BM95+BM96-(BM92) -> 22899 | BN97: =BN91+BN95+BN96-(BN92) -> 24879 | BO97: 12248 | BP97: 36852 | BQ97: 68593 | BR97: 79975
A99: Total non-operating income (expense) | B99: Million | C99: 8-K | D99: 85929 | E99: -100 | F99: -62 | G99: -18 | H99: -59 | I99: -26 | J99: -12 | K99: -90 | L99: -162 | M99: -234 | N99: -102 | O99: -159 | P99: -170 | Q99: -15 | R99: -106 | S99: -84 | T99: -89 | U99: -52 | V99: 38 | W99: -31 | X99: -255 | Y99: -11 | Z99: -378 | AA99: -334 | AB99: -436 | AC99: -19 | AD99: -195 | AE99: -525 | AF99: 174 | AG99: -606 | AH99: 378 | AI99: 615 | AJ99: 892 | AK99: 1403 | AL99: 932 | AM99: -537 | AN99: 11474 | AO99: -8934 | AP99: -5970 | AQ99: 419 | AR99: -3699 | AS99: -655 | AT99: -118 | AU99: 1001 | AV99: 477 | AW99: -2324 | AX99: 573 | AY99: 626 | AZ99: 1146 | BA99: 3274 | BB99: 1686 | BC99: 10748 | BD99: 1628 | BF99: -239 | BG99: -289 | BH99: -665 | BI99: -294 | BJ99: -300 | BK99: -1160 | BL99: -565 | BM99: 1279 | BN99: 13272 | BO99: -18184 | BP99: 705 | BQ99: 21 | BR99: 17336
A100: Provision for income taxes | B100: Million | C100: 8-K | D100: 85930 | E100: 18 | F100: -13 | G100: 12 | H100: -179 | I100: -73 | J100: -94 | K100: 205 | L100: -205 | M100: -71 | N100: -266 | O100: -161 | P100: -453 | Q100: -475 | R100: -307 | S100: -229 | T100: -414 | U100: -229 | V100: -467 | W100: -58 | X100: -16 | Y100: -287 | Z100: -74 | AA100: -508 | AB100: -327 | AC100: -836 | AD100: -257 | AE100: -494 | AF100: -786 | AG100: -744 | AH100: -984 | AI100: -569 | AJ100: -566 | AK100: -2156 | AL100: -868 | AM100: -1155 | AN100: -612 | AO100: 1422 | AP100: 637 | AQ100: -69 | AR100: 1227 | AS100: -948 | AT100: -804 | AU100: -2306 | AV100: -3062 | AW100: -2467 | AX100: -1767 | AY100: -2706 | AZ100: -2325 | BA100: -4553 | BB100: -2678 | BC100: -6910 | BD100: -4946 | BF100: -161 | BG100: -167 | BH100: -950 | BI100: -1425 | BJ100: -769 | BK100: -1197 | BL100: -2374 | BM100: -2863 | BN100: -4791 | BO100: 3217 | BP100: -7120 | BQ100: -9265 | BR100: -19087
A101: Equity-method investment activity, net of tax | B101: Million | C101: 8-K | D101: 85931 | E101: -17 | F101: -11 | G101: -10 | H101: -33 | I101: 61 | J101: -5 | K101: -8 | L101: -10 | M101: -7 | N101: -4 | O101: -7 | P101: -3 | Q101: -68 | R101: -15 | S101: -10 | T101: -3 | U101: 0 | V101: -2 | W101: -2 | X101: 0 | Y101: 0 | Z101: 3 | AA101: 1 | AB101: 4 | AC101: -4 | AD101: -7 | AE101: -4 | AF101: 1 | AG101: -104 | AH101: 6 | AI101: 91 | AJ101: 23 | AK101: -5 | AL101: 12 | AM101: -4 | AN101: 1 | AO101: -1 | AP101: -12 | AQ101: -3 | AR101: 13 | AS101: 1 | AT101: -9 | AU101: -4 | AW101: -85 | AX101: 7 | AY101: -3 | AZ101: -20 | BA101: 1 | BB101: -15 | BC101: -73 | BD101: -467 | BF101: -71 | BG101: 37 | BH101: -22 | BI101: -96 | BJ101: -4 | BK101: 9 | BL101: -14 | BM101: 16 | BN101: 4 | BO101: -3 | BP101: -12 | BQ101: -101 | BR101: -554
A102: Net income (loss) | B102: Million | C102: 8-K | D102: 85932 | E102: =E97+E99+E100+E101 -> 82 | F102: =F97+F99+F100+F101 -> -7 | G102: =G97+G99+G100+G101 -> -41 | H102: =H97+H99+H100+H101 -> 239 | I102: =I97+I99+I100+I101 -> 108 | J102: =J97+J99+J100+J101 -> -126 | K102: =K97+K99+K100+K101 -> -437 | L102: =L97+L99+L100+L101 -> 214 | ... AR102: =AR97+AR99+AR100+AR101 -> 278 | AS102: 3172 | AT102: 6750 | AU102: 9879 | AV102: 10624 | AW102: 10431 | AX102: 13485 | AY102: 15328 | AZ102: 20004 | BA102: 17127 | BB102: 18164 | BC102: 21187 | BD102: 21192 | BF102: =BF97+BF99+BF100+BF101 -> 274 | BG102: =BG97+BG99+BG100+BG101 -> -241 | BH102: =BH97+BH99+BH100+BH101 -> 596 | BI102: =BI97+BI99+BI100+BI101 -> 2371 | BJ102: =BJ97+BJ99+BJ100+BJ101 -> 3033 | BK102: =BK97+BK99+BK100+BK101 -> 10073 | BL102: =BL97+BL99+BL100+BL101 -> 11588 | BM102: =BM97+BM99+BM100+BM101 -> 21331 | BN102: =BN97+BN99+BN100+BN101 -> 33364 | BO102: -2722 | BP102: 30425 | BQ102: 59248 | BR102: 77670
A104: Leased square footage of properties
A105: North America
A106: Office space | B106: Thousand | C106: 10-K | D106: 3727657 | H106: 4485 | L106: 5672 | P106: 7245 | T106: 8454 | X106: 12712 | AB106: 16642 | AF106: 18051 | AJ106: 23731 | AN106: 27519 | AR106: 30611 | AV106: 29655 | AZ106: 29551
A107: Physical stores | B107: Thousand | C107: 10-K | D107: 3727658 | X107: 20349 | AB107: 19176 | AF107: 20072 | AJ107: 21157 | AN107: 22396 | AR107: 22881 | AV107: 22871 | AZ107: 23975
A108: Fulfilment data centres and other | B108: Thousand | C108: 10-K | D108: 3727659 | H108: 48013 | L108: 57898 | P108: 69890 | T108: 97215 | X108: 131419 | AB108: 153917 | AF108: 187148 | AJ108: 285677 | AN108: 370392 | AR108: 391598 | AV108: 413017 | AZ108: 448168
A110: International
A111: Office space | B111: Thousand | C111: 10-K | D111: 3727660 | H111: 3002 | L111: 3371 | P111: 4843 | T111: 7314 | X111: 7466 | AB111: 14738 | AF111: 15863 | AJ111: 19023 | AN111: 20983 | AR111: 23956 | AV111: 24528 | AZ111: 23771
A112: Physical stores | B112: Thousand | C112: 10-K | D112: 3727661 | X112: 202 | AB112: 173 | AF112: 169 | AJ112: 169 | AN112: 235 | AR112: 291 | AV112: 255 | AZ112: 222
A113: Fulfilment data centres and other | B113: Thousand | C113: 10-K | D113: 3727662 | H113: 36131 | L113: 43969 | P113: 47976 | T113: 59175 | X113: 67832 | AB113: 72596 | AF113: 76868 | AJ113: 104668 | AN113: 129035 | AR113: 148146 | AV113: 173765 | AZ113: 176287
A114: Total | B114: Thousand | C114: 10-K | D114: 3727663 | P114: =SUM(P106:P108,P111:P113) -> 129954 | T114: =SUM(T106:T108,T111:T113) -> 172158 | X114: =SUM(X106:X108,X111:X113) -> 239980 | AB114: =SUM(AB106:AB108,AB111:AB113) -> 277242 | AF114: =SUM(AF106:AF108,AF111:AF113) -> 318171 | AJ114: =SUM(AJ106:AJ108,AJ111:AJ113) -> 454425 | AN114: =SUM(AN106:AN108,AN111:AN113) -> 570560 | AR114: =SUM(AR106:AR108,AR111:AR113) -> 617483 | AV114: 664091 | AZ114: 701974
A116: Owned square footage of properties
A117: North America
...
