Workbook
Name a: Daloopa!$A$2
Name IQ_CH: 110000
Name IQ_CQ: 5000
Name IQ_CY: 10000
Name IQ_DAILY: 500000
Name IQ_FH: 100000
Name IQ_FQ: 500
Name IQ_FY: 1000
Name IQ_LTM: 2000
Name IQ_MONTH: 15000
Name IQ_NTM: 6000
Name IQ_WEEK: 50000
Name IQ_YTD: 3000

Sheet How to Use 
A1: Instructions
A2: Tab | B2: Details
A3: Color Code | B3: Just familiarize yourself with the color code conventions used in this file. I will maintain these color code conventions in every model.
A4: Model | B4: The most important worksheet in this file is the "Model" Worksheet.
B5: If you want to change the assumptions, just change the cells that are filled yellow. Since the rest of the cells are formula driven, they will automatically be changed.
B6: I have made a few comments here and there whenever I thought it might be helpful for subscribers
B7: Please let me know asap if you think there has been any error/mistake (conceptual or otherwise) in the model
A9: Segment | B9: Alphabet only reported these segments from 2019, and operating income by segments from 2020. 2017-2018 as well as 2023-2030 are my personal estimates.
A10: Valuation | B10: Just change the current stock price and choose your multiple to run your valuation estimates.
A11: Daloopa | B11: database from company filings. Feel free to sign up for this by clicking below link (not a paid promotion; I don't get paid if you do so but I do get complimentary access to it)
B12: https://daloopa.com/?utm_source=MBI&utm_medium=Organic&utm_campaign=SourceLink

Sheet Color Code
A1: Color | B1: Meaning
A2: Black | B2: Formula driven (both historical and forecasts)
A3: Blue | B3: Hard coded numbers (Actual for Historical, estimated for forecasts)
A4: Yellow | B4: Indication that there has been explicit assumption made in these cells. Change the numbers in these cells to drive your narrative.

Sheet Model
B1: 2016 | C1: 2017 | D1: 2018 | E1: 2019 | F1: 2020 | G1: 2021 | H1: 2022 | I1: 2023 | J1: 2024 | K1: 2025 | L1: 2026 | M1: 2027 | N1: 2028 | O1: 2029 | P1: 2030
A2: Revenue | B2: =Daloopa!AW275 -> 90272 | C2: =Daloopa!AX275 -> 110855 | D2: =Daloopa!AY275 -> 136819 | E2: =Daloopa!AZ275 -> 161857 | F2: =Daloopa!BA275 -> 182527 | G2: =Daloopa!BB275 -> 257637 | H2: =Daloopa!BC275 -> 282836 | I2: =I42 -> 299512.45 | J2: =J42 -> 325856.97 | K2: =K42 -> 361873.68 | L2: =L42 -> 394974.85 | M2: =M42 -> 428349.53 | N2: =N42 -> 460460.35 | O2: =O42 -> 490454.91 | P2: =P42 -> 520370.4
A3: Growth $ | C3: =C2-B2 -> 20583 | D3: =D2-C2 -> 25964 | E3: =E2-D2 -> 25038 | F3: =F2-E2 -> 20670 | G3: =G2-F2 -> 75110 | H3: =H2-G2 -> 25199 | I3: =I2-H2 -> 16676.45 | J3: =J2-I2 -> 26344.52 | ... P3: =P2-O2 -> 29915.487
A4: Growth % | C4: =C2/B2-1 -> 0.2280109 | D4: =D2/C2-1 -> 0.23421587 | E4: =E2/D2-1 -> 0.1830009 | F4: =F2/E2-1 -> 0.12770532 | G4: =G2/F2-1 -> 0.41150076 | H4: =H2/G2-1 -> 0.097808156 | I4: =I2/H2-1 -> 0.058961554 | J4: =J2/I2-1 -> 0.087958013 | ... P4: =P2/O2-1 -> 0.060995387
A6: Segments
A8: Google Search & Other | C8: =C28-C12-C16-C24 -> 69210 | D8: =D28-D12-D16-D24 -> 85161 | E8: =Daloopa!AZ80 -> 98115 | F8: =Daloopa!BA80 -> 104062 | G8: =Daloopa!BB80 -> 148951 | H8: =Daloopa!BC80 -> 162450 | I8: =H8*(1+I10) -> 170572.5 | J8: =I8*(1+J10) -> 182512.58 | K8: =J8*(1+K10) -> 200763.83 | L8: =K8*(1+L10) -> 216824.94 | M8: =L8*(1+M10) -> 232002.68 | N8: =M8*(1+N10) -> 245922.85 | O8: =N8*(1+O10) -> 258218.99 | P8: =O8*(1+P10) -> 271129.94
A9: Growth | D9: =D8-C8 -> 15951 | E9: =E8-D8 -> 12954 | F9: =F8-E8 -> 5947 | G9: =G8-F8 -> 44889 | H9: =H8-G8 -> 13499 | I9: =I8-H8 -> 8122.5 | J9: =J8-I8 -> 11940.075 | K9: =K8-J8 -> 18251.258 | ... P9: =P8-O8 -> 12910.949
A10: Growth % | D10: =D8/C8-1 -> 0.23047248 | E10: =E8/D8-1 -> 0.15211188 | F10: =F8/E8-1 -> 0.060612547 | G10: =G8/F8-1 -> 0.43136784 | H10: =H8/G8-1 -> 0.090627119 | I10: 0.05 | J10: 0.07 | K10: 0.1 | L10: 0.08 | M10: 0.07 | N10: 0.06 | O10: 0.05 | P10: 0.05
A12: YouTube Ads | C12: =D12-D13 -> 9649 | D12: =E12-E13 -> 12149 | E12: =Daloopa!AZ81 -> 15149 | F12: =Daloopa!BA81 -> 19772 | G12: =Daloopa!BB81 -> 28845 | H12: =Daloopa!BC81 -> 29243 | I12: =H12*(1+I14) -> 30705.15 | J12: =I12*(1+J14) -> 33775.665 | K12: =J12*(1+K14) -> 37828.745 | L12: =K12*(1+L14) -> 41989.907 | M12: =L12*(1+M14) -> 46188.897 | N12: =M12*(1+N14) -> 50345.898 | O12: =N12*(1+O14) -> 54373.57 | P12: =O12*(1+P14) -> 58179.72
A13: =A9 -> Growth | D13: 2500 | E13: 3000 | F13: =F12-E12 -> 4623 | G13: =G12-F12 -> 9073 | H13: =H12-G12 -> 398 | I13: =I12-H12 -> 1462.15 | J13: =J12-I12 -> 3070.515 | K13: =K12-J12 -> 4053.0798 | L13: =L12-K12 -> 4161.1619 | M13: =M12-L12 -> 4198.9907 | ... P13: =P12-O12 -> 3806.1499
A14: =A10 -> Growth % | D14: =D12/C12-1 -> 0.25909421 | E14: =E12/D12-1 -> 0.2469339 | F14: =F12/E12-1 -> 0.30516866 | G14: =G12/F12-1 -> 0.45888125 | H14: =H12/G12-1 -> 0.013797885 | I14: 0.05 | J14: 0.1 | K14: 0.12 | L14: 0.11 | M14: 0.1 | N14: 0.09 | O14: 0.08 | P14: 0.07
A16: Google Network | C16: =Daloopa!AX84 -> 17587 | D16: =Daloopa!AY84 -> 19982 | E16: =Daloopa!AZ84 -> 21547 | F16: =Daloopa!BA84 -> 23090 | G16: =Daloopa!BB84 -> 31701 | H16: =Daloopa!BC84 -> 32780 | I16: =H16*(1+I18) -> 34091.2 | J16: =I16*(1+J18) -> 35795.76 | K16: =J16*(1+K18) -> 37585.548 | L16: =K16*(1+L18) -> 39088.97 | M16: =L16*(1+M18) -> 40652.529 | N16: =M16*(1+N18) -> 42278.63 | O16: =N16*(1+O18) -> 43969.775 | P16: =O16*(1+P18) -> 45288.868
A17: =A13 -> Growth | D17: =D16-C16 -> 2395 | E17: =E16-D16 -> 1565 | F17: =F16-E16 -> 1543 | G17: =G16-F16 -> 8611 | H17: =H16-G16 -> 1079 | I17: =I16-H16 -> 1311.2 | J17: =J16-I16 -> 1704.56 | K17: =K16-J16 -> 1789.788 | ... P17: =P16-O16 -> 1319.0933
A18: =A14 -> Growth % | D18: =D16/C16-1 -> 0.13618013 | E18: =E16/D16-1 -> 0.078320488 | F18: =F16/E16-1 -> 0.071610897 | G18: =G16/F16-1 -> 0.37293201 | H18: =H16/G16-1 -> 0.034036781 | I18: 0.04 | J18: 0.05 | K18: 0.05 | L18: 0.04 | M18: 0.04 | N18: 0.04 | O18: 0.04 | P18: 0.03
A20: Google Advertising | C20: =C8+C12+C16 -> 96446 | D20: =D8+D12+D16 -> 117292 | E20: =E8+E12+E16 -> 134811 | F20: =F8+F12+F16 -> 146924 | G20: =G8+G12+G16 -> 209497 | H20: =H8+H12+H16 -> 224473 | I20: =I8+I12+I16 -> 235368.85 | J20: =J8+J12+J16 -> 252084 | ... P20: =P8+P12+P16 -> 374598.53
A21: =A17 -> Growth | D21: =D20-C20 -> 20846 | E21: =E20-D20 -> 17519 | F21: =F20-E20 -> 12113 | G21: =G20-F20 -> 62573 | H21: =H20-G20 -> 14976 | I21: =I20-H20 -> 10895.85 | J21: =J20-I20 -> 16715.15 | K21: =K20-J20 -> 24094.125 | ... P21: =P20-O20 -> 18036.193
A22: =A18 -> Growth % | D22: =D20/C20-1 -> 0.21614168 | E22: =E20/D20-1 -> 0.14936228 | F22: =F20/E20-1 -> 0.089851718 | G22: =G20/F20-1 -> 0.42588685 | H22: =H20/G20-1 -> 0.071485511 | I22: =I20/H20-1 -> 0.048539691 | J22: =J20/I20-1 -> 0.071016832 | K22: =K20/J20-1 -> 0.095579748 | ... P22: =P20/O20-1 -> 0.050583561
A24: Google Other | C24: =D24-D25 -> 11014 | D24: =E24-E25 -> 13514 | E24: =Daloopa!AZ88 -> 17014 | F24: =Daloopa!BA88 -> 21711 | G24: =Daloopa!BB88 -> 28032 | H24: =Daloopa!BC88 -> 29055 | I24: =H24*(1+I26) -> 31379.4 | J24: =I24*(1+J26) -> 34517.34 | K24: =J24*(1+K26) -> 38659.421 | L24: =K24*(1+L26) -> 42525.363 | M24: =L24*(1+M26) -> 46777.899 | N24: =M24*(1+N26) -> 50987.91 | O24: =N24*(1+O26) -> 55066.943 | P24: =O24*(1+P26) -> 58921.629
A25: =A21 -> Growth | D25: 2500 | E25: 3500 | F25: =F24-E24 -> 4697 | G25: =G24-F24 -> 6321 | H25: =H24-G24 -> 1023 | I25: =I24-H24 -> 2324.4 | J25: =J24-I24 -> 3137.94 | K25: =K24-J24 -> 4142.0808 | L25: =L24-K24 -> 3865.9421 | M25: =M24-L24 -> 4252.5363 | ... P25: =P24-O24 -> 3854.686
A26: =A22 -> Growth % | F26: =F24/E24-1 -> 0.27606677 | G26: =G24/F24-1 -> 0.29114274 | H26: =H24/G24-1 -> 0.036494007 | I26: 0.08 | J26: 0.1 | K26: 0.12 | L26: 0.1 | M26: 0.1 | N26: 0.09 | O26: 0.08 | P26: 0.07
A28: Google Services | C28: =C2-C32-C36 -> 107460 | D28: =D2-D32-D36 -> 130806 | E28: =E20+E24 -> 151825 | F28: =F20+F24 -> 168635 | G28: =G20+G24 -> 237529 | H28: =H20+H24 -> 253528 | I28: =I20+I24 -> 266748.25 | J28: =J20+J24 -> 286601.34 | K28: =K20+K24 -> 314837.55 | L28: =L20+L24 -> 340429.18 | ... P28: =P20+P24 -> 433520.15
A29: =A25 -> Growth | D29: =D28-C28 -> 23346 | E29: =E28-D28 -> 21019 | F29: =F28-E28 -> 16810 | G29: =G28-F28 -> 68894 | H29: =H28-G28 -> 15999 | I29: =I28-H28 -> 13220.25 | J29: =J28-I28 -> 19853.09 | K29: =K28-J28 -> 28236.206 | ... P29: =P28-O28 -> 21890.879
A30: =A26 -> Growth % | F30: =F28/E28-1 -> 0.11071958 | G30: =G28/F28-1 -> 0.40853915 | H30: =H28/G28-1 -> 0.067355986 | I30: =I28/H28-1 -> 0.052145128 | J30: =J28/I28-1 -> 0.074426318 | K30: =K28/J28-1 -> 0.098520845 | L30: =L28/K28-1 -> 0.081285199 | M30: =M28/L28-1 -> 0.07400315 | ... P30: =P28/O28-1 -> 0.053181054
A32: Google Cloud | C32: =D32-D33 -> 2918 | D32: =E32-E33 -> 5418 | E32: 8918 | F32: =Daloopa!BA93 -> 13059 | G32: =Daloopa!BB93 -> 19206 | H32: =Daloopa!BC93 -> 26280 | I32: =H32*(1+I34) -> 31536 | J32: =I32*(1+J34) -> 37843.2 | K32: =J32*(1+K34) -> 45411.84 | L32: =K32*(1+L34) -> 52677.734 | M32: =L32*(1+M34) -> 60579.395 | N32: =M32*(1+N34) -> 68454.716 | O32: =N32*(1+O34) -> 75984.735 | P32: =O32*(1+P34) -> 83583.208
A33: =A29 -> Growth | D33: 2500 | E33: 3500 | F33: =F32-E32 -> 4141 | G33: =G32-F32 -> 6147 | H33: =H32-G32 -> 7074 | I33: =I32-H32 -> 5256 | J33: =J32-I32 -> 6307.2 | K33: =K32-J32 -> 7568.64 | L33: =L32-K32 -> 7265.8944 | M33: =M32-L32 -> 7901.6602 | ... P33: =P32-O32 -> 7598.4735
A34: =A30 -> Growth % | F34: =F32/E32-1 -> 0.46434178 | G34: =G32/F32-1 -> 0.47070986 | H34: =H32/G32-1 -> 0.3683224 | I34: 0.2 | J34: 0.2 | K34: 0.2 | L34: 0.16 | M34: 0.15 | N34: 0.13 | O34: 0.11 | P34: 0.1
A36: Other bets | C36: 477 | D36: 595 | E36: =Daloopa!AZ94 -> 659 | F36: =Daloopa!BA94 -> 657 | G36: =Daloopa!BB94 -> 753 | H36: =Daloopa!BC94 -> 1068 | I36: =H36*(1+I38) -> 1228.2 | J36: =I36*(1+J38) -> 1412.43 | K36: =J36*(1+K38) -> 1624.2945 | L36: =K36*(1+L38) -> 1867.9387 | M36: =L36*(1+M38) -> 2148.1295 | N36: =M36*(1+N38) -> 2470.3489 | O36: =N36*(1+O38) -> 2840.9012 | P36: =O36*(1+P38) -> 3267.0364
A37: =A33 -> Growth | D37: =D36-C36 -> 118 | E37: =E36-D36 -> 64 | F37: =F36-E36 -> -2 | G37: =G36-F36 -> 96 | H37: =H36-G36 -> 315 | I37: =I36-H36 -> 160.2 | J37: =J36-I36 -> 184.23 | K37: =K36-J36 -> 211.8645 | ... P37: =P36-O36 -> 426.13518
A38: =A34 -> Growth % | F38: =F36/E36-1 -> -0.0030349014 | G38: =G36/F36-1 -> 0.14611872 | H38: =H36/G36-1 -> 0.41832669 | I38: 0.15 | J38: 0.15 | K38: 0.15 | L38: 0.15 | M38: 0.15 | N38: 0.15 | O38: 0.15 | P38: 0.15
A40: Hedging Gains | E40: =Daloopa!AZ95 -> 455 | F40: =Daloopa!BA95 -> 176 | G40: =Daloopa!BB95 -> 149 | H40: =Daloopa!BC95 -> 1960
A42: Total revenues | C42: =C28+C32+C36+C40 -> 110855 | D42: =D28+D32+D36+D40 -> 136819 | E42: =E28+E32+E36+E40 -> 161857 | F42: =F28+F32+F36+F40 -> 182527 | G42: =G28+G32+G36+G40 -> 257637 | H42: =H28+H32+H36+H40 -> 282836 | I42: =I28+I32+I36+I40 -> 299512.45 | J42: =J28+J32+J36+J40 -> 325856.97 | ... P42: =P28+P32+P36+P40 -> 520370.4
A43: Growth | D43: =D42-C42 -> 25964 | E43: =E42-D42 -> 25038 | F43: =F42-E42 -> 20670 | G43: =G42-F42 -> 75110 | H43: =H42-G42 -> 25199 | I43: =I42-H42 -> 16676.45 | J43: =J42-I42 -> 26344.52 | K43: =K42-J42 -> 36016.711 | ... P43: =P42-O42 -> 29915.487
A44: Growth % | D44: =D42/C42-1 -> 0.23421587 | E44: =E42/D42-1 -> 0.1830009 | F44: =F42/E42-1 -> 0.12770532 | G44: =G42/F42-1 -> 0.41150076 | H44: =H42/G42-1 -> 0.097808156 | I44: =I42/H42-1 -> 0.058961554 | J44: =J42/I42-1 -> 0.087958013 | K44: =K42/J42-1 -> 0.1105292 | ... P44: =P42/O42-1 -> 0.060995387
A46: Cost of revenue | B46: =Daloopa!AW279 -> 35138 | C46: =Daloopa!AX279 -> 45583 | D46: =Daloopa!AY279 -> 59549 | E46: =Daloopa!AZ279 -> 71896 | F46: =Daloopa!BA279 -> 84732 | G46: =Daloopa!BB279 -> 110939 | H46: =Daloopa!BC279 -> 126203 | I46: =Segment!H28 -> 134742.37 | J46: =Segment!I28 -> 146942.56 | K46: =Segment!J28 -> 163256.16 | L46: =Segment!K28 -> 178732.58 | M46: =Segment!L28 -> 194461.47 | N46: =Segment!M28 -> 207393.29 | O46: =Segment!N28 -> 219334.47 | P46: =Segment!O28 -> 230854.86
A47: As % of revenue | B47: =B46/B2 -> 0.38924583 | C47: =C46/C2 -> 0.4111948 | D47: =D46/D2 -> 0.43523926 | E47: =E46/E2 -> 0.44419457 | F47: =F46/F2 -> 0.46421625 | G47: =G46/G2 -> 0.43060197 | H47: =H46/H2 -> 0.44620557 | I47: =I46/I2 -> 0.44987234 | ... P47: =P46/P2 -> 0.44363566
A49: Gross Profit | B49: =B2-B46 -> 55134 | C49: =C2-C46 -> 65272 | D49: =D2-D46 -> 77270 | E49: =E2-E46 -> 89961 | F49: =F2-F46 -> 97795 | G49: =G2-G46 -> 146698 | H49: =H2-H46 -> 156633 | I49: =I2-I46 -> 164770.08 | ... P49: =P2-P46 -> 289515.54
A50: Gross Margin | B50: =B49/B2 -> 0.61075417 | C50: =C49/C2 -> 0.5888052 | D50: =D49/D2 -> 0.56476074 | E50: =E49/E2 -> 0.55580543 | F50: =F49/F2 -> 0.53578375 | G50: =G49/G2 -> 0.56939803 | H50: =H49/H2 -> 0.55379443 | I50: =I49/I2 -> 0.55012766 | ... P50: =P49/P2 -> 0.55636434
A52: R&D | B52: =Daloopa!AW280 -> 13948 | C52: =Daloopa!AX280 -> 16625 | D52: =Daloopa!AY280 -> 21419 | E52: =Daloopa!AZ280 -> 26018 | F52: =Daloopa!BA280 -> 27573 | G52: =Daloopa!BB280 -> 31562 | H52: =Daloopa!BC280 -> 39500 | I52: =Segment!H76 -> 43000 | J52: =Segment!I76 -> 46500 | K52: =Segment!J76 -> 50000 | L52: =Segment!K76 -> 53500 | M52: =Segment!L76 -> 57000 | N52: =Segment!M76 -> 60500 | O52: =Segment!N76 -> 64000 | P52: =Segment!O76 -> 67500
A53: As % of revenue | B53: =B52/B2 -> 0.15451081 | C53: =C52/C2 -> 0.14997068 | D53: =D52/D2 -> 0.15654989 | E53: =E52/E2 -> 0.16074683 | F53: =F52/F2 -> 0.15106258 | G53: =G52/G2 -> 0.1225057 | H53: =H52/H2 -> 0.1396569 | I53: =I52/I2 -> 0.14356665 | ... P53: =P52/P2 -> 0.1297153
A55: Sales & Marketing | B55: =Daloopa!AW281 -> 10485 | C55: =Daloopa!AX281 -> 12893 | D55: =Daloopa!AY281 -> 16333 | E55: =Daloopa!AZ281 -> 18464 | F55: =Daloopa!BA281 -> 17946 | G55: =Daloopa!BB281 -> 22912 | H55: =Daloopa!BC281 -> 26567 | I55: =Segment!H91 -> 29167 | J55: =Segment!I91 -> 31767 | K55: =Segment!J91 -> 34367 | L55: =Segment!K91 -> 36967 | M55: =Segment!L91 -> 39567 | N55: =Segment!M91 -> 42167 | O55: =Segment!N91 -> 44767 | P55: =Segment!O91 -> 47367
A56: As % of revenue | B56: =B55/B2 -> 0.11614897 | C56: =C55/C2 -> 0.11630508 | D56: =D55/D2 -> 0.11937669 | E56: =E55/E2 -> 0.11407601 | F56: =F55/F2 -> 0.098319701 | G56: =G55/G2 -> 0.088931326 | H56: =H55/H2 -> 0.093930758 | I56: =I55/I2 -> 0.097381595 | ... P56: =P55/P2 -> 0.091025547
A58: General & Administrative | B58: =Daloopa!AW282 -> 6985 | C58: =Daloopa!AX282 -> 6872 | D58: =Daloopa!AY282 -> 8126 | E58: =Daloopa!AZ282 -> 9551 | F58: =Daloopa!BA282 -> 11052 | G58: =Daloopa!BB282 -> 13510 | H58: =Daloopa!BC282 -> 15724 | I58: =Segment!H106 -> 17012.482 | J58: =Segment!I106 -> 18511.013 | K58: =Segment!J106 -> 20093.375 | L58: =Segment!K106 -> 21649.292 | M58: =Segment!L106 -> 23201.22 | N58: =Segment!M106 -> 24740.353 | O58: =Segment!N106 -> 26261.293 | P58: =Segment!O106 -> 27780.202
A59: As % of revenue | B59: =B58/B2 -> 0.07737726 | C59: =C58/C2 -> 0.061990889 | D59: =D58/D2 -> 0.059392336 | E59: =E58/E2 -> 0.059008878 | F59: =F58/F2 -> 0.060549946 | G59: =G58/G2 -> 0.05243812 | H59: =H58/H2 -> 0.055594055 | I59: =I58/I2 -> 0.056800585 | ... P59: =P58/P2 -> 0.053385438
A61: European Commission Fines | B61: =Daloopa!AW283 -> 0 | C61: =Daloopa!AX283 -> 2736 | D61: =Daloopa!AY283 -> 5071 | E61: =Daloopa!AZ283 -> 1697 | F61: =Daloopa!BA283 -> 0 | G61: =Daloopa!BB283 -> 0 | H61: =Daloopa!BC283 -> 0
A63: Total Opex (ex Cost of Revenue) | B63: =B52+B55+B58+B61 -> 31418 | C63: =C52+C55+C58+C61 -> 39126 | D63: =D52+D55+D58+D61 -> 50949 | E63: =E52+E55+E58+E61 -> 55730 | F63: =F52+F55+F58+F61 -> 56571 | G63: =G52+G55+G58+G61 -> 67984 | H63: =H52+H55+H58+H61 -> 81791 | I63: =I52+I55+I58+I61 -> 89179.482 | ... P63: =P52+P55+P58+P61 -> 142647.2
A64: Total # of employees | B64: =Daloopa!T935 -> 72053 | C64: =Daloopa!X935 -> 80110 | D64: =Daloopa!AB935 -> 98771 | E64: =Daloopa!AF935 -> 118899 | F64: =Daloopa!AJ935 -> 135301 | G64: =Daloopa!AN935 -> 156500 | H64: =Daloopa!AR935 -> 190234 | I64: =H64*(1+I65) -> 180722.3 | J64: =I64*(1+J65) -> 189758.42 | K64: =J64*(1+K65) -> 208734.26 | L64: =K64*(1+L65) -> 229607.68 | M64: =L64*(1+M65) -> 252568.45 | N64: =M64*(1+N65) -> 265196.87 | O64: =N64*(1+O65) -> 278456.72 | P64: =O64*(1+P65) -> 292379.55
A65: Increase | C65: =C64/B64-1 -> 0.11182047 | D65: =D64/C64-1 -> 0.2329422 | E65: =E64/D64-1 -> 0.20378451 | F65: =F64/E64-1 -> 0.13794902 | G65: =G64/F64-1 -> 0.15668029 | H65: =H64/G64-1 -> 0.21555272 | I65: -0.05 | J65: 0.05 | K65: 0.1 | L65: 0.1 | M65: 0.1 | N65: 0.05 | O65: 0.05 | P65: 0.05
A66: Opex per avg employee | C66: =C63*1000000/AVERAGE(B64:C64) -> 514264.31 | D66: =D63*1000000/AVERAGE(C64:D64) -> 569641.27 | E66: =E63*1000000/AVERAGE(D64:E64) -> 512059.54 | F66: =F63*1000000/AVERAGE(E64:F64) -> 445090.48 | G66: =G63*1000000/AVERAGE(F64:G64) -> 465961.39 | H66: =H63*1000000/AVERAGE(G64:H64) -> 471779.52 | I66: =I63*1000000/AVERAGE(H64:I64) -> 480808.56 | J66: =J63*1000000/AVERAGE(I64:J64) -> 522445.62 | ... P66: =P63*1000000/AVERAGE(O64:P64) -> 499783.25
A67: Increase YoY % | D67: =D66/C66-1 -> 0.10768191 | E67: =E66/D66-1 -> -0.1010842 | F67: =F66/E66-1 -> -0.13078374 | G67: =G66/F66-1 -> 0.046891391 | H67: =H66/G66-1 -> 0.012486288 | I67: =I66/H66-1 -> 0.019138266 | J67: =J66/I66-1 -> 0.086597997 | K67: =K66/J66-1 -> 0.0035064005 | ... P67: =P66/O66-1 -> 0.0061186059
A69: Total Opex | B69: =B52+B55+B58+B46+B61 -> 66556 | C69: =C52+C55+C58+C46+C61 -> 84709 | D69: =D52+D55+D58+D46+D61 -> 110498 | E69: =E52+E55+E58+E46+E61 -> 127626 | F69: =F52+F55+F58+F46+F61 -> 141303 | G69: =G52+G55+G58+G46+G61 -> 178923 | H69: =H52+H55+H58+H46+H61 -> 207994 | I69: =I52+I55+I58+I46+I61 -> 223921.85 | ... P69: =P52+P55+P58+P46+P61 -> 373502.06
A70: Operating Income | B70: =B49-B52-B55-B58-B61 -> 23716 | C70: =C49-C52-C55-C58-C61 -> 26146 | D70: =D49-D52-D55-D58-D61 -> 26321 | E70: =E49-E52-E55-E58-E61 -> 34231 | F70: =F49-F52-F55-F58-F61 -> 41224 | G70: =G49-G52-G55-G58-G61 -> 78714 | H70: =H49-H52-H55-H58-H61 -> 74842 | I70: =I49-I52-I55-I58-I61 -> 75590.601 | ... P70: =P49-P52-P55-P58-P61 -> 146868.33
A71: Operating margin | B71: =B70/B2 -> 0.26271712 | C71: =C70/C2 -> 0.23585765 | D71: =D70/D2 -> 0.19237825 | E71: =E70/E2 -> 0.21148915 | F71: =F70/F2 -> 0.22585152 | G71: =G70/G2 -> 0.30552289 | H71: =H70/H2 -> 0.26461271 | I71: =I70/I2 -> 0.25237883 | ... P71: =P70/P2 -> 0.28223806
A72: Operating margin, ex EU fines | B72: =(B70+B61)/B2 -> 0.26271712 | C72: =(C70+C61)/C2 -> 0.26053854 | D72: =(D70+D61)/D2 -> 0.22944182 | E72: =(E70+E61)/E2 -> 0.22197372 | F72: =(F70+F61)/F2 -> 0.22585152 | G72: =(G70+G61)/G2 -> 0.30552289 | H72: =(H70+H61)/H2 -> 0.26461271 | I72: =(I70+I61)/I2 -> 0.25237883 | ... P72: =(P70+P61)/P2 -> 0.28223806
A74: Other income (expense), net | B74: =Daloopa!AW288 -> 434 | C74: =Daloopa!AX288 -> 1047 | D74: =Daloopa!AY288 -> 8592 | E74: =Daloopa!AZ288 -> 5394 | F74: =Daloopa!BA288 -> 6858 | G74: =Daloopa!BB288 -> 12020 | H74: =Daloopa!BC288 -> -3514 | I74: =I75*(AVERAGE(H169:I169)+AVERAGE(H147:I147)) -> 5182.12 | J74: =J75*(AVERAGE(I169:J169)+AVERAGE(I147:J147)) -> 5182.12 | K74: =K75*(AVERAGE(J169:K169)+AVERAGE(J147:K147)) -> 5082.12 | L74: =L75*(AVERAGE(K169:L169)+AVERAGE(K147:L147)) -> 4882.12 | M74: =M75*(AVERAGE(L169:M169)+AVERAGE(L147:M147)) -> 4682.12 | N74: =N75*(AVERAGE(M169:N169)+AVERAGE(M147:N147)) -> 4482.12 | O74: =O75*(AVERAGE(N169:O169)+AVERAGE(N147:O147)) -> 4282.12 | P74: =P75*(AVERAGE(O169:P169)+AVERAGE(O147:P147)) -> 4082.12
A75: As % of net cash and LT investments | D75: =D74/(AVERAGE(C169:D169)+AVERAGE(C147:D147)) -> 0.07647462 | E75: =E74/(AVERAGE(D169:E169)+AVERAGE(D147:E147)) -> 0.043643248 | F75: =F74/(AVERAGE(E169:F169)+AVERAGE(E147:F147)) -> 0.050488839 | G75: =G74/(AVERAGE(F169:G169)+AVERAGE(F147:G147)) -> 0.080712852 | H75: =H74/(AVERAGE(G169:H169)+AVERAGE(G147:H147)) -> -0.024752231 | I75: 0.04 | J75: 0.04 | K75: 0.04 | L75: 0.04 | M75: 0.04 | N75: 0.04 | O75: 0.04 | P75: 0.04
A77: Profit before tax | B77: =B70+B74 -> 24150 | C77: =C70+C74 -> 27193 | D77: =D70+D74 -> 34913 | E77: =E70+E74 -> 39625 | F77: =F70+F74 -> 48082 | G77: =G70+G74 -> 90734 | H77: =H70+H74 -> 71328 | I77: =I70+I74 -> 80772.721 | ... P77: =P70+P74 -> 150950.45
A78: Income taxes | B78: =Daloopa!AW291 -> 4672 | C78: =Daloopa!AX291 -> 14531 | D78: =Daloopa!AY291 -> 4177 | E78: =Daloopa!AZ291 -> 5282 | F78: =Daloopa!BA291 -> 7813 | G78: =Daloopa!BB291 -> 14701 | H78: =Daloopa!BC291 -> 11356 | I78: =I79*I77 -> 12115.908 | J78: =J79*J77 -> 13097.777 | K78: =K79*K77 -> 14885.889 | L78: =L79*L77 -> 16351.215 | M78: =M79*M77 -> 17820.295 | N78: =N79*N77 -> 19521.274 | O78: =O79*O77 -> 21056.14 | P78: =P79*P77 -> 22642.568
A79: Effective tax | B79: =B78/B77 -> 0.19345756 | C79: =C78/C77 -> 0.53436546 | D79: =D78/D77 -> 0.11964025 | E79: =E78/E77 -> 0.13329968 | F79: =F78/F77 -> 0.16249324 | G79: =G78/G77 -> 0.16202306 | H79: =H78/H77 -> 0.15920817 | I79: 0.15 | J79: 0.15 | K79: 0.15 | L79: 0.15 | M79: 0.15 | N79: 0.15 | O79: 0.15 | P79: 0.15
A80: Net Income | B80: =B77-B78 -> 19478 | C80: =C77-C78 -> 12662 | D80: =D77-D78 -> 30736 | E80: =E77-E78 -> 34343 | F80: =F77-F78 -> 40269 | G80: =G77-G78 -> 76033 | H80: =H77-H78 -> 59972 | I80: =I77-I78 -> 68656.813 | ... P80: =P77-P78 -> 128307.89
A81: EPS | D81: =D80/AVERAGE(C193:D193) -> #DIV/0! | E81: =E80/AVERAGE(D193:E193) -> 2.4700299 | F81: =F80/AVERAGE(E193:F193) -> 2.921933 | G81: =G80/AVERAGE(F193:G193) -> 5.6093789 | H81: =H80/AVERAGE(G193:H193) -> 4.5438738 | I81: =I80/AVERAGE(H193:I193) -> 5.4068568 | J81: =J80/AVERAGE(I193:J193) -> 6.0684185 | K81: =K80/AVERAGE(J193:K193) -> 7.1685641 | ... P81: =P80/AVERAGE(O193:P193) -> 14.136307
A82: Cash Flow
A84: Net Income | B84: =B80 -> 19478 | C84: =C80 -> 12662 | D84: =D80 -> 30736 | E84: =E80 -> 34343 | F84: =F80 -> 40269 | G84: =G80 -> 76033 | H84: =H80 -> 59972 | I84: =I80 -> 68656.813 | ... P84: =P80 -> 128307.89
A85: D&A | B85: =Daloopa!AW408 -> 5267 | C85: =Daloopa!AX408 -> 6103 | D85: =Daloopa!AY408 -> 8164 | E85: =Daloopa!AZ408 -> 10856 | F85: =Daloopa!BA408 -> 12905 | G85: =Daloopa!BB408 -> 11555 | H85: =Daloopa!BC408 -> 15287 | I85: =I86*I2 -> 16487.858 | J85: =J86*J2 -> 18263.954 | K85: =K86*K2 -> 20644.528 | L85: =L86*L2 -> 22927.891 | M85: =M86*M2 -> 25293.607 | N85: =N86*N2 -> 27650.179 | O85: =O86*O2 -> 29941.777 | P85: =P86*P2 -> 32288.457
A86: As % of revenue | B86: =B85/B2 -> 0.058345888 | C86: =C85/C2 -> 0.055053899 | D86: =D85/D2 -> 0.059670075 | E86: =E85/E2 -> 0.067071551 | F86: =F85/F2 -> 0.070701869 | G86: =G85/G2 -> 0.044849925 | H86: =H85/H2 -> 0.05404899 | I86: =H86+0.1% -> 0.05504899 | J86: =I86+0.1% -> 0.05604899 | K86: =J86+0.1% -> 0.05704899 | L86: =K86+0.1% -> 0.05804899 | M86: =L86+0.1% -> 0.05904899 | N86: =M86+0.1% -> 0.06004899 | O86: =N86+0.1% -> 0.06104899 | P86: =O86+0.1% -> 0.06204899
A87: Amortization of intangibles | B87: =Daloopa!AW409 -> 877 | C87: =Daloopa!AX409 -> 812 | D87: =Daloopa!AY409 -> 871 | E87: =Daloopa!AZ409 -> 925 | F87: =Daloopa!BA409 -> 792 | G87: =Daloopa!BB409 -> 886 | H87: =Daloopa!BC409 -> 641 | I87: =I88*I2 -> 898.53735 | J87: =J88*J2 -> 977.57091 | K87: =K88*K2 -> 1085.621 | L87: =L88*L2 -> 1184.9246 | M87: =M88*M2 -> 1285.0486 | N87: =N88*N2 -> 1381.381 | O87: =O88*O2 -> 1471.3647 | P87: =P88*P2 -> 1561.1112
A88: =A86 -> As % of revenue | B88: =B87/B2 -> 0.0097150833 | C88: =C87/C2 -> 0.0073248839 | D88: =D87/D2 -> 0.0063660749 | E88: =E87/E2 -> 0.0057149212 | F88: =F87/F2 -> 0.0043390841 | G88: =G87/G2 -> 0.003438947 | H88: =H87/H2 -> 0.002266331 | I88: 0.003 | J88: 0.003 | K88: 0.003 | L88: 0.003 | M88: 0.003 | N88: 0.003 | O88: 0.003 | P88: 0.003
A89: SBC | B89: =Daloopa!AW410 -> 6703 | C89: =Daloopa!AX410 -> 7679 | D89: =Daloopa!AY410 -> 9353 | E89: =Daloopa!AZ410 -> 10794 | F89: =Daloopa!BA410 -> 12991 | G89: =Daloopa!BB410 -> 15376 | H89: =Daloopa!BC410 -> 19362 | I89: =I90*I2 -> 20366.847 | J89: =J90*J2 -> 22158.274 | K89: =K90*K2 -> 24607.41 | L89: =L90*L2 -> 26858.29 | M89: =M90*M2 -> 29127.768 | N89: =N90*N2 -> 31311.304 | O89: =O90*O2 -> 33350.934 | P89: =P90*P2 -> 35385.187
A90: As % of revenue | B90: =B89/B2 -> 0.074253368 | C90: =C89/C2 -> 0.069270669 | D90: =D89/D2 -> 0.068360389 | E90: =E89/E2 -> 0.066688497 | F90: =F89/F2 -> 0.071173032 | G90: =G89/G2 -> 0.059680869 | H90: =H89/H2 -> 0.068456632 | I90: 0.068 | J90: 0.068 | K90: 0.068 | L90: 0.068 | M90: 0.068 | N90: 0.068 | O90: 0.068 | P90: 0.068
A91: Deferred income taxes | B91: =Daloopa!AW412 -> -38 | C91: =Daloopa!AX412 -> 258 | D91: =Daloopa!AY412 -> 778 | E91: =Daloopa!AZ412 -> 173 | F91: =Daloopa!BA412 -> 1390 | G91: =Daloopa!BB412 -> 1808 | H91: =Daloopa!BC412 -> -8081
A92: Other | B92: =Daloopa!AW415+Daloopa!AW416+Daloopa!AW417+Daloopa!AW418 -> 449 | C92: =Daloopa!AX415+Daloopa!AX416+Daloopa!AX417+Daloopa!AX418 -> 331 | D92: =Daloopa!AY415+Daloopa!AY416+Daloopa!AY417+Daloopa!AY418 -> -6839 | E92: =Daloopa!AZ415+Daloopa!AZ416+Daloopa!AZ417+Daloopa!AZ418 -> -3390 | F92: =Daloopa!BA415+Daloopa!BA416+Daloopa!BA417+Daloopa!BA418 -> -5050 | G92: =Daloopa!BB415+Daloopa!BB416+Daloopa!BB417+Daloopa!BB418 -> -12483 | H92: =Daloopa!BC415+Daloopa!BC416+Daloopa!BC417+Daloopa!BC418 -> 6549
A93: NWC
A94: Accounts receivable | B94: =Daloopa!AW420 -> -2578 | C94: =Daloopa!AX420 -> -3768 | D94: =Daloopa!AY420 -> -2169 | E94: =Daloopa!AZ420 -> -4340 | F94: =Daloopa!BA420 -> -6524 | G94: =Daloopa!BB420 -> -9095 | H94: =Daloopa!BC420 -> -2317 | I94: =H134-I134 -> -1319.8262 | J94: =I134-J134 -> -3060.1149 | K94: =J134-K134 -> -4933.796 | L94: =K134-L134 -> -4534.407 | M94: =L134-M134 -> -4571.8743 | N94: =M134-N134 -> -4398.7417 | O94: =N134-O134 -> -4108.8443 | P94: =O134-P134 -> -4098.0119
A95: Income taxes, net | B95: =Daloopa!AW421 -> 3125 | C95: =Daloopa!AX421 -> 8211 | D95: =Daloopa!AY421 -> -2251 | E95: =Daloopa!AZ421 -> -3128 | F95: =Daloopa!BA421 -> 1209 | G95: =Daloopa!BB421 -> -625 | H95: =Daloopa!BC421 -> 584
A96: Inventories | B96: =Daloopa!AW422 -> 0 | C96: =Daloopa!AX422 -> 0 | D96: =Daloopa!AY422 -> 0 | E96: =Daloopa!AZ422 -> 0 | F96: =Daloopa!BA422 -> 0 | G96: =Daloopa!BB422 -> 0 | H96: =Daloopa!BC422 -> 0 | I96: =H137-I137 -> 537.57131 | J96: =I137-J137 -> -283.06551 | K96: =J137-K137 -> -268.16876 | L96: =K137-L137 -> -254.40689 | M96: =L137-M137 -> -258.55697 | N96: =M137-N137 -> -212.57796 | O96: =N137-O137 -> -196.29339 | P96: =O137-P137 -> -189.37628
A97: Other assets | B97: =Daloopa!AW423 -> 312 | C97: =Daloopa!AX423 -> -2164 | D97: =Daloopa!AY423 -> -1207 | E97: =Daloopa!AZ423 -> -621 | F97: =Daloopa!BA423 -> -1330 | G97: =Daloopa!BB423 -> -1846 | H97: =Daloopa!BC423 -> -5046 | I97: =H140-I140 -> -880.3735 | J97: =I140-J140 -> -790.3356 | K97: =J140-K140 -> -1080.5013 | L97: =K140-L140 -> -993.03513 | M97: =L140-M140 -> -1001.2405 | N97: =M140-N140 -> -963.32444 | O97: =N140-O140 -> -899.8369 | P97: =O140-P140 -> -897.46462
A98: Accounts payable | B98: =Daloopa!AW424 -> 110 | C98: =Daloopa!AX424 -> 731 | D98: =Daloopa!AY424 -> 1067 | E98: =Daloopa!AZ424 -> 428 | F98: =Daloopa!BA424 -> 694 | G98: =Daloopa!BB424 -> 283 | H98: =Daloopa!BC424 -> 707 | I98: =I153-H153 -> 944.42206 | J98: =J153-I153 -> 604.85403 | K98: =K153-J153 -> 657.4236 | L98: =L153-K153 -> 633.76262 | M98: =M153-L153 -> 640.57016 | N98: =N153-M153 -> 563.58791 | O98: =O153-N153 -> 535.94853 | P98: =P153-O153 -> 524.36437
A99: Accrued expenses and other liabilities | B99: =Daloopa!AW425 -> 1515 | C99: =Daloopa!AX425 -> 4891 | D99: =Daloopa!AY425 -> 8614 | E99: =Daloopa!AZ425 -> 7170 | F99: =Daloopa!BA425 -> 5504 | G99: =Daloopa!BB425 -> 7304 | H99: =Daloopa!BC425 -> 3915 | I99: =I158-H158+I156-H156+I176-H176 -> 8570.6815 | J99: =J158-I158+J156-I156+J176-I176 -> 6445.4194 | K99: =K158-J158+K156-J156+K176-J176 -> 7991.6569 | L99: =L158-K158+L156-K156+L176-K176 -> 7632.7852 | M99: =M158-L158+M156-L156+M176-L176 -> 7711.1625 | N99: =N158-M158+N156-M156+N176-M176 -> 6905.3218 | O99: =O158-N158+O156-N156+O176-N176 -> 6542.8472 | P99: =P158-O158+P156-O156+P176-O176 -> 6426.4744
A100: Accrued revenue share | B100: =Daloopa!AW426 -> 593 | C100: =Daloopa!AX426 -> 955 | D100: =Daloopa!AY426 -> 483 | E100: =Daloopa!AZ426 -> 1273 | F100: =Daloopa!BA426 -> 1639 | G100: =Daloopa!BB426 -> 1682 | H100: =Daloopa!BC426 -> -445 | I100: =I160-H160 -> 615.3735 | J100: =J160-I160 -> 790.3356 | K100: =K160-J160 -> 1080.5013 | L100: =L160-K160 -> 993.03513 | M100: =M160-L160 -> 1001.2405 | N100: =N160-M160 -> 963.32444 | O100: =O160-N160 -> 899.8369 | P100: =P160-O160 -> 897.46462
A101: Deferred revenue | B101: =Daloopa!AW427 -> 223 | C101: =Daloopa!AX427 -> 390 | D101: =Daloopa!AY427 -> 371 | E101: =Daloopa!AZ427 -> 37 | F101: =Daloopa!BA427 -> 635 | G101: =Daloopa!BB427 -> 774 | H101: =Daloopa!BC427 -> 367 | I101: =I162-H162+I171-H171 -> 285.1992 | J101: =J162-I162+J171-I171 -> 421.51232 | K101: =K162-J162+K171-J171 -> 576.26737 | L101: =L162-K162+L171-K171 -> 529.61874 | M101: =M162-L162+M171-L171 -> 533.99492 | N101: =N162-M162+N171-M171 -> 513.77303 | O101: =O162-N162+O171-N171 -> 479.91301 | P101: =P162-O162+P171-O171 -> 478.6478
A102: Change in NWC | B102: =B94+B95+B96+B97+B98+B99+B100+B101 -> 3300 | C102: =C94+C95+C96+C97+C98+C99+C100+C101 -> 9246 | D102: =D94+D95+D96+D97+D98+D99+D100+D101 -> 4908 | E102: =E94+E95+E96+E97+E98+E99+E100+E101 -> 819 | F102: =F94+F95+F96+F97+F98+F99+F100+F101 -> 1827 | G102: =G94+G95+G96+G97+G98+G99+G100+G101 -> -1523 | H102: =H94+H95+H96+H97+H98+H99+H100+H101 -> -2235 | I102: =I94+I95+I96+I97+I98+I99+I100+I101 -> 8753.0479 | ... P102: =P94+P95+P96+P97+P98+P99+P100+P101 -> 3142.0983
A103: As % of revenue | B103: =B102/B2 -> 0.036556186 | C103: =C102/C2 -> 0.083406251 | D103: =D102/D2 -> 0.035872211 | E103: =E102/E2 -> 0.0050600221 | F103: =F102/F2 -> 0.010009478 | G103: =G102/G2 -> -0.005911418 | H103: =H102/H2 -> -0.0079021058 | I103: =I102/I2 -> 0.029224321 | ... P103: =P102/P2 -> 0.0060381957
A104: Cash Flow from Operations | B104: =+B102+B91+B89+B85+B84+B92 -> 35159 | C104: =+C102+C91+C89+C85+C84+C92 -> 36279 | D104: =+D102+D91+D89+D85+D84+D92 -> 47100 | E104: =+E102+E91+E89+E85+E84+E92 -> 53595 | F104: =+F102+F91+F89+F85+F84+F92 -> 64332 | G104: =+G102+G91+G89+G85+G84+G92 -> 90766 | H104: =+H102+H91+H89+H85+H84+H92 -> 90854 | I104: =+I102+I91+I89+I85+I84+I92 -> 114264.57 | ... P104: =+P102+P91+P89+P85+P84+P92 -> 199123.63
A105: OCF Margin | B105: =B104/B2 -> 0.38947847 | C105: =C104/C2 -> 0.32726535 | D105: =D104/D2 -> 0.34425043 | E105: =E104/E2 -> 0.33112562 | F105: =F104/F2 -> 0.35245197 | G105: =G104/G2 -> 0.35230188 | H105: =H104/H2 -> 0.32122502 | I105: =I104/I2 -> 0.38150189 | ... P105: =P104/P2 -> 0.38265749
A107: Capex | B107: =Daloopa!AW431+Daloopa!AW432 -> -9972 | C107: =Daloopa!AX431+Daloopa!AX432 -> -13085 | D107: =Daloopa!AY431+Daloopa!AY432 -> -25041 | E107: =Daloopa!AZ431+Daloopa!AZ432 -> -23548 | F107: =Daloopa!BA431+Daloopa!BA432 -> -22281 | G107: =Daloopa!BB431+Daloopa!BB432 -> -24640 | H107: =Daloopa!BC431+Daloopa!BC432 -> -31485 | I107: =-I109*(I85) -> -32975.715 | J107: =-J109*(J85) -> -36527.908 | K107: =-K109*(K85) -> -41289.056 | L107: =-L109*(L85) -> -41270.204 | M107: =-M109*(M85) -> -40469.771 | N107: =-N109*(N85) -> -41475.268 | O107: =-O109*(O85) -> -38924.31 | P107: =-P109*(P85) -> -38746.149
A108: As % of sales | B108: =-B107/B2 -> 0.11046615 | C108: =-C107/C2 -> 0.11803708 | D108: =-D107/D2 -> 0.18302283 | E108: =-E107/E2 -> 0.14548645 | F108: =-F107/F2 -> 0.12206961 | G108: =-G107/G2 -> 0.095638437 | H108: =-H107/H2 -> 0.11131893 | I108: =-I107/I2 -> 0.11009798 | ... P108: =-P107/P2 -> 0.074458787
A109: Capex/D&A | B109: =-B107/(B85) -> 1.8932979 | C109: =-C107/(C85) -> 2.1440275 | D109: =-D107/(D85) -> 3.0672464 | E109: =-E107/(E85) -> 2.1691231 | F109: =-F107/(F85) -> 1.7265401 | G109: =-G107/(G85) -> 2.1324102 | H109: =-H107/(H85) -> 2.0595931 | I109: 2 | J109: 2 | K109: 2 | L109: 1.8 | M109: 1.6 | N109: 1.5 | O109: 1.3 | P109: 1.2
A110: Acuisition | B110: =Daloopa!AW440 -> -986 | C110: =Daloopa!AX440 -> -287 | D110: =Daloopa!AY440 -> -1491 | E110: =Daloopa!AZ440 -> -2515 | F110: =Daloopa!BA440 -> -738 | G110: =Daloopa!BB440 -> -2618 | H110: =Daloopa!BC440 -> -6969
A111: Other investing activities | B111: =B113-B110-B107 -> -20207 | C111: =C113-C110-C107 -> -18029 | D111: =D113-D110-D107 -> -1972 | E111: =E113-E110-E107 -> -3428 | F111: =F113-F110-F107 -> -9754 | G111: =G113-G110-G107 -> -8265 | H111: =H113-H110-H107 -> 18156
A113: Cash Flow from Investing | B113: =Daloopa!AW443 -> -31165 | C113: =Daloopa!AX443 -> -31401 | D113: =Daloopa!AY443 -> -28504 | E113: =Daloopa!AZ443 -> -29491 | F113: =Daloopa!BA443 -> -32773 | G113: =Daloopa!BB443 -> -35523 | H113: =Daloopa!BC443 -> -20298 | I113: =I111+I110+I107 -> -32975.715 | J113: =J111+J110+J107 -> -36527.908 | K113: =K111+K110+K107 -> -41289.056 | L113: =L111+L110+L107 -> -41270.204 | M113: =M111+M110+M107 -> -40469.771 | N113: =N111+N110+N107 -> -41475.268 | O113: =O111+O110+O107 -> -38924.31 | P113: =P111+P110+P107 -> -38746.149
A115: Taxes paid for equity awards | B115: =Daloopa!AW446 -> -3304 | C115: =Daloopa!AX446 -> -4166 | D115: =Daloopa!AY446 -> -4993 | E115: =Daloopa!AZ446 -> -4765 | F115: =Daloopa!BA446 -> -5720 | G115: =Daloopa!BB446 -> -10162 | H115: =Daloopa!BC446 -> -9300 | I115: =-I116*I89 -> -10183.423 | J115: =-J116*J89 -> -11079.137 | K115: =-K116*K89 -> -12303.705 | L115: =-L116*L89 -> -13429.145 | M115: =-M116*M89 -> -14563.884 | N115: =-N116*N89 -> -15655.652 | O115: =-O116*O89 -> -16675.467 | P115: =-P116*P89 -> -17692.594
A116: As % of SBC | B116: =-B115/B89 -> 0.49291362 | C116: =-C115/C89 -> 0.54251856 | D116: =-D115/D89 -> 0.53383941 | E116: =-E115/E89 -> 0.44144895 | F116: =-F115/F89 -> 0.44030483 | G116: =-G115/G89 -> 0.6609001 | H116: =-H115/H89 -> 0.48032228 | I116: 0.5 | J116: 0.5 | K116: 0.5 | L116: 0.5 | M116: 0.5 | N116: 0.5 | O116: 0.5 | P116: 0.5
A118: Repurchases of ordinary shares | B118: =Daloopa!AW449 -> -3693 | C118: =Daloopa!AX449 -> -4846 | D118: =Daloopa!AY449 -> -9075 | E118: =Daloopa!AZ449 -> -18396 | F118: =Daloopa!BA449 -> -31149 | G118: =Daloopa!BB449 -> -50274 | H118: =Daloopa!BC449 -> -59296 | I118: =-I128-I120-I115 -> -71105.426 | J118: =-J128-J120-J115 -> -71164.524 | K118: =-K128-K120-K115 -> -85035.933 | L118: =-L128-L120-L115 -> -96751.067 | M118: =-M128-M120-M115 -> -109424.69 | N118: =-N128-N120-N115 -> -120822.48 | O118: =-O128-O120-O115 -> -135264.63 | P118: =-P128-P120-P115 -> -147684.89
A119: Proceeds from sale of interest in consolidated entities | B119: =Daloopa!AW452 -> 0 | C119: =Daloopa!AX452 -> 800 | D119: =Daloopa!AY452 -> 950 | E119: =Daloopa!AZ452 -> 220 | F119: =Daloopa!BA452 -> 2800 | G119: =Daloopa!BB452 -> 310 | H119: =Daloopa!BC452 -> 35
A120: Proceeds/repayment of debt | B120: =Daloopa!AW450+Daloopa!AW451 -> -1335 | C120: =Daloopa!AX450+Daloopa!AX451 -> -86 | D120: =Daloopa!AY450+Daloopa!AY451 -> -61 | E120: =Daloopa!AZ450+Daloopa!AZ451 -> -268 | F120: =Daloopa!BA450+Daloopa!BA451 -> 9661 | G120: =Daloopa!BB450+Daloopa!BB451 -> -1236 | H120: =Daloopa!BC450+Daloopa!BC451 -> -1196 | I120: 0 | J120: 0 | K120: 5000 | L120: 5000 | M120: 5000 | N120: 5000 | O120: 5000 | P120: 5000
A121: Cash Flow from Financing | B121: =B115+B118+B119+B120 -> -8332 | C121: =C115+C118+C119+C120 -> -8298 | D121: =D115+D118+D119+D120 -> -13179 | E121: =E115+E118+E119+E120 -> -23209 | F121: =F115+F118+F119+F120 -> -24408 | G121: =G115+G118+G119+G120 -> -61362 | H121: =H115+H118+H119+H120 -> -69757 | I121: =I115+I118+I119+I120 -> -81288.85 | ... P121: =P115+P118+P119+P120 -> -160377.48
A122: Effect of exchange rates | B122: =Daloopa!AW455 -> -170 | C122: =Daloopa!AX455 -> 405 | D122: =Daloopa!AY455 -> -302 | E122: =Daloopa!AZ455 -> -23 | F122: =Daloopa!BA455 -> 24 | G122: =Daloopa!BB455 -> -287 | H122: =Daloopa!BC455 -> -506
A124: Change in Cash | B124: =B121+B122+B113+B104 -> -4508 | C124: =C121+C122+C113+C104 -> -3015 | D124: =D121+D122+D113+D104 -> 5115 | E124: =E121+E122+E113+E104 -> 872 | F124: =F121+F122+F113+F104 -> 7175 | G124: =G121+G122+G113+G104 -> -6406 | H124: =H121+H122+H113+H104 -> 293 | I124: =I121+I122+I113+I104 -> 0 | ... P124: =P121+P122+P113+P104 -> 0
A125: Beginning Cash | I125: =H126 -> 21879 | J125: =I126 -> 21879 | K125: =J126 -> 21879 | L125: =K126 -> 21879 | M125: =L126 -> 21879 | N125: =M126 -> 21879 | O125: =N126 -> 21879 | P125: =O126 -> 21879
A126: Ending Cash | H126: =H132 -> 21879 | I126: =I125+I124 -> 21879 | J126: =J125+J124 -> 21879 | K126: =K125+K124 -> 21879 | L126: =L125+L124 -> 21879 | M126: =M125+M124 -> 21879 | N126: =N125+N124 -> 21879 | O126: =O125+O124 -> 21879 | P126: =P125+P124 -> 21879
A128: Free Cash Flow | B128: =B104+B107 -> 25187 | C128: =C104+C107 -> 23194 | D128: =D104+D107 -> 22059 | E128: =E104+E107 -> 30047 | F128: =F104+F107 -> 42051 | G128: =G104+G107 -> 66126 | H128: =H104+H107 -> 59369 | I128: =I104+I107 -> 81288.85 | ... P128: =P104+P107 -> 160377.48
...

Sheet Segment
A1: Segment | B1: 2017 | C1: 2018 | D1: 2019 | E1: 2020 | F1: 2021 | G1: 2022 | H1: 2023 | I1: 2024 | J1: 2025 | K1: 2026 | L1: 2027 | M1: 2028 | N1: 2029 | O1: 2030
A3: Revenue
A4: =Model!A8 -> Google Search & Other | B4: =Model!C8 -> 69210 | C4: =Model!D8 -> 85161 | D4: =Model!E8 -> 98115 | E4: =Model!F8 -> 104062 | F4: =Model!G8 -> 148951 | G4: =Model!H8 -> 162450 | H4: =Model!I8 -> 170572.5 | I4: =Model!J8 -> 182512.58 | ... O4: =Model!P8 -> 271129.94
A5: =Model!A12 -> YouTube Ads | B5: =Model!C12 -> 9649 | C5: =Model!D12 -> 12149 | D5: =Model!E12 -> 15149 | E5: =Model!F12 -> 19772 | F5: =Model!G12 -> 28845 | G5: =Model!H12 -> 29243 | H5: =Model!I12 -> 30705.15 | I5: =Model!J12 -> 33775.665 | ... O5: =Model!P12 -> 58179.72
A6: =Model!A16 -> Google Network | B6: =Model!C16 -> 17587 | C6: =Model!D16 -> 19982 | D6: =Model!E16 -> 21547 | E6: =Model!F16 -> 23090 | F6: =Model!G16 -> 31701 | G6: =Model!H16 -> 32780 | H6: =Model!I16 -> 34091.2 | I6: =Model!J16 -> 35795.76 | ... O6: =Model!P16 -> 45288.868
A7: =Model!A20 -> Google Advertising | B7: =B4+B5+B6 -> 96446 | C7: =C4+C5+C6 -> 117292 | D7: =D4+D5+D6 -> 134811 | E7: =E4+E5+E6 -> 146924 | F7: =F4+F5+F6 -> 209497 | G7: =G4+G5+G6 -> 224473 | H7: =H4+H5+H6 -> 235368.85 | I7: =I4+I5+I6 -> 252084 | ... O7: =O4+O5+O6 -> 374598.53
A8: Google Other | B8: =Model!C24 -> 11014 | C8: =Model!D24 -> 13514 | D8: =Model!E24 -> 17014 | E8: =Model!F24 -> 21711 | F8: =Model!G24 -> 28032 | G8: =Model!H24 -> 29055 | H8: =Model!I24 -> 31379.4 | I8: =Model!J24 -> 34517.34 | ... O8: =Model!P24 -> 58921.629
A9: =Model!A28 -> Google Services | B9: =B7+B8 -> 107460 | C9: =C7+C8 -> 130806 | D9: =D7+D8 -> 151825 | E9: =E7+E8 -> 168635 | F9: =F7+F8 -> 237529 | G9: =G7+G8 -> 253528 | H9: =H7+H8 -> 266748.25 | I9: =I7+I8 -> 286601.34 | ... O9: =O7+O8 -> 433520.15
A10: =Model!A32 -> Google Cloud | B10: =Model!C32 -> 2918 | C10: =Model!D32 -> 5418 | D10: =Model!E32 -> 8918 | E10: =Model!F32 -> 13059 | F10: =Model!G32 -> 19206 | G10: =Model!H32 -> 26280 | H10: =Model!I32 -> 31536 | I10: =Model!J32 -> 37843.2 | ... O10: =Model!P32 -> 83583.208
A11: =Model!A36 -> Other bets | B11: =Model!C36 -> 477 | C11: =Model!D36 -> 595 | D11: =Model!E36 -> 659 | E11: =Model!F36 -> 657 | F11: =Model!G36 -> 753 | G11: =Model!H36 -> 1068 | H11: =Model!I36 -> 1228.2 | I11: =Model!J36 -> 1412.43 | ... O11: =Model!P36 -> 3267.0364
A12: =Model!A40 -> Hedging Gains | B12: =Model!C40 -> 0 | C12: =Model!D40 -> 0 | D12: =Model!E40 -> 455 | E12: =Model!F40 -> 176 | F12: =Model!G40 -> 149 | G12: =Model!H40 -> 1960 | H12: =Model!I40 -> 0 | I12: =Model!J40 -> 0 | ... O12: =Model!P40 -> 0
A13: =Model!A42 -> Total revenues | B13: =Model!C2 -> 110855 | C13: =Model!D2 -> 136819 | D13: =Model!E2 -> 161857 | E13: =Model!F2 -> 182527 | F13: =Model!G2 -> 257637 | G13: =Model!H2 -> 282836 | H13: =Model!I2 -> 299512.45 | I13: =Model!J2 -> 325856.97 | ... O13: =Model!P2 -> 520370.4
A15: Operating Income | B15: =Model!C70 -> 26146 | C15: =Model!D70 -> 26321 | D15: =Model!E70 -> 34231 | E15: =E18+E20+E22+E24 -> 41224 | F15: =F18+F20+F22+F24 -> 78714 | G15: =G18+G20+G22+G24 -> 74842 | H15: =H18+H20+H22+H24 -> 75590.601 | I15: =I18+I20+I22+I24 -> 82136.392 | J15: =J18+J20+J22+J24 -> 94157.142 | K15: =K18+K20+K22+K24 -> 104125.98 | L15: =L18+L20+L22+L24 -> 114119.85 | ... O15: =O18+O20+O22+O24 -> 146868.33
A16: Operating Margin | B16: =B15/Model!C2 -> 0.23585765 | C16: =C15/Model!D2 -> 0.19237825 | D16: =D15/Model!E2 -> 0.21148915 | E16: =E15/Model!F2 -> 0.22585152 | F16: =F15/Model!G2 -> 0.30552289 | G16: =G15/Model!H2 -> 0.26461271 | H16: =H15/Model!I2 -> 0.25237883 | I16: =I15/Model!J2 -> 0.25206271 | ... O16: =O15/Model!P2 -> 0.28223806
A17: Operating Income Breakdown
A18: =A9 -> Google Services | B18: =B9-B130 -> 36469.54 | C18: =C9-C130 -> 41223.44 | D18: =D9-D130 -> 47217.72 | E18: =Daloopa!BA108 -> 54606 | F18: =Daloopa!BB108 -> 91855 | G18: =Daloopa!BC108 -> 86572 | H18: =H9-H130 -> 86825.5 | I18: =I9-I130 -> 92446.502 | J18: =J9-J130 -> 102704.67 | K18: =K9-K130 -> 111028.63 | L18: =L9-L130 -> 118865.36 | M18: =M9-M130 -> 128226.22 | N18: =N9-N130 -> 136633.95 | O18: =O9-O130 -> 145264.47
A19: Margin | B19: =B18/B9 -> 0.33937782 | C19: =C18/C9 -> 0.31514946 | D19: =D18/D9 -> 0.31100096 | E19: =E18/E9 -> 0.32381178 | F19: =F18/F9 -> 0.38671068 | G19: =G18/G9 -> 0.34146919 | H19: =H18/H9 -> 0.32549604 | I19: =I18/I9 -> 0.3225613 | ... O19: =O18/O9 -> 0.33508123
A20: =A10 -> Google Cloud | B20: =B10-B134 -> -2130.14 | C20: =C10-C134 -> -3142.44 | D20: =D10-D134 -> -4013.1 | E20: =Daloopa!BA109 -> -5607 | F20: =Daloopa!BB109 -> -3099 | G20: =Daloopa!BC109 -> -2968 | H20: =H10-H134 -> -2187.88 | I20: =I10-I134 -> -738.608 | J20: =J10-J134 -> 1609.44 | K20: =K10-K134 -> 3786.4367 | L20: =L10-L134 -> 6440.0307 | M20: =M10-M134 -> 9114.8275 | N20: =N10-N134 -> 11588.152 | O20: =O10-O134 -> 14147.046
A21: Margin | B21: =B20/B10 -> -0.73 | C21: =C20/C10 -> -0.58 | D21: =D20/D10 -> -0.45 | E21: =E20/E10 -> -0.42935906 | F21: =F20/F10 -> -0.16135583 | G21: =G20/G10 -> -0.1129376 | H21: =H20/H10 -> -0.06937722 | I21: =I20/I10 -> -0.019517588 | ... O21: =O20/O10 -> 0.16925703
A22: =A11 -> Other bets | B22: =Daloopa!AX110 -> -3355 | C22: =Daloopa!AY110 -> -3358 | D22: =Daloopa!AZ110 -> -4824 | E22: =Daloopa!BA110 -> -4476 | F22: =Daloopa!BB110 -> -5281 | G22: =Daloopa!BC110 -> -6083 | H22: =H11-H138 -> -6379.536 | I22: =I11-I138 -> -6705.4878 | J22: =J11-J138 -> -7008.5951 | K22: =K11-K138 -> -7284.7956 | L22: =L11-L138 -> -7529.3223 | M22: =M11-M138 -> -7785.9907 | N22: =N11-N138 -> -8013.6593 | O22: =O11-O138 -> -8207.9781
A23: Margin | B23: =B22/B11 -> -7.033543 | C23: =C22/C11 -> -5.6436975 | D23: =D22/D11 -> -7.3201821 | E23: =E22/E11 -> -6.8127854 | F23: =F22/F11 -> -7.0132802 | G23: =G22/G11 -> -5.6956929 | H23: =H22/H11 -> -5.1942159 | I23: =I22/I11 -> -4.7474833 | ... O23: =O22/O11 -> -2.512362
A24: Corporate Costs | B24: =-B109 -> -2500 | C24: =-C109 -> -3000 | D24: =-D109 -> -3000 | E24: =Daloopa!BA111 -> -3299 | F24: =Daloopa!BB111 -> -4761 | G24: =Daloopa!BC111 -> -2679 | H24: =-H140 -> -2667.4825 | I24: =-I140 -> -2866.0134 | J24: =-J140 -> -3148.3755 | K24: =-K140 -> -3404.2918 | L24: =-L140 -> -3656.2201 | M24: =-M140 -> -3895.3528 | N24: =-N140 -> -4116.2928 | O24: =-O140 -> -4335.2015
A26: Cost Structure: Google Services
A28: Cost of Revenue | B28: =Model!C46 -> 45583 | C28: =Model!D46 -> 59549 | D28: =Model!E46 -> 71896 | E28: =Model!F46 -> 84732 | F28: =Model!G46 -> 110939 | G28: =Model!H46 -> 126203 | H28: =H70 -> 134742.37 | I28: =I70 -> 146942.56 | J28: =J70 -> 163256.16 | K28: =K70 -> 178732.58 | L28: =L70 -> 194461.47 | M28: =M70 -> 207393.29 | N28: =N70 -> 219334.47 | O28: =O70 -> 230854.86
A29: As % of revenue | B29: =B28/B13 -> 0.4111948 | C29: =C28/C13 -> 0.43523926 | D29: =D28/D13 -> 0.44419457 | E29: =E28/E13 -> 0.46421625 | F29: =F28/F13 -> 0.43060197 | G29: =G28/G13 -> 0.44620557 | H29: =H28/H13 -> 0.44987234 | I29: =I28/I13 -> 0.45094191 | ... O29: =O28/O13 -> 0.44363566
A31: Traffic Acquisition Cost (TAC) | B31: =Daloopa!AX1175 -> 21672 | C31: =Daloopa!AY1175 -> 26726 | D31: =Daloopa!AZ1175 -> 30089 | E31: =Daloopa!BA1175 -> 32778 | F31: =Daloopa!BB1175 -> 45566 | G31: =Daloopa!BC1175 -> 48955 | H31: =H33+H36 -> 51347.141 | I31: =I33+I36 -> 54653.494 | J31: =J33+J36 -> 59084.654 | K31: =K33+K36 -> 62990.89 | L31: =L33+L36 -> 66823.113 | M31: =M33+M36 -> 70517.418 | N31: =N33+N36 -> 74009.785 | O31: =O33+O36 -> 77374.622
A32: As % of Google Services revenue | B32: =B31/B9 -> 0.20167504 | C32: =C31/C9 -> 0.20431784 | D32: =D31/D9 -> 0.19818212 | E32: =E31/E9 -> 0.19437246 | F32: =F31/F9 -> 0.19183342 | G32: =G31/G9 -> 0.19309504 | H32: =H31/H9 -> 0.19249289 | I32: =I31/I9 -> 0.19069518 | ... O32: =O31/O9 -> 0.17847987
A33: Google Network | B33: =B34*B6 -> 12645.053 | C33: =C34*C6 -> 14147.256 | D33: =D34*D6 -> 14867.43 | E33: =E34*E6 -> 15932.1 | F33: =F34*F6 -> 21873.69 | G33: =G34*G6 -> 22618.2 | H33: =H34*H6 -> 23522.928 | I33: =I34*I6 -> 24699.074 | ... O33: =O34*O6 -> 31249.319
A34: As % of related revenue | B34: 0.719 | C34: 0.708 | D34: 0.69 | E34: =D34 -> 0.69 | F34: =E34 -> 0.69 | G34: =F34 -> 0.69 | H34: =G34 -> 0.69 | I34: =H34 -> 0.69 | J34: =I34 -> 0.69 | K34: =J34 -> 0.69 | L34: =K34 -> 0.69 | ... O34: =N34 -> 0.69
A36: TAC (ex Network) | B36: =B31-B33 -> 9026.947 | C36: =C31-C33 -> 12578.744 | D36: =D31-D33 -> 15221.57 | E36: =E31-E33 -> 16845.9 | F36: =F31-F33 -> 23692.31 | G36: =G31-G33 -> 26336.8 | H36: =H37*H4 -> 27824.213 | I36: =I37*I4 -> 29954.42 | J36: =J37*J4 -> 33150.626 | K36: =K37*K4 -> 36019.501 | L36: =L37*L4 -> 38772.869 | M36: =M37*M4 -> 41345.163 | N36: =N37*N4 -> 43670.641 | O36: =O37*O4 -> 46125.303
A37: As % of Search & other revenue | B37: =B36/B4 -> 0.13042836 | C37: =C36/C4 -> 0.14770545 | D37: =D36/D4 -> 0.15514009 | E37: =E36/E4 -> 0.1618833 | F37: =F36/F4 -> 0.1590611 | G37: =G36/G4 -> 0.1621225 | H37: =G37+0.1% -> 0.1631225 | I37: =H37+0.1% -> 0.1641225 | J37: =I37+0.1% -> 0.1651225 | K37: =J37+0.1% -> 0.1661225 | L37: =K37+0.1% -> 0.1671225 | M37: =L37+0.1% -> 0.1681225 | N37: =M37+0.1% -> 0.1691225 | O37: =N37+0.1% -> 0.1701225
A39: Cost of revenue, ex TAC | B39: =B28-B31 -> 23911 | C39: =C28-C31 -> 32823 | D39: =D28-D31 -> 41807 | E39: =E28-E31 -> 51954 | F39: =F28-F31 -> 65373 | G39: =G28-G31 -> 77248 | H39: =H28-H31 -> 83395.226 | I39: =I28-I31 -> 92289.07 | ... O39: =O28-O31 -> 153480.24
A41: YouTube Ads | B41: =B42*B5 -> 7236.75 | C41: =C42*C5 -> 9111.75 | D41: =D42*D5 -> 11361.75 | E41: =E42*E5 -> 14829 | F41: =F42*F5 -> 21633.75 | G41: =G42*G5 -> 21932.25 | H41: =H42*H5 -> 23028.863 | I41: =I42*I5 -> 25331.749 | ... O41: =O42*O5 -> 43634.79
A42: As % of related revenue | B42: 0.75 | C42: 0.75 | D42: 0.75 | E42: 0.75 | F42: 0.75 | G42: 0.75 | H42: 0.75 | I42: 0.75 | J42: 0.75 | K42: 0.75 | L42: 0.75 | M42: 0.75 | N42: 0.75 | O42: 0.75
A44: Google Other | B44: =B49+B50 -> 4570.81 | C44: =C49+C50 -> 5756.964 | D44: =D49+D50 -> 7435.118 | E44: =E49+E50 -> 10801.222 | F44: =F49+F50 -> 12109.824 | G44: =G49+G50 -> 14934.27 | H44: =H49+H50 -> 15901.511 | I44: =I49+I50 -> 17241.411 | ... O44: =O49+O50 -> 28282.382
A45: As % of related revenue | B45: =B44/B8 -> 0.415 | C45: =C44/C8 -> 0.426 | D45: =D44/D8 -> 0.437 | E45: =E44/E8 -> 0.4975 | F45: =F44/F8 -> 0.432 | G45: =G44/G8 -> 0.514 | H45: =H44/H8 -> 0.50675 | I45: =I44/I8 -> 0.4995 | ... O45: =O44/O8 -> 0.48
A46: PlayStore Mix in Other revenue | B46: 0.7 | C46: 0.68 | D46: 0.66 | E46: 0.55 | F46: 0.6 | G46: 0.52 | H46: =G46-0.5% -> 0.515 | I46: =H46-0.5% -> 0.51 | J46: =I46-0.5% -> 0.505 | K46: =J46-0.5% -> 0.5 | L46: =K46-0.5% -> 0.495 | M46: =L46-0.5% -> 0.49 | N46: =M46-0.5% -> 0.485 | O46: =N46-0.5% -> 0.48
A47: PlayStore revenue | B47: =B46*B8 -> 7709.8 | C47: =C46*C8 -> 9189.52 | D47: =D46*D8 -> 11229.24 | E47: =E46*E8 -> 11941.05 | F47: =F46*F8 -> 16819.2 | G47: =G46*G8 -> 15108.6 | H47: =H46*H8 -> 16160.391 | I47: =I46*I8 -> 17603.843 | ... O47: =O46*O8 -> 28282.382
A48: Playstore Cost of revenue % of revenue | B48: 0.25 | C48: 0.25 | D48: 0.25 | E48: 0.25 | F48: 0.22 | G48: 0.25 | H48: =G48-1% -> 0.24 | I48: =H48-1% -> 0.23 | J48: =I48-1% -> 0.22 | K48: =J48 -> 0.22 | L48: =K48 -> 0.22 | M48: =L48 -> 0.22 | N48: =M48 -> 0.22 | O48: =N48 -> 0.22
A49: Playstore Cost of revenue | B49: =B8*B46*B48 -> 1927.45 | C49: =C8*C46*C48 -> 2297.38 | D49: =D8*D46*D48 -> 2807.31 | E49: =E8*E46*E48 -> 2985.2625 | F49: =F8*F46*F48 -> 3700.224 | G49: =G8*G46*G48 -> 3777.15 | H49: =H8*H46*H48 -> 3878.4938 | I49: =I8*I46*I48 -> 4048.884 | ... O49: =O8*O46*O48 -> 6222.124
A50: Cost of revenue for the rest of "Other" | B50: =B51*(B8-B47) -> 2643.36 | C50: =C51*(C8-C47) -> 3459.584 | D50: =D51*(D8-D47) -> 4627.808 | E50: =E51*(E8-E47) -> 7815.96 | F50: =F51*(F8-F47) -> 8409.6 | G50: =G51*(G8-G47) -> 11157.12 | H50: =H51*(H8-H47) -> 12023.017 | I50: =I51*(I8-I47) -> 13192.527 | ... O50: =O51*(O8-O47) -> 22060.258
A51: Cost of revenue for the rest of "Other" as % of related revenue | B51: 0.8 | C51: 0.8 | D51: 0.8 | E51: 0.8 | F51: 0.75 | G51: 0.8 | H51: =G51-1% -> 0.79 | I51: =H51-1% -> 0.78 | J51: =I51-1% -> 0.77 | K51: =J51-1% -> 0.76 | L51: =K51-1% -> 0.75 | M51: =L51-1% -> 0.74 | N51: =M51-1% -> 0.73 | O51: =N51-1% -> 0.72
A53: Google Cloud | B53: =B54*B10 -> 1459 | C53: =C54*C10 -> 2438.1 | D53: =D54*D10 -> 3567.2 | E53: =E54*E10 -> 4570.65 | F53: =F54*F10 -> 5761.8 | G53: =G54*G10 -> 8409.6 | H53: =H54*H10 -> 10012.68 | I53: =I54*I10 -> 11920.608 | ... O53: =O54*O10 -> 25074.962
A54: As % of related revenue | B54: 0.5 | C54: 0.45 | D54: 0.4 | E54: 0.35 | F54: 0.3 | G54: 0.32 | H54: =G54-0.25% -> 0.3175 | I54: =H54-0.25% -> 0.315 | J54: =I54-0.25% -> 0.3125 | K54: =J54-0.25% -> 0.31 | L54: =K54-0.25% -> 0.3075 | M54: =L54-0.25% -> 0.305 | N54: =M54-0.25% -> 0.3025 | O54: =N54-0.25% -> 0.3
A56: Other bets | B56: =B57*B11 -> 238.5 | C56: =C57*C11 -> 297.5 | D56: =D57*D11 -> 329.5 | E56: =E57*E11 -> 328.5 | F56: =F57*F11 -> 376.5 | G56: =G57*G11 -> 534 | H56: =H57*H11 -> 589.536 | I56: =I57*I11 -> 649.7178 | ... O56: =O57*O11 -> 1306.8146
A57: As % of related revenue | B57: 0.5 | C57: 0.5 | D57: 0.5 | E57: 0.5 | F57: 0.5 | G57: 0.5 | H57: =G57-2% -> 0.48 | I57: =H57-2% -> 0.46 | J57: =I57-2% -> 0.44 | K57: =J57-2% -> 0.42 | L57: =K57-2% -> 0.4 | M57: =L57 -> 0.4 | N57: =M57 -> 0.4 | O57: =N57 -> 0.4
A59: Total Cost of revenue (YT Ads+Google Other+Google Cloud+other Bets) | B59: =B41+B44+B53+B56 -> 13505.06 | C59: =C41+C44+C53+C56 -> 17604.314 | D59: =D41+D44+D53+D56 -> 22693.568 | E59: =E41+E44+E53+E56 -> 30529.372 | F59: =F41+F44+F53+F56 -> 39881.874 | G59: =G41+G44+G53+G56 -> 45810.12 | H59: =H41+H44+H53+H56 -> 49532.589 | I59: =I41+I44+I53+I56 -> 55143.486 | ... O59: =O41+O44+O53+O56 -> 98298.949
A61: Google Search Costs, ex TAC | B61: =B39-B59 -> 10405.94 | C61: =C39-C59 -> 15218.686 | D61: =D39-D59 -> 19113.432 | E61: =E39-E59 -> 21424.628 | F61: =F39-F59 -> 25491.126 | G61: =G39-G59 -> 31437.88 | H61: =H62*H4 -> 33862.637 | I61: =I62*I4 -> 37145.584 | J61: =J62*J4 -> 41863.961 | K61: =K62*K4 -> 46297.203 | L61: =L62*L4 -> 50698.021 | M61: =M62*M4 -> 52510.288 | N61: =N62*N4 -> 53844.707 | O61: =O62*O4 -> 55181.293
A62: As % of Google Search revenue | B62: =B61/B4 -> 0.15035313 | C62: =C61/C4 -> 0.17870488 | D62: =D61/D4 -> 0.19480642 | E62: =E61/E4 -> 0.2058833 | F62: =F61/F4 -> 0.17113766 | G62: =G61/G4 -> 0.19352342 | H62: =G62+0.5% -> 0.19852342 | I62: =H62+0.5% -> 0.20352342 | J62: =I62+0.5% -> 0.20852342 | K62: =J62+0.5% -> 0.21352342 | L62: =K62+0.5% -> 0.21852342 | M62: =L62-0.5% -> 0.21352342 | N62: =M62-0.5% -> 0.20852342 | O62: =N62-0.5% -> 0.20352342
A64: Google Search & Other Cost of Revenue | B64: =B36+B61 -> 19432.887 | C64: =C36+C61 -> 27797.43 | D64: =D36+D61 -> 34335.002 | E64: =E36+E61 -> 38270.528 | F64: =F36+F61 -> 49183.436 | G64: =G36+G61 -> 57774.68 | H64: =H36+H61 -> 61686.849 | I64: =I36+I61 -> 67100.004 | ... O64: =O36+O61 -> 101306.6
A65: As % of related revenue | B65: =B64/B4 -> 0.28078149 | C65: =C64/C4 -> 0.32641033 | D65: =D64/D4 -> 0.34994651 | E65: =E64/E4 -> 0.3677666 | F65: =F64/F4 -> 0.33019876 | G65: =G64/G4 -> 0.35564592 | H65: =H64/H4 -> 0.36164592 | I65: =I64/I4 -> 0.36764592 | ... O65: =O64/O4 -> 0.37364592
A67: Google Services | B67: =B64+B41+B44+B33 -> 43885.5 | C67: =C64+C41+C44+C33 -> 56813.4 | D67: =D64+D41+D44+D33 -> 67999.3 | E67: =E64+E41+E44+E33 -> 79832.85 | F67: =F64+F41+F44+F33 -> 104800.7 | G67: =G64+G41+G44+G33 -> 117259.4 | H67: =H64+H41+H44+H33 -> 124140.15 | I67: =I64+I41+I44+I33 -> 134372.24 | ... O67: =O64+O41+O44+O33 -> 204473.09
A68: As % of related revenue | B68: =B67/B9 -> 0.40838917 | C68: =C67/C9 -> 0.43433329 | D68: =D67/D9 -> 0.44787947 | E68: =E67/E9 -> 0.47340617 | F68: =F67/F9 -> 0.44121223 | G68: =G67/G9 -> 0.46251065 | H68: =H67/H9 -> 0.46538319 | I68: =I67/I9 -> 0.46884721 | ... O68: =O67/O9 -> 0.47165762
A70: Calculated Cost of revenue | B70: =B53+B44+B41+B64+B56+B33 -> 45583 | C70: =C53+C44+C41+C64+C56+C33 -> 59549 | D70: =D53+D44+D41+D64+D56+D33 -> 71896 | E70: =E53+E44+E41+E64+E56+E33 -> 84732 | F70: =F53+F44+F41+F64+F56+F33 -> 110939 | G70: =G53+G44+G41+G64+G56+G33 -> 126203 | H70: =H53+H44+H41+H64+H56+H33 -> 134742.37 | I70: =I53+I44+I41+I64+I56+I33 -> 146942.56 | ... O70: =O53+O44+O41+O64+O56+O33 -> 230854.86
A71: Reported Cost of revenue | B71: =B28 -> 45583 | C71: =C28 -> 59549 | D71: =D28 -> 71896 | E71: =E28 -> 84732 | F71: =F28 -> 110939 | G71: =G28 -> 126203
A72: Delta | B72: =B70-B71 -> 0 | C72: =C70-C71 -> 0 | D72: =D70-D71 -> 0 | E72: =E70-E71 -> 0 | F72: =F70-F71 -> 0 | G72: =G70-G71 -> 0
A74: Leftover Costs | B74: =B126-B70 -> 39126 | C74: =C126-C70 -> 50949 | D74: =D126-D70 -> 55730 | E74: =E126-E70 -> 56571 | F74: =F126-F70 -> 67984 | G74: =G126-G70 -> 81791 | H74: =H126-H70 -> 89179.483 | I74: =I126-I70 -> 96778.013 | ... O74: =O126-O70 -> 142647.2
A76: R&D | B76: =Model!C52 -> 16625 | C76: =Model!D52 -> 21419 | D76: =Model!E52 -> 26018 | E76: =Model!F52 -> 27573 | F76: =Model!G52 -> 31562 | G76: =Model!H52 -> 39500 | H76: =H79+H83+H87 -> 43000 | I76: =I79+I83+I87 -> 46500 | J76: =J79+J83+J87 -> 50000 | K76: =K79+K83+K87 -> 53500 | L76: =L79+L83+L87 -> 57000 | M76: =M79+M83+M87 -> 60500 | N76: =N79+N83+N87 -> 64000 | O76: =O79+O83+O87 -> 67500
A77: As % of revenue | B77: =B76/B13 -> 0.14997068 | C77: =C76/C13 -> 0.15654989 | D77: =D76/D13 -> 0.16074683 | E77: =E76/E13 -> 0.15106258 | F77: =F76/F13 -> 0.1225057 | G77: =G76/G13 -> 0.1396569 | H77: =H76/H13 -> 0.14356665 | I77: =I76/I13 -> 0.14270065 | ... O77: =O76/O13 -> 0.1297153
A79: Google Services | B79: =B76-B83-B87 -> 12012.2 | C79: =C76-C83-C87 -> 15140 | D79: =D76-D83-D87 -> 17659.44 | E79: =E76-E83-E87 -> 17880.18 | F79: =F76-F83-F87 -> 19953.02 | G79: =G76-G83-G87 -> 25742 | H79: =G79+H80 -> 27742 | I79: =H79+I80 -> 29742 | J79: =I79+J80 -> 31742 | K79: =J79+K80 -> 33742 | L79: =K79+L80 -> 35742 | M79: =L79+M80 -> 37742 | N79: =M79+N80 -> 39742 | O79: =N79+O80 -> 41742
A80: Increase $ | C80: =C79-B79 -> 3127.8 | D80: =D79-C79 -> 2519.44 | E80: =E79-D79 -> 220.74 | F80: =F79-E79 -> 2072.84 | G80: =G79-F79 -> 5788.98 | H80: 2000 | I80: 2000 | J80: 2000 | K80: 2000 | L80: 2000 | M80: 2000 | N80: 2000 | O80: 2000
A81: =A65 -> As % of related revenue | B81: =B79/B9 -> 0.11178299 | C81: =C79/C9 -> 0.11574393 | D81: =D79/D9 -> 0.11631444 | E81: =E79/E9 -> 0.10602888 | F81: =F79/F9 -> 0.084002459 | G81: =G79/G9 -> 0.10153514 | H81: =H79/H9 -> 0.10400068 | I81: =I79/I9 -> 0.10377481 | ... O81: =O79/O9 -> 0.096286181
A83: Google Cloud | B83: =B85*B10 -> 1750.8 | C83: =C85*C10 -> 2709 | D83: =D85*D10 -> 3745.56 | E83: =E85*E10 -> 4962.42 | F83: =F85*F10 -> 6337.98 | G83: =G85*G10 -> 7884 | H83: =G83+H84 -> 9084 | I83: =H83+I84 -> 10284 | J83: =I83+J84 -> 11484 | K83: =J83+K84 -> 12684 | L83: =K83+L84 -> 13884 | M83: =L83+M84 -> 15084 | N83: =M83+N84 -> 16284 | O83: =N83+O84 -> 17484
A84: Increase $ | C84: =C83-B83 -> 958.2 | D84: =D83-C83 -> 1036.56 | E84: =E83-D83 -> 1216.86 | F84: =F83-E83 -> 1375.56 | G84: =G83-F83 -> 1546.02 | H84: 1200 | I84: 1200 | J84: 1200 | K84: 1200 | L84: 1200 | M84: 1200 | N84: 1200 | O84: 1200
A85: =A42 -> As % of related revenue | B85: 0.6 | C85: 0.5 | D85: 0.42 | E85: 0.38 | F85: 0.33 | G85: 0.3 | H85: =H83/H10 -> 0.28805175 | I85: =I83/I10 -> 0.27175292 | J85: =J83/J10 -> 0.25288559 | K85: =K83/K10 -> 0.24078484 | L85: =L83/L10 -> 0.22918684 | M85: =M83/M10 -> 0.22035005 | N85: =N83/N10 -> 0.2143062 | O85: =O83/O10 -> 0.20918077
A87: =A56 -> Other bets | B87: =B89*B11 -> 2862 | C87: =C89*C11 -> 3570 | D87: =D89*D11 -> 4613 | E87: =E89*E11 -> 4730.4 | F87: =F89*F11 -> 5271 | G87: =G89*G11 -> 5874 | H87: =G87+H88 -> 6174 | I87: =H87+I88 -> 6474 | J87: =I87+J88 -> 6774 | K87: =J87+K88 -> 7074 | L87: =K87+L88 -> 7374 | M87: =L87+M88 -> 7674 | N87: =M87+N88 -> 7974 | O87: =N87+O88 -> 8274
A88: Increase $ | C88: =C87-B87 -> 708 | D88: =D87-C87 -> 1043 | E88: =E87-D87 -> 117.4 | F88: =F87-E87 -> 540.6 | G88: =G87-F87 -> 603 | H88: 300 | I88: 300 | J88: 300 | K88: 300 | L88: 300 | M88: 300 | N88: 300 | O88: 300
A89: =A57 -> As % of related revenue | B89: 6 | C89: 6 | D89: 7 | E89: 7.2 | F89: 7 | G89: 5.5 | H89: =H87/H11 -> 5.0268686 | I89: =I87/I11 -> 4.58359 | J89: =J87/J11 -> 4.170426 | K89: =K87/K11 -> 3.7870622 | L89: =L87/L11 -> 3.432754 | M89: =M87/M11 -> 3.1064438 | N89: =N87/N11 -> 2.8068558 | O89: =O87/O11 -> 2.5325705
A91: S&M | B91: =Model!C55 -> 12893 | C91: =Model!D55 -> 16333 | D91: =Model!E55 -> 18464 | E91: =Model!F55 -> 17946 | F91: =Model!G55 -> 22912 | G91: =Model!H55 -> 26567 | H91: =H94+H98+H102 -> 29167 | I91: =I94+I98+I102 -> 31767 | J91: =J94+J98+J102 -> 34367 | K91: =K94+K98+K102 -> 36967 | L91: =L94+L98+L102 -> 39567 | M91: =M94+M98+M102 -> 42167 | N91: =N94+N98+N102 -> 44767 | O91: =O94+O98+O102 -> 47367
A92: =A77 -> As % of revenue | B92: =B91/B13 -> 0.11630508 | C92: =C91/C13 -> 0.11937669 | D92: =D91/D13 -> 0.11407601 | E92: =E91/E13 -> 0.098319701 | F92: =F91/F13 -> 0.088931326 | G92: =G91/G13 -> 0.093930758 | H92: =H91/H13 -> 0.097381595 | I92: =I91/I13 -> 0.097487557 | ... O92: =O91/O13 -> 0.091025547
A94: =A79 -> Google Services | B94: =B91-B98-B102 -> 11341.4 | C94: =C91-C98-C102 -> 13597.4 | D94: =D91-D98-D102 -> 14134.58 | E94: =E91-E98-E102 -> 11747.52 | F94: =F91-F98-F102 -> 15045.16 | G94: =G91-G98-G102 -> 16625.6 | H94: =G94+H95 -> 17625.6 | I94: =H94+I95 -> 18625.6 | J94: =I94+J95 -> 19625.6 | K94: =J94+K95 -> 20625.6 | L94: =K94+L95 -> 21625.6 | M94: =L94+M95 -> 22625.6 | N94: =M94+N95 -> 23625.6 | O94: =N94+O95 -> 24625.6
A95: =A80 -> Increase $ | C95: =C94-B94 -> 2256 | D95: =D94-C94 -> 537.18 | E95: =E94-D94 -> -2387.06 | F95: =F94-E94 -> 3297.64 | G95: =G94-F94 -> 1580.44 | H95: 1000 | I95: 1000 | J95: 1000 | K95: 1000 | L95: 1000 | M95: 1000 | N95: 1000 | O95: 1000
A96: =A81 -> As % of related revenue | B96: =B94/B9 -> 0.10554067 | C96: =C94/C9 -> 0.10395089 | D96: =D94/D9 -> 0.093097843 | E96: =E94/E9 -> 0.069662407 | F96: =F94/F9 -> 0.063340308 | G96: =G94/G9 -> 0.065576978 | H96: =H94/H9 -> 0.066075785 | I96: =I94/I9 -> 0.064987833 | ... O96: =O94/O9 -> 0.056803818
A98: =A83 -> Google Cloud | B98: =B100*B10 -> 1313.1 | C98: =C100*C10 -> 2438.1 | D98: =D100*D10 -> 4013.1 | E98: =E100*E10 -> 5876.55 | F98: =F100*F10 -> 7490.34 | G98: =G100*G10 -> 9460.8 | H98: =G98+H99 -> 10960.8 | I98: =H98+I99 -> 12460.8 | J98: =I98+J99 -> 13960.8 | K98: =J98+K99 -> 15460.8 | L98: =K98+L99 -> 16960.8 | M98: =L98+M99 -> 18460.8 | N98: =M98+N99 -> 19960.8 | O98: =N98+O99 -> 21460.8
A99: =A84 -> Increase $ | C99: =C98-B98 -> 1125 | D99: =D98-C98 -> 1575 | E99: =E98-D98 -> 1863.45 | F99: =F98-E98 -> 1613.79 | G99: =G98-F98 -> 1970.46 | H99: 1500 | I99: 1500 | J99: 1500 | K99: 1500 | L99: 1500 | M99: 1500 | N99: 1500 | O99: 1500
A100: =A85 -> As % of related revenue | B100: 0.45 | C100: 0.45 | D100: 0.45 | E100: 0.45 | F100: 0.39 | G100: 0.36 | H100: =H98/H10 -> 0.34756469 | I100: =I98/I10 -> 0.32927448 | J100: =J98/J10 -> 0.30742643 | K100: =K98/K10 -> 0.29349782 | L100: =L98/L10 -> 0.27997639 | M100: =M98/M10 -> 0.26967901 | N100: =N98/N10 -> 0.26269487 | O100: =O98/O10 -> 0.25675971
A102: =A87 -> Other bets | B102: =B104*B11 -> 238.5 | C102: =C104*C11 -> 297.5 | D102: =D104*D11 -> 316.32 | E102: =E104*E11 -> 321.93 | F102: =F104*F11 -> 376.5 | G102: =G104*G11 -> 480.6 | H102: =G102+H103 -> 580.6 | I102: =H102+I103 -> 680.6 | J102: =I102+J103 -> 780.6 | K102: =J102+K103 -> 880.6 | L102: =K102+L103 -> 980.6 | M102: =L102+M103 -> 1080.6 | N102: =M102+N103 -> 1180.6 | O102: =N102+O103 -> 1280.6
A103: =A88 -> Increase $ | C103: =C102-B102 -> 59 | D103: =D102-C102 -> 18.82 | E103: =E102-D102 -> 5.61 | F103: =F102-E102 -> 54.57 | G103: =G102-F102 -> 104.1 | H103: 100 | I103: 100 | J103: 100 | K103: 100 | L103: 100 | M103: 100 | N103: 100 | O103: 100
A104: =A89 -> As % of related revenue | B104: 0.5 | C104: 0.5 | D104: 0.48 | E104: 0.49 | F104: 0.5 | G104: 0.45 | H104: =H102/H11 -> 0.47272431 | I104: =I102/I11 -> 0.48186459 | J104: =J102/J11 -> 0.48057788 | K104: =K102/K11 -> 0.47142875 | L104: =L102/L11 -> 0.45649017 | M104: =M102/M11 -> 0.43742809 | N104: =N102/N11 -> 0.41557235 | O104: =O102/O11 -> 0.39197604
A106: G&A | B106: =Model!C58 -> 6872 | C106: =Model!D58 -> 8126 | D106: =Model!E58 -> 9551 | E106: =Model!F58 -> 11052 | F106: =Model!G58 -> 13510 | G106: =Model!H58 -> 15724 | H106: =H112+H116+H120+H109 -> 17012.482 | I106: =I112+I116+I120+I109 -> 18511.013 | J106: =J112+J116+J120+J109 -> 20093.375 | K106: =K112+K116+K120+K109 -> 21649.292 | L106: =L112+L116+L120+L109 -> 23201.22 | M106: =M112+M116+M120+M109 -> 24740.353 | N106: =N112+N116+N120+N109 -> 26261.293 | O106: =O112+O116+O120+O109 -> 27780.202
A107: =A92 -> As % of revenue | B107: =B106/B13 -> 0.061990889 | C107: =C106/C13 -> 0.059392336 | D107: =D106/D13 -> 0.059008878 | E107: =E106/E13 -> 0.060549946 | F107: =F106/F13 -> 0.05243812 | G107: =G106/G13 -> 0.055594055 | H107: =H106/H13 -> 0.056800585 | I107: =I106/I13 -> 0.056807173 | ... O107: =O106/O13 -> 0.053385438
A109: Corporate Costs | B109: 2500 | C109: 3000 | D109: 3000 | E109: =-E24 -> 3299 | F109: =-F24 -> 4761 | G109: =-G24 -> 2679 | H109: =H110*H9 -> 2667.4825 | I109: =I110*I9 -> 2866.0134 | J109: =J110*J9 -> 3148.3755 | K109: =K110*K9 -> 3404.2918 | L109: =L110*L9 -> 3656.2201 | M109: =M110*M9 -> 3895.3528 | N109: =N110*N9 -> 4116.2928 | O109: =O110*O9 -> 4335.2015
A110: As % of revenue | B110: =B109/B9 -> 0.023264471 | C110: =C109/C9 -> 0.022934728 | D110: =D109/D9 -> 0.019759592 | E110: =E109/E9 -> 0.019562961 | F110: =F109/F9 -> 0.020043868 | G110: =G109/G9 -> 0.01056688 | H110: 0.01 | I110: 0.01 | J110: 0.01 | K110: 0.01 | L110: 0.01 | M110: 0.01 | N110: 0.01 | O110: 0.01
A112: =A94 -> Google Services | B112: =B106-B116-B120-B109 -> 3751.36 | C112: =C106-C116-C120-C109 -> 4031.76 | D112: =D106-D116-D120-D109 -> 4813.96 | E112: =E106-E116-E120-E109 -> 5532.16 | F112: =F106-F116-F120-F109 -> 6101.62 | G112: =G106-G116-G120-G109 -> 9415 | H112: =G112+H113 -> 10415 | I112: =H112+I113 -> 11415 | J112: =I112+J113 -> 12415 | K112: =J112+K113 -> 13415 | L112: =K112+L113 -> 14415 | M112: =L112+M113 -> 15415 | N112: =M112+N113 -> 16415 | O112: =N112+O113 -> 17415
A113: =A95 -> Increase $ | C113: =C112-B112 -> 280.4 | D113: =D112-C112 -> 782.2 | E113: =E112-D112 -> 718.2 | F113: =F112-E112 -> 569.46 | G113: =G112-F112 -> 3313.38 | H113: 1000 | I113: 1000 | J113: 1000 | K113: 1000 | L113: 1000 | M113: 1000 | N113: 1000 | O113: 1000
A114: =A96 -> As % of related revenue | B114: =B112/B9 -> 0.034909362 | C114: =C112/C9 -> 0.030822439 | D114: =D112/D9 -> 0.031707295 | E114: =E112/E9 -> 0.032805527 | F114: =F112/F9 -> 0.025687895 | G114: =G112/G9 -> 0.037135938 | H114: =H112/H9 -> 0.039044305 | I114: =I112/I9 -> 0.039828844 | ... O114: =O112/O9 -> 0.040171143
A116: =A98 -> Google Cloud | B116: =B118*B10 -> 525.24 | C116: =C118*C10 -> 975.24 | D116: =D118*D10 -> 1605.24 | E116: =E118*E10 -> 2089.44 | F116: =F118*F10 -> 2496.78 | G116: =G118*G10 -> 3416.4 | H116: =G116+H117 -> 3666.4 | I116: =H116+I117 -> 3916.4 | J116: =I116+J117 -> 4166.4 | K116: =J116+K117 -> 4416.4 | L116: =K116+L117 -> 4666.4 | M116: =L116+M117 -> 4916.4 | N116: =M116+N117 -> 5166.4 | O116: =N116+O117 -> 5416.4
A117: =A99 -> Increase $ | C117: =C116-B116 -> 450 | D117: =D116-C116 -> 630 | E117: =E116-D116 -> 484.2 | F117: =F116-E116 -> 407.34 | G117: =G116-F116 -> 919.62 | H117: 250 | I117: 250 | J117: 250 | K117: 250 | L117: 250 | M117: 250 | N117: 250 | O117: 250
A118: =A100 -> As % of related revenue | B118: 0.18 | C118: 0.18 | D118: 0.18 | E118: 0.16 | F118: 0.13 | G118: 0.13 | H118: =H116/H10 -> 0.11626078 | I118: =I116/I10 -> 0.10349019 | J118: =J116/J10 -> 0.091746998 | K118: =K116/K10 -> 0.083838078 | L118: =L116/L10 -> 0.077029492 | M118: =M116/M10 -> 0.071819742 | N118: =N116/N10 -> 0.067992604 | O118: =O116/O10 -> 0.06480249
A120: =A102 -> Other bets | B120: =B122*B11 -> 95.4 | C120: =C122*C11 -> 119 | D120: =D122*D11 -> 131.8 | E120: =E122*E11 -> 131.4 | F120: =F122*F11 -> 150.6 | G120: =G122*G11 -> 213.6 | H120: =G120+H121 -> 263.6 | I120: =H120+I121 -> 313.6 | J120: =I120+J121 -> 363.6 | K120: =J120+K121 -> 413.6 | L120: =K120+L121 -> 463.6 | M120: =L120+M121 -> 513.6 | N120: =M120+N121 -> 563.6 | O120: =N120+O121 -> 613.6
A121: =A103 -> Increase $ | C121: =C120-B120 -> 23.6 | D121: =D120-C120 -> 12.8 | E121: =E120-D120 -> -0.4 | F121: =F120-E120 -> 19.2 | G121: =G120-F120 -> 63 | H121: 50 | I121: 50 | J121: 50 | K121: 50 | L121: 50 | M121: 50 | N121: 50 | O121: 50
A122: =A104 -> As % of related revenue | B122: 0.2 | C122: 0.2 | D122: 0.2 | E122: 0.2 | F122: 0.2 | G122: 0.2 | H122: =H120/H11 -> 0.21462303 | I122: =I120/I11 -> 0.2220287 | J122: =J120/J11 -> 0.22385103 | K122: =K120/K11 -> 0.22142055 | L122: =L120/L11 -> 0.21581567 | M122: =M120/M11 -> 0.20790586 | N122: =N120/N11 -> 0.19838775 | O122: =O120/O11 -> 0.18781548
A124: European Commission Fines | B124: =Model!C61 -> 2736 | C124: =Model!D61 -> 5071 | D124: =Model!E61 -> 1697 | E124: =Model!F61 -> 0 | F124: =Model!G61 -> 0 | G124: =Model!H61 -> 0 | H124: =Model!I61 -> 0 | I124: =Model!J61 -> 0 | ... O124: =Model!P61 -> 0
A126: Total Expenses | B126: =Model!C69 -> 84709 | C126: =Model!D69 -> 110498 | D126: =Model!E69 -> 127626 | E126: =E13-E15 -> 141303 | F126: =F13-F15 -> 178923 | G126: =G13-G15 -> 207994 | H126: =H13-H15 -> 223921.85 | I126: =I13-I15 -> 243720.58 | J126: =J13-J15 -> 267716.54 | K126: =K13-K15 -> 290848.87 | L126: =L13-L15 -> 314229.69 | ... O126: =O13-O15 -> 373502.06
A128: =A18 -> Google Services
A129: Reported | E129: =E9-E18 -> 114029 | F129: =F9-F18 -> 145674 | G129: =G9-G18 -> 166956
A130: Calculated | B130: =B112+B94+B79+B67 -> 70990.46 | C130: =C112+C94+C79+C67 -> 89582.56 | D130: =D112+D94+D79+D67 -> 104607.28 | E130: =E112+E94+E79+E67 -> 114992.71 | F130: =F112+F94+F79+F67 -> 145900.5 | G130: =G112+G94+G79+G67 -> 169042 | H130: =H112+H94+H79+H67 -> 179922.75 | I130: =I112+I94+I79+I67 -> 194154.84 | ... O130: =O112+O94+O79+O67 -> 288255.69
A132: =A20 -> Google Cloud
A133: =A129 -> Reported | E133: =E10-E20 -> 18666 | F133: =F10-F20 -> 22305 | G133: =G10-G20 -> 29248
A134: =A130 -> Calculated | B134: =B116+B98+B83+B53 -> 5048.14 | C134: =C116+C98+C83+C53 -> 8560.44 | D134: =D116+D98+D83+D53 -> 12931.1 | E134: =E116+E98+E83+E53 -> 17499.06 | F134: =F116+F98+F83+F53 -> 22086.9 | G134: =G116+G98+G83+G53 -> 29170.8 | H134: =H116+H98+H83+H53 -> 33723.88 | I134: =I116+I98+I83+I53 -> 38581.808 | ... O134: =O116+O98+O83+O53 -> 69436.162
...

Sheet Valuation
A1: Items | C1: 2021 | D1: 2022 | E1: 2023 | F1: 2024 | G1: 2025 | H1: 2026 | I1: 2027 | J1: 2028 | K1: 2029 | L1: 2030
A2: FCF
A3: OCF | C3: =Model!G104 -> 90766 | D3: =Model!H104 -> 90854 | E3: =Model!I104 -> 114264.57 | F3: =Model!J104 -> 118771.57 | G3: =Model!K104 -> 133628.69 | H3: =Model!L104 -> 146450.42 | I3: =Model!M104 -> 159458.35 | J3: =Model!N104 -> 172953.4 | ... L3: =Model!P104 -> 199123.63
A4: Capex | C4: =Model!G107 -> -24640 | D4: =Model!H107 -> -31485 | E4: =Model!I107 -> -32975.715 | F4: =Model!J107 -> -36527.908 | G4: =Model!K107 -> -41289.056 | H4: =Model!L107 -> -41270.204 | I4: =Model!M107 -> -40469.771 | J4: =Model!N107 -> -41475.268 | ... L4: =Model!P107 -> -38746.149 | O4: Terminal Multiple
A5: FCF | C5: =C3+C4 -> 66126 | D5: =D3+D4 -> 59369 | E5: =E3+E4 -> 81288.85 | F5: =F3+F4 -> 82243.661 | G5: =G3+G4 -> 92339.638 | H5: =H3+H4 -> 105180.21 | I5: =I3+I4 -> 118988.57 | J5: =J3+J4 -> 131478.13 | K5: =K3+K4 -> 146940.1 | L5: =L3+L4-Model!P89 -> 124992.29 | O5: 7
A6: FCF/share | C6: =C5/C14 -> 4.9164824 | D6: =D5/D14 -> 4.5855411 | E6: =E5/E14 -> 6.5296435 | F6: =F5/F14 -> 6.8467296 | G6: =G5/G14 -> 8.0141073 | H6: =H5/H14 -> 9.5558049 | I6: =I5/I14 -> 11.365944 | J6: =J5/J14 -> 13.249066 | ... L6: =L5/L14 -> 14.213707 | O6: =O5+1 -> 8
A7: Terminal FCF multiple | L7: 14 | O7: =O6+1 -> 9
A8: Terminal Stock price | L8: =L7*L6 -> 198.9919 | O8: =O7+1 -> 10
A9: Current price* | B9: 92.66 | O9: =O8+1 -> 11
A10: Dividend/share | C10: 0 | D10: 0 | E10: 0 | F10: 0 | G10: 0 | H10: 0 | I10: 0 | J10: 0 | K10: 0 | L10: 0 | O10: =O9+1 -> 12
A11: Cash flow | D11: =-B9 -> -92.66 | E11: =E10+E8 -> 0 | F11: =F10+F8 -> 0 | G11: =G10+G8 -> 0 | H11: =H10+H8 -> 0 | I11: =I10+I8 -> 0 | J11: =J10+J8 -> 0 | K11: =K10+K8 -> 0 | L11: =L10+L8 -> 198.9919 | O11: =O10+1 -> 13
O12: =O11+1 -> 14
A13: IRR | B13: =IRR(D11:L11) -> 0.10025383 | O13: =O12+1 -> 15
A14: #diluted shares outstanding | C14: =Model!G193 -> 13449.86 | D14: =Model!H193 -> 12947 | E14: =Model!I193 -> 12449.202 | F14: =Model!J193 -> 12012.109 | G14: =Model!K193 -> 11522.136 | H14: =Model!L193 -> 11006.944 | I14: =Model!M193 -> 10468.869 | J14: =Model!N193 -> 9923.5772 | ... L14: =Model!P193 -> 8793.7857 | O14: =O13+1 -> 16
O15: =O14+1 -> 17
A16: *Closing price of March 09, 2023 | O16: =O15+1 -> 18
O17: =O16+1 -> 19
A18: Stock price | D18: =B9 -> 92.66 | E18: =D18*1.1 -> 101.926 | F18: =E18*1.1 -> 112.1186 | G18: =F18*1.1 -> 123.33046 | H18: =G18*1.1 -> 135.66351 | I18: =H18*1.1 -> 149.22986 | J18: =I18*1.1 -> 164.15284 | K18: =J18*1.1 -> 180.56813 | L18: =K18*1.1 -> 198.62494 | O18: =O17+1 -> 20
O19: =O18+1 -> 21
O20: =O19+1 -> 22
O21: =O20+1 -> 23
O22: =O21+1 -> 24
O23: =O22+1 -> 25
O24: =O23+1 -> 26
O25: =O24+1 -> 27
O26: =O25+1 -> 28
O27: =O26+1 -> 29
O28: =O27+1 -> 30
O29: =O28+1 -> 31
O30: =O29+1 -> 32
... O40: =O39+1 -> 42

Sheet Daloopa
A1: Calendar | B1: Unit | C1: Source | D1: Tag Id | E1: 2013Q1 | F1: 2013Q2 | G1: 2013Q3 | H1: 2013Q4 | I1: 2014Q1 | J1: 2014Q2 | K1: 2014Q3 | L1: 2014Q4 | M1: 2015Q1 | N1: 2015Q2 | O1: 2015Q3 | P1: 2015Q4 | Q1: 2016Q1 | R1: 2016Q2 | S1: 2016Q3 | T1: 2016Q4 | U1: 2017Q1 | V1: 2017Q2 | W1: 2017Q3 | X1: 2017Q4 | Y1: 2018Q1 | Z1: 2018Q2 | AA1: 2018Q3 | AB1: 2018Q4 | AC1: 2019Q1 | AD1: 2019Q2 | AE1: 2019Q3 | AF1: 2019Q4 | AG1: 2020Q1 | AH1: 2020Q2 | AI1: 2020Q3 | AJ1: 2020Q4 | AK1: 2021Q1 | AL1: 2021Q2 | AM1: 2021Q3 | AN1: 2021Q4 | AO1: 2022Q1 | AP1: 2022Q2 | AQ1: 2022Q3 | AR1: 2022Q4 | AT1: 2013FY | AU1: 2014FY | AV1: 2015FY | AW1: 2016FY | AX1: 2017FY | AY1: 2018FY | AZ1: 2019FY | BA1: 2020FY | BB1: 2021FY | BC1: 2022FY
A2: Fiscal | E2: 2013Q1 | F2: 2013Q2 | G2: 2013Q3 | H2: 2013Q4 | I2: 2014Q1 | J2: 2014Q2 | K2: 2014Q3 | L2: 2014Q4 | M2: 2015Q1 | N2: 2015Q2 | O2: 2015Q3 | P2: 2015Q4 | Q2: 2016Q1 | R2: 2016Q2 | S2: 2016Q3 | T2: 2016Q4 | U2: 2017Q1 | V2: 2017Q2 | W2: 2017Q3 | X2: 2017Q4 | Y2: 2018Q1 | Z2: 2018Q2 | AA2: 2018Q3 | AB2: 2018Q4 | AC2: 2019Q1 | AD2: 2019Q2 | AE2: 2019Q3 | AF2: 2019Q4 | AG2: 2020Q1 | AH2: 2020Q2 | AI2: 2020Q3 | AJ2: 2020Q4 | AK2: 2021Q1 | AL2: 2021Q2 | AM2: 2021Q3 | AN2: 2021Q4 | AO2: 2022Q1 | AP2: 2022Q2 | AQ2: 2022Q3 | AR2: 2022Q4 | AT2: 2013FY | AU2: 2014FY | AV2: 2015FY | AW2: 2016FY | AX2: 2017FY | AY2: 2018FY | AZ2: 2019FY | BA2: 2020FY | BB2: 2021FY | BC2: 2022FY
A3: Fiscal Date | E3: 41364 | F3: 41455 | G3: 41547 | H3: 41639 | I3: 41729 | J3: 41820 | K3: 41912 | L3: 42004 | M3: 42094 | N3: 42185 | O3: 42277 | P3: 42369 | Q3: 42460 | R3: 42551 | S3: 42643 | T3: 42735 | U3: 42825 | V3: 42916 | W3: 43008 | X3: 43100 | Y3: 43190 | Z3: 43281 | AA3: 43373 | AB3: 43465 | AC3: 43555 | AD3: 43646 | AE3: 43738 | AF3: 43830 | AG3: 43921 | AH3: 44012 | AI3: 44104 | AJ3: 44196 | AK3: 44286 | AL3: 44377 | AM3: 44469 | AN3: 44561 | AO3: 44651 | AP3: 44742 | AQ3: 44834 | AR3: 44926
A4: Documents
A5: 10Q 10K | E5: 10-Q | F5: 10-Q | G5: 10-Q | H5: 10-K | I5: 10-Q | J5: 10-Q | K5: 10-Q | L5: 10-K | M5: 10-Q | N5: 10-Q | O5: 10-Q | P5: 10-K | Q5: 10-Q | R5: 10-Q | S5: 10-Q | T5: 10-K | U5: 10-Q | V5: 10-Q | W5: 10-Q | X5: 10-K | Y5: 10-Q | Z5: 10-Q | AA5: 10-Q | AB5: 10-K | AC5: 10-Q | AD5: 10-Q | AE5: 10-Q | AF5: 10-K | AG5: 10-Q | AH5: 10-Q | AI5: 10-Q | AJ5: 10-K | AK5: 10-Q | AL5: 10-Q | AM5: 10-Q | AN5: 10-K | AO5: 10-Q | AP5: 10-Q | AQ5: 10-Q | AR5: 10-K
A6: 10K | P6: 10-K
A7: 8K | E7: EX-99.1 | F7: EX-99.1 | G7: EX-99.1 | H7: EX-99.1 | I7: EX-99.1 | J7: EX-99.1 | K7: EX-99.1 | L7: EX-99.1 | M7: EX-99.1 | N7: EX-99.1 | O7: EX-99.1 | P7: EX-99.1 | Q7: EX-99.1 | R7: EX-99.1 | S7: EX-99.1 | T7: EX-99.1 | U7: EX-99.1 | V7: EX-99.1 | W7: EX-99.1 | X7: EX-99.1 | Y7: EX-99.1 | Z7: EX-99.1 | AA7: EX-99.1 | AB7: EX-99.1 | AC7: EX-99.1 | AD7: EX-99.1 | AE7: EX-99.1 | AF7: EX-99.1 | AG7: EX-99.1 | AH7: EX-99.1 | AI7: EX-99.1 | AJ7: EX-99.1 | AK7: EX-99.1 | AL7: EX-99.1 | AM7: EX-99.01 | AN7: EX-99.1 | AO7: EX-99.1 | AP7: EX-99.1 | AQ7: EX-99.1 | AR7: EX-99.1
A8: Earnings transcripts | M8: Earnings | N8: Earnings | O8: Earnings | P8: Earnings | Q8: Earnings | R8: Earnings | S8: Earnings | T8: Earnings | U8: Earnings | V8: Earnings | W8: Earnings | X8: Earnings | Y8: Earnings | Z8: Earnings | AA8: Earnings | AB8: Earnings | AC8: Earnings | AD8: Earnings | AE8: Earnings | AF8: Earnings | AG8: Earnings
A9: Conference transcripts | Q9: Alphabet Inc at Morgan Stanley Technology, Media & Telecom Conference | T9: Alphabet Inc at Credit Suisse Technology, Media, and Telecom Conference | U9: Alphabet Inc at Morgan Stanley Technology, Media & Telecom Conference | V9: Alphabet Inc Annual Shareholders Meeting | W9: Alphabet Inc at Citi Global Technology Conference | X9: Alphabet Inc at Credit Suisse Technology, Media and Telecom Conference | Y9: Alphabet Inc at Morgan Stanley Technology, Media & Telecom Conference | Z9: Alphabet Inc Annual Shareholders Meeting | AC9: Alphabet Inc at Morgan Stanley Technology, Media & Telecom Conference | AD9: Alphabet Inc Annual Shareholders Meeting | AG9: Alphabet Inc at Morgan Stanley Technology, Media & Telecom Conference
A10: Conference transcripts | T10: Alphabet Inc at Phocuswright Conference | U10: Alphabet Inc at Goldman Sachs Technology Conference | Y10: Alphabet Inc at Goldman Sachs Technology & Internet Conference | Z10: Alphabet Inc at Red Hat, Inc., the 14th annual Red Hat Summit | AC10: Alphabet Inc at Goldman Sachs Technology & Internet Conference | AG10: Alphabet Inc at Goldman Sachs Technology & Internet Conference
A11: Conference transcripts | AG11: Salesforce.Com Inc, UnitedHealth Group Inc, Alphabet Inc, Color, and Novartis AG at JPMorgan Healthcare Conference Panel
A12: Earning Brief | M12: Earnings Summary | N12: Earnings Summary | O12: Earnings Summary | P12: Earnings Summary | Q12: Earnings Summary | R12: Earnings Summary | S12: Earnings Summary | T12: Earnings Summary | U12: Earnings Summary | V12: Earnings Summary | W12: Earnings Summary | X12: Earnings Summary | Y12: Earnings Summary | Z12: Earnings Summary | AA12: Earnings Summary | AB12: Earnings Summary | AC12: Earnings Summary | AD12: Earnings Summary | AE12: Earnings Summary | AF12: Earnings Summary | AG12: Earnings Summary
A14: Guidance
A15: Annual
A16: Impact on operating result | B16: Billion | C16: 8-K | D16: 2690429 | AJ16: 2.1
A18: Additional information for Fiscal year
A19: Employee severance and related charges-Low | B19: Billion | C19: 8-K | D19: 3814027 | AR19: 1.9
A20: Employee severance and related charges-High | B20: Billion | C20: 8-K | D20: 3814028 | AR20: 2.3
A21: Reduction in depreciation- approx | B21: Billion | C21: 8-K | D21: 3814030 | AR21: 3.4
A23: Quarterly
A24: Exit costs relating to office space reductions-approx | B24: Billion | C24: 8-K | D24: 3814029 | AR24: 0.5
A26: KPIs
A27: Deferred revenue recognized as revenue | B27: Billion | C27: 10-K | D27: 3501224 | AJ27: 1.8 | AK27: 1.3 | AL27: 0.5 | AM27: 0.3 | AN27: 0.2 | AO27: 1.4 | AP27: 0.7 | AQ27: 0.3 | AR27: 0.1 | BA27: 1.8 | BB27: 2.3 | BC27: 2.5
A29: Remaining performance obligations | B29: Billion | C29: 10-K | D29: 3321078 | AF29: 11.4 | AG29: 12.8 | AH29: 14.8 | AI29: 19 | AJ29: 29.8 | AK29: 30.7 | AL29: 35.3 | AM29: 37.1 | AN29: 51 | AO29: 50.5 | AP29: 51.2 | AQ29: 52.4 | AR29: 64.3
A31: Revenue
A32: Increase (decrease) in Google service segment revenue | B32: Billion | C32: 10-K | D32: 3501225 | AK32: 13 | AL32: 22.1 | AM32: 17.3 | AO32: 10.3 | AP32: 5.8 | AQ32: 1.5 | AR32: =BC32-SUM(AO32,AP32,AQ32) -> -1.6 | BA32: 16.8 | BC32: 16
A33: Increase (decrease) in Google cloud segment revenue | B33: Billion | C33: 10-K | D33: 3501226 | AK33: 1.3 | AL33: 1.6 | AM33: 1.5 | AO33: 1.8 | AP33: 1.6 | AQ33: 1.9 | AR33: =BC33-SUM(AO33,AP33,AQ33) -> 1.8 | BA33: 4.1 | BC33: 7.1
A35: Traffic acquisition costs (TAC) to Google network members and distribution partners
A36: TAC to Google network members | B36: Million | C36: 8-K | D36: 2621598 | I36: 2387 | J36: 2400 | K36: 2421 | L36: 2656 | M36: 2432 | N36: 2432 | O36: 2514 | P36: 2864 | Q36: 2571 | R36: 2623 | S36: 2623 | T36: 3082 | U36: 2824 | V36: 3042 | W36: 3101 | X36: 3674 | Y36: 3386 | Z36: 3411 | AA36: 3427 | AB36: 3930 | AC36: 3477 | AD36: 3621 | AE36: 3634 | AT36: 9293 | AU36: 9864 | AV36: 10242 | AW36: 10899 | AX36: 12641 | AY36: 14154
A37: TAC to distribution partners | B37: Million | C37: 8-K | D37: 2621599 | I37: 845 | J37: 893 | K37: 927 | L37: 968 | M37: 913 | N37: 945 | O37: 1052 | P37: 1191 | Q37: 1217 | R37: 1352 | S37: 1559 | T37: 1766 | U37: 1805 | V37: 2049 | W37: 2401 | X37: 2776 | Y37: 2902 | Z37: 3009 | AA37: 3155 | AB37: 3506 | AC37: 3383 | AD37: 3617 | AE37: 3856 | AT37: 2965 | AU37: 3633 | AV37: 4101 | AW37: 5894 | AX37: 9031 | AY37: 12572
A38: Total TAC | B38: Million | C38: 8-K | D38: 2621600 | E38: 2960 | F38: 3010 | G38: 2970 | H38: 3310 | I38: =SUM(I36:I37) -> 3232 | J38: =SUM(J36:J37) -> 3293 | K38: =SUM(K36:K37) -> 3348 | L38: =SUM(L36:L37) -> 3624 | M38: =SUM(M36:M37) -> 3345 | N38: =SUM(N36:N37) -> 3377 | O38: =SUM(O36:O37) -> 3566 | P38: =SUM(P36:P37) -> 4055 | ... AE38: =SUM(AE36:AE37) -> 7490 | AF38: 8501 | AG38: 7452 | AH38: 6694 | AI38: 8166 | AJ38: 10466 | AK38: 9712 | AL38: 10929 | AM38: 11498 | AN38: 13427 | AO38: 11990 | AP38: 12214 | AQ38: 11826 | AR38: 12925 | AT38: =SUM(AT36:AT37) -> 12258 | AU38: =SUM(AU36:AU37) -> 13497 | AV38: =SUM(AV36:AV37) -> 14343 | AW38: =SUM(AW36:AW37) -> 16793 | AX38: =SUM(AX36:AX37) -> 21672 | AY38: =SUM(AY36:AY37) -> 26726 | AZ38: 30100 | BA38: 32800 | BB38: 45566 | BC38: =SUM(AO38,AP38,AQ38,AR38) -> 48955
A40: TAC to Google network members as % of Google network members' properties revenues | B40: Percent | C40: 8-K | D40: 13994 | I40: 0.68 | J40: 0.67 | K40: 0.68 | L40: 0.68 | M40: 0.68 | N40: 0.67 | O40: 0.68 | P40: 0.69 | Q40: 0.7 | R40: 0.7 | S40: 0.7 | T40: 0.7 | U40: 0.7 | V40: 0.72 | W40: 0.71 | X40: 0.74 | Y40: 0.73 | Z40: 0.71 | AA40: 0.7 | AB40: 0.7 | AC40: 0.69 | AD40: 0.69 | AE40: 0.69 | AW40: 0.699 | AX40: 0.719 | AY40: 0.708
A41: TAC to distribution partners as % of Google properties revenues | B41: Percent | C41: 8-K | D41: 13996 | I41: 0.08 | J41: 0.08 | K41: 0.08 | L41: 0.08 | M41: 0.08 | N41: 0.08 | O41: 0.08 | P41: 0.08 | Q41: 0.08 | R41: 0.09 | S41: 0.1 | T41: 0.1 | U41: 0.1 | V41: 0.11 | W41: 0.12 | X41: 0.12 | Y41: 0.13 | Z41: 0.13 | AA41: 0.13 | AB41: 0.13 | AC41: 0.13 | AD41: 0.13 | AE41: 0.13 | AW41: 0.092 | AX41: 0.116 | AY41: 0.131
A42: Total TAC as % of advertising revenues | B42: Percent | C42: 10-K | D42: 13999 | I42: 0.23 | J42: 0.23 | K42: 0.23 | L42: 0.22 | M42: 0.22 | N42: 0.21 | O42: 0.21 | P42: 0.21 | Q42: 0.21 | R42: 0.21 | S42: 0.21 | T42: 0.22 | U42: 0.22 | V42: 0.22 | W42: 0.23 | X42: 0.24 | Y42: 0.24 | Z42: 0.23 | AA42: 0.23 | AB42: 0.23 | AC42: 0.22 | AD42: 0.22 | AE42: 0.22 | AT42: 0.24 | AU42: 0.226 | AV42: 0.213 | AW42: 0.212 | AX42: 0.227 | AY42: 0.23 | AZ42: 0.223
A44: Monetization metrics information (QoQ)
A45: Aggregate paid clicks | B45: Percent | C45: 8-K | D45: 14002 | M45: -0.01 | N45: 0.07 | O45: 0.06 | P45: 0.17 | Q45: -0.03 | R45: 0.07 | S45: 0.09 | T45: 0.2 | U45: 0.02 | V45: 0.12 | W45: 0.06 | X45: 0.18
A46: Paid clicks on Google properties | B46: Percent | C46: 8-K | D46: 14004 | M46: -0.03 | N46: 0.1 | O46: 0.07 | P46: 0.22 | Q46: -0.04 | R46: 0.09 | S46: 0.11 | T46: 0.23 | U46: 0.01 | V46: 0.15 | W46: 0.07 | X46: 0.19 | Y46: 0.08 | Z46: 0.15 | AA46: 0.1 | AB46: 0.22 | AC46: -0.09 | AD46: 0.06 | AE46: 0.01
A47: Paid clicks on Google network members' properties | B47: Percent | C47: 8-K | D47: 14007 | M47: 0.04 | N47: -0.02 | O47: 0 | P47: 0.01 | Q47: 0.04 | R47: -0.03 | S47: 0.01 | T47: 0.06 | U47: 0.06 | V47: -0.05 | W47: 0.02 | X47: 0.09
A49: Aggregate cost per click | B49: Percent | C49: 8-K | D49: 14010 | M49: -0.05 | N49: -0.04 | O49: -0.01 | P49: -0.05 | Q49: 0 | R49: -0.01 | S49: -0.05 | T49: -0.09 | U49: -0.04 | V49: -0.06 | W49: 0.01 | X49: -0.06
A50: Cost-per-click on Google properties | B50: Percent | C50: 8-K | D50: 14013 | M50: -0.03 | N50: -0.05 | O50: -0.02 | P50: -0.08 | Q50: 0.02 | R50: -0.02 | S50: -0.06 | T50: -0.11 | U50: -0.03 | V50: -0.08 | W50: 0.01 | X50: -0.07 | Y50: -0.07 | Z50: -0.1 | AA50: -0.07 | AB50: -0.09 | AC50: 0.05 | AD50: -0.01 | AE50: 0.03
A51: Cost-per-click on Google network members properties | B51: Percent | C51: 8-K | D51: 14017 | M51: -0.11 | N51: -0.03 | O51: 0.01 | P51: 0.07 | Q51: -0.12 | R51: -0.02 | S51: -0.06 | T51: 0 | U51: -0.09 | V51: 0.05 | W51: 0 | X51: 0.01
A53: Impressions on Google network members properties | B53: Percent | C53: 8-K | D53: 14020 | Y53: 0.05 | Z53: -0.04 | AA53: -0.01 | AB53: 0.07 | AC53: 0.05 | AD53: 0 | AE53: 0
A54: Cost-per-impression on Google network members properties | B54: Percent | C54: 8-K | D54: 14022 | Y54: -0.1 | Z54: 0.07 | AA54: 0.02 | AB54: 0.07 | AC54: -0.14 | AD54: 0.05 | AE54: 0
A56: Google properties
A57: Google websites revenues | B57: Million | C57: 10-Q | D57: 1277764 | K57: 11252 | O57: 13087 | Q57: 14328 | R57: 15400 | S57: 16089 | T57: =AW57-SUM(Q57,R57,S57) -> 17968 | U57: 17403 | V57: 18425 | W57: 19723 | X57: =AX57-SUM(U57,V57,W57) -> 22237 | Y57: 21998 | Z57: 23262 | AA57: 24054 | AB57: =AY57-SUM(Y57,Z57,AA57) -> 27022 | AC57: 25682 | AD57: 27335 | AE57: 28647 | AT57: 37422 | AU57: 45085 | AV57: 52357 | AW57: 63785 | AX57: 77788 | AY57: 96336
A58: Google websites as a percentage of advertising revenues | B58: Percent | C58: 10-Q | D58: 1277765 | K58: 0.759 | O58: 0.78
A59: Google websites as a percentage of google segment revenues | B59: Percent | C59: 10-Q | D59: 1277766 | Q59: 0.713 | R59: 0.722 | S59: 0.723 | U59: 0.71 | V59: 0.715 | W59: 0.718 | Y59: 0.71 | Z59: 0.715 | AA59: 0.716 | AC59: 0.71 | AD59: 0.705 | AE59: 0.71 | AT59: 0.674 | AU59: 0.686 | AV59: 0.702 | AW59: 0.713 | AX59: 0.709 | AY59: 0.707
A60: Aggregate paid clicks | B60: Percent | C60: 10-Q | D60: 2690435 | M60: 0.13 | N60: 0.18 | AT60: 0.25 | AU60: 0.2
A61: Paid clicks on google websites change | B61: Percent | C61: 10-K | D61: 1277767 | M61: 0.25 | N61: 0.3 | O61: 0.35 | Q61: 0.38 | R61: 0.37 | S61: 0.42 | U61: 0.53 | V61: 0.61 | W61: 0.55 | Y61: 0.59 | Z61: 0.58 | AA61: 0.62 | AC61: 0.39 | AD61: 0.28 | AE61: 0.18 | AG61: 0.12 | AH61: 0.08 | AI61: 0.27 | AK61: 0.25 | AL61: 0.26 | AM61: 0.22 | AO61: 0.16 | AP61: 0.12 | AQ61: 0.08 | AT61: 0.33 | AU61: 0.29 | AV61: 0.33 | AW61: 0.4 | AX61: 0.54 | AY61: 0.62 | AZ61: 0.23 | BA61: 0.19 | BB61: 0.23 | BC61: 0.1
A62: Cost-per-click on google websites change | B62: Percent | C62: 10-K | D62: 1277768 | M62: -0.13 | N62: -0.16 | O62: -0.16 | Q62: -0.12 | R62: -0.09 | S62: -0.13 | U62: -0.21 | V62: -0.26 | W62: -0.21 | Y62: -0.19 | Z62: -0.22 | AA62: -0.28 | AC62: -0.19 | AD62: -0.11 | AE62: -0.02 | AG62: -0.04 | AH62: -0.15 | AI62: -0.15 | AK62: 0.03 | AL62: 0.31 | AM62: 0.18 | AO62: 0.08 | AP62: 0 | AQ62: -0.05 | AT62: -0.1 | AU62: -0.07 | AV62: -0.15 | AW62: -0.13 | AX62: -0.21 | AY62: -0.25 | AZ62: -0.07 | BA62: -0.1 | BB62: 0.15 | BC62: -0.01
A64: Google network members properties
A65: Google network members properties revenues | B65: Million | C65: 10-Q | D65: 1277769 | K65: 3568 | O65: 3694 | Q65: 3692 | R65: 3743 | S65: 3732 | T65: =AW65-SUM(Q65,R65,S65) -> 4431 | U65: 4008 | V65: 4247 | W65: 4342 | X65: =AX65-SUM(U65,V65,W65) -> 4990 | Y65: 4644 | Z65: 4825 | AA65: 4900 | AB65: =AY65-SUM(Y65,Z65,AA65) -> 5613 | AC65: 5038 | AD65: 5266 | AE65: 5269 | AT65: 13650 | AU65: 14539 | AV65: 15033 | AW65: 15598 | AX65: 17587 | AY65: 19982
A66: Google network members properties as a percentage of advertising revenues | B66: Percent | C66: 10-Q | D66: 1277770 | K66: 0.241 | O66: 0.22
A67: Google network members properties revenues as a percentage of google segment revenues | B67: Percent | C67: 10-Q | D67: 1277771 | Q67: 0.184 | R67: 0.176 | S67: 0.168 | U67: 0.164 | V67: 0.165 | W67: 0.158 | Y67: 0.15 | Z67: 0.148 | AA67: 0.146 | AC67: 0.139 | AD67: 0.136 | AE67: 0.131 | AT67: 0.246 | AU67: 0.221 | AV67: 0.202 | AW67: 0.174 | AX67: 0.16 | AY67: 0.147
A68: Paid clicks change | B68: Percent | C68: 10-K | D68: 1277772 | M68: -0.12 | N68: -0.09 | O68: -0.05 | Q68: 0.02 | S68: 0.01 | U68: 0.1 | V68: 0.09 | W68: 0.1 | AT68: 0.11 | AU68: 0.02 | AV68: -0.07 | AW68: 0.03 | AX68: 0.1
A69: Cost-per-click change | B69: Percent | C69: 10-K | D69: 3752347 | M69: 0.02 | N69: -0.03 | O69: -0.04 | Q69: -0.08 | R69: -0.08 | S69: -0.14 | U69: -0.17 | V69: -0.11 | W69: -0.05 | AT69: -0.08 | AU69: -0.06 | AV69: -0.03 | AW69: -0.13 | AX69: -0.09
A70: Aggregate cost per click | B70: Percent | C70: 10-Q | D70: 3752348 | M70: -0.07 | N70: -0.11 | AT70: -0.08 | AU70: -0.05
A71: Impressions change | B71: Percent | C71: 10-K | D71: 1277774 | Y71: 0 | Z71: 0.01 | AA71: 0.01 | AC71: 0.06 | AD71: 0.11 | AE71: 0.12 | AG71: 0.12 | AH71: 0.16 | AI71: 0.15 | AK71: 0.07 | AL71: -0.01 | AM71: 0.02 | AO71: 0.05 | AP71: 0.06 | AQ71: 0.03 | AY71: 0.02 | AZ71: 0.09 | BA71: 0.15 | BB71: 0.02 | BC71: 0.03
A72: Cost-per-impression change | B72: Percent | C72: 10-K | D72: 1277775 | Y72: 0.18 | Z72: 0.14 | AA72: 0.11 | AC72: 0.01 | AD72: -0.01 | AE72: -0.03 | AG72: -0.07 | AH72: -0.23 | AI72: -0.07 | AK72: 0.19 | AL72: 0.63 | AM72: 0.39 | AO72: 0.17 | AP72: 0.02 | AQ72: -0.05 | AY72: 0.12 | AZ72: 0.01 | BA72: -0.08 | BB72: 0.35 | BC72: 0.01
A74: Google cloud
A75: Google cloud | B75: Million | C75: 10-Q | D75: 1277776 | AC75: 1825 | AD75: 2100 | AE75: 2379 | AF75: =AZ75-SUM(AC75,AD75,AE75) -> 2614 | AG75: 2777 | AH75: 3007 | AI75: 3444 | AZ75: 8918
A76: Google cloud revenues as a percentage of google segment revenues | B76: Percent | C76: 10-Q | D76: 1277777 | AC76: 0.051 | AD76: 0.054 | AE76: 0.059 | AG76: 0.068 | AH76: 0.079 | AI76: 0.075 | AZ76: 0.055
A78: Segmental Breakdown
A79: Revenue
A80: Google Search & other | B80: Million | C80: 10-K | D80: 2690438 | AB80: 23320 | AC80: 22547 | AD80: 23642 | AE80: 24741 | AF80: 27185 | AG80: 24502 | AH80: 21319 | AI80: 26338 | AJ80: 31903 | AK80: 31879 | AL80: 35845 | AM80: 37926 | AN80: 43301 | AO80: 39618 | AP80: 40689 | AQ80: 39539 | AR80: 42604 | AZ80: 98115 | BA80: 104062 | BB80: 148951 | BC80: 162450
A81: YouTube ads | B81: Million | C81: 10-K | D81: 2690439 | AB81: 3605 | AC81: 3025 | AD81: 3603 | AE81: 3804 | AF81: 4717 | AG81: 4038 | AH81: 3812 | AI81: 5037 | AJ81: 6885 | AK81: 6005 | AL81: 7002 | AM81: 7205 | AN81: 8633 | AO81: 6869 | AP81: 7340 | AQ81: 7071 | AR81: 7963 | AZ81: 15149 | BA81: 19772 | BB81: 28845 | BC81: 29243
A82: Google properties | B82: Million | C82: 8-K | D82: 2621603 | AB82: =SUM(AB80:AB81) -> 26925 | AC82: =SUM(AC80:AC81) -> 25572 | AD82: =SUM(AD80:AD81) -> 27245 | AE82: =SUM(AE80:AE81) -> 28545 | AF82: =SUM(AF80:AF81) -> 31902 | AG82: =SUM(AG80:AG81) -> 28540 | AH82: =SUM(AH80:AH81) -> 25131 | AI82: =SUM(AI80:AI81) -> 31375 | AW82: 63785 | AX82: 77788 | AY82: 96336 | AZ82: =SUM(AZ80:AZ81) -> 113264
A84: Google Network Members properties | B84: Million | C84: 10-K | D84: 2690440 | AB84: 5593 | AC84: 5015 | AD84: 5249 | AE84: 5251 | AF84: 6032 | AG84: 5223 | AH84: 4736 | AI84: 5720 | AJ84: 7411 | AK84: 6800 | AL84: 7597 | AM84: 7999 | AN84: 9305 | AO84: 8174 | AP84: 8259 | AQ84: 7872 | AR84: 8475 | AW84: 15598 | AX84: 17587 | AY84: 19982 | AZ84: 21547 | BA84: 23090 | BB84: 31701 | BC84: 32780
A85: Google advertising | B85: Million | C85: 10-K | D85: 2690441 | AB85: =AB82+AB84 -> 32518 | AC85: =AC82+AC84 -> 30587 | AD85: =AD82+AD84 -> 32494 | AE85: =AE82+AE84 -> 33796 | AF85: =AF82+AF84 -> 37934 | AG85: =AG82+AG84 -> 33763 | AH85: =AH82+AH84 -> 29867 | AI85: =AI82+AI84 -> 37095 | AJ85: =SUM(AJ84,AJ80:AJ81) -> 46199 | AK85: =SUM(AK84,AK80:AK81) -> 44684 | AL85: =SUM(AL84,AL80:AL81) -> 50444 | AM85: =SUM(AM84,AM80:AM81) -> 53130 | AN85: =SUM(AN84,AN80:AN81) -> 61239 | AO85: =SUM(AO84,AO80:AO81) -> 54661 | AP85: =SUM(AP84,AP80:AP81) -> 56288 | AQ85: =SUM(AQ84,AQ80:AQ81) -> 54482 | AR85: =SUM(AR84,AR80:AR81) -> 59042 | AW85: =AW82+AW84 -> 79383 | AX85: =AX82+AX84 -> 95375 | AY85: =AY82+AY84 -> 116318 | AZ85: =AZ82+AZ84 -> 134811 | BA85: =SUM(BA84,BA80:BA81) -> 146924 | BB85: =SUM(BB84,BB80:BB81) -> 209497 | BC85: =SUM(BC84,BC80:BC81) -> 224473
A87: Google Cloud | B87: Million | C87: 8-K | D87: 2621606 | AB87: 1709 | AC87: 1825 | AD87: 2100 | AE87: 2379 | AF87: 2614 | AG87: 2777 | AH87: 3007 | AI87: 3444 | AZ87: 8918
A88: Google other | B88: Million | C88: 10-K | D88: 2690442 | AB88: 4771 | AC88: 3620 | AD88: 4080 | AE88: 4050 | AF88: 5264 | AG88: 4435 | AH88: 5124 | AI88: 5478 | AJ88: 6674 | AK88: 6494 | AL88: 6623 | AM88: 6754 | AN88: 8161 | AO88: 6811 | AP88: 6553 | AQ88: 6895 | AR88: 8796 | AW88: 10601 | AX88: 15003 | AY88: 19906 | AZ88: 17014 | BA88: 21711 | BB88: 28032 | BC88: 29055
A89: Google service revenues | B89: Million | C89: 10-K | D89: 2690443 | AJ89: =SUM(AJ85,AJ88) -> 52873 | AK89: =SUM(AK85,AK88) -> 51178 | AL89: =SUM(AL85,AL88) -> 57067 | AM89: =SUM(AM85,AM88) -> 59884 | AN89: =SUM(AN85,AN88) -> 69400 | AO89: =SUM(AO85,AO88) -> 61472 | AP89: =SUM(AP85,AP88) -> 62841 | AQ89: =SUM(AQ85,AQ88) -> 61377 | AR89: =SUM(AR85,AR88) -> 67838 | BA89: =SUM(BA85,BA88) -> 168635 | BB89: =SUM(BB85,BB88) -> 237529 | BC89: =SUM(BC85,BC88) -> 253528
A91: Google revenues | B91: Million | C91: 8-K | D91: 2690444 | AB91: =SUM(AB85,AB87:AB88) -> 38998 | AC91: =SUM(AC85,AC87:AC88) -> 36032 | AD91: =SUM(AD85,AD87:AD88) -> 38674 | AE91: =SUM(AE85,AE87:AE88) -> 40225 | AF91: =SUM(AF85,AF87:AF88) -> 45812 | AG91: =SUM(AG85,AG87:AG88) -> 40975 | AH91: =SUM(AH85,AH87:AH88) -> 37998 | AI91: =SUM(AI85,AI87:AI88) -> 46017 | AW91: =SUM(AW85,AW87:AW88) -> 89984 | AX91: =SUM(AX85,AX87:AX88) -> 110378 | AY91: =SUM(AY85,AY87:AY88) -> 136224 | AZ91: =SUM(AZ85,AZ87:AZ88) -> 160743
A93: Google Cloud | B93: Million | C93: 10-K | D93: 2690445 | AJ93: 3831 | AK93: 4047 | AL93: 4628 | AM93: 4990 | AN93: 5541 | AO93: 5821 | AP93: 6276 | AQ93: 6868 | AR93: 7315 | BA93: 13059 | BB93: 19206 | BC93: 26280
A94: Other Bets revenues | B94: Million | C94: 10-K | D94: 2690446 | AB94: 154 | AC94: 170 | AD94: 162 | AE94: 155 | AF94: 172 | AG94: 135 | AH94: 148 | AI94: 178 | AJ94: 196 | AK94: 198 | AL94: 192 | AM94: 182 | AN94: 181 | AO94: 440 | AP94: 193 | AQ94: 209 | AR94: 226 | AW94: 288 | AX94: 477 | AY94: 595 | AZ94: 659 | BA94: 657 | BB94: 753 | BC94: 1068
A95: Hedging gains | B95: Million | C95: 10-K | D95: 2690447 | AB95: 124 | AC95: 137 | AD95: 108 | AE95: 119 | AF95: 91 | AG95: 49 | AH95: 151 | AI95: -22 | AJ95: -2 | AK95: -109 | AL95: -7 | AM95: 62 | AN95: 203 | AO95: 278 | AP95: 375 | AQ95: 638 | AR95: 669 | AZ95: 455 | BA95: 176 | BB95: 149 | BC95: 1960
A96: Total revenues | B96: Million | C96: 10-K | D96: 2690448 | AB96: =SUM(AB89,AB91,AB93:AB95) -> 39276 | AC96: =SUM(AC89,AC91,AC93:AC95) -> 36339 | AD96: =SUM(AD89,AD91,AD93:AD95) -> 38944 | AE96: =SUM(AE89,AE91,AE93:AE95) -> 40499 | AF96: =SUM(AF89,AF91,AF93:AF95) -> 46075 | AG96: =SUM(AG89,AG91,AG93:AG95) -> 41159 | AH96: =SUM(AH89,AH91,AH93:AH95) -> 38297 | AI96: =SUM(AI89,AI91,AI93:AI95) -> 46173 | ... AR96: =SUM(AR89,AR91,AR93:AR95) -> 76048 | AW96: =SUM(AW89,AW91,AW93:AW95) -> 90272 | AX96: =SUM(AX89,AX91,AX93:AX95) -> 110855 | AY96: =SUM(AY89,AY91,AY93:AY95) -> 136819 | AZ96: =SUM(AZ89,AZ91,AZ93:AZ95) -> 161857 | BA96: =SUM(BA89,BA91,BA93:BA95) -> 182527 | BB96: =SUM(BB89,BB91,BB93:BB95) -> 257637 | BC96: =SUM(BC89,BC91,BC93:BC95) -> 282836
A98: Revenue
A99: Google | B99: Million | C99: 8-K | D99: 2621613 | L99: 17997 | M99: 17178 | N99: 17652 | O99: 18533 | P99: 21178 | Q99: 20091 | R99: 21315 | S99: 22254 | T99: 25802 | U99: 24506 | V99: 25762 | W99: 27470 | X99: 31914 | Y99: 30996 | Z99: 32512 | AA99: 33594 | AB99: 39122 | AC99: 36169 | AD99: 38782 | AE99: 40344 | AF99: 45812 | AG99: 40975 | AH99: 37998 | AI99: 46017 | AT99: 55507 | AU99: 65674 | AV99: 74541 | AW99: 89463 | AX99: 109652 | AY99: 136224 | AZ99: 160743
A100: Google services | B100: Million | C100: 10-K | D100: 2690449 | AG100: 0 | AH100: 0 | AI100: 0 | AJ100: 52873 | AK100: 51178 | AL100: 57067 | AM100: 59884 | AN100: 69400 | AO100: 61472 | AP100: 62841 | AQ100: 61377 | AR100: 67838 | BA100: 168635 | BB100: 237529 | BC100: 253528
A101: Google cloud | B101: Million | C101: 10-K | D101: 2621615 | AG101: 0 | AH101: 0 | AI101: 0 | AJ101: 3831 | AK101: 4047 | AL101: 4628 | AM101: 4990 | AN101: 5541 | AO101: 5821 | AP101: 6276 | AQ101: 6868 | AR101: 7315 | BA101: 13059 | BB101: 19206 | BC101: 26280
A102: Other bets | B102: Million | C102: 10-K | D102: 2621616 | L102: 106 | M102: 80 | N102: 75 | O102: 142 | P102: 151 | Q102: 166 | R102: 185 | S102: 197 | T102: 262 | U102: 244 | V102: 248 | W102: 302 | X102: 409 | Y102: 150 | Z102: 145 | AA102: 146 | AB102: 154 | AC102: 170 | AD102: 162 | AE102: 155 | AF102: 172 | AG102: 135 | AH102: 148 | AI102: 178 | AJ102: 196 | AK102: 198 | AL102: 192 | AM102: 182 | AN102: 181 | AO102: 440 | AP102: 193 | AQ102: 209 | AR102: 226 | AT102: 12 | AU102: 327 | AV102: 448 | AW102: 809 | AX102: 1203 | AY102: 595 | AZ102: 659 | BA102: 657 | BB102: 753 | BC102: 1068
A103: Hedging gains (losses) | B103: Million | C103: 10-K | D103: 2621617 | AC103: 0 | AD103: 0 | AE103: 0 | AF103: 91 | AG103: 49 | AH103: 151 | AI103: -22 | AJ103: -2 | AK103: -109 | AL103: -7 | AM103: 62 | AN103: 203 | AO103: 278 | AP103: 375 | AQ103: 638 | AR103: 669 | AZ103: 455 | BA103: 176 | BB103: 149 | BC103: 1960
A104: Total revenues | B104: Million | C104: 10-K | D104: 2621618 | L104: =SUM(L99:L103) -> 18103 | M104: =SUM(M99:M103) -> 17258 | N104: =SUM(N99:N103) -> 17727 | O104: =SUM(O99:O103) -> 18675 | P104: =SUM(P99:P103) -> 21329 | Q104: =SUM(Q99:Q103) -> 20257 | R104: =SUM(R99:R103) -> 21500 | S104: =SUM(S99:S103) -> 22451 | ... AR104: =SUM(AR99:AR103) -> 76048 | AT104: =SUM(AT99:AT103) -> 55519 | AU104: =SUM(AU99:AU103) -> 66001 | AV104: =SUM(AV99:AV103) -> 74989 | AW104: =SUM(AW99:AW103) -> 90272 | AX104: =SUM(AX99:AX103) -> 110855 | AY104: =SUM(AY99:AY103) -> 136819 | AZ104: =SUM(AZ99:AZ103) -> 161857 | BA104: =SUM(BA99:BA103) -> 182527 | ... BC104: =SUM(BC99:BC103) -> 282836
A106: Operating income (loss)
A107: Google | B107: Million | C107: 8-K | D107: 2621619 | L107: 5223 | M107: 5188 | N107: 5630 | O107: 5835 | P107: 6772 | Q107: 6272 | R107: 6994 | S107: 6778 | T107: 7883 | U107: 7598 | V107: 7803 | W107: 8744 | X107: 8763 | Y107: 8368 | Z107: 8959 | AA107: 9490 | AB107: 9700 | AC107: 9325 | AD107: 10388 | AE107: 10865 | AF107: 11459 | AG107: 9270 | AH107: 7572 | AI107: 12589 | AT107: 16260 | AU107: 19011 | AV107: 23425 | AW107: 27892 | AX107: 32908 | AY107: 36517 | AZ107: 41673
A108: Google services | B108: Million | C108: 10-K | D108: 2690450 | AJ108: 19066 | AK108: 19546 | AL108: 22343 | AM108: 23973 | AN108: 25993 | AO108: 22920 | AP108: 22770 | AQ108: 19781 | AR108: 21101 | BA108: 54606 | BB108: 91855 | BC108: 86572
A109: Google cloud | B109: Million | C109: 10-K | D109: 2690451 | AJ109: -1243 | AK109: -974 | AL109: -591 | AM109: -644 | AN109: -890 | AO109: -931 | AP109: -858 | AQ109: -699 | AR109: -480 | BA109: -5607 | BB109: -3099 | BC109: -2968
A110: Other bets | B110: Million | C110: 10-K | D110: 2621622 | L110: -634 | M110: -633 | N110: -683 | O110: -1009 | P110: -1242 | Q110: -802 | R110: -859 | S110: -865 | T110: -1088 | U110: -855 | V110: -772 | W110: -812 | X110: -916 | Y110: -571 | Z110: -732 | AA110: -727 | AB110: -1328 | AC110: -868 | AD110: -989 | AE110: -941 | AF110: -2026 | AG110: -1121 | AH110: -1116 | AI110: -1103 | AJ110: -1136 | AK110: -1145 | AL110: -1398 | AM110: -1288 | AN110: -1450 | AO110: -1155 | AP110: -1686 | AQ110: -1611 | AR110: -1631 | AT110: -527 | AU110: -1942 | AV110: -3567 | AW110: -3578 | AX110: -3355 | AY110: -3358 | AZ110: -4824 | BA110: -4476 | BB110: -5281 | BC110: -6083
A111: Corporate costs, unallocated | B111: Million | C111: 10-K | D111: 2621623 | AJ111: -1036 | AK111: -990 | AL111: -993 | AM111: -1010 | AN111: -1768 | AO111: -740 | AP111: -773 | AQ111: -336 | AR111: -830 | BA111: -3299 | BB111: -4761 | BC111: -2679
A112: Reconciling items | B112: Million | C112: 8-K | D112: 2621624 | L112: -190 | M112: -108 | N112: -122 | O112: -118 | P112: -150 | Q112: -128 | R112: -167 | S112: -146 | T112: -156 | U112: -175 | V112: -2899 | W112: -150 | X112: -183 | Y112: -796 | Z112: -5420 | AA112: -453 | AB112: -169 | AC112: -1849 | AD112: -219 | AE112: -747 | AF112: -167 | AG112: -172 | AH112: -73 | AI112: -273 | AT112: -330 | AU112: -573 | AV112: -498 | AW112: -598 | AX112: -3407 | AY112: -6838 | AZ112: -2618
A113: Total income from operations | B113: Million | C113: 10-K | D113: 2621625 | L113: =SUM(L107:L112) -> 4399 | M113: =SUM(M107:M112) -> 4447 | N113: =SUM(N107:N112) -> 4825 | O113: =SUM(O107:O112) -> 4708 | P113: =SUM(P107:P112) -> 5380 | Q113: =SUM(Q107:Q112) -> 5342 | R113: =SUM(R107:R112) -> 5968 | S113: =SUM(S107:S112) -> 5767 | ... AR113: =SUM(AR107:AR112) -> 18160 | AT113: =SUM(AT107:AT112) -> 15403 | AU113: =SUM(AU107:AU112) -> 16496 | AV113: =SUM(AV107:AV112) -> 19360 | AW113: =SUM(AW107:AW112) -> 23716 | AX113: =SUM(AX107:AX112) -> 26146 | AY113: =SUM(AY107:AY112) -> 26321 | AZ113: =SUM(AZ107:AZ112) -> 34231 | BA113: =SUM(BA107:BA112) -> 41224 | ... BC113: =SUM(BC107:BC112) -> 74842
A115: Stock-based compensation
A116: Google | B116: Million | C116: 8-K | D116: 2621626 | L116: 1078 | M116: 1055 | N116: 992 | O116: 1269 | P116: 1271 | Q116: 1316 | R116: 1320 | S116: 1628 | T116: 1653 | U116: 1854 | V116: 1854 | W116: 1654 | X116: 1676 | Y116: 2304 | Z116: 2288 | AA116: 2071 | AB116: 2092 | AC116: 2612 | AD116: 2600 | AE116: 2470 | AF116: 2503 | AG116: 2988 | AH116: 3126 | AI116: 2921 | AT116: 2911 | AU116: 3677 | AV116: 4587 | AW116: 5926 | AX116: 7038 | AY116: 8755 | AZ116: 10185
A117: Other bets | B117: Million | C117: 8-K | D117: 2621627 | L117: 101 | M117: 117 | N117: 109 | O117: 134 | P117: 138 | Q117: 145 | R117: 150 | S117: 200 | T117: 161 | U117: 114 | V117: 111 | W117: 130 | X117: 138 | Y117: 112 | Z117: 127 | AA117: 125 | AB117: 125 | AC117: 123 | AD117: 125 | AE117: 117 | AF117: 109 | AG117: 135 | AH117: 136 | AI117: 130 | AT117: 124 | AU117: 347 | AV117: 498 | AW117: 647 | AX117: 493 | AY117: 489 | AZ117: 474
A118: Reconciling items | B118: Million | C118: 8-K | D118: 2621628 | L118: 22 | M118: 31 | N118: 31 | O118: 29 | P118: 27 | Q118: 33 | R118: 33 | S118: 32 | T118: 32 | U118: 41 | V118: 38 | W118: 36 | X118: 33 | Y118: 41 | Z118: -2 | AA118: 34 | AB118: 36 | AC118: 34 | AD118: 35 | AE118: 34 | AF118: 32 | AG118: 67 | AH118: 67 | AI118: 66 | AT118: 92 | AU118: 151 | AV118: 118 | AW118: 130 | AX118: 148 | AY118: 109 | AZ118: 135
A119: Total stock-based compensation | B119: Million | C119: 8-K | D119: 2621629 | L119: =SUM(L116:L118) -> 1201 | M119: =SUM(M116:M118) -> 1203 | N119: =SUM(N116:N118) -> 1132 | O119: =SUM(O116:O118) -> 1432 | P119: =SUM(P116:P118) -> 1436 | Q119: =SUM(Q116:Q118) -> 1494 | R119: =SUM(R116:R118) -> 1503 | S119: =SUM(S116:S118) -> 1860 | ... AI119: =SUM(AI116:AI118) -> 3117 | AT119: =SUM(AT116:AT118) -> 3127 | AU119: =SUM(AU116:AU118) -> 4175 | AV119: =SUM(AV116:AV118) -> 5203 | AW119: =SUM(AW116:AW118) -> 6703 | AX119: =SUM(AX116:AX118) -> 7679 | AY119: =SUM(AY116:AY118) -> 9353 | AZ119: =SUM(AZ116:AZ118) -> 10794
A121: Operating income (loss), excluding stock-based compensation
A122: Google | B122: Million | C122: 8-K | D122: 14043 | L122: 6301 | M122: 6243 | N122: 6622 | O122: 7104 | P122: 8043 | Q122: 7588 | R122: 8314 | S122: 8406 | T122: 9536 | AT122: 19171 | AU122: 22688 | AV122: =SUM(M122,N122,O122,P122) -> 28012 | AW122: =SUM(Q122,R122,S122,T122) -> 33844
A123: Other bets | B123: Million | C123: 8-K | D123: 14045 | L123: -533 | M123: -516 | N123: -574 | O123: -875 | P123: -1104 | Q123: -657 | R123: -709 | S123: -665 | T123: -927 | AT123: -403 | AU123: -1595 | AV123: =SUM(M123,N123,O123,P123) -> -3069 | AW123: =SUM(Q123,R123,S123,T123) -> -2958
...
