Workbook
Name IQ_CH: 110000
Name IQ_CQ: 5000
Name IQ_CY: 10000
Name IQ_DAILY: 500000
Name IQ_FH: 100000
Name IQ_FQ: 500
Name IQ_FY: 1000
Name IQ_LTM: 2000
Name IQ_MONTH: 15000
Name IQ_NTM: 6000
Name IQ_WEEK: 50000
Name IQ_YTD: 3000

Sheet How to Use 
A1: Instructions
A2: Tab | B2: Details
A3: Color Code | B3: Just familiarize yourself with the color code conventions used in this file. I will maintain these color code conventions in every model.
A4: Model | B4: The most important worksheet in this file is the "Model" Worksheet.
B5: If you want to change the assumptions, just change the cells that are filled yellow. Since the rest of the cells are formula driven, they will automatically be changed.
B6: I have made a few comments here and there whenever I thought it might be helpful for subscribers
B7: Please let me know asap if you think there has been any error/mistake (conceptual or otherwise) in the model
B8: If you want to see consolidated numbers for Meta, you will find it here
A9: PP&E | B9: Granular analysis on PP&E to estimate capex and depreciation expense
A10: Valuation | B10: Just change the current stock price and choose your multiple to run your valuation estimates.
A11: FOA | B11: Family of Apss. Linked with Model worksheet. It's just easier to see what's going on within FOA on a single worksheet here.
A12: RL | B12: Reality Labs modeling. If you want to change modeling within RL, do it here.
A13: Quarterly Data | B13: Quarterly database. Some numbers on Model worksheet may be tracked with some data on this worksheet.

Sheet Color Code
A1: Color | B1: Meaning
A2: Black | B2: Formula driven (both historical and forecasts)
A3: Blue | B3: Hard coded numbers (Actual for Historical, estimated for forecasts)
A4: Yellow | B4: Indication that there has been explicit assumption made in these cells. Change the numbers in these cells to drive your narrative.

Sheet Daloopa
A1: Calendar | B1: Unit | C1: Source | D1: Tag Id | E1: 2013Q1 | F1: 2013Q2 | G1: 2013Q3 | H1: 2013Q4 | I1: 2014Q1 | J1: 2014Q2 | K1: 2014Q3 | L1: 2014Q4 | M1: 2015Q1 | N1: 2015Q2 | O1: 2015Q3 | P1: 2015Q4 | Q1: 2016Q1 | R1: 2016Q2 | S1: 2016Q3 | T1: 2016Q4 | U1: 2017Q1 | V1: 2017Q2 | W1: 2017Q3 | X1: 2017Q4 | Y1: 2018Q1 | Z1: 2018Q2 | AA1: 2018Q3 | AB1: 2018Q4 | AC1: 2019Q1 | AD1: 2019Q2 | AE1: 2019Q3 | AF1: 2019Q4 | AG1: 2020Q1 | AH1: 2020Q2 | AI1: 2020Q3 | AJ1: 2020Q4 | AK1: 2021Q1 | AL1: 2021Q2 | AM1: 2021Q3 | AN1: 2021Q4 | AO1: 2022Q1 | AP1: 2022Q2 | AQ1: 2022Q3 | AR1: 2022Q4 | AS1: 2023Q1 | AT1: 2023Q2 | AU1: 2023Q3 | AV1: 2023Q4 | AW1: 2024Q1 | AX1: 2024Q2 | AY1: 2024Q3 | AZ1: 2024Q4 | BA1: 2025Q1 | BB1: 2025Q2 | BC1: 2025Q3 | BD1: 2025Q4 | BF1: 2013FY | BG1: 2014FY | BH1: 2015FY | BI1: 2016FY | BJ1: 2017FY | BK1: 2018FY | BL1: 2019FY | BM1: 2020FY | BN1: 2021FY | BO1: 2022FY | BP1: 2023FY | BQ1: 2024FY | BR1: 2025FY
A2: Fiscal | E2: 2013Q1 | F2: 2013Q2 | G2: 2013Q3 | H2: 2013Q4 | I2: 2014Q1 | J2: 2014Q2 | K2: 2014Q3 | L2: 2014Q4 | M2: 2015Q1 | N2: 2015Q2 | O2: 2015Q3 | P2: 2015Q4 | Q2: 2016Q1 | R2: 2016Q2 | S2: 2016Q3 | T2: 2016Q4 | U2: 2017Q1 | V2: 2017Q2 | W2: 2017Q3 | X2: 2017Q4 | Y2: 2018Q1 | Z2: 2018Q2 | AA2: 2018Q3 | AB2: 2018Q4 | AC2: 2019Q1 | AD2: 2019Q2 | AE2: 2019Q3 | AF2: 2019Q4 | AG2: 2020Q1 | AH2: 2020Q2 | AI2: 2020Q3 | AJ2: 2020Q4 | AK2: 2021Q1 | AL2: 2021Q2 | AM2: 2021Q3 | AN2: 2021Q4 | AO2: 2022Q1 | AP2: 2022Q2 | AQ2: 2022Q3 | AR2: 2022Q4 | AS2: 2023Q1 | AT2: 2023Q2 | AU2: 2023Q3 | AV2: 2023Q4 | AW2: 2024Q1 | AX2: 2024Q2 | AY2: 2024Q3 | AZ2: 2024Q4 | BA2: 2025Q1 | BB2: 2025Q2 | BC2: 2025Q3 | BD2: 2025Q4 | BF2: 2013FY | BG2: 2014FY | BH2: 2015FY | BI2: 2016FY | BJ2: 2017FY | BK2: 2018FY | BL2: 2019FY | BM2: 2020FY | BN2: 2021FY | BO2: 2022FY | BP2: 2023FY | BQ2: 2024FY | BR2: 2025FY
A3: Fiscal Date | E3: 41364 | F3: 41455 | G3: 41547 | H3: 41639 | I3: 41729 | J3: 41820 | K3: 41912 | L3: 42004 | M3: 42094 | N3: 42185 | O3: 42277 | P3: 42369 | Q3: 42460 | R3: 42551 | S3: 42643 | T3: 42735 | U3: 42825 | V3: 42916 | W3: 43008 | X3: 43100 | Y3: 43190 | Z3: 43281 | AA3: 43373 | AB3: 43465 | AC3: 43555 | AD3: 43646 | AE3: 43738 | AF3: 43830 | AG3: 43921 | AH3: 44012 | AI3: 44104 | AJ3: 44196 | AK3: 44286 | AL3: 44377 | AM3: 44469 | AN3: 44561 | AO3: 44651 | AP3: 44742 | AQ3: 44834 | AR3: 44926 | AS3: 45016 | AT3: 45107 | AU3: 45199 | AV3: 45291 | AW3: 45382 | AX3: 45473 | AY3: 45565 | AZ3: 45657 | BA3: 45747 | BB3: 45838 | BC3: 45930 | BD3: 46022
A4: Documents
A5: 10Q/10K | E5: 10-Q | F5: 10-Q | G5: 10-Q | H5: 10-K | I5: 10-Q | J5: 10-Q | K5: 10-Q | L5: 10-K | M5: 10-Q | N5: 10-Q | O5: 10-Q | P5: 10-K | Q5: 10-Q | R5: 10-Q | S5: 10-Q | T5: 10-K | U5: 10-Q | V5: 10-Q | W5: 10-Q | X5: 10-K | Y5: 10-Q | Z5: 10-Q | AA5: 10-Q | AB5: 10-K | AC5: 10-Q | AD5: 10-Q | AE5: 10-Q | AF5: 10-K | AG5: 10-Q | AH5: 10-Q | AI5: 10-Q | AJ5: 10-K | AK5: 10-Q | AL5: 10-Q | AM5: 10-Q | AN5: 10-K | AO5: 10-Q | AP5: 10-Q | AQ5: 10-Q | AR5: 10-K | AS5: 10-Q | AT5: 10-Q | AU5: 10-Q | AV5: 10-K | AW5: 10-Q | AX5: 10-Q | AY5: 10-Q | AZ5: 10-K | BA5: 10-Q | BB5: 10-Q | BC5: 10-Q | BD5: 10-K
A6: 8-K | E6: EX-99.1 | F6: EX-99.1 | G6: EX-99.1 | H6: EX-99.1 | I6: EX-99.1 | J6: EX-99.1 | K6: EX-99.1 | L6: EX-99.1 | M6: EX-99.1 | N6: EX-99.1 | O6: EX-99.1 | P6: EX-99.1 | Q6: EX-99.1 | R6: EX-99.1 | S6: EX-99.1 | T6: EX-99.1 | U6: EX-99.1 | V6: EX-99.1 | W6: EX-99.1 | X6: EX-99.1 | Y6: EX-99.1 | Z6: EX-99.1 | AA6: EX-99.1 | AB6: EX-99.1 | AC6: EX-99.1 | AD6: EX-99.1 | AE6: EX-99.1 | AF6: EX-99.1 | AG6: EX-99.1 | AH6: EX-99.1 | AI6: EX-99.1 | AJ6: EX-99.1 | AK6: EX-99.1 | AL6: EX-99.1 | AM6: EX-99.1 | AN6: EX-99.1 | AO6: EX-99.1 | AP6: EX-99.1 | AQ6: EX-99.1 | AR6: EX-99.1 | AS6: EX-99.1 | AT6: EX-99.1 | AU6: EX-99.1 | AV6: EX-99.1 | AW6: EX-99.1 | AX6: EX-99.1 | AZ6: EX-99.1 | BC6: EX-99.1 | BD6: EX-99.1
A7: News article | AY7: News Article | AZ7: News Article | BA7: News Article | BB7: News Article | BD7: News Article
A8: Transcript | AW8: Earnings | AX8: Earnings | AY8: Earnings | AZ8: Earnings
A9: Private | AT9: PRIVATE
A11: Guidance
A12: Quarter
A13: Total revenue - low | B13: Billion | C13: News Article | D13: 2541430 | AM13: 31.5 | AN13: 27 | AO13: 28 | AP13: 26 | AQ13: 30 | AR13: 26 | AS13: 29.5 | AT13: 32 | AU13: 36.5 | AV13: 34.5 | AW13: 36.5 | AX13: 38.5 | AY13: 45 | AZ13: 39.5 | BA13: 42.5 | BB13: 47.5 | BC13: 56 | BD13: 53.5 | BN13: 27 | BO13: 26 | BP13: 34.5 | BQ13: 39.5 | BR13: 53.5
A14: Total revenue - high | B14: Billion | C14: News Article | D14: 2541431 | AM14: 34 | AN14: 29 | AO14: 30 | AP14: 28.5 | AQ14: 32.5 | AR14: 28.5 | AS14: 32 | AT14: 34.5 | AU14: 40 | AV14: 37 | AW14: 39 | AX14: 41 | AY14: 48 | AZ14: 41.8 | BA14: 45.5 | BB14: 50.5 | BC14: 59 | BD14: 56.5 | BN14: 29 | BO14: 28.5 | BP14: 37 | BQ14: 41.8 | BR14: 56.5
A15: Total revenue YOY growth-low | B15: Percent | C15: 8-K | D15: 6882821 | AZ15: 0.08 | BQ15: 0.08
A16: Total revenue YOY growth-High | B16: Percent | C16: 8-K | D16: 6882820 | AZ16: 0.15 | BQ16: 0.15
A17: Total revenue growth on basis of constant currency-Low | B17: Percent | C17: 8-K | D17: 6882819 | AZ17: 0.11 | BQ17: 0.11
A18: Total revenue growth on basis of constant currency-High | B18: Percent | C18: 8-K | D18: 6882818 | AZ18: 0.18 | BQ18: 0.18
A19: Foreign currency impact | B19: Percent | C19: News Article | D19: 3669082 | AO19: 0.03 | AP19: 0.06 | AQ19: 0.07 | AR19: 0.02 | AS19: 0.01 | AT19: -0.03 | AU19: -0.02 | AW19: 0.01 | AX19: 0.02 | AZ19: 0.03 | BA19: 0.01 | BB19: 0.01 | BC19: 0.01 | BD19: 0.04 | BO19: 0.02 | BQ19: 0.03 | BR19: 0.04
A20: Advertising revenue growth rate (YoY) | B20: Percent | C20: 8-K | D20: 2541432 | AG20: -0.17 | AH20: 0.1
A21: Tax rate-Low | B21: Percent | C21: 8-K | D21: 7735518 | BC21: 0.12
A22: Tax rate-High | B22: Percent | C22: 8-K | D22: 7735519 | BC22: 0.15
A24: Annual
A25: Total expenses - low | B25: Billion | C25: News Article | D25: 2635932 | AG25: 52 | AH25: 52 | AI25: 53 | AJ25: 68 | AK25: 70 | AL25: 70 | AM25: 70 | AN25: 90 | AO25: 87 | AP25: 85 | AQ25: 85 | AR25: 89 | AS25: 86 | AT25: 88 | AU25: 87 | AV25: 94 | AW25: 96 | AX25: 96 | AY25: 96 | AZ25: 114 | BA25: 113 | BB25: 114 | BC25: 116 | BD25: 162 | BM25: 68 | BN25: 90 | BO25: 89 | BP25: 94 | BQ25: 114 | BR25: 162
A26: Total expenses - high | B26: Billion | C26: News Article | D26: 2635933 | AG26: 56 | AH26: 55 | AI26: 54 | AJ26: 73 | AK26: 73 | AL26: 73 | AM26: 71 | AN26: 95 | AO26: 92 | AP26: 88 | AQ26: 87 | AR26: 95 | AS26: 90 | AT26: 91 | AU26: 89 | AV26: 99 | AW26: 99 | AX26: 99 | AY26: 98 | AZ26: 119 | BA26: 118 | BB26: 118 | BC26: 118 | BD26: 169 | BM26: 73 | BN26: 95 | BO26: 95 | BP26: 99 | BQ26: 119 | BR26: 169
A27: Restructuring costs related to facilities consolidation charges-low | B27: Billion | C27: 8-K | D27: 4237278 | AS27: 3
A28: Restructuring costs related to facilities consolidation charges-high | B28: Billion | C28: 8-K | D28: 4237279 | AS28: 5
A29: Restructuring costs related to facilities consolidation charges-Approx | B29: Billion | C29: 8-K | D29: 4625528 | AT29: 4 | AU29: 3.5
A30: Capital expenditures, including principal payments on finance leases - low | B30: Billion | C30: News Article | D30: 3669083 | AN30: 29 | AO30: 29 | AP30: 30 | AQ30: 32 | BD30: 115 | BN30: 29 | BR30: 115
A31: Capital expenditures, including principal payments on finance leases - high | B31: Billion | C31: News Article | D31: 3669084 | AN31: 34 | AO31: 34 | AP31: 34 | AQ31: 33 | BD31: 135 | BN31: 34 | BR31: 135
A32: Capital expenditures - low | B32: Billion | C32: 8-K | D32: 3669085 | AG32: 14 | AJ32: 21 | AK32: 19 | AL32: 19 | AR32: 30 | AS32: 30 | AT32: 27 | AU32: 27 | AV32: 30 | AW32: 35 | AX32: 37 | AY32: 38 | AZ32: 60 | BA32: 64 | BB32: 66 | BC32: 70 | BM32: 21 | BO32: 30 | BP32: 30 | BQ32: 60
A33: Capital expenditures - high | B33: Billion | C33: 8-K | D33: 3669086 | AG33: 16 | AJ33: 23 | AK33: 21 | AL33: 21 | AR33: 33 | AS33: 33 | AT33: 30 | AU33: 29 | AV33: 37 | AW33: 40 | AX33: 40 | AY33: 40 | AZ33: 65 | BA33: 72 | BB33: 72 | BC33: 72 | BM33: 23 | BO33: 33 | BP33: 37 | BQ33: 65
A34: Capital expenditures - approx. | B34: Billion | C34: 8-K | D34: 2399729 | AH34: 16 | AI34: 16 | AM34: 19
A35: Reduction in operating profit due to investment in Facebook Reality Labs | B35: Billion | C35: 8-K | D35: 2076062 | AM35: -10
A36: Restructuring charges related to consolidating our office facilities footprint | B36: Billion | C36: 8-K | D36: 3815475 | AR36: 1 | BO36: 1
A37: Tax rate | B37: Percent | C37: 8-K | D37: 4237280 | AS37: 0.2
A38: Tax rate -Low | B38: Percent | C38: News Article | D38: 6882817 | AZ38: 0.12 | BA38: 0.12 | BD38: 0.13 | BQ38: 0.12 | BR38: 0.13
A39: Tax rate -High | B39: Percent | C39: News Article | D39: 6882816 | AZ39: 0.15 | BA39: 0.15 | BD39: 0.16 | BQ39: 0.15 | BR39: 0.16
A41: Next year
A42: Total expenses - low | B42: Billion | C42: 8-K | D42: 2635936 | AI42: 68 | AM42: 91 | AQ42: 96 | AU42: 94
A43: Total expenses - high | B43: Billion | C43: 8-K | D43: 2635937 | AI43: 73 | AM43: 97 | AQ43: 101 | AU43: 99
A44: Capital expenditures - low | B44: Billion | C44: 8-K | D44: 2635938 | AI44: 21 | AM44: 29 | AQ44: 34 | AU44: 30
A45: Capital expenditures - high | B45: Billion | C45: 8-K | D45: 2635939 | AI45: 23 | AM45: 34 | AQ45: 39 | AU45: 35
A47: KPIs
A48: Headcount | B48: Actual | C48: News Article | D48: 2541439 | E48: 4900 | F48: 5299 | G48: 5794 | H48: 6337 | I48: 6818 | J48: 7185 | K48: 8348 | L48: 9199 | M48: 10082 | N48: 10955 | O48: 11996 | P48: 12691 | Q48: 13598 | R48: 14495 | S48: 15724 | T48: 17048 | U48: 18770 | V48: 20658 | W48: 23165 | X48: 25105 | Y48: 27742 | Z48: 30275 | AA48: 33606 | AB48: 35587 | AC48: 37773 | AD48: 39651 | AE48: 43030 | AF48: 44942 | AG48: 48268 | AH48: 52534 | AI48: 56653 | AJ48: 58604 | AK48: 60654 | AL48: 63404 | AM48: 68177 | AN48: 71970 | AO48: 77805 | AP48: 83553 | AQ48: 87314 | AR48: 86482 | AS48: 77114 | AT48: 71469 | AU48: 66185 | AV48: 67317 | AW48: 69329 | AX48: 70799 | AY48: 72404 | AZ48: 74067 | BA48: 76834 | BB48: 75945 | BC48: 78450 | BD48: 78865
A49: Family daily active people (DAP) | B49: Billion | C49: News Article | D49: 2541442 | AA49: 2 | AB49: 2 | AC49: 2.1 | AD49: 2.1 | AE49: 2.2 | AF49: 2.26 | AG49: 2.36 | AH49: 2.47 | AI49: 2.54 | AJ49: 2.6 | AK49: 2.72 | AL49: 2.76 | AM49: 2.81 | AN49: 2.82 | AO49: 2.87 | AP49: 2.88 | AQ49: 2.93 | AR49: 2.96 | AS49: 3.02 | AT49: 3.07 | AU49: 3.14 | AV49: 3.19 | AW49: 3.24 | AX49: 3.27 | AY49: 3.29 | AZ49: 3.35 | BA49: 3.43 | BB49: 3.48 | BC49: 3.54 | BD49: 3.58
A50: Family (DAP/MAP) | B50: Percent | C50: Others | D50: 2541449 | AB50: 0.77 | AC50: 0.78 | AD50: 0.78 | AE50: 0.78 | AF50: 0.78 | AG50: 0.79 | AH50: 0.79 | AI50: 0.79 | AJ50: 0.79 | AK50: 0.79 | AL50: 0.79 | AM50: 0.79 | AN50: 0.79 | AO50: 0.79 | AP50: 0.79 | AQ50: 0.79 | AR50: 0.79 | AS50: 0.79 | AT50: 0.79 | AU50: 0.79 | AV50: 0.8
A51: Facebook daily active users (DAUs) | B51: Billion(2015Q3) | C51: 8-K | D51: 2541440 | E51: 0.665 | F51: 0.699 | G51: 0.728 | H51: 0.757 | I51: 0.802 | J51: 0.829 | K51: 0.864 | L51: 0.89 | M51: 0.936 | N51: 0.968 | O51: 1.01 | P51: 1.04 | Q51: 1.09 | R51: 1.13 | S51: 1.18 | T51: 1.23 | U51: 1.28 | V51: 1.32 | W51: 1.37 | X51: 1.4 | Y51: 1.45 | Z51: 1.47 | AA51: 1.49 | AB51: 1.52 | AC51: 1.56 | AD51: 1.59 | AE51: 1.62 | AF51: 1.66 | AG51: 1.73 | AH51: 1.79 | AI51: 1.82 | AJ51: 1.84 | AK51: 1.88 | AL51: 1.91 | AM51: 1.93 | AN51: 1.93 | AO51: 1.96 | AP51: 1.97 | AQ51: 1.98 | AR51: 2 | AS51: 2.04 | AT51: 2.06 | AU51: 2.09 | AV51: 2.11
A52: Facebook monthly active users (MAUs) | B52: Billion | C52: 8-K | D52: 2541441 | E52: 1.11 | F52: 1.15 | G52: 1.19 | H52: 1.23 | I52: 1.28 | J52: 1.32 | K52: 1.35 | L52: 1.39 | M52: 1.44 | N52: 1.49 | O52: 1.55 | P52: 1.59 | Q52: 1.65 | R52: 1.71 | S52: 1.79 | T52: 1.86 | U52: 1.94 | V52: 2.01 | W52: 2.07 | X52: 2.13 | Y52: 2.2 | Z52: 2.23 | AA52: 2.27 | AB52: 2.32 | AC52: 2.38 | AD52: 2.41 | AE52: 2.45 | AF52: 2.5 | AG52: 2.6 | AH52: 2.7 | AI52: 2.74 | AJ52: 2.8 | AK52: 2.85 | AL52: 2.9 | AM52: 2.91 | AN52: 2.91 | AO52: 2.94 | AP52: 2.93 | AQ52: 2.96 | AR52: 2.96 | AS52: 2.99 | AT52: 3.03 | AU52: 3.05 | AV52: 3.07
A53: Daily active users/ monthly active users (DAUs/MAUs) | B53: Percent | C53: Others | D53: 2541460 | E53: 0.6 | F53: 0.61 | G53: 0.61 | H53: 0.62 | I53: 0.63 | J53: 0.63 | K53: 0.64 | L53: 0.64 | M53: 0.65 | N53: 0.65 | O53: 0.65 | P53: 0.65 | Q53: 0.66 | R53: 0.66 | S53: 0.66 | T53: 0.66 | U53: 0.66 | V53: 0.66 | W53: 0.66 | X53: 0.66 | Y53: 0.66 | Z53: 0.66 | AA53: 0.66 | AB53: 0.66 | AC53: 0.66 | AD53: 0.66 | AE53: 0.66 | AF53: 0.66 | AG53: 0.67 | AH53: 0.66 | AI53: 0.66 | AJ53: 0.66 | AK53: 0.66 | AL53: 0.66 | AM53: 0.66 | AN53: 0.66 | AO53: 0.67 | AP53: 0.67 | AQ53: 0.67 | AR53: 0.67 | AS53: 0.68 | AT53: 0.68 | AU53: 0.68 | AV53: 0.69
A54: Changes in number of advertisement (ad impressions) delivered (YoY) | B54: Percent | C54: News Article | D54: 4012799 | E54: 0.39 | F54: 0.43 | G54: 0.16 | I54: -0.17 | J54: -0.25 | K54: -0.56 | M54: -0.62 | N54: -0.55 | O54: -0.1 | Q54: 0.5 | R54: 0.49 | S54: 0.5 | U54: 0.32 | V54: 0.19 | W54: 0.1 | Y54: 0.08 | Z54: 0.21 | AA54: 0.25 | AC54: 0.32 | AD54: 0.33 | AE54: 0.37 | AG54: 0.39 | AH54: 0.4 | AI54: 0.35 | AK54: 0.12 | AL54: 0.06 | AM54: 0.09 | AN54: 0.13 | AO54: 0.15 | AP54: 0.15 | AQ54: 0.17 | AR54: 0.23 | AS54: 0.26 | AT54: 0.34 | AU54: 0.31 | AV54: 0.21 | AW54: 0.2 | AX54: 0.1 | AY54: 0.07 | AZ54: 0.06 | BA54: 0.05 | BB54: 0.11 | BC54: 0.14 | BD54: 0.18 | BF54: 0.2 | BG54: -0.4 | BH54: -0.38 | BI54: 0.5 | BJ54: 0.15 | BK54: 0.22 | BL54: 0.33 | BM54: 0.34 | BN54: 0.1 | BO54: 0.18 | BP54: 0.28 | BQ54: 0.11 | BR54: 0.12
A55: Change in average price per advertisement (YoY) | B55: Percent | C55: News Article | D55: 4012800 | E55: 0.03 | F55: 0.13 | G55: 0.42 | I55: 1.18 | J55: 1.23 | K55: 2.74 | M55: 2.85 | N55: 2.2 | O55: 0.61 | Q55: 0.05 | R55: 0.09 | S55: 0.06 | U55: 0.14 | V55: 0.24 | W55: 0.35 | Y55: 0.39 | Z55: 0.17 | AA55: 0.07 | AC55: -0.04 | AD55: -0.04 | AE55: -0.06 | AG55: -0.16 | AH55: -0.21 | AI55: -0.09 | AK55: 0.3 | AL55: 0.47 | AM55: 0.22 | AN55: 0.06 | AO55: -0.08 | AP55: -0.14 | AQ55: -0.18 | AR55: -0.22 | AS55: -0.17 | AT55: -0.16 | AU55: -0.06 | AV55: 0.02 | AW55: 0.06 | AX55: 0.1 | AY55: 0.11 | AZ55: 0.14 | BA55: 0.1 | BB55: 0.09 | BC55: 0.1 | BD55: 0.06 | BF55: 0.36 | BG55: 1.73 | BH55: 1.4 | BI55: 0.05 | BJ55: 0.29 | BK55: 0.13 | BL55: -0.05 | BM55: -0.1 | BN55: 0.24 | BO55: -0.16 | BP55: -0.09 | BQ55: 0.1 | BR55: 0.09
A56: Mobile advertising revenue | B56: Percent | C56: 8-K | D56: 768638 | E56: 0.3 | F56: 0.41 | G56: 0.49 | H56: 0.53 | I56: 0.59 | J56: 0.62 | K56: 0.66 | L56: 0.69 | M56: 0.73 | N56: 0.76 | O56: 0.78 | P56: 0.8 | Q56: 0.82 | R56: 0.84 | S56: 0.84 | T56: 0.84 | U56: 0.85 | V56: 0.87 | W56: 0.88 | X56: 0.89 | Y56: 0.91 | Z56: 0.91 | AA56: 0.92 | AB56: 0.93 | AC56: 0.93 | AD56: 0.94 | AE56: 0.94
A57: Mobile daily active users | B57: Billion(2016Q2) | C57: 8-K | D57: 2837 | F57: 0.469 | G57: 0.507 | H57: 0.556 | I57: 0.609 | J57: 0.654 | K57: 0.703 | L57: 0.745 | M57: 0.798 | N57: 0.844 | O57: 0.894 | P57: 0.934 | Q57: 0.989 | R57: 1.03 | S57: 1.09 | T57: 1.15
A58: Mobile monthly active users | B58: Billion(2014Q1) | C58: 8-K | D58: 2842 | E58: 0.751 | F58: 0.819 | G58: 0.874 | H58: 0.945 | I58: 1.01 | J58: 1.07 | K58: 1.12 | L58: 1.19 | M58: 1.25 | N58: 1.31 | O58: 1.39 | P58: 1.44 | Q58: 1.51 | R58: 1.57 | S58: 1.66 | T58: 1.74
A59: Facebook and insta reels play per day | B59: Billion | C59: Transcript | D59: 6623770 | AS59: 2 | AT59: 200
A60: Threads Monthly actives | B60: Million | C60: Transcript | D60: 7163926 | AX60: 200 | AY60: 275 | AZ60: 320 | BA60: 350 | BC60: 150
A61: Whatsapp monthly active user US | B61: Million | C61: Transcript | D61: 7163927 | AZ61: 100 | BA61: 100
A62: Whatsapp monthly active user | B62: Billion | C62: Transcript | D62: 7263205 | BA62: 3
A63: Facebook monthly active users | B63: Billion | C63: Transcript | D63: 7163928 | AZ63: 3
A64: Family of App expense | B64: Billion | C64: Others | D64: 7163929 | AZ64: 19 | BA64: 20.1 | BB64: 22.2
A65: Reels re-shared in a day | B65: Billion | C65: Transcript | D65: 7163930 | AZ65: 4.5
A66: MetaAI Monthly active user | B66: Million | C66: Others | D66: 7163931 | AY66: 500 | AZ66: 700 | BB66: 1000
A67: User using atleast one Generative AI ad creative tools | B67: Million | C67: Transcript | D67: 7163932 | AY67: 1 | AZ67: 4
A68: ARR | B68: Billion | C68: Transcript | D68: 7163933 | AZ68: 20
A69: Change in Ad conversion | B69: Percent | C69: Transcript | D69: 7263206 | BA69: 0.05
A70: Daily activities each on facebook and whatsapp | B70: Billion | C70: Transcript | D70: 7946680 | BD70: 2
A71: Click to message revenue growth | B71: Percent | C71: Others | D71: 7563009 | BB71: 0.4
A72: Instagram video time spent (YoY) | B72: Percent | C72: Transcript | D72: 7563010 | BB72: 0.2 | BC72: 0.3
A73: Instagram monthly actives | B73: Million | C73: Others | D73: 7741486 | BC73: 3000
A74: Facebook video time spent (YoY) | B74: Percent | C74: Others | D74: 7563011 | BB74: 0.2
A75: Business AI active user | B75: Billion | C75: Transcript | D75: 7737238 | BC75: 1
A76: Using at least one app | B76: Billion | C76: Transcript | D76: 7741487 | BB76: 3.4 | BC76: 3.5
A77: Change In Time Spend on Facebook (QoQ) | B77: Percent | C77: Transcript | D77: 7913670 | BC77: 0.05
A78: Change In Time Spend On Threads (QoQ) | B78: Percent | C78: Transcript | D78: 7913671 | BC78: 0.1
A79: New AI Data Center to be Build (Gigawatt) | B79: Actual | C79: Transcript | D79: 7913672 | AZ79: 2 | BQ79: 2
A80: Whatsapp Business Daily Actives | B80: Billion | C80: Transcript | D80: 7913673 | BB80: 1.5
A81: Change in Ad Conversion on Instagram | B81: Percent | C81: Transcript | D81: 7913674 | BB81: 0.05
A82: Change in Ad Conversion On Facebook | B82: Percent | C82: Transcript | D82: 7913675 | BB82: 0.03
A84: Foreign exchange impact on revenue
A85: FX impact on revenue | B85: Million | C85: 10-K | D85: 2541477 | Y85: -536 | Z85: -373 | AD85: 574 | AE85: 297 | AG85: 275 | AH85: 297 | AI85: -114 | AJ85: =BM85-SUM(AG85,AH85,AI85) -> -338 | AK85: -706 | AL85: -982 | AM85: -259 | AN85: =BN85-SUM(AK85,AL85,AM85) -> 307 | AO85: 893 | AQ85: 1790 | AS85: 816 | AT85: 274 | AU85: -647 | AV85: =BP85-SUM(AS85,AT85,AU85) -> -817 | AW85: -106 | AX85: 371 | AY85: 544 | AZ85: =BQ85-SUM(AW85,AX85,AY85) -> 65 | BA85: 1240 | BB85: 82 | BC85: -412 | BD85: =BR85-SUM(BA85,BB85,BC85) -> -492 | BI85: 270 | BJ85: -293 | BL85: 1670 | BM85: 120 | BN85: -1640 | BO85: 5960 | BP85: -374 | BQ85: 874 | BR85: 418
A86: FX impact on advertisement | B86: Million | C86: 10-K | D86: 2541478 | Y86: -535 | Z86: -371 | AD86: 572 | AE86: 295 | AG86: 274 | AH86: 295 | AI86: -109 | AJ86: =BM86-SUM(AG86,AH86,AI86) -> -331 | AK86: -695 | AL86: -975 | AM86: -256 | AN86: =BN86-SUM(AK86,AL86,AM86) -> 306 | AO86: 888 | AQ86: 1780 | AS86: 806 | AT86: 269 | AU86: -645 | AV86: =BP86-SUM(AS86,AT86,AU86) -> -809 | AW86: -105 | AX86: 367 | AY86: 538 | AZ86: =BQ86-SUM(AW86,AX86,AY86) -> 80 | BA86: 1220 | BB86: 80 | BC86: -409 | BD86: =BR86-SUM(BA86,BB86,BC86) -> -471 | BI86: 269 | BJ86: -292 | BL86: 1660 | BM86: 129 | BN86: -1620 | BO86: 5900 | BP86: -379 | BQ86: 880 | BR86: 420
A87: FX impact on revenue and advertisement | B87: Million | C87: 10-Q | D87: 239476 | M87: 188 | N87: 332 | O87: 342 | P87: 322 | Q87: 202 | R87: 203 | S87: 234 | U87: 22 | V87: 141 | W87: -128 | AA87: 159 | AC87: 503 | AP87: 1260 | BH87: 1190 | BK87: -401
A88: Change in revenue on a constant currency basis (YoY) | B88: Percent | C88: News Article | D88: 6937345 | AQ88: 0.02 | AR88: 0.02 | AS88: 0.06 | AT88: 0.12 | AU88: 0.21 | AV88: 0.22 | AW88: 0.27 | AX88: 0.23 | AY88: 0.2 | AZ88: 0.21 | BA88: 0.19 | BB88: 0.22 | BC88: 0.25 | BD88: 0.23 | BO88: 0.04 | BP88: 0.15 | BQ88: 0.23 | BR88: 0.22
A89: Change in revenue on a reported basis (YoY) | B89: Percent | C89: News Article | D89: 7735572 | BC89: 0.26 | BD89: 0.24 | BR89: 0.22
A90: Revenue on a constant currency basis | B90: Billion | C90: 8-K | D90: 6937346 | AW90: 36.35
A92: Family monthly active people (MAP) | B92: Billion | C92: 8-K | D92: 2541443 | AA92: 2.6 | AB92: 2.7 | AC92: 2.7 | AD92: 2.7 | AE92: 2.8 | AF92: 2.89 | AG92: 2.99 | AH92: 3.14 | AI92: 3.21 | AJ92: 3.3 | AK92: 3.45 | AL92: 3.51 | AM92: 3.58 | AN92: 3.59 | AO92: 3.64 | AP92: 3.65 | AQ92: 3.71 | AR92: 3.74 | AS92: 3.81 | AT92: 3.88 | AU92: 3.96 | AV92: 3.98
A94: Family average revenue per person
A95: Advertising | B95: Dollar | C95: PRIVATE | D95: 233426 | AB95: 6.41 | AC95: 5.6 | AD95: 6.1 | AE95: 6.23 | AF95: 7.26 | AG95: 5.93 | AH95: 5.98 | AI95: 6.68 | AJ95: 8.35 | AK95: 7.54 | AL95: 8.21 | AM95: 7.98 | BL95: =SUM(AC95,AD95,AE95,AF95) -> 25.19 | BM95: =SUM(AG95,AH95,AI95,AJ95) -> 26.94
A96: Other | B96: Dollar | C96: PRIVATE | D96: 233425 | AB96: 0.11 | AC96: 0.06 | AD96: 0.1 | AE96: 0.1 | AF96: 0.12 | AG96: 0.1 | AH96: 0.12 | AI96: 0.08 | AJ96: 0.27 | AK96: 0.22 | AL96: 0.14 | AM96: 0.21 | BL96: =SUM(AC96,AD96,AE96,AF96) -> 0.38 | BM96: =SUM(AG96,AH96,AI96,AJ96) -> 0.57
A97: Total | B97: Dollar | C97: 10-K | D97: 7259181 | AB97: =SUM(AB95:AB96) -> 6.52 | AC97: =SUM(AC95:AC96) -> 5.66 | AD97: =SUM(AD95:AD96) -> 6.2 | AE97: =SUM(AE95:AE96) -> 6.33 | AF97: =SUM(AF95:AF96) -> 7.38 | AG97: =SUM(AG95:AG96) -> 6.03 | AH97: =SUM(AH95:AH96) -> 6.1 | AI97: =SUM(AI95:AI96) -> 6.76 | AJ97: =SUM(AJ95:AJ96) -> 8.62 | AK97: 7.75 | AL97: 8.36 | AM97: 8.18 | AN97: 9.39 | AO97: 7.72 | AP97: 7.91 | AQ97: 7.53 | AR97: 8.63 | AS97: 7.59 | AT97: 8.32 | AU97: 8.71 | AV97: 10.1 | BL97: =SUM(AC97,AD97,AE97,AF97) -> 25.57 | BM97: =SUM(AG97,AH97,AI97,AJ97) -> 27.51 | BN97: =SUM(AK97,AL97,AM97,AN97) -> 33.68 | BO97: =SUM(AO97,AP97,AQ97,AR97) -> 31.79 | BP97: 34.72
A99: Family average revenue per person | B99: Dollar | C99: 10-K | D99: 7259182 | AO99: 9.57 | AP99: 9.87 | AQ99: 9.44 | AR99: 10.68 | AS99: 9.47 | AT99: 10.42 | AU99: 10.93 | AV99: 12.33 | AW99: 11.2 | AX99: 11.89 | AY99: 12.29 | AZ99: 14.25 | BA99: 12.36 | BB99: 13.65 | BC99: 14.46 | BD99: 16.56 | BO99: =SUM(AO99,AP99,AQ99,AR99) -> 39.56 | BP99: =SUM(AS99,AT99,AU99,AV99) -> 43.15 | BQ99: 49.63 | BR99: 57.03
A101: Deferred revenue and deposits
A102: Deferred revenue | B102: Million | C102: 10-K | D102: 142213 | H102: 13 | L102: 38 | P102: 28 | T102: 62 | X102: 68 | Y102: 64 | Z102: 62 | AA102: 85 | AB102: 117 | AC102: 111 | AD102: 164 | AE102: 192 | AF102: 234 | AG102: 210 | AH102: 222 | AI102: 332 | AJ102: 335 | AK102: 378 | AL102: 386 | AM102: 463 | AN102: 596 | AO102: 565 | AP102: 549 | AQ102: 513 | AR102: 526 | AS102: 492 | AT102: 520 | AU102: 526 | AV102: 675 | AW102: 645 | AX102: 675 | AY102: 732 | AZ102: 772 | BA102: 778 | BB102: 876 | BC102: 924 | BD102: 1080
A103: Deposits | B103: Million | C103: 10-K | D103: 142214 | H103: 25 | L103: 28 | P103: 28 | T103: 28 | X103: 30 | Y103: 30 | Z103: 29 | AA103: 30 | AB103: 30 | AC103: 31 | AD103: 34 | AE103: 33 | AF103: 35 | AG103: 37 | AH103: 42 | AI103: 47 | AJ103: 47
A104: Total deferred revenue and deposits | B104: Million | C104: 10-K | D104: 142215 | H104: =SUM(H102:H103) -> 38 | L104: =SUM(L102:L103) -> 66 | P104: =SUM(P102:P103) -> 56 | T104: =SUM(T102:T103) -> 90 | X104: =SUM(X102:X103) -> 98 | Y104: =SUM(Y102:Y103) -> 94 | Z104: =SUM(Z102:Z103) -> 91 | AA104: =SUM(AA102:AA103) -> 115 | AB104: =SUM(AB102:AB103) -> 147 | AC104: =SUM(AC102:AC103) -> 142 | AD104: =SUM(AD102:AD103) -> 198 | AE104: =SUM(AE102:AE103) -> 225 | ... AJ104: =SUM(AJ102:AJ103) -> 382
A106: Realized deferred revenue within an year | B106: Million | C106: 10-K | D106: 4261647 | AK106: 334 | AL106: 348 | AM106: 418 | AN106: 517 | AO106: 472 | AP106: 482 | AQ106: 478 | AR106: 482 | AS106: 460 | AT106: 494 | AU106: 509 | AV106: 626 | AW106: 599 | AX106: 637 | AY106: 704 | AZ106: 721
A108: Average revenue per user
A109: Worldwide
A110: Payments and other fees | B110: Dollar | C110: PRIVATE | D110: 233438 | I110: 0.19 | J110: 0.18 | K110: 0.18 | L110: 0.19 | M110: 0.16 | N110: 0.15 | O110: 0.13 | P110: 0.13 | Q110: 0.11 | R110: 0.12 | S110: 0.11 | T110: 0.1 | U110: 0.09 | V110: 0.08 | W110: 0.09 | X110: 0.09 | Y110: 0.08 | Z110: 0.09 | AA110: 0.08 | AB110: 0.12 | AC110: 0.07 | AD110: 0.11 | AE110: 0.11 | AF110: 0.14 | AG110: 0.12 | AH110: 0.14 | AI110: 0.09 | AJ110: 0.32 | AK110: 0.26 | AL110: 0.17 | AM110: 0.25 | BG110: =SUM(I110,J110,K110,L110) -> 0.74 | BH110: =SUM(M110,N110,O110,P110) -> 0.57 | BI110: =SUM(Q110,R110,S110,T110) -> 0.44 | BJ110: =SUM(U110,V110,W110,X110) -> 0.35 | BK110: =SUM(Y110,Z110,AA110,AB110) -> 0.37 | BL110: =SUM(AC110,AD110,AE110,AF110) -> 0.43 | BM110: =SUM(AG110,AH110,AI110,AJ110) -> 0.67
A111: Advertising | B111: Dollar | C111: PRIVATE | D111: 233439 | I111: 1.81 | J111: 2.06 | K111: 2.22 | L111: 2.62 | M111: 2.34 | N111: 2.61 | O111: 2.83 | P111: 3.6 | Q111: 3.21 | R111: 3.71 | S111: 3.89 | T111: 4.73 | U111: 4.14 | V111: 4.65 | W111: 4.97 | X111: 6.08 | Y111: 5.45 | Z111: 5.89 | AA111: 6.01 | AB111: 7.25 | AC111: 6.35 | AD111: 6.94 | AE111: 7.15 | AF111: 8.38 | AG111: 6.84 | AH111: 6.91 | AI111: 7.8 | AJ111: 9.82 | AK111: 9.01 | AL111: 9.95 | AM111: 9.74 | BG111: =SUM(I111,J111,K111,L111) -> 8.71 | BH111: =SUM(M111,N111,O111,P111) -> 11.38 | BI111: =SUM(Q111,R111,S111,T111) -> 15.54 | BJ111: =SUM(U111,V111,W111,X111) -> 19.84 | BK111: =SUM(Y111,Z111,AA111,AB111) -> 24.6 | BL111: =SUM(AC111,AD111,AE111,AF111) -> 28.82 | BM111: =SUM(AG111,AH111,AI111,AJ111) -> 31.37
...

Sheet Model
C1: 2017 | D1: 2018 | E1: 2019 | F1: 2020 | G1: 2021 | H1: 2022 | I1: 2023 | J1: 2024 | K1: 2025 | L1: 2026 | M1: 2027 | N1: 2028 | O1: 2029 | P1: 2030
A2: Revenue | C2: =Daloopa!BJ244 -> 40653 | D2: =Daloopa!BK244 -> 55838 | E2: =Daloopa!BL244 -> 70697 | F2: =Daloopa!BM244 -> 85965 | G2: =Daloopa!BN244 -> 117929 | H2: =Daloopa!BO244 -> 116609 | I2: =Daloopa!BP244 -> 134902 | J2: =Daloopa!BQ244 -> 164501 | K2: =Daloopa!BR244 -> 200966 | L2: =L45+L57 -> 250111.93 | M2: =M45+M57 -> 297787.79 | N2: =N45+N57 -> 355540.95 | O2: =O45+O57 -> 413799.28 | P2: =P45+P57 -> 475992.56
A3: Growth $ | D3: =D2-C2 -> 15185 | E3: =E2-D2 -> 14859 | F3: =F2-E2 -> 15268 | G3: =G2-F2 -> 31964 | H3: =H2-G2 -> -1320 | I3: =I2-H2 -> 18293 | J3: =J2-I2 -> 29599 | K3: =K2-J2 -> 36465 | ... P3: =P2-O2 -> 62193.275
A4: Growth % | D4: =D2/C2-1 -> 0.37352717 | E4: =E2/D2-1 -> 0.2661091 | F4: =F2/E2-1 -> 0.2159639 | G4: =G2/F2-1 -> 0.37182574 | H4: =H2/G2-1 -> -0.011193176 | I4: =I2/H2-1 -> 0.15687468 | J4: =J2/I2-1 -> 0.21941113 | K4: =K2/J2-1 -> 0.22167038 | ... P4: =P2/O2-1 -> 0.15029817
A5: Consensus (Feb 01, 2026) | L5: 250923 | M5: 292277 | N5: 341285 | O5: 384459 | P5: 433848
A6: Consensus incremental growth | L6: =L5-K2 -> 49957 | M6: =M5-L2 -> 42165.071 | N6: =N5-M2 -> 43497.213 | O6: =O5-N2 -> 28918.052 | P6: =P5-O2 -> 20048.715
A8: DAP | E8: ='Quarterly Data'!E12 -> 2260 | F8: ='Quarterly Data'!I12 -> 2600 | G8: ='Quarterly Data'!M12 -> 2820 | H8: ='Quarterly Data'!Q12 -> 2960 | I8: ='Quarterly Data'!U12 -> 3190 | J8: ='Quarterly Data'!Y12 -> 3350 | K8: =Daloopa!BD49*1000 -> 3580 | L8: =K8+L9 -> 3730 | M8: =L8+M9 -> 3880 | N8: =M8+N9 -> 4030 | O8: =N8+O9 -> 4180 | P8: =O8+P9 -> 4330
A9: Growth YoY | F9: =F8-E8 -> 340 | G9: =G8-F8 -> 220 | H9: =H8-G8 -> 140 | I9: =I8-H8 -> 230 | J9: =J8-I8 -> 160 | K9: =K8-J8 -> 230 | L9: 150 | M9: 150 | N9: 150 | O9: 150 | P9: 150
A11: FOA
A12: Ad Revenue by Geography
A13: UCAN | C13: =Daloopa!BJ213 -> 19484 | D13: =Daloopa!BK213 -> 26489 | E13: =Daloopa!BL213 -> 33493 | F13: =Daloopa!BM213 -> 40576 | G13: =Daloopa!BN213 -> 53419 | H13: =Daloopa!BO213 -> 52583 | I13: =Daloopa!BP213 -> 59581 | J13: =Daloopa!BQ213 -> 70415 | K13: =Daloopa!BR213 -> 85278 | L13: =K13*(1+L15) -> 104039.16 | M13: =L13*(1+M15) -> 119645.03 | N13: =M13*(1+N15) -> 137591.79 | O13: =N13*(1+O15) -> 154102.8 | P13: =O13*(1+P15) -> 169513.08
A14: Growth $ | C14: =C13-B13 -> 19484 | D14: =D13-C13 -> 7005 | E14: =E13-D13 -> 7004 | F14: =F13-E13 -> 7083 | G14: =G13-F13 -> 12843 | H14: =H13-G13 -> -836 | I14: =I13-H13 -> 6998 | J14: =J13-I13 -> 10834 | ... P14: =P13-O13 -> 15410.28
A15: Growth % | C15: =C13/B13-1 -> #DIV/0! | D15: =D13/C13-1 -> 0.35952576 | E15: =E13/D13-1 -> 0.26441164 | F15: =F13/E13-1 -> 0.21147703 | G15: =G13/F13-1 -> 0.31651715 | H15: =H13/G13-1 -> -0.015649862 | I15: =I13/H13-1 -> 0.13308484 | J15: =J13/I13-1 -> 0.18183649 | K15: =K13/J13-1 -> 0.21107719 | L15: 0.22 | M15: 0.15 | N15: 0.15 | O15: 0.12 | P15: 0.1
A17: Europe | C17: =Daloopa!BJ212 -> 9708 | D17: =Daloopa!BK212 -> 13592 | E17: =Daloopa!BL212 -> 16780 | F17: =Daloopa!BM212 -> 20455 | G17: =Daloopa!BN212 -> 28573 | H17: =Daloopa!BO212 -> 25335 | I17: =Daloopa!BP212 -> 30417 | J17: =Daloopa!BQ212 -> 37974 | K17: =Daloopa!BR212 -> 47163 | L17: =K17*(1+L19) -> 57538.86 | M17: =L17*(1+M19) -> 66169.689 | N17: =M17*(1+N19) -> 76095.142 | O17: =N17*(1+O19) -> 85226.559 | P17: =O17*(1+P19) -> 93749.215
A18: Growth $ | C18: =C17-B17 -> 9708 | D18: =D17-C17 -> 3884 | E18: =E17-D17 -> 3188 | F18: =F17-E17 -> 3675 | G18: =G17-F17 -> 8118 | H18: =H17-G17 -> -3238 | I18: =I17-H17 -> 5082 | J18: =J17-I17 -> 7557 | ... P18: =P17-O17 -> 8522.6559
A19: Growth % | C19: =C17/B17-1 -> #DIV/0! | D19: =D17/C17-1 -> 0.40008241 | E19: =E17/D17-1 -> 0.23454974 | F19: =F17/E17-1 -> 0.21901073 | G19: =G17/F17-1 -> 0.39687118 | H19: =H17/G17-1 -> -0.11332377 | I19: =I17/H17-1 -> 0.20059207 | J19: =J17/I17-1 -> 0.24844659 | K19: =K17/J17-1 -> 0.24198136 | L19: 0.22 | M19: 0.15 | N19: 0.15 | O19: 0.12 | P19: 0.1
A21: Asia Pacific | C21: =Daloopa!BJ211 -> 6716 | D21: =Daloopa!BK211 -> 9525 | E21: =Daloopa!BL211 -> 12540 | F21: =Daloopa!BM211 -> 15453 | G21: =Daloopa!BN211 -> 21468 | H21: =Daloopa!BO211 -> 23181 | I21: =Daloopa!BP211 -> 26473 | J21: =Daloopa!BQ211 -> 32121 | K21: =Daloopa!BR211 -> 38285 | L21: =K21*(1+L23) -> 47856.25 | M21: =L21*(1+M23) -> 58384.625 | N21: =M21*(1+N23) -> 70061.55 | O21: =N21*(1+O23) -> 84073.86 | P21: =O21*(1+P23) -> 99207.155
A22: Growth $ | C22: =C21-B21 -> 6716 | D22: =D21-C21 -> 2809 | E22: =E21-D21 -> 3015 | F22: =F21-E21 -> 2913 | G22: =G21-F21 -> 6015 | H22: =H21-G21 -> 1713 | I22: =I21-H21 -> 3292 | J22: =J21-I21 -> 5648 | ... P22: =P21-O21 -> 15133.295
A23: Growth % | C23: =C21/B21-1 -> #DIV/0! | D23: =D21/C21-1 -> 0.41825491 | E23: =E21/D21-1 -> 0.31653543 | F23: =F21/E21-1 -> 0.23229665 | G23: =G21/F21-1 -> 0.38924481 | H23: =H21/G21-1 -> 0.079793181 | I23: =I21/H21-1 -> 0.14201286 | J23: =J21/I21-1 -> 0.21334945 | K23: =K21/J21-1 -> 0.19189938 | L23: 0.25 | M23: 0.22 | N23: 0.2 | O23: 0.2 | P23: 0.18
A25: Rest of the World | C25: =Daloopa!BJ210 -> 4034 | D25: =Daloopa!BK210 -> 5406 | E25: =Daloopa!BL210 -> 6842 | F25: =Daloopa!BM210 -> 7685 | G25: =Daloopa!BN210 -> 11474 | H25: =Daloopa!BO210 -> 12542 | I25: =Daloopa!BP210 -> 15477 | J25: =Daloopa!BQ210 -> 20122 | K25: =Daloopa!BR210 -> 25448 | L25: =K25*(1+L27) -> 33082.4 | M25: =L25*(1+M27) -> 41353 | N25: =M25*(1+N27) -> 50657.425 | O25: =N25*(1+O27) -> 60788.91 | P25: =O25*(1+P27) -> 71730.914
A26: Growth $ | C26: =C25-B25 -> 4034 | D26: =D25-C25 -> 1372 | E26: =E25-D25 -> 1436 | F26: =F25-E25 -> 843 | G26: =G25-F25 -> 3789 | H26: =H25-G25 -> 1068 | I26: =I25-H25 -> 2935 | J26: =J25-I25 -> 4645 | ... P26: =P25-O25 -> 10942.004
A27: Growth % | C27: =C25/B25-1 -> #DIV/0! | D27: =D25/C25-1 -> 0.34010907 | E27: =E25/D25-1 -> 0.26563078 | F27: =F25/E25-1 -> 0.12320959 | G27: =G25/F25-1 -> 0.49303839 | H27: =H25/G25-1 -> 0.093080007 | I27: =I25/H25-1 -> 0.23401371 | J27: =J25/I25-1 -> 0.30012276 | K27: =K25/J25-1 -> 0.26468542 | L27: 0.3 | M27: 0.25 | N27: =M27-2.5% -> 0.225 | O27: 0.2 | P27: 0.18
A29: Advertising Revenue | C29: =C13+C17+C21+C25 -> 39942 | D29: 55013 | E29: 69655 | F29: 84169 | G29: =G13+G17+G21+G25 -> 114934 | H29: =H13+H17+H21+H25 -> 113641 | I29: =I13+I17+I21+I25 -> 131948 | J29: =J13+J17+J21+J25 -> 160632 | K29: =K13+K17+K21+K25 -> 196174 | L29: =L13+L17+L21+L25 -> 242516.67 | M29: =M13+M17+M21+M25 -> 285552.35 | N29: =N13+N17+N21+N25 -> 334405.91 | ... P29: =P13+P17+P21+P25 -> 434200.37
A30: Growth $ | D30: =D29-C29 -> 15071 | E30: =E29-D29 -> 14642 | F30: =F29-E29 -> 14514 | G30: =G29-F29 -> 30765 | H30: =H29-G29 -> -1293 | I30: =I29-H29 -> 18307 | J30: =J29-I29 -> 28684 | K30: =K29-J29 -> 35542 | ... P30: =P29-O29 -> 50008.235
A31: Growth | D31: =D29/C29-1 -> 0.37732212 | E31: =E29/D29-1 -> 0.26615527 | F31: =F29/E29-1 -> 0.20836982 | G31: =G29/F29-1 -> 0.36551462 | H31: =H29/G29-1 -> -0.011249935 | I31: =I29/H29-1 -> 0.16109503 | J31: =J29/I29-1 -> 0.21738867 | K31: =K29/J29-1 -> 0.22126351 | ... P31: =P29/O29-1 -> 0.13016465
A32: Overall ARPU (DAP) | F32: =F29/AVERAGE(E8:F8) -> 34.637449 | G32: =G29/AVERAGE(F8:G8) -> 42.41107 | H32: =H29/AVERAGE(G8:H8) -> 39.322145 | I32: =I29/AVERAGE(H8:I8) -> 42.909919 | J32: =J29/AVERAGE(I8:J8) -> 49.122936 | K32: =K29/AVERAGE(J8:K8) -> 56.615873 | L32: =L29/AVERAGE(K8:L8) -> 66.35203 | M32: =M29/AVERAGE(L8:M8) -> 75.046609 | ... P32: =P29/AVERAGE(O8:P8) -> 102.04474
A33: Growth % | G33: =G32/F32-1 -> 0.22442824 | H33: =H32/G32-1 -> -0.072832984 | I33: =I32/H32-1 -> 0.09124053 | J33: =J32/I32-1 -> 0.1447921 | K33: =K32/J32-1 -> 0.15253439 | L33: =L32/K32-1 -> 0.17196868 | M33: =M32/L32-1 -> 0.13103712 | N33: =N32/M32-1 -> 0.12666908 | ... P33: =P32/O32-1 -> 0.090323359
A35: FOA Ad revenue mix
A36: UCAN | C36: =C13/C29 -> 0.48780732 | D36: =D13/D29 -> 0.48150437 | E36: =E13/E29 -> 0.48084129 | F36: =F13/F29 -> 0.48207772 | G36: =G13/G29 -> 0.46477979 | H36: =H13/H29 -> 0.46271152 | I36: =I13/I29 -> 0.4515491 | J36: =J13/J29 -> 0.43836222 | ... P36: =P13/P29 -> 0.3904029
A37: Europe | C37: =C17/C29 -> 0.24305243 | D37: =D17/D29 -> 0.24706887 | E37: =E17/E29 -> 0.24090159 | F37: =F17/F29 -> 0.24302297 | G37: =G17/G29 -> 0.24860355 | H37: =H17/H29 -> 0.2229389 | I37: =I17/I29 -> 0.23052263 | J37: =J17/J29 -> 0.23640371 | ... P37: =P17/P29 -> 0.21591234
A38: Asia Pacific | C38: =C21/C29 -> 0.16814381 | D38: =D21/D29 -> 0.17314089 | E38: =E21/E29 -> 0.18003015 | F38: =F21/F29 -> 0.18359491 | G38: =G21/G29 -> 0.18678546 | H38: =H21/H29 -> 0.20398448 | I38: =I21/I29 -> 0.20063207 | J38: =J21/J29 -> 0.19996638 | ... P38: =P21/P29 -> 0.22848243
A39: Rest of the World | C39: =C25/C29 -> 0.10099644 | D39: =D25/D29 -> 0.098267682 | E39: =E25/E29 -> 0.098226976 | F39: =F25/F29 -> 0.091304399 | G39: =G25/G29 -> 0.099831207 | H39: =H25/H29 -> 0.1103651 | I39: =I25/I29 -> 0.11729621 | J39: =J25/J29 -> 0.12526769 | ... P39: =P25/P29 -> 0.16520233
A41: Other revenue | C41: =711-125 -> 586 | D41: =825-250 -> 575 | E41: =Daloopa!BL152 -> 541 | F41: =Daloopa!BM152 -> 657 | G41: =Daloopa!BN152 -> 721 | H41: =Daloopa!BO152 -> 808 | I41: =Daloopa!BP152 -> 1058 | J41: =Daloopa!BQ152 -> 1722 | K41: =Daloopa!BR152 -> 2584 | L41: =K41*(1+L43) -> 3876 | M41: =L41*(1+M43) -> 6201.6 | N41: =M41*(1+N43) -> 10542.72 | O41: =N41*(1+O43) -> 15814.08 | P41: =O41*(1+P43) -> 23721.12
A42: Growth $ | D42: =D41-C41 -> -11 | E42: =E41-D41 -> -34 | F42: =F41-E41 -> 116 | G42: =G41-F41 -> 64 | H42: =H41-G41 -> 87 | I42: =I41-H41 -> 250 | J42: =J41-I41 -> 664 | K42: =K41-J41 -> 862 | ... P42: =P41-O41 -> 7907.04
A43: Growth % | D43: =D41/C41-1 -> -0.018771331 | E43: =E41/D41-1 -> -0.059130435 | F43: =F41/E41-1 -> 0.21441774 | G43: =G41/F41-1 -> 0.097412481 | H43: =H41/G41-1 -> 0.12066574 | I43: =I41/H41-1 -> 0.30940594 | J43: =J41/I41-1 -> 0.62759924 | K43: =K41/J41-1 -> 0.50058072 | L43: 0.5 | M43: 0.6 | N43: 0.7 | O43: 0.5 | P43: 0.5
A45: FOA Revenue | C45: =C29+C41 -> 40528 | D45: =D29+D41 -> 55588 | E45: =E29+E41 -> 70196 | F45: =F29+F41 -> 84826 | G45: =G29+G41 -> 115655 | H45: =H29+H41 -> 114449 | I45: =I29+I41 -> 133006 | J45: =J29+J41 -> 162354 | ... P45: =P29+P41 -> 457921.49
A46: Growth | D46: =D45/C45-1 -> 0.37159495 | E46: =E45/D45-1 -> 0.26279053 | F46: =F45/E45-1 -> 0.20841643 | G46: =G45/F45-1 -> 0.3634381 | H46: =H45/G45-1 -> -0.010427565 | I46: =I45/H45-1 -> 0.16214209 | J46: =J45/I45-1 -> 0.2206517 | K46: =K45/J45-1 -> 0.22422607 | ... P46: =P45/O45-1 -> 0.14478594
A47: Growth $ | D47: =D45-C45 -> 15060 | E47: =E45-D45 -> 14608 | F47: =F45-E45 -> 14630 | G47: =G45-F45 -> 30829 | H47: =H45-G45 -> -1206 | I47: =I45-H45 -> 18557 | J47: =J45-I45 -> 29348 | K47: =K45-J45 -> 36404 | ... P47: =P45-O45 -> 57915.275
A49: Instagram revenue | D49: 11300 | E49: 17900 | F49: 22000 | G49: 32400 | H49: =H51*H45 -> 34351.127 | I49: =I51*I45 -> 42581.01 | J49: =J51*J45 -> 55223.663 | K49: =K51*K45 -> 70587.618 | L49: =L51*L45 -> 91200.653 | M49: =M51*M45 -> 112367.15 | N49: =N51*N45 -> 138028.96 | O49: =O51*O45 -> 166059.99 | P49: =P51*P45 -> 196971.97
A50: Growth | E50: =E49/D49-1 -> 0.5840708 | F50: =F49/E49-1 -> 0.22905028 | G50: =G49/F49-1 -> 0.47272727 | H50: =H49/G49-1 -> 0.060219966 | I50: =I49/H49-1 -> 0.23958118 | J50: =J49/I49-1 -> 0.29690823 | K50: =K49/J49-1 -> 0.27821326 | L50: =L49/K49-1 -> 0.29202055 | ... P50: =P49/O49-1 -> 0.18614944
A51: As % of FOA revenue | D51: =D49/D45 -> 0.20328128 | E51: =E49/E45 -> 0.25500028 | F51: =F49/F45 -> 0.25935444 | G51: =G49/G45 -> 0.28014353 | H51: =G51+2% -> 0.30014353 | I51: =H51+2% -> 0.32014353 | J51: =I51+2% -> 0.34014353 | K51: =J51+1.5% -> 0.35514353 | L51: =K51+1.5% -> 0.37014353 | M51: =L51+1.5% -> 0.38514353 | N51: =M51+1.5% -> 0.40014353 | O51: =N51+1.5% -> 0.41514353 | P51: =O51+1.5% -> 0.43014353
A53: FOA ex IG | D53: =D45-D49 -> 44288 | E53: =E45-E49 -> 52296 | F53: =F45-F49 -> 62826 | G53: =G45-G49 -> 83255 | H53: =H45-H49 -> 80097.873 | I53: =I45-I49 -> 90424.99 | J53: =J45-J49 -> 107130.34 | K53: =K45-K49 -> 128170.38 | ... P53: =P45-P49 -> 260949.52
A54: Growth | E54: =E53/D53-1 -> 0.18081647 | F54: =F53/E53-1 -> 0.20135383 | G54: =G53/F53-1 -> 0.32516792 | H54: =H53/G53-1 -> -0.037921169 | I54: =I53/H53-1 -> 0.12893122 | J54: =J53/I53-1 -> 0.1847426 | K54: =K53/J53-1 -> 0.1963967 | L54: =L53/K53-1 -> 0.21082589 | ... P54: =P53/O53-1 -> 0.11542525
A57: RL Revenue | C57: 125 | D57: 250 | E57: =Daloopa!BL156 -> 501 | F57: =Daloopa!BM156 -> 1139 | G57: =Daloopa!BN156 -> 2274 | H57: =Daloopa!BO156 -> 2159 | I57: =Daloopa!BP156 -> 1896 | J57: =Daloopa!BQ156 -> 2146 | K57: =Daloopa!BR156 -> 2207 | L57: =RL!I66 -> 3719.2589 | M57: =RL!J66 -> 6033.8393 | N57: =RL!K66 -> 10592.321 | O57: =RL!L66 -> 13793.071 | P57: =RL!M66 -> 18071.071
A58: Growth | D58: =D57/C57-1 -> 1 | E58: =E57/D57-1 -> 1.004 | F58: =F57/E57-1 -> 1.2734531 | G58: =G57/F57-1 -> 0.99648815 | H58: =H57/G57-1 -> -0.05057168 | I58: =I57/H57-1 -> -0.12181566 | J58: =J57/I57-1 -> 0.13185654 | K58: =K57/J57-1 -> 0.028424977 | ... P58: =P57/O57-1 -> 0.31015572
A60: Cost of revenue | C60: =Daloopa!BJ246 -> 5454 | D60: =Daloopa!BK246 -> 9355 | E60: =Daloopa!BL246 -> 12770 | F60: =Daloopa!BM246 -> 16692 | G60: =Daloopa!BN246 -> 22649 | H60: =Daloopa!BO246 -> 25249 | I60: =Daloopa!BP246 -> 25959 | J60: =Daloopa!BQ246 -> 30161 | K60: =Daloopa!BR246 -> 36175 | L60: =L63+L66 -> 51239.074 | M60: =M63+M66 -> 70033.558 | N60: =N63+N66 -> 90632.925 | O60: =O63+O66 -> 109784.77 | P60: =P63+P66 -> 125323.04
A61: As % of revenue | C61: =C60/C2 -> 0.13415984 | D61: =D60/D2 -> 0.16753824 | E61: =E60/E2 -> 0.18063001 | F61: =F60/F2 -> 0.19417205 | G61: =G60/G2 -> 0.19205624 | H61: =H60/H2 -> 0.21652703 | I61: =I60/I2 -> 0.19242858 | J61: =J60/J2 -> 0.18334843 | ... P61: =P60/P2 -> 0.26328781
A62: Restructuring | H62: 1495 | I62: -47 | J62: 31
A63: FOA COGS | C63: =C60-C66-C62 -> 5268.64 | D63: =D60-D66-D62 -> 8894.08 | E63: =E60-E66-E62 -> 12119.85 | F63: =F60-F66-F62 -> 15339.9 | G63: =G60-G66-G62 -> 19945.4 | H63: =H60-H66-H62 -> 21680.25 | I63: =I60-I66-I62 -> 24274.75 | J63: =J60-J66-J62 -> 28221 | K63: =K60-K66-K62 -> 34193.5 | L63: =L68+L70+L72 -> 47816.014 | M63: =M68+M70+M72 -> 64962.826 | N63: =N68+N70+N72 -> 82277.952 | O63: =O68+O70+O72 -> 100449.46 | P63: =P68+P70+P72 -> 116438.25
A64: FOA COGS as % of related revenue | C64: =C63/C45 -> 0.13 | D64: =D63/D45 -> 0.16 | E64: =E63/E45 -> 0.17265727 | F64: =F63/F45 -> 0.1808396 | G64: =G63/G45 -> 0.17245601 | H64: =H63/H45 -> 0.18943154 | I64: =I63/I45 -> 0.18250868 | J64: =J63/J45 -> 0.17382387 | ... P64: =P63/P45 -> 0.25427558
A65: Est. COGS per DAP | F65: =F63/AVERAGE(E8:F8) -> 6.312716 | G65: =G63/AVERAGE(F8:G8) -> 7.3599262 | H65: =H63/AVERAGE(G8:H8) -> 7.5018166 | I65: =I63/AVERAGE(H8:I8) -> 7.8942276 | J65: =J63/AVERAGE(I8:J8) -> 8.6302752 | K65: =K63/AVERAGE(J8:K8) -> 9.868254 | L65: =L63/AVERAGE(K8:L8) -> 13.082357 | M65: =M63/AVERAGE(L8:M8) -> 17.073016 | ... P65: =P63/AVERAGE(O8:P8) -> 27.365042
A66: RL COGS | C66: =C60-C63 -> 185.36 | D66: =D60-D63 -> 460.92 | E66: =RL!B67 -> 650.15 | F66: =RL!C67 -> 1352.1 | G66: =RL!D67 -> 2703.6 | H66: =RL!E67 -> 2073.75 | I66: =RL!F67 -> 1731.25 | J66: =RL!G67 -> 1909 | K66: =RL!H67 -> 1981.5 | L66: =RL!I67 -> 3423.0607 | ... P66: =RL!M67 -> 8884.7857
A67: RL COGS as % of related revenue | C67: =C66/C57 -> 1.48288 | D67: =D66/D57 -> 1.84368 | E67: =E66/E57 -> 1.2977046 | F67: =F66/F57 -> 1.1870939 | G67: =G66/G57 -> 1.1889182 | H67: =H66/H57 -> 0.96051413 | I67: =I66/I57 -> 0.91310654 | J67: =J66/J57 -> 0.88956198 | ... P67: =P66/P57 -> 0.49165794
A68: SBC | C68: =Daloopa!BJ279 -> 178 | D68: =Daloopa!BK279 -> 284 | E68: =Daloopa!BL279 -> 377 | F68: =Daloopa!BM279 -> 447 | G68: =Daloopa!BN279 -> 577 | H68: =Daloopa!BO279 -> 768 | I68: =Daloopa!BP279 -> 740 | J68: =Daloopa!BQ279 -> 1055 | K68: =Daloopa!BR279 -> 1124 | L68: =L69*L2 -> 1398.8725 | M68: =M69*M2 -> 1665.5229 | N68: =N69*N2 -> 1988.5355 | O68: =O69*O2 -> 2314.3736 | P68: =P69*P2 -> 2662.2197
A69: As % of revenue | C69: =C68/C2 -> 0.0043785207 | D69: =D68/D2 -> 0.0050861421 | E69: =E68/E2 -> 0.0053326167 | F69: =F68/F2 -> 0.0051997906 | G69: =G68/G2 -> 0.0048927745 | H69: =H68/H2 -> 0.0065861126 | I69: =I68/I2 -> 0.0054854635 | J69: =J68/J2 -> 0.0064133349 | K69: =K68/K2 -> 0.0055929859 | L69: =K69 -> 0.0055929859 | M69: =L69 -> 0.0055929859 | N69: =M69 -> 0.0055929859 | O69: =N69 -> 0.0055929859 | P69: =O69 -> 0.0055929859
A70: Depreciation | C70: 2330 | D70: 3680 | E70: 5180 | F70: 6390 | G70: 7560 | H70: 8500 | I70: 11020 | J70: 15290 | K70: 18000 | L70: ='PP&E'!O45 -> 28228.845 | M70: ='PP&E'!P45 -> 42344.021 | N70: ='PP&E'!Q45 -> 56205.679 | O70: ='PP&E'!R45 -> 71007.336 | P70: ='PP&E'!S45 -> 83636.404
A71: As % of Cost of revenue ex SBC | C71: =C70/(C60-C68) -> 0.44162244 | D71: =D70/(D60-D68) -> 0.40568846 | E71: =E70/(E60-E68) -> 0.41797789 | F71: =F70/(F60-F68) -> 0.3933518 | G71: =G70/(G60-G68) -> 0.3425154 | H71: =H70/(H60-H68) -> 0.34720804 | I71: =I70/(I60-I68) -> 0.43697212 | J71: =J70/(J60-J68) -> 0.52532124 | ... P71: =P70/(P60-P68) -> 0.68185102
A72: FOA COGS ex SBC, depr, and RL | C72: =C60-C68-C70-C66 -> 2760.64 | D72: =D60-D68-D70-D66 -> 4930.08 | E72: =E60-E68-E70-E66 -> 6562.85 | F72: =F60-F68-F70-F66 -> 8502.9 | G72: =G60-G68-G70-G66 -> 11808.4 | H72: =H60-H68-H70-H66 -> 13907.25 | I72: =I60-I68-I70-I66 -> 12467.75 | J72: =J60-J68-J70-J66 -> 11907 | K72: =K60-K68-K70-K66 -> 15069.5 | L72: =L73*L45 -> 18188.296 | M72: =M73*M45 -> 20953.282 | N72: =N73*N45 -> 24083.738 | O72: =O73*O45 -> 27127.754 | P72: =P73*P45 -> 30139.628
A73: As % of FOA revenue | C73: =C72/C45 -> 0.068116857 | D73: =D72/D45 -> 0.088689645 | E73: =E72/E45 -> 0.093493219 | F73: =F72/F45 -> 0.10023931 | G73: =G72/G45 -> 0.10210021 | H73: =H72/H45 -> 0.12151482 | I73: =I72/I45 -> 0.093738252 | J73: =J72/J45 -> 0.073339739 | K73: =K72/K45 -> 0.075818332 | L73: =K73-0.2% -> 0.073818332 | M73: =L73-0.2% -> 0.071818332 | N73: =M73-0.2% -> 0.069818332 | O73: =N73-0.2% -> 0.067818332 | P73: =O73-0.2% -> 0.065818332
A75: Gross Profit | C75: =C2-C60 -> 35199 | D75: =D2-D60 -> 46483 | E75: =E2-E60 -> 57927 | F75: =F2-F60 -> 69273 | G75: =G2-G60 -> 95280 | H75: =H2-H60 -> 91360 | I75: =I2-I60 -> 108943 | J75: =J2-J60 -> 134340 | ... P75: =P2-P60 -> 350669.52
A76: Gross Margin | C76: =C75/C2 -> 0.86584016 | D76: =D75/D2 -> 0.83246176 | E76: =E75/E2 -> 0.81936999 | F76: =F75/F2 -> 0.80582795 | G76: =G75/G2 -> 0.80794376 | H76: =H75/H2 -> 0.78347297 | I76: =I75/I2 -> 0.80757142 | J76: =J75/J2 -> 0.81665157 | ... P76: =P75/P2 -> 0.73671219
A78: R&D | C78: =Daloopa!BJ247 -> 7754 | D78: =Daloopa!BK247 -> 10273 | E78: =Daloopa!BL247 -> 13600 | F78: =Daloopa!BM247 -> 18447 | G78: =Daloopa!BN247 -> 24655 | H78: =Daloopa!BO247 -> 35338 | I78: =Daloopa!BP247 -> 38483 | J78: =Daloopa!BQ247 -> 43873 | K78: =Daloopa!BR247 -> 57372 | L78: =L81+L83 -> 84409.948 | M78: =M81+M83 -> 86858.487 | N78: =N81+N83 -> 95207.67 | O78: =O81+O83 -> 102921.43 | P78: =P81+P83 -> 107742.73
A79: As % of revenue | C79: =C78/C2 -> 0.19073623 | D79: =D78/D2 -> 0.18397865 | E79: =E78/E2 -> 0.19237026 | F79: =F78/F2 -> 0.21458733 | G79: =G78/G2 -> 0.20906647 | H79: =H78/H2 -> 0.30304693 | I79: =I78/I2 -> 0.28526634 | J79: =J78/J2 -> 0.26670355 | ... P79: =P78/P2 -> 0.22635381
A80: =A62 -> Restructuring | H80: 1719 | I80: 1572 | J80: 254
A81: FOA R&D | C81: =C78-C83-C80 -> 7295.04 | D81: =D78-D83-D80 -> 9449.96 | E81: =E78-E83-E80 -> 10600 | F81: =F78-F83-F80 -> 13437 | G81: =G78-G83-G80 -> 17685 | H81: =H78-H83-H80 -> 23434 | I81: =I78-I83-I80 -> 23936 | J81: =J78-J83-J80 -> 28849 | K81: =K78-K83-K80 -> 41952 | L81: =L82*L45 -> 68989.948 | M81: =M82*M45 -> 72938.487 | N81: =N82*N45 -> 82787.67 | O81: =O82*O45 -> 92001.429 | P81: =P82*P45 -> 100742.73
A82: FOA R&D as % of related revenue | C82: =C81/C45 -> 0.18 | D82: =D81/D45 -> 0.17 | E82: =E81/E45 -> 0.15100576 | F82: =F81/F45 -> 0.15840662 | G82: =G81/G45 -> 0.15291168 | H82: =H81/H45 -> 0.20475496 | I82: =I81/I45 -> 0.17996181 | J82: =J81/J45 -> 0.17769196 | K82: =K81/K45 -> 0.21107075 | L82: 0.28 | M82: 0.25 | N82: =M82-1% -> 0.24 | O82: =N82-1% -> 0.23 | P82: 0.22
A83: RL R&D | C83: =C78-C81-C80 -> 458.96 | D83: =D78-D81-D80 -> 823.04 | E83: =RL!B71 -> 3000 | F83: =RL!C71 -> 5010 | G83: =RL!D71 -> 6970 | H83: =RL!E71 -> 10185 | I83: =RL!F71 -> 12975 | J83: =RL!G71 -> 14770 | K83: =RL!H71 -> 15420 | L83: =RL!I71 -> 15420 | ... P83: =RL!M71 -> 7000
A84: RL R&D as % of related revenue | C84: =C83/C57 -> 3.67168 | D84: =D83/D57 -> 3.29216 | E84: =E83/E57 -> 5.988024 | F84: =F83/F57 -> 4.3985953 | G84: =G83/G57 -> 3.0650836 | H84: =H83/H57 -> 4.7174618 | I84: =I83/I57 -> 6.8433544 | J84: =J83/J57 -> 6.8825722 | ... P84: =P83/P57 -> 0.38735943
A85: SBC | C85: =Daloopa!BJ280 -> 2820 | D85: =Daloopa!BK280 -> 3022 | E85: =Daloopa!BL280 -> 3488 | F85: =Daloopa!BM280 -> 4918 | G85: =Daloopa!BN280 -> 7106 | H85: =Daloopa!BO280 -> 9361 | I85: =Daloopa!BP280 -> 11429 | J85: =Daloopa!BQ280 -> 13683 | K85: =Daloopa!BR280 -> 17485 | L85: =L86*L2 -> 21760.93 | M85: =M86*M2 -> 25908.957 | N85: =N86*N2 -> 30933.757 | O85: =O86*O2 -> 36002.51 | P85: =P86*P2 -> 41413.622
A86: As % of revenue | C86: =C85/C2 -> 0.069367574 | D86: =D85/D2 -> 0.05412085 | E86: =E85/E2 -> 0.049337313 | F86: =F85/F2 -> 0.057209329 | G86: =G85/G2 -> 0.060256595 | H86: =H85/H2 -> 0.080276823 | I86: =I85/I2 -> 0.08472076 | J86: =J85/J2 -> 0.083178826 | K86: =K85/K2 -> 0.087004767 | L86: =K86 -> 0.087004767 | M86: =L86 -> 0.087004767 | N86: =M86 -> 0.087004767 | O86: =N86 -> 0.087004767 | P86: =O86 -> 0.087004767
A88: Sales & Marketing | C88: =Daloopa!BJ248 -> 4725 | D88: =Daloopa!BK248 -> 7846 | E88: =Daloopa!BL248 -> 9876 | F88: =Daloopa!BM248 -> 11591 | G88: =Daloopa!BN248 -> 14043 | H88: =Daloopa!BO248 -> 15262 | I88: =Daloopa!BP248 -> 12301 | J88: =Daloopa!BQ248 -> 11347 | K88: =Daloopa!BR248 -> 11991 | L88: =L91+L93 -> 13649.647 | M88: =M91+M93 -> 14972.93 | N88: =N91+N93 -> 16384.712 | O88: =O91+O93 -> 17600.849 | P88: =P91+P93 -> 17142.436
A89: As % of revenue | C89: =C88/C2 -> 0.11622758 | D89: =D88/D2 -> 0.14051363 | E89: =E88/E2 -> 0.13969475 | F89: =F88/F2 -> 0.13483394 | G89: =G88/G2 -> 0.11908012 | H89: =H88/H2 -> 0.13088184 | I89: =I88/I2 -> 0.091184712 | J89: =J88/J2 -> 0.068978304 | ... P89: =P88/P2 -> 0.036014085
A90: =A80 -> Restructuring | H90: 638 | I90: 395 | J90: 54
A91: FOA S&M | C91: =C88-C93-C90 -> 4458.08 | D91: =D88-D93-D90 -> 7226.44 | E91: =E88-E93-E90 -> 9201 | F91: =F88-F93-F90 -> 10891 | G91: =G88-G93-G90 -> 12643 | H91: =H88-H93-H90 -> 13074 | I91: =I88-I93-I90 -> 9906 | J91: =J88-J93-J90 -> 9293 | K91: =K88-K93-K90 -> 9491 | L91: =L92*L45 -> 11149.647 | M91: =M92*M45 -> 12472.93 | N91: =N92*N45 -> 13884.712 | O91: =O92*O45 -> 15100.849 | P91: =P92*P45 -> 16142.436
A92: FOA S&M as % of related revenue | C92: =C91/C45 -> 0.11 | D92: =D91/D45 -> 0.13 | E92: =E91/E45 -> 0.13107584 | F92: =F91/F45 -> 0.12839224 | G92: =G91/G45 -> 0.1093165 | H92: =H91/H45 -> 0.11423429 | I92: =I91/I45 -> 0.074477843 | J92: =J91/J45 -> 0.057239119 | K92: =K91/K45 -> 0.047751537 | L92: =K92-0.25% -> 0.045251537 | M92: =L92-0.25% -> 0.042751537 | N92: =M92-0.25% -> 0.040251537 | O92: =N92-0.25% -> 0.037751537 | P92: =O92-0.25% -> 0.035251537
A93: RL S&M | C93: =C88-C91 -> 266.92 | D93: =D88-D91 -> 619.56 | E93: =RL!B75 -> 675 | F93: =RL!C75 -> 700 | G93: =RL!D75 -> 1400 | H93: =RL!E75 -> 1550 | I93: =RL!F75 -> 2000 | J93: =RL!G75 -> 2000 | K93: =RL!H75 -> 2500 | L93: =RL!I75 -> 2500 | ... P93: =RL!M75 -> 1000
A94: RL S&M as % of related revenue | C94: =C93/C57 -> 2.13536 | D94: =D93/D57 -> 2.47824 | E94: =E93/E57 -> 1.3473054 | F94: =F93/F57 -> 0.61457419 | G94: =G93/G57 -> 0.61565523 | H94: =H93/H57 -> 0.71792497 | I94: =I93/I57 -> 1.0548523 | J94: =J93/J57 -> 0.93196645 | ... P94: =P93/P57 -> 0.055337062
A95: SBC | C95: =Daloopa!BJ281 -> 436 | D95: =Daloopa!BK281 -> 511 | E95: =Daloopa!BL281 -> 569 | F95: =Daloopa!BM281 -> 691 | G95: =Daloopa!BN281 -> 837 | H95: =Daloopa!BO281 -> 1004 | I95: =Daloopa!BP281 -> 952 | J95: =Daloopa!BQ281 -> 1026 | K95: =Daloopa!BR281 -> 926 | L95: =L96*L2 -> 1152.4519 | M95: =M96*M2 -> 1372.1301 | N95: =N96*N2 -> 1638.2419 | O95: =O96*O2 -> 1906.6814 | P95: =P96*P2 -> 2193.2521
A96: As % of revenue | C96: =C95/C2 -> 0.010724916 | D96: =D95/D2 -> 0.0091514739 | E96: =E95/E2 -> 0.008048432 | F96: =F95/F2 -> 0.0080381551 | G96: =G95/G2 -> 0.0070974909 | H96: =H95/H2 -> 0.0086099701 | I96: =I95/I2 -> 0.0070569747 | J96: =J95/J2 -> 0.0062370442 | K96: =K95/K2 -> 0.0046077446 | L96: =K96 -> 0.0046077446 | M96: =L96 -> 0.0046077446 | N96: =M96 -> 0.0046077446 | O96: =N96 -> 0.0046077446 | P96: =O96 -> 0.0046077446
A98: General & Administrative | C98: =Daloopa!BJ249 -> 2517 | D98: =Daloopa!BK249 -> 3451 | E98: =Daloopa!BL249 -> 10465 | F98: =Daloopa!BM249 -> 6564 | G98: =Daloopa!BN249 -> 9829 | H98: =Daloopa!BO249 -> 11816 | I98: =Daloopa!BP249 -> 11408 | J98: =Daloopa!BQ249 -> 9740 | K98: =Daloopa!BR249 -> 12152 | L98: =L101+L103 -> 14458.483 | M98: =M101+M103 -> 16552.406 | N98: =N101+N103 -> 18951.921 | O98: =O101+O103 -> 21337.433 | P98: =P101+P103 -> 23251.692
A99: As % of revenue | C99: =C98/C2 -> 0.06191425 | D99: =D98/D2 -> 0.06180379 | E99: =E98/E2 -> 0.14802608 | F99: =F98/F2 -> 0.076356657 | G99: =G98/G2 -> 0.083346759 | H99: =H98/H2 -> 0.10133009 | I99: =I98/I2 -> 0.084565092 | J99: =J98/J2 -> 0.059209367 | ... P99: =P98/P2 -> 0.048848857
A100: =A90 -> Restructuring | H100: 759 | I100: 335 | J100: 50
A101: FOA G&A | C101: =C98-C103-C100 -> 2431.68 | D101: =D98-D103-D100 -> 3335.28 | E101: =E98-E103-E100 -> 9790 | F101: =F98-F103-F100 -> 5864 | G101: =G98-G103-G100 -> 8429 | H101: =H98-H103-H100 -> 9507 | I101: =I98-I103-I100 -> 9773 | J101: =J98-J103-J100 -> 8490 | K101: =K98-K103-K100 -> 10652 | L101: =L102*L45 -> 12958.483 | M101: =M102*M45 -> 15052.406 | N101: =N102*N45 -> 17451.921 | O101: =O102*O45 -> 19837.433 | P101: =P102*P45 -> 22251.692
A102: FOA G&A as % of related revenue | C102: =C101/C45 -> 0.06 | D102: =D101/D45 -> 0.06 | E102: =E101/E45 -> 0.13946664 | F102: =F101/F45 -> 0.069129748 | G102: =G101/G45 -> 0.07288055 | H102: =H101/H45 -> 0.083067567 | I102: =I101/I45 -> 0.073477888 | J102: =J101/J45 -> 0.052293137 | K102: =K101/K45 -> 0.053592811 | L102: =K102-0.1% -> 0.052592811 | M102: =L102-0.1% -> 0.051592811 | N102: =M102-0.1% -> 0.050592811 | O102: =N102-0.1% -> 0.049592811 | P102: =O102-0.1% -> 0.048592811
A103: RL G&A | C103: =C98-C101 -> 85.32 | D103: =D98-D101 -> 115.72 | E103: =RL!B79 -> 675 | F103: =RL!C79 -> 700 | G103: =RL!D79 -> 1400 | H103: =RL!E79 -> 1550 | I103: =RL!F79 -> 1300 | J103: =RL!G79 -> 1200 | K103: =RL!H79 -> 1500 | L103: =RL!I79 -> 1500 | ... P103: =RL!M79 -> 1000
A104: RL G&A as % of related revenue | C104: =C103/C57 -> 0.68256 | D104: =D103/D57 -> 0.46288 | E104: =E103/E57 -> 1.3473054 | F104: =F103/F57 -> 0.61457419 | G104: =G103/G57 -> 0.61565523 | H104: =H103/H57 -> 0.71792497 | I104: =I103/I57 -> 0.68565401 | J104: =J103/J57 -> 0.55917987 | ... P104: =P103/P57 -> 0.055337062
A105: SBC | C105: =Daloopa!BJ282 -> 289 | D105: =Daloopa!BK282 -> 335 | E105: =Daloopa!BL282 -> 402 | F105: =Daloopa!BM282 -> 480 | G105: =Daloopa!BN282 -> 644 | H105: =Daloopa!BO282 -> 859 | I105: =Daloopa!BP282 -> 906 | J105: =Daloopa!BQ282 -> 926 | K105: =Daloopa!BR282 -> 892 | L105: =L106*L2 -> 1250.5596 | M105: =M106*M2 -> 1488.9389 | N105: =N106*N2 -> 1777.7047 | O105: =O106*O2 -> 2068.9964 | P105: =P106*P2 -> 2379.9628
A106: As % of revenue | C106: =C105/C2 -> 0.0071089464 | D106: =D105/D2 -> 0.0059994985 | E106: =E105/E2 -> 0.0056862385 | F106: =F105/F2 -> 0.0055836678 | G106: =G105/G2 -> 0.0054609129 | H106: =H105/H2 -> 0.0073664983 | I106: =I105/I2 -> 0.0067159864 | J106: =J105/J2 -> 0.0056291451 | K106: =K105/K2 -> 0.0044385617 | L106: 0.005 | M106: 0.005 | N106: 0.005 | O106: 0.005 | P106: 0.005
A108: Total Opex | C108: =C122 -> 20450 | D108: =D122 -> 30925 | E108: =E122-5000 -> 41711 | F108: =F122 -> 53294 | G108: =G122 -> 71176 | H108: =H122 -> 87665 | I108: =I122 -> 88151 | J108: =J122 -> 95121 | K108: =K122 -> 117690 | L108: =L122 -> 163757.15 | M108: =M122 -> 188417.38 | ... P108: =P122 -> 273459.89
A109: Total # of employees | C109: 25105 | D109: 35587 | E109: 44942 | F109: 58604 | G109: 71970 | H109: 86482 | I109: ='Quarterly Data'!U91 -> 67317 | J109: ='Quarterly Data'!Y91 -> 74067 | K109: =Daloopa!BD48 -> 78865 | L109: =K109*(1+L110) -> 82808.25 | M109: =L109*(1+M110) -> 86948.663 | N109: =M109*(1+N110) -> 91296.096 | O109: =N109*(1+O110) -> 95860.9 | P109: =O109*(1+P110) -> 100653.95
A110: Increase | C110: =C109/B109-1 -> #DIV/0! | D110: =D109/C109-1 -> 0.41752639 | E110: =E109/D109-1 -> 0.26287689 | F110: =F109/E109-1 -> 0.30399181 | G110: =G109/F109-1 -> 0.22807317 | H110: =H109/G109-1 -> 0.20163957 | I110: =I109/H109-1 -> -0.22160681 | J110: =J109/I109-1 -> 0.10027185 | K110: =K109/J109-1 -> 0.064779186 | L110: 0.05 | M110: 0.05 | N110: 0.05 | O110: 0.05 | P110: 0.05
A111: Opex per avg employee | C111: =C108*1000000/AVERAGE(B109:C109) -> 814578.77 | D111: =D108*1000000/AVERAGE(C109:D109) -> 1019079.9 | E111: =E108*1000000/AVERAGE(D109:E109) -> 1035924.9 | F111: =F108*1000000/AVERAGE(E109:F109) -> 1029378.2 | G111: =G108*1000000/AVERAGE(F109:G109) -> 1090201.7 | H111: =H108*1000000/AVERAGE(G109:H109) -> 1106518.1 | I111: =I108*1000000/AVERAGE(H109:I109) -> 1146314.3 | J111: =J108*1000000/AVERAGE(I109:J109) -> 1345569.5 | ... P111: =P108*1000000/AVERAGE(O109:P109) -> 2783096.5
A112: Increase YoY % | D112: =D111/C111-1 -> 0.25105144 | E112: =E111/D111-1 -> 0.016529617 | F112: =F111/E111-1 -> -0.0063196653 | G112: =G111/F111-1 -> 0.059087588 | H112: =H111/G111-1 -> 0.014966347 | I112: =I111/H111-1 -> 0.035965326 | J112: =J111/I111-1 -> 0.17382245 | K112: =K111/J111-1 -> 0.1438394 | ... P112: =P111/O111-1 -> 0.034944173
A113: Increase YoY % | D113: =D108/C108-1 -> 0.51222494 | E113: =E108/D108-1 -> 0.3487793 | F113: =F108/E108-1 -> 0.27769653 | G113: =G108/F108-1 -> 0.33553496 | H113: =H108/G108-1 -> 0.23166517 | I113: =I108/H108-1 -> 0.0055438316 | J113: =J108/I108-1 -> 0.07906887 | K113: =K108/J108-1 -> 0.23726622 | ... P113: =P108/O108-1 -> 0.086691382
A115: FOA EBIT (reported) | E115: 28489 | F115: 39294 | G115: 56946 | H115: 42661 | I115: 62871 | J115: 87109 | K115: =Daloopa!BR160 -> 102469
A116: FOA EBIT (calculated) | C116: =C45-C63-C81-C91-C101 -> 21074.56 | D116: =D45-D63-D81-D91-D101 -> 26682.24 | E116: =E45-E63-E81-E91-E101 -> 28485.15 | F116: =F45-F63-F81-F91-F101 -> 39294.1 | G116: =G45-G63-G81-G91-G101 -> 56952.6 | H116: =H45-H63-H81-H91-H101 -> 46753.75 | I116: =I45-I63-I81-I91-I101 -> 65116.25 | J116: =J45-J63-J81-J91-J101 -> 87501 | ... P116: =P45-P63-P81-P91-P101 -> 202346.38
A117: Margin | C117: =C116/C45 -> 0.52 | D117: =D116/D45 -> 0.48 | E117: =E115/E45 -> 0.40584934 | F117: =F115/F45 -> 0.46323061 | G117: =G115/G45 -> 0.49237819 | H117: =H115/H45 -> 0.37275118 | I117: =I115/I45 -> 0.47269296 | J117: =J116/J45 -> 0.53895192 | K117: =K116/K45 -> 0.51554906 | L117: =L116/L45 -> 0.42809138 | M117: =M116/M45 -> 0.4329926 | N117: =N116/N45 -> 0.43063332 | O117: =O116/O45 -> 0.43153589 | P117: =P116/P45 -> 0.44188007
A118: RL EBIT (reported) | E118: -4503 | F118: -6623 | G118: -10193 | H118: -13717 | I118: -16119 | J118: -17729 | K118: =Daloopa!BR161 -> -19193
A119: RL EBIT (calculated) | C119: =C57-C66-C83-C93-C103 -> -871.56 | D119: =D57-D66-D83-D93-D103 -> -1769.24 | E119: =RL!B84 -> -4499.15 | F119: =RL!C84 -> -6623.1 | G119: =RL!D84 -> -10199.6 | H119: =RL!E84 -> -13718.75 | I119: =RL!F84 -> -16118.75 | J119: =RL!G84 -> -17729 | K119: =RL!H84 -> -19191.5 | L119: =L57-L66-L83-L93-L103 -> -19123.802 | M119: =M57-M66-M83-M93-M103 -> -16956.893 | N119: =N57-N66-N83-N93-N103 -> -14182.652 | O119: =O57-O66-O83-O93-O103 -> -10462.239 | P119: =P57-P66-P83-P93-P103 -> 186.28571
A120: Margin | C120: =C119/C57 -> -6.97248 | D120: =D119/D57 -> -7.07696 | E120: =E118/E57 -> -8.988024 | F120: =F118/F57 -> -5.8147498 | G120: =G118/G57 -> -4.4824099 | H120: =H119/H57 -> -6.3542149 | I120: =I119/I57 -> -8.5014504 | J120: =J119/J57 -> -8.2614166 | K120: =K119/K57 -> -8.6957408 | L120: =L119/L57 -> -5.1418312 | M120: =M119/M57 -> -2.8102991 | N120: =N119/N57 -> -1.3389559 | O120: =O119/O57 -> -0.75851411 | P120: =P119/P57 -> 0.010308504
...

Sheet PP&E
A1: Items | B1: 2013 | C1: 2014 | D1: 2015 | E1: 2016 | F1: =Model!C1 -> 2017 | G1: =Model!D1 -> 2018 | H1: =Model!E1 -> 2019 | I1: =Model!F1 -> 2020 | J1: =Model!G1 -> 2021 | K1: =Model!H1 -> 2022 | L1: =Model!I1 -> 2023 | M1: =Model!J1 -> 2024 | ... S1: =Model!P1 -> 2030
A2: Land | B2: =Daloopa!BF521 -> 45 | C2: =Daloopa!BG521 -> 153 | D2: =Daloopa!BH521 -> 596 | E2: =Daloopa!BI521 -> 696 | F2: =Daloopa!BJ521 -> 798 | G2: =Daloopa!BK521 -> 899 | H2: =Daloopa!BL521 -> 1097 | I2: =Daloopa!BM521 -> 1326 | ... N2: =Daloopa!BR521 -> 3687 | O2: =N2+O3 -> 4687 | P2: =O2+P3 -> 5687 | Q2: =P2+Q3 -> 6687 | R2: =Q2+R3 -> 7687 | S2: =R2+S3 -> 8687
A3: Increase | C3: =C2-B2 -> 108 | D3: =D2-C2 -> 443 | E3: =E2-D2 -> 100 | F3: =F2-E2 -> 102 | G3: =G2-F2 -> 101 | H3: =H2-G2 -> 198 | I3: =I2-H2 -> 229 | J3: =J2-I2 -> 362 | ... N3: =N2-M2 -> 1126 | O3: 1000 | P3: 1000 | Q3: 1000 | R3: 1000 | S3: 1000
A4: Buildings | B4: =Daloopa!BF522 -> 1071 | C4: =Daloopa!BG522 -> 1420 | D4: =Daloopa!BH522 -> 2273 | E4: =Daloopa!BI522 -> 3109 | F4: =Daloopa!BJ522 -> 4909 | G4: =Daloopa!BK522 -> 7401 | H4: =Daloopa!BL522 -> 11226 | I4: =Daloopa!BM522 -> 17360 | ... N4: =Daloopa!BR522 -> 55568 | O4: =N4+O5 -> 65568 | P4: =O4+P5 -> 75568 | Q4: =P4+Q5 -> 85568 | R4: =Q4+R5 -> 95568 | S4: =R4+S5 -> 105568
A5: Increase | C5: =C4-B4 -> 349 | D5: =D4-C4 -> 853 | E5: =E4-D4 -> 836 | F5: =F4-E4 -> 1800 | G5: =G4-F4 -> 2492 | H5: =H4-G4 -> 3825 | I5: =I4-H4 -> 6134 | J5: =J4-I4 -> 5171 | ... N5: =N4-M4 -> 8492 | O5: 10000 | P5: 10000 | Q5: 10000 | R5: 10000 | S5: 10000
A6: Leasehold improvements | B6: =Daloopa!BF523 -> 203 | C6: =Daloopa!BG523 -> 304 | D6: =Daloopa!BH523 -> 447 | E6: =Daloopa!BI523 -> 531 | F6: =Daloopa!BJ523 -> 959 | G6: =Daloopa!BK523 -> 1841 | H6: =Daloopa!BL523 -> 3112 | I6: =Daloopa!BM523 -> 4321 | ... N6: =Daloopa!BR523 -> 8346 | O6: =N6+O7 -> 9346 | P6: =O6+P7 -> 10346 | Q6: =P6+Q7 -> 11346 | R6: =Q6+R7 -> 12346 | S6: =R6+S7 -> 13346
A7: Increase | C7: =C6-B6 -> 101 | D7: =D6-C6 -> 143 | E7: =E6-D6 -> 84 | F7: =F6-E6 -> 428 | G7: =G6-F6 -> 882 | H7: =H6-G6 -> 1271 | I7: =I6-H6 -> 1209 | J7: =J6-I6 -> 1474 | ... N7: =N6-M6 -> 1053 | O7: 1000 | P7: 1000 | Q7: 1000 | R7: 1000 | S7: 1000
A9: Network equipment | B9: =Daloopa!BF524 -> 2351 | C9: =Daloopa!BG524 -> 3020 | D9: =Daloopa!BH524 -> 3633 | E9: =Daloopa!BI524 -> 5179 | F9: =Daloopa!BJ524 -> 7998 | G9: =Daloopa!BK524 -> 13017 | H9: =Daloopa!BL524 -> 17004 | I9: =Daloopa!BM524 -> 22003 | ... N9: =Daloopa!BR524 -> 0
A10: Servers and network assets | B10: =Daloopa!BF525 -> 0 | C10: =Daloopa!BG525 -> 0 | D10: =Daloopa!BH525 -> 0 | E10: =Daloopa!BI525 -> 0 | F10: =Daloopa!BJ525 -> 0 | G10: =Daloopa!BK525 -> 0 | H10: =Daloopa!BL525 -> 0 | I10: =Daloopa!BM525 -> 0 | ... N10: =Daloopa!BR525 -> 98040
A11: Computer software, office equipment and other | B11: =Daloopa!BF526 -> 95 | C11: =Daloopa!BG526 -> 149 | D11: =Daloopa!BH526 -> 248 | E11: =Daloopa!BI526 -> 398 | F11: =Daloopa!BJ526 -> 681 | G11: =Daloopa!BK526 -> 1187 | H11: =Daloopa!BL526 -> 1813 | I11: =Daloopa!BM526 -> 2458 | ... N11: =Daloopa!BR526 -> 0
A12: Equipment and other | B12: =Daloopa!BF527 -> 0 | C12: =Daloopa!BG527 -> 0 | D12: =Daloopa!BH527 -> 0 | E12: =Daloopa!BI527 -> 0 | F12: =Daloopa!BJ527 -> 0 | G12: =Daloopa!BK527 -> 0 | H12: =Daloopa!BL527 -> 0 | I12: =Daloopa!BM527 -> 0 | ... N12: =Daloopa!BR527 -> 9377
A13: Sub-total Servers and Network Assets | B13: =B9+B10+B11+B12 -> 2446 | C13: =C9+C10+C11+C12 -> 3169 | D13: =D9+D10+D11+D12 -> 3881 | E13: =E9+E10+E11+E12 -> 5577 | F13: =F9+F10+F11+F12 -> 8679 | G13: =G9+G10+G11+G12 -> 14204 | H13: =H9+H10+H11+H12 -> 18817 | I13: =I9+I10+I11+I12 -> 24461 | ... N13: =N9+N10+N11+N12 -> 107417 | O13: =N13+O14 -> 207417 | P13: =O13+P14 -> 287417 | Q13: =P13+Q14 -> 367417 | R13: =Q13+R14 -> 447417 | S13: =R13+S14 -> 527417
A14: Increase | C14: =C13-B13 -> 723 | D14: =D13-C13 -> 712 | E14: =E13-D13 -> 1696 | F14: =F13-E13 -> 3102 | G14: =G13-F13 -> 5525 | H14: =H13-G13 -> 4613 | I14: =I13-H13 -> 5644 | J14: =J13-I13 -> 5887 | ... N14: =N13-M13 -> 31870 | O14: 100000 | P14: 80000 | Q14: 80000 | R14: 80000 | S14: 80000
A16: Finance lease right of use assets | B16: =Daloopa!BF528 -> 0 | C16: =Daloopa!BG528 -> 0 | D16: =Daloopa!BH528 -> 0 | E16: =Daloopa!BI528 -> 0 | F16: =Daloopa!BJ528 -> 0 | G16: =Daloopa!BK528 -> 0 | H16: =Daloopa!BL528 -> 1635 | I16: =Daloopa!BM528 -> 2295 | ... N16: =Daloopa!BR528 -> 8187 | O16: =N16+O17 -> 11187 | P16: =O16+P17 -> 14187 | Q16: =P16+Q17 -> 17187 | R16: =Q16+R17 -> 20187 | S16: =R16+S17 -> 23187
A17: Increase | I17: =I16-H16 -> 660 | J17: =J16-I16 -> 545 | K17: =K16-J16 -> 513 | L17: =L16-K16 -> 832 | M17: =M16-L16 -> 1199 | N17: =N16-M16 -> 2803 | O17: 3000 | P17: 3000 | Q17: 3000 | R17: 3000 | S17: 3000
A18: Construction in progress | B18: =Daloopa!BF529 -> 377 | C18: =Daloopa!BG529 -> 738 | D18: =Daloopa!BH529 -> 622 | E18: =Daloopa!BI529 -> 1890 | F18: =Daloopa!BJ529 -> 2992 | G18: =Daloopa!BK529 -> 7228 | H18: =Daloopa!BL529 -> 10099 | I18: =Daloopa!BM529 -> 11288 | ... N18: =Daloopa!BR529 -> 50521 | O18: =N18+O19 -> 60521 | P18: =O18+P19 -> 55521 | Q18: =P18+Q19 -> 50521 | R18: =Q18+R19 -> 45521 | S18: =R18+S19 -> 35521
A19: Increase | C19: =C18-B18 -> 361 | D19: =D18-C18 -> -116 | E19: =E18-D18 -> 1268 | F19: =F18-E18 -> 1102 | G19: =G18-F18 -> 4236 | H19: =H18-G18 -> 2871 | I19: =I18-H18 -> 1189 | J19: =J18-I18 -> 3399 | ... N19: =N18-M18 -> 23719 | O19: 10000 | P19: -5000 | Q19: -5000 | R19: -5000 | S19: -10000
A20: Property and equipment, gross | B20: =B2+B4+B6+B16+B18+B13 -> 4142 | C20: =C2+C4+C6+C16+C18+C13 -> 5784 | D20: =D2+D4+D6+D16+D18+D13 -> 7819 | E20: =E2+E4+E6+E16+E18+E13 -> 11803 | F20: =F2+F4+F6+F16+F18+F13 -> 18337 | G20: =G2+G4+G6+G16+G18+G13 -> 31573 | H20: =H2+H4+H6+H16+H18+H13 -> 45986 | I20: =I2+I4+I6+I16+I18+I13 -> 61051 | ... S20: =S2+S4+S6+S16+S18+S13 -> 713726
B21: =[1]Sheet1!BB458 -> 0 | C21: =[1]Sheet1!BC458 -> 0 | D21: =[1]Sheet1!BD458 -> 0 | E21: =[1]Sheet1!BE458 -> 0 | F21: =[1]Sheet1!BF458 -> 0 | G21: =[1]Sheet1!BG458 -> 0 | H21: =[1]Sheet1!BH458 -> 0 | I21: =[1]Sheet1!BI458 -> 0 | ... L21: =[1]Sheet1!BL458 -> 0
A22: Less: Accumulated depreciation | B22: =Daloopa!BF532 -> -1260 | C22: =Daloopa!BG532 -> -1817 | D22: =Daloopa!BH532 -> -2132 | E22: =Daloopa!BI532 -> -3212 | F22: =Daloopa!BJ532 -> -4616 | G22: =Daloopa!BK532 -> -6890 | H22: =Daloopa!BL532 -> -10663 | I22: =Daloopa!BM532 -> -15418 | ... N22: =Daloopa!BR532 -> -57326 | O22: =N22-O45 -> -85554.845 | P22: =O22-P45 -> -127898.87 | Q22: =P22-Q45 -> -184104.54 | R22: =Q22-R45 -> -255111.88 | S22: =R22-S45 -> -338748.29
A23: Property and equipment, net | B23: =B20+B22 -> 2882 | C23: =C20+C22 -> 3967 | D23: =D20+D22 -> 5687 | E23: =E20+E22 -> 8591 | F23: =F20+F22 -> 13721 | G23: =G20+G22 -> 24683 | H23: =H20+H22 -> 35323 | I23: =I20+I22 -> 45633 | ... S23: =S20+S22 -> 374977.71
A25: Capex | O25: =O23-N23+O45 -> 125000 | P25: =P23-O23+P45 -> 90000 | Q25: =Q23-P23+Q45 -> 90000 | R25: =R23-Q23+R45 -> 90000 | S25: =S23-R23+S45 -> 85000
A27: PP&E Mix (as % of Gross PP&E)
A28: Land | B28: =B2/B$20 -> 0.010864317 | C28: =C2/C$20 -> 0.026452282 | D28: =D2/D$20 -> 0.076224581 | E28: =E2/E$20 -> 0.058968059 | F28: =F2/F$20 -> 0.043518569 | G28: =G2/G$20 -> 0.028473696 | H28: =H2/H$20 -> 0.023855086 | I28: =I2/I$20 -> 0.021719546 | ... S28: =S2/S$20 -> 0.012171337
A29: Buildings | B29: =B4/B$20 -> 0.25857074 | C29: =C4/C$20 -> 0.24550484 | D29: =D4/D$20 -> 0.29070214 | E29: =E4/E$20 -> 0.26340761 | F29: =F4/F$20 -> 0.26771009 | G29: =G4/G$20 -> 0.23440915 | H29: =H4/H$20 -> 0.24411777 | I29: =I4/I$20 -> 0.28435243 | ... S29: =S4/S$20 -> 0.1479111
A30: Leasehold improvements | B30: =B6/B$20 -> 0.04901014 | C30: =C6/C$20 -> 0.052558783 | D30: =D6/D$20 -> 0.057168436 | E30: =E6/E$20 -> 0.044988562 | F30: =F6/F$20 -> 0.052298631 | G30: =G6/G$20 -> 0.058309315 | H30: =H6/H$20 -> 0.06767277 | I30: =I6/I$20 -> 0.070776891 | ... S30: =S6/S$20 -> 0.018699053
A31: Land, buildings, and lease improvement | B31: =B28+B29+B30 -> 0.3184452 | C31: =C28+C29+C30 -> 0.32451591 | D31: =D28+D29+D30 -> 0.42409515 | E31: =E28+E29+E30 -> 0.36736423 | F31: =F28+F29+F30 -> 0.36352729 | G31: =G28+G29+G30 -> 0.32119216 | H31: =H28+H29+H30 -> 0.33564563 | I31: =I28+I29+I30 -> 0.37684886 | ... S31: =S28+S29+S30 -> 0.17878149
A33: Network equipment | B33: =B9/B$20 -> 0.56760019 | C33: =C9/C$20 -> 0.52213001 | D33: =D9/D$20 -> 0.46463742 | E33: =E9/E$20 -> 0.43878675 | F33: =F9/F$20 -> 0.43616731 | G33: =G9/G$20 -> 0.41228265 | H33: =H9/H$20 -> 0.36976471 | I33: =I9/I$20 -> 0.3604036 | ... S33: =S9/S$20 -> 0
A34: Servers and network assets | B34: =B10/B$20 -> 0 | C34: =C10/C$20 -> 0 | D34: =D10/D$20 -> 0 | E34: =E10/E$20 -> 0 | F34: =F10/F$20 -> 0 | G34: =G10/G$20 -> 0 | H34: =H10/H$20 -> 0 | I34: =I10/I$20 -> 0 | ... S34: =S10/S$20 -> 0
A35: Computer software, office equipment and other | B35: =B11/B$20 -> 0.02293578 | C35: =C11/C$20 -> 0.025760719 | D35: =D11/D$20 -> 0.031717611 | E35: =E11/E$20 -> 0.033720241 | F35: =F11/F$20 -> 0.037138027 | G35: =G11/G$20 -> 0.037595414 | H35: =H11/H$20 -> 0.039425042 | I35: =I11/I$20 -> 0.040261421 | ... S35: =S11/S$20 -> 0
A36: Equipment and other | B36: =B12/B$20 -> 0 | C36: =C12/C$20 -> 0 | D36: =D12/D$20 -> 0 | E36: =E12/E$20 -> 0 | F36: =F12/F$20 -> 0 | G36: =G12/G$20 -> 0 | H36: =H12/H$20 -> 0 | I36: =I12/I$20 -> 0 | ... S36: =S12/S$20 -> 0
A37: Sub-total Servers and Network Assets | B37: =B13/B20 -> 0.59053597 | C37: =C13/C20 -> 0.54789073 | D37: =D13/D20 -> 0.49635503 | E37: =E13/E20 -> 0.47250699 | F37: =F13/F20 -> 0.47330534 | G37: =G13/G20 -> 0.44987806 | H37: =H13/H20 -> 0.40918975 | I37: =I13/I20 -> 0.40066502 | ... S37: =S13/S20 -> 0.73896285
A39: Finance lease right of use assets | B39: =B16/B$20 -> 0 | C39: =C16/C$20 -> 0 | D39: =D16/D$20 -> 0 | E39: =E16/E$20 -> 0 | F39: =F16/F$20 -> 0 | G39: =G16/G$20 -> 0 | H39: =H16/H$20 -> 0.035554299 | I39: =I16/I$20 -> 0.037591522 | ... S39: =S16/S$20 -> 0.032487257
A40: Construction in progress | B40: =B18/B$20 -> 0.091018831 | C40: =C18/C$20 -> 0.12759336 | D40: =D18/D$20 -> 0.079549815 | E40: =E18/E$20 -> 0.16012878 | F40: =F18/F$20 -> 0.16316737 | G40: =G18/G$20 -> 0.22892978 | H40: =H18/H$20 -> 0.21961032 | I40: =I18/I$20 -> 0.1848946 | ... S40: =S18/S$20 -> 0.049768399
A41: Property and equipment, gross | B41: =B20/B$20 -> 1 | C41: =C20/C$20 -> 1 | D41: =D20/D$20 -> 1 | E41: =E20/E$20 -> 1 | F41: =F20/F$20 -> 1 | G41: =G20/G$20 -> 1 | H41: =H20/H$20 -> 1 | I41: =I20/I$20 -> 1 | ... S41: =S20/S$20 -> 1
A43: Depreciable Gross PP&E | B43: =B20-B2-B18 -> 3720 | C43: =C20-C2-C18 -> 4893 | D43: =D20-D2-D18 -> 6601 | E43: =E20-E2-E18 -> 9217 | F43: =F20-F2-F18 -> 14547 | G43: =G20-G2-G18 -> 23446 | H43: =H20-H2-H18 -> 34790 | I43: =I20-I2-I18 -> 48437 | ... S43: =S20-S2-S18 -> 669518
A45: Depreciation expense | B45: 857 | C45: 923 | D45: 1220 | E45: 1590 | F45: 2330 | G45: =Model!D70 -> 3680 | H45: =Model!E70 -> 5180 | I45: =Model!F70 -> 6390 | J45: =Model!G70 -> 7560 | K45: =Model!H70 -> 8500 | L45: =Model!I70 -> 11020 | M45: =Model!J70 -> 15290 | N45: =Model!K70 -> 18000 | O45: =O46*AVERAGE(N43:O43) -> 28228.845 | P45: =P46*AVERAGE(O43:P43) -> 42344.021 | Q45: =Q46*AVERAGE(P43:Q43) -> 56205.679 | R45: =R46*AVERAGE(Q43:R43) -> 71007.336 | S45: =S46*AVERAGE(R43:S43) -> 83636.404
A46: As % of avg gross PP&E ex land and construction in progress | C46: =C45/AVERAGE(B43:C43) -> 0.21432718 | D46: =D45/AVERAGE(C43:D43) -> 0.21228467 | E46: =E45/AVERAGE(D43:E43) -> 0.20103679 | F46: =F45/AVERAGE(E43:F43) -> 0.19609493 | G46: =G45/AVERAGE(F43:G43) -> 0.1937199 | H46: =H45/AVERAGE(G43:H43) -> 0.17789683 | I46: =I45/AVERAGE(H43:I43) -> 0.15355594 | J46: =J45/AVERAGE(I43:J43) -> 0.1375158 | ... N46: =N45/AVERAGE(M43:N43) -> 0.11435178 | O46: =N46+0.5% -> 0.11935178 | P46: =O46+0.5% -> 0.12435178 | Q46: =P46+0.5% -> 0.12935178 | R46: =Q46+0.5% -> 0.13435178 | S46: =R46 -> 0.13435178

Sheet Valuation
A1: Items | C1: 2021 | D1: 2022 | E1: 2023 | F1: 2024 | G1: 2025 | H1: 2026 | I1: 2027 | J1: 2028 | K1: 2029 | L1: 2030 | M1: Terminal P/E
A2: FCF
A3: OCF | C3: =Model!G167 -> 57683 | D3: =Model!H167 -> 50475 | E3: =Model!I167 -> 71113 | F3: =Model!J167 -> 91328 | G3: =Model!K167 -> 115800 | H3: =Model!L167 -> 136942.73 | I3: =Model!M167 -> 160888.02 | J3: =Model!N167 -> 201594.13 | ... L3: =Model!P167 -> 291568.87
A4: Capex | C4: =Model!G170 -> -18567 | D4: =Model!H170 -> -31431 | E4: =Model!I170 -> -27266 | F4: =Model!J170 -> -37256 | G4: =Model!K170 -> -69691 | H4: =Model!L170 -> -125000 | I4: =Model!M170 -> -90000 | J4: =Model!N170 -> -90000 | ... L4: =Model!P170 -> -85000 | O4: Terminal Multiple
A5: FCF | C5: =C3+C4 -> 39116 | D5: =D3+D4 -> 19044 | E5: =E3+E4 -> 43847 | F5: =F3+F4 -> 54072 | G5: =G3+G4 -> 46109 | H5: =H3+H4 -> 11942.728 | I5: =I3+I4 -> 70888.02 | J5: =J3+J4 -> 111594.13 | K5: =K3+K4 -> 153480.26 | L5: =L3+L4-Model!P152 -> 157919.81 | O5: 10
A6: FCF/share | C6: =C5/C14 -> 13.681707 | D6: =D5/D14 -> 7.0481125 | E6: =E5/E14 -> 16.678205 | F6: =F5/F14 -> 20.685539 | G6: =G5/G14 -> 17.913364 | H6: =H5/H14 -> 4.5782308 | I6: =I5/I14 -> 27.473373 | J6: =J5/J14 -> 44.0485 | ... L6: =L5/L14 -> 66.932689 | O6: =O5+0.5 -> 10.5
A7: Terminal FCF multiple | L7: 16.5 | M7: =L8/Model!P136 -> 16.40605 | O7: =O6+0.5 -> 11
A8: Terminal Stock price | L8: =L7*L6 -> 1104.3894 | O8: =O7+0.5 -> 11.5
A9: Current price* | B9: 695 | O9: =O8+0.5 -> 12
A10: Dividend/share | E10: 0 | H10: =-Model!L182/Valuation!H14 -> 2.7897457 | I10: =-Model!M182/Valuation!I14 -> 3.3106732 | J10: =-Model!N182/Valuation!J14 -> 4.1434088 | K10: =-Model!O182/Valuation!K14 -> 5.1574691 | L10: =-Model!P182/Valuation!L14 -> 6.7315981 | O10: =O9+0.5 -> 12.5
A11: Cash flow | G11: =-B9 -> -695 | H11: =H10+H8 -> 2.7897457 | I11: =I10+I8 -> 3.3106732 | J11: =J10+J8 -> 4.1434088 | K11: =K10+K8 -> 5.1574691 | L11: =L10+L8 -> 1111.121 | O11: =O10+0.5 -> 13
O12: =O11+0.5 -> 13.5
A13: IRR | B13: =IRR(G11:L11) -> 0.10216992 | O13: =O12+0.5 -> 14
A14: #diluted shares outstanding | C14: =Model!G252 -> 2859 | D14: =Model!H252 -> 2702 | E14: =Model!I252 -> 2629 | F14: =Model!J252 -> 2614 | G14: =Model!K252 -> 2574 | H14: =Model!L252 -> 2608.5903 | I14: =Model!M252 -> 2580.2445 | J14: =Model!N252 -> 2533.4377 | ... L14: =Model!P252 -> 2359.3825 | O14: =O13+0.5 -> 14.5
O15: =O14+0.5 -> 15
A16: *prices as of February 02, 2026 | O16: =O15+0.5 -> 15.5
O17: =O16+0.5 -> 16
A18: Stock price | F18: =B9 -> 695 | G18: =B9 -> 695 | H18: =G18*(1.1)^(11/12) -> 758.452 | I18: =H18*1.1 -> 834.2972 | J18: =I18*1.1 -> 917.72692 | K18: =J18*1.1 -> 1009.4996 | L18: =K18*1.1 -> 1110.4496 | O18: =O17+0.5 -> 16.5
O19: =O18+0.5 -> 17
O20: =O19+1 -> 18
O21: =O20+1 -> 19
O22: =O21+1 -> 20
O23: =O22+1 -> 21
O24: =O23+1 -> 22
O25: =O24+1 -> 23
O26: =O25+1 -> 24
O27: =O26+1 -> 25
O28: =O27+1 -> 26
O29: =O28+1 -> 27
O30: =O29+1 -> 28
O31: =O30+1 -> 29
... O40: =O39+1 -> 38

Sheet FOA
A1: FOA | B1: =Model!C1 -> 2017 | C1: =Model!D1 -> 2018 | D1: =Model!E1 -> 2019 | E1: =Model!F1 -> 2020 | F1: =Model!G1 -> 2021 | G1: =Model!H1 -> 2022 | H1: =Model!I1 -> 2023 | I1: =Model!J1 -> 2024 | ... O1: =Model!P1 -> 2030
A2: Revenue | B2: =Model!C45 -> 40528 | C2: =Model!D45 -> 55588 | D2: =Model!E45 -> 70196 | E2: =Model!F45 -> 84826 | F2: =Model!G45 -> 115655 | G2: =Model!H45 -> 114449 | H2: =Model!I45 -> 133006 | I2: =Model!J45 -> 162354 | ... O2: =Model!P45 -> 457921.49
A3: Growth $ | C3: =C2-B2 -> 15060 | D3: =D2-C2 -> 14608 | E3: =E2-D2 -> 14630 | F3: =F2-E2 -> 30829 | G3: =G2-F2 -> -1206 | H3: =H2-G2 -> 18557 | I3: =I2-H2 -> 29348 | J3: =J2-I2 -> 36404 | ... O3: =O2-N2 -> 57915.275
A4: Growth % | C4: =C2/B2-1 -> 0.37159495 | D4: =D2/C2-1 -> 0.26279053 | E4: =E2/D2-1 -> 0.20841643 | F4: =F2/E2-1 -> 0.3634381 | G4: =G2/F2-1 -> -0.010427565 | H4: =H2/G2-1 -> 0.16214209 | I4: =I2/H2-1 -> 0.2206517 | J4: =J2/I2-1 -> 0.22422607 | ... O4: =O2/N2-1 -> 0.14478594
A6: Cost of Revenue | B6: =Model!C63 -> 5268.64 | C6: =Model!D63 -> 8894.08 | D6: =Model!E63 -> 12119.85 | E6: =Model!F63 -> 15339.9 | F6: =Model!G63 -> 19945.4 | G6: =Model!H63 -> 21680.25 | H6: =Model!I63 -> 24274.75 | I6: =Model!J63 -> 28221 | ... O6: =Model!P63 -> 116438.25
A7: As % of revenue | B7: =B6/B2 -> 0.13 | C7: =C6/C2 -> 0.16 | D7: =D6/D2 -> 0.17265727 | E7: =E6/E2 -> 0.1808396 | F7: =F6/F2 -> 0.17245601 | G7: =G6/G2 -> 0.18943154 | H7: =H6/H2 -> 0.18250868 | I7: =I6/I2 -> 0.17382387 | ... O7: =O6/O2 -> 0.25427558
A8: Gross Profit | B8: =B2-B6 -> 35259.36 | C8: =C2-C6 -> 46693.92 | D8: =D2-D6 -> 58076.15 | E8: =E2-E6 -> 69486.1 | F8: =F2-F6 -> 95709.6 | G8: =G2-G6 -> 92768.75 | H8: =H2-H6 -> 108731.25 | I8: =I2-I6 -> 134133 | ... O8: =O2-O6 -> 341483.24
A9: Gross Margin | B9: =B8/B2 -> 0.87 | C9: =C8/C2 -> 0.84 | D9: =D8/D2 -> 0.82734273 | E9: =E8/E2 -> 0.8191604 | F9: =F8/F2 -> 0.82754399 | G9: =G8/G2 -> 0.81056846 | H9: =H8/H2 -> 0.81749132 | I9: =I8/I2 -> 0.82617613 | ... O9: =O8/O2 -> 0.74572442
A11: Operating expenses (estimated)*
A13: R&D | B13: =Model!C81 -> 7295.04 | C13: =Model!D81 -> 9449.96 | D13: =Model!E81 -> 10600 | E13: =Model!F81 -> 13437 | F13: =Model!G81 -> 17685 | G13: =Model!H81 -> 23434 | H13: =Model!I81 -> 23936 | I13: =Model!J81 -> 28849 | ... O13: =Model!P81 -> 100742.73
A14: As % of revenue | B14: =B13/B2 -> 0.18 | C14: =C13/C2 -> 0.17 | D14: =D13/D2 -> 0.15100576 | E14: =E13/E2 -> 0.15840662 | F14: =F13/F2 -> 0.15291168 | G14: =G13/G2 -> 0.20475496 | H14: =H13/H2 -> 0.17996181 | I14: =I13/I2 -> 0.17769196 | ... O14: =O13/O2 -> 0.22
A16: S&M | B16: =Model!C91 -> 4458.08 | C16: =Model!D91 -> 7226.44 | D16: =Model!E91 -> 9201 | E16: =Model!F91 -> 10891 | F16: =Model!G91 -> 12643 | G16: =Model!H91 -> 13074 | H16: =Model!I91 -> 9906 | I16: =Model!J91 -> 9293 | ... O16: =Model!P91 -> 16142.436
A17: =A14 -> As % of revenue | B17: =B16/B2 -> 0.11 | C17: =C16/C2 -> 0.13 | D17: =D16/D2 -> 0.13107584 | E17: =E16/E2 -> 0.12839224 | F17: =F16/F2 -> 0.1093165 | G17: =G16/G2 -> 0.11423429 | H17: =H16/H2 -> 0.074477843 | I17: =I16/I2 -> 0.057239119 | ... O17: =O16/O2 -> 0.035251537
A19: G&A | B19: =Model!C101 -> 2431.68 | C19: =Model!D101 -> 3335.28 | D19: =Model!E101-5000 -> 4790 | E19: =Model!F101 -> 5864 | F19: =Model!G101 -> 8429 | G19: =Model!H101 -> 9507 | H19: =Model!I101 -> 9773 | I19: =Model!J101 -> 8490 | J19: =Model!K101 -> 10652 | K19: =Model!L101 -> 12958.483 | L19: =Model!M101 -> 15052.406 | ... O19: =Model!P101 -> 22251.692
A20: =A17 -> As % of revenue | B20: =B19/B2 -> 0.06 | C20: =C19/C2 -> 0.06 | D20: =D19/D2 -> 0.068237506 | E20: =E19/E2 -> 0.069129748 | F20: =F19/F2 -> 0.07288055 | G20: =G19/G2 -> 0.083067567 | H20: =H19/H2 -> 0.073477888 | I20: =I19/I2 -> 0.052293137 | ... O20: =O19/O2 -> 0.048592811
A22: Total Costs | B22: =B13+B6+B16+B19 -> 19453.44 | C22: =C13+C6+C16+C19 -> 28905.76 | D22: =D13+D6+D16+D19 -> 36710.85 | E22: =E13+E6+E16+E19 -> 45531.9 | F22: =F13+F6+F16+F19 -> 58702.4 | G22: =G13+G6+G16+G19 -> 67695.25 | H22: =H13+H6+H16+H19 -> 67889.75 | I22: =I13+I6+I16+I19 -> 74853 | ... O22: =O13+O6+O16+O19 -> 255575.11
A23: As % of revenue | B23: =B22/B2 -> 0.48 | C23: =C22/C2 -> 0.52 | D23: =D22/D2 -> 0.52297638 | E23: =E22/E2 -> 0.53676821 | F23: =F22/F2 -> 0.50756474 | G23: =G22/G2 -> 0.59148835 | H23: =H22/H2 -> 0.51042622 | I23: =I22/I2 -> 0.46104808 | ... O23: =O22/O2 -> 0.55811993
A25: EBIT | B25: =B8-B13-B16-B19 -> 21074.56 | C25: =C8-C13-C16-C19 -> 26682.24 | D25: =D8-D13-D16-D19 -> 33485.15 | E25: =E8-E13-E16-E19 -> 39294.1 | F25: =F8-F13-F16-F19 -> 56952.6 | G25: =G8-G13-G16-G19 -> 46753.75 | H25: =H8-H13-H16-H19 -> 65116.25 | I25: =I8-I13-I16-I19 -> 87501 | ... O25: =O8-O13-O16-O19 -> 202346.38
A26: EBIT Margin | B26: =B25/B2 -> 0.52 | C26: =C25/C2 -> 0.48 | D26: =D25/D2 -> 0.47702362 | E26: =E25/E2 -> 0.46323179 | F26: =F25/F2 -> 0.49243526 | G26: =G25/G2 -> 0.40851165 | H26: =H25/H2 -> 0.48957378 | I26: =I25/I2 -> 0.53895192 | ... O26: =O25/O2 -> 0.44188007
A28: *adjusted for FTC penalty in 2019 and restructuring expenses in 2022

Sheet RL
B1: 2019 | C1: 2020 | D1: 2021 | E1: 2022 | F1: 2023 | G1: 2024 | H1: 2025 | I1: 2026 | J1: 2027 | K1: 2028 | L1: 2029 | M1: 2030
A3: VR+Horizon
A5: Hardware revenue | B5: =B6*B9 -> 500 | C5: =C6*C9 -> 1125 | D5: =D6*D9 -> 2250 | E5: =E6*E9 -> 1800 | F5: =F6*F9 -> 1400 | G5: =G6*G9 -> 1400 | H5: =H6*H9 -> 750 | I5: =I6*I9 -> 900 | ... M5: =M6*M9 -> 900
A6: Unit Sold | B6: 2.5 | C6: 4.5 | D6: 7.5 | E6: 4.5 | F6: 3.5 | G6: 4 | H6: 2.5 | I6: 3 | J6: 3 | K6: 3 | L6: 3 | M6: 3
A7: Install base | C7: =B6+C6 -> 7 | D7: =C6+D6 -> 12 | E7: =D6+E6 -> 12 | F7: =E6+F6 -> 8 | G7: =F6+G6 -> 7.5 | H7: =G6+H6 -> 6.5 | I7: =H6+I6 -> 5.5 | J7: =I6+J6 -> 6 | ... M7: =L6+M6 -> 6
A9: Price | B9: 200 | C9: 250 | D9: 300 | E9: 400 | F9: 400 | G9: 350 | H9: 300 | I9: 300 | J9: 300 | K9: 300 | L9: 300 | M9: 300
A11: Software revenue | B11: 1 | C11: 14 | D11: 24 | E11: 325 | F11: 400 | G11: 560 | H11: 710 | I11: =I12*AVERAGE(H7:I7) -> 818.57143 | J11: =J12*AVERAGE(I7:J7) -> 1014.4643 | K11: =K12*AVERAGE(J7:K7) -> 1118.5714 | L11: =L12*AVERAGE(K7:L7) -> 1178.5714 | M11: =M12*AVERAGE(L7:M7) -> 1238.5714
A12: Per installed base | D12: =D11/AVERAGE(C7:D7) -> 2.5263158 | E12: =E11/AVERAGE(D7:E7) -> 27.083333 | F12: =F11/AVERAGE(E7:F7) -> 40 | G12: =G11/AVERAGE(F7:G7) -> 72.258065 | H12: =H11/AVERAGE(G7:H7) -> 101.42857 | I12: =H12+I13 -> 136.42857 | J12: =I12+J13 -> 176.42857 | K12: =J12+K13 -> 186.42857 | L12: =K12+L13 -> 196.42857 | M12: =L12+M13 -> 206.42857
A13: Increase $ | E13: =E12-D12 -> 24.557018 | F13: =F12-E12 -> 12.916667 | G13: =G12-F12 -> 32.258065 | H13: =H12-G12 -> 29.170507 | I13: 35 | J13: 40 | K13: 10 | L13: 10 | M13: 10
A15: Advertising | H15: =H18*AVERAGE(G16:H16) -> 0 | I15: =I18*AVERAGE(H16:I16) -> 0.6875 | J15: =J18*AVERAGE(I16:J16) -> 4.375 | K15: =K18*AVERAGE(J16:K16) -> 11.25 | L15: =L18*AVERAGE(K16:L16) -> 27 | M15: =M18*AVERAGE(L16:M16) -> 45
A16: MAU | G16: =G17*G7 -> 0 | H16: =H17*H7 -> 0 | I16: =I17*I7 -> 0.275 | J16: =J17*J7 -> 0.6 | K16: =K17*K7 -> 0.9 | L16: =L17*L7 -> 1.8 | M16: =M17*M7 -> 1.8
A17: As % of install base | I17: =H17+5% -> 0.05 | J17: =I17+5% -> 0.1 | K17: =J17+5% -> 0.15 | L17: 0.3 | M17: 0.3
A18: ARPU | I18: =H18+5 -> 5 | J18: =I18+5 -> 10 | K18: =J18+5 -> 15 | L18: =K18+5 -> 20 | M18: =L18+5 -> 25
A20: Total VR revenue | B20: =B5+B11 -> 501 | C20: =C5+C11 -> 1139 | D20: =D5+D11 -> 2274 | E20: =E5+E11 -> 2125 | F20: =F5+F11 -> 1800 | G20: =G15+G11+G5 -> 1960 | H20: =H15+H11+H5 -> 1460 | I20: =I15+I11+I5 -> 1719.2589 | J20: =J15+J11+J5 -> 1918.8393 | K20: =K15+K11+K5 -> 2029.8214 | L20: =L15+L11+L5 -> 2105.5714 | M20: =M15+M11+M5 -> 2183.5714
A22: Cost of Revenue | B22: =B23+B25+B27 -> 650.15 | C22: =C23+C25+C27 -> 1352.1 | D22: =D23+D25+D27 -> 2703.6 | E22: =E23+E25+E27 -> 2028.75 | F22: =F23+F25+F27 -> 1600 | G22: =G23+G25+G27 -> 1624 | H22: =H23+H25+H27 -> 856.5 | I22: =I23+I25+I27 -> 1023.0607 | ... M22: =M23+M25+M27 -> 1094.7857
A23: Hardware | B23: =B24*B5 -> 650 | C23: =C24*C5 -> 1350 | D23: =D24*D5 -> 2700 | E23: =E24*E5 -> 1980 | F23: =F24*F5 -> 1540 | G23: =G24*G5 -> 1540 | H23: =H24*H5 -> 750 | I23: =I24*I5 -> 900 | ... M23: =M24*M5 -> 900
A24: As % of revenue | B24: 1.3 | C24: 1.2 | D24: 1.2 | E24: 1.1 | F24: 1.1 | G24: 1.1 | H24: 1 | I24: 1 | J24: 1 | K24: 1 | L24: 1 | M24: 1
A25: Software | B25: =B26*B11 -> 0.15 | C25: =C26*C11 -> 2.1 | D25: =D26*D11 -> 3.6 | E25: =E26*E11 -> 48.75 | F25: =F26*F11 -> 60 | G25: =G26*G11 -> 84 | H25: =H26*H11 -> 106.5 | I25: =I26*I11 -> 122.78571 | ... M25: =M26*M11 -> 185.78571
A26: =A24 -> As % of revenue | B26: 0.15 | C26: 0.15 | D26: 0.15 | E26: 0.15 | F26: 0.15 | G26: 0.15 | H26: 0.15 | I26: 0.15 | J26: 0.15 | K26: 0.15 | L26: 0.15 | M26: 0.15
A27: Advertising | H27: =H28*H15 -> 0 | I27: =I28*I15 -> 0.275 | J27: =J28*J15 -> 1.3125 | K27: =K28*K15 -> 2.8125 | L27: =L28*L15 -> 5.4 | M27: =M28*M15 -> 9
A28: As % of revenue | B28: 0 | C28: 0 | D28: 0 | E28: 0 | F28: 0 | G28: 0 | H28: 0.5 | I28: 0.4 | J28: 0.3 | K28: 0.25 | L28: 0.2 | M28: 0.2
A30: Gross Profit | B30: =B20-B22 -> -149.15 | C30: =C20-C22 -> -213.1 | D30: =D20-D22 -> -429.6 | E30: =E20-E22 -> 96.25 | F30: =F20-F22 -> 200 | G30: =G20-G22 -> 336 | H30: =H20-H22 -> 603.5 | I30: =I20-I22 -> 696.19821 | ... M30: =M20-M22 -> 1088.7857
A31: Gross Margin | B31: =B30/B20 -> -0.29770459 | C31: =C30/C20 -> -0.18709394 | D31: =D30/D20 -> -0.18891821 | E31: =E30/E20 -> 0.045294118 | F31: =F30/F20 -> 0.11111111 | G31: =G30/G20 -> 0.17142857 | H31: =H30/H20 -> 0.41335616 | I31: =I30/I20 -> 0.40494087 | ... M31: =M30/M20 -> 0.4986261
A34: AR
A36: =A5 -> Hardware revenue | E36: =E37*E40 -> 30 | F36: =F37*F40 -> 87.5 | G36: =G37*G40 -> 190 | H36: =H37*H40 -> 750 | I36: =I37*I40 -> 2000 | J36: =J37*J40 -> 4000 | K36: =K37*K40 -> 8000 | L36: =L37*L40 -> 10000 | M36: =M37*M40 -> 12000
A37: =A6 -> Unit Sold | E37: 0.2 | F37: 0.5 | G37: 1 | H37: 3 | I37: 5 | J37: =I37+5 -> 10 | K37: 20 | L37: 25 | M37: 30
A38: Install base | I38: =H37+I37 -> 8 | J38: =I37+J37 -> 15 | K38: =J37+K37 -> 30 | L38: =K37+L37 -> 45 | M38: =L37+M37 -> 55
A40: =A9 -> Price | E40: 150 | F40: 175 | G40: 190 | H40: 250 | I40: 400 | J40: 400 | K40: 400 | L40: 400 | M40: 400
A42: =A11 -> Software revenue | J42: =J43*AVERAGE(I38:J38) -> 115 | K42: =K43*AVERAGE(J38:K38) -> 562.5 | L42: =L43*AVERAGE(K38:L38) -> 1687.5 | M42: =M43*AVERAGE(L38:M38) -> 3750
A43: Per device | J43: =J44 -> 10 | K43: =J43+K44 -> 25 | L43: =K43+L44 -> 45 | M43: =L43+M44 -> 75
A44: Increase | J44: 10 | K44: 15 | L44: 20 | M44: 30
A46: =A15 -> Advertising | M46: =AVERAGE(L47:M47)*M49 -> 137.5
A47: MAU | M47: =M48*M38 -> 5.5
A48: As % of install base | M48: 0.1
A49: ARPU | M49: 25
A51: Total AR revenue | B51: =B36+B42+B46 -> 0 | C51: =C36+C42+C46 -> 0 | D51: =D36+D42+D46 -> 0 | E51: =E36+E42+E46 -> 30 | F51: =F36+F42+F46 -> 87.5 | G51: =G36+G42+G46 -> 190 | H51: =H36+H42+H46 -> 750 | I51: =I36+I42+I46 -> 2000 | ... M51: =M36+M42+M46 -> 15887.5
A53: Cost of Revenue | B53: =B54+B56+B58 -> 0 | C53: =C54+C56+C58 -> 0 | D53: =D54+D56+D58 -> 0 | E53: =E54+E56+E58 -> 45 | F53: =F54+F56+F58 -> 131.25 | G53: =G54+G56+G58 -> 285 | H53: =H54+H56+H58 -> 1125 | I53: =I54+I56+I58 -> 2400 | ... M53: =M54+M56+M58 -> 7790
A54: Hardware | E54: =E55*E36 -> 45 | F54: =F55*F36 -> 131.25 | G54: =G55*G36 -> 285 | H54: =H55*H36 -> 1125 | I54: =I55*I36 -> 2400 | J54: =J55*J36 -> 4000 | K54: =K55*K36 -> 7200 | L54: =L55*L36 -> 8000 | M54: =M55*M36 -> 7200
A55: As % of revenue | E55: 1.5 | F55: 1.5 | G55: 1.5 | H55: 1.5 | I55: 1.2 | J55: 1 | K55: 0.9 | L55: 0.8 | M55: 0.6
A56: Software | J56: =J57*J42 -> 17.25 | K56: =K57*K42 -> 84.375 | L56: =L57*L42 -> 253.125 | M56: =M57*M42 -> 562.5
A57: As % of revenue | J57: 0.15 | K57: 0.15 | L57: 0.15 | M57: 0.15
A58: Advertising | J58: =J59*J46 -> 0 | K58: =K59*K46 -> 0 | L58: =L59*L46 -> 0 | M58: =M59*M46 -> 27.5
A59: As % of revenue | J59: 0.5 | K59: 0.4 | L59: 0.3 | M59: 0.2
A61: AR Gross Profit | B61: =B51-B53 -> 0 | C61: =C51-C53 -> 0 | D61: =D51-D53 -> 0 | E61: =E51-E53 -> -15 | F61: =F51-F53 -> -43.75 | G61: =G51-G53 -> -95 | H61: =H51-H53 -> -375 | I61: =I51-I53 -> -400 | ... M61: =M51-M53 -> 8097.5
A62: Gross Margin | E62: =E61/E51 -> -0.5 | F62: =F61/F51 -> -0.5 | G62: =G61/G51 -> -0.5 | H62: =H61/H51 -> -0.5 | I62: =I61/I51 -> -0.2 | J62: =J61/J51 -> 0.023754557 | K62: =K61/K51 -> 0.14927007 | L62: =L61/L51 -> 0.29385027 | M62: =M61/M51 -> 0.50967742
A64: Overall
A65: Revenue (reported) | B65: =Model!E57 -> 501 | C65: =Model!F57 -> 1139 | D65: =Model!G57 -> 2274 | E65: =Model!H57 -> 2159 | F65: =Model!I57 -> 1896 | G65: =Model!J57 -> 2146 | H65: =Model!K57 -> 2207
A66: Revenue (calculated) | B66: =B51+B20 -> 501 | C66: =C51+C20 -> 1139 | D66: =D51+D20 -> 2274 | E66: =E51+E20 -> 2155 | F66: =F51+F20 -> 1887.5 | G66: =G51+G20 -> 2150 | H66: =H51+H20 -> 2210 | I66: =I51+I20 -> 3719.2589 | ... M66: =M51+M20 -> 18071.071
A67: Cost of revenue | B67: =B22+B53 -> 650.15 | C67: =C22+C53 -> 1352.1 | D67: =D22+D53 -> 2703.6 | E67: =E22+E53 -> 2073.75 | F67: =F22+F53 -> 1731.25 | G67: =G22+G53 -> 1909 | H67: =H22+H53 -> 1981.5 | I67: =I22+I53 -> 3423.0607 | ... M67: =M22+M53 -> 8884.7857
A68: Gross Profit | B68: =B66-B67 -> -149.15 | C68: =C66-C67 -> -213.1 | D68: =D66-D67 -> -429.6 | E68: =E66-E67 -> 81.25 | F68: =F66-F67 -> 156.25 | G68: =G66-G67 -> 241 | H68: =H66-H67 -> 228.5 | I68: =I66-I67 -> 296.19821 | ... M68: =M66-M67 -> 9186.2857
A69: Gross Margin | B69: =B68/B66 -> -0.29770459 | C69: =C68/C66 -> -0.18709394 | D69: =D68/D66 -> -0.18891821 | E69: =E68/E66 -> 0.037703016 | F69: =F68/F66 -> 0.082781457 | G69: =G68/G66 -> 0.11209302 | H69: =H68/H66 -> 0.10339367 | I69: =I68/I66 -> 0.079639041 | ... M69: =M68/M66 -> 0.50834206
A71: R&D | B71: 3000 | C71: 5010 | D71: 6970 | E71: 10185 | F71: 12975 | G71: 14770 | H71: 15420 | I71: =H71+I72 -> 15420 | J71: =I71+J72 -> 13920 | K71: =J71+K72 -> 12420 | L71: =K71+L72 -> 10920 | M71: 7000
A72: Increase $ | C72: =C71-B71 -> 2010 | D72: =D71-C71 -> 1960 | E72: =E71-D71 -> 3215 | F72: =F71-E71 -> 2790 | G72: =G71-F71 -> 1795 | H72: =H71-G71 -> 650 | J72: -1500 | K72: -1500 | L72: -1500
A73: As % of revenue | B73: =B71/B66 -> 5.988024 | C73: =C71/C66 -> 4.3985953 | D73: =D71/D66 -> 3.0650836 | E73: =E71/E66 -> 4.7262181 | F73: =F71/F66 -> 6.8741722 | G73: =G71/G66 -> 6.8697674 | H73: =H71/H66 -> 6.9773756 | I73: =I71/I66 -> 4.1459872 | ... M73: =M71/M66 -> 0.38735943
A75: S&M | B75: 675 | C75: 700 | D75: 1400 | E75: 1550 | F75: 2000 | G75: =F75+G76 -> 2000 | H75: =G75+H76 -> 2500 | I75: =H75+I76 -> 2500 | J75: =I75+J76 -> 2500 | K75: =J75+K76 -> 2500 | L75: =K75+L76 -> 2500 | M75: 1000
A76: Increase $ | C76: =C75-B75 -> 25 | D76: =D75-C75 -> 700 | E76: =E75-D75 -> 150 | F76: =F75-E75 -> 450 | G76: 0 | H76: 500
A77: =A73 -> As % of revenue | B77: =B75/B66 -> 1.3473054 | C77: =C75/C66 -> 0.61457419 | D77: =D75/D66 -> 0.61565523 | E77: =E75/E66 -> 0.71925754 | F77: =F75/F66 -> 1.0596026 | G77: =G75/G66 -> 0.93023256 | H77: =H75/H66 -> 1.1312217 | I77: =I75/I66 -> 0.67217692 | ... M77: =M75/M66 -> 0.055337062
A79: G&A | B79: 675 | C79: 700 | D79: 1400 | E79: 1550 | F79: 1300 | G79: 1200 | H79: =G79+H80 -> 1500 | I79: =H79+I80 -> 1500 | J79: =I79+J80 -> 1500 | K79: =J79+K80 -> 1500 | L79: =K79+L80 -> 1500 | M79: 1000
A80: Increase $ | C80: =C79-B79 -> 25 | D80: =D79-C79 -> 700 | E80: =E79-D79 -> 150 | F80: =F79-E79 -> -250 | G80: 0 | H80: 300
A81: =A77 -> As % of revenue | B81: =B79/B66 -> 1.3473054 | C81: =C79/C66 -> 0.61457419 | D81: =D79/D66 -> 0.61565523 | E81: =E79/E66 -> 0.71925754 | F81: =F79/F66 -> 0.68874172 | G81: =G79/G66 -> 0.55813953 | H81: =H79/H66 -> 0.67873303 | I81: =I79/I66 -> 0.40330615 | ... M81: =M79/M66 -> 0.055337062
A83: Restructuring | E83: 515
A84: EBIT (calculated) | B84: =B68-B71-B75-B79-B83 -> -4499.15 | C84: =C68-C71-C75-C79-C83 -> -6623.1 | D84: =D68-D71-D75-D79-D83 -> -10199.6 | E84: =E68-E71-E75-E79-E83 -> -13718.75 | F84: =F68-F71-F75-F79-F83 -> -16118.75 | G84: =G68-G71-G75-G79-G83 -> -17729 | H84: =H68-H71-H75-H79-H83 -> -19191.5 | I84: =I68-I71-I75-I79-I83 -> -19123.802 | ... M84: =M68-M71-M75-M79-M83 -> 186.28571
A85: Margin | B85: =B84/B66 -> -8.9803393 | C85: =C84/C66 -> -5.8148376 | D85: =D84/D66 -> -4.4853122 | E85: =E84/E66 -> -6.3660093 | F85: =F84/F66 -> -8.5397351 | G85: =G84/G66 -> -8.2460465 | H85: =H84/H66 -> -8.6839367 | I85: =I84/I66 -> -5.1418312 | ... M85: =M84/M66 -> 0.010308504
A86: Reported EBIT | B86: =Model!E118 -> -4503 | C86: =Model!F118 -> -6623 | D86: =Model!G118 -> -10193 | E86: =Model!H118 -> -13717 | F86: =Model!I118 -> -16119 | G86: =Model!J118 -> -17729 | H86: =Model!K118 -> -19193
C88: =-C84+B84 -> 2123.95 | D88: =-D84+C84 -> 3576.5 | E88: =-E84+D84 -> 3519.15 | F88: =-F84+E84 -> 2400 | G88: =-G84+F84 -> 1610.25 | H88: =-H84+G84 -> 1462.5 | I88: =-I84+H84 -> -67.698214 | J88: =-J84+I84 -> -2166.9089 | ... M88: =-M84+L84 -> -10648.525
A90: Opex | B90: =B71+B75+B79 -> 4350 | C90: =C71+C75+C79 -> 6410 | D90: =D71+D75+D79 -> 9770 | E90: =E71+E75+E79 -> 13285 | F90: =F71+F75+F79 -> 16275 | G90: =G71+G75+G79 -> 17970 | H90: =H71+H75+H79 -> 19420 | I90: =I71+I75+I79 -> 19420 | ... M90: =M71+M75+M79 -> 9000

Sheet Quarterly Data
B1: 1Q'19 | C1: 2Q'19 | D1: 3Q'19 | E1: 4Q'19 | F1: 1Q'20 | G1: 2Q'20 | H1: 3Q'20 | I1: 4Q'20 | J1: 1Q'21 | K1: 2Q'21 | L1: 3Q'21 | M1: 4Q'21 | N1: 1Q'22 | O1: 2Q'22 | P1: 3Q'22 | Q1: 4Q'22 | R1: 1Q'23 | S1: 2Q'23 | T1: 3Q'23 | U1: 4Q'23 | V1: 1Q'24 | W1: 2Q'24 | X1: 3Q'24 | Y1: 4Q'24
A2: Facebook (includes Messenger)
A4: DAU | B4: =B21+B22+B23+B24 -> 1558 | C4: =C21+C22+C23+C24 -> 1587 | D4: =D21+D22+D23+D24 -> 1621 | E4: =E21+E22+E23+E24 -> 1651 | F4: =F21+F22+F23+F24 -> 1723 | G4: =G21+G22+G23+G24 -> 1785 | H4: =H21+H22+H23+H24 -> 1821 | I4: =I21+I22+I23+I24 -> 1845 | ... Q4: =Q21+Q22+Q23+Q24 -> 2000 | R4: 2037 | S4: 2064 | T4: 2085 | U4: 2110 | AC4: GOOG | AD4: 0.0297
A5: Growth QoQ | C5: =C4-B4 -> 29 | D5: =D4-C4 -> 34 | E5: =E4-D4 -> 30 | F5: =F4-E4 -> 72 | G5: =G4-F4 -> 62 | H5: =H4-G4 -> 36 | I5: =I4-H4 -> 24 | J5: =J4-I4 -> 32 | ... U5: =U4-T4 -> 25
A6: DAU/MAU | B6: =B4/B7 -> 0.65572391 | C6: =C4/C7 -> 0.65741508 | D6: =D4/D7 -> 0.66190282 | E6: =E4/E7 -> 0.66119343 | F6: =F4/F7 -> 0.66192854 | G6: =G4/G7 -> 0.66111111 | H6: =H4/H7 -> 0.66459854 | I6: =I4/I7 -> 0.65963532 | ... U6: =U4/U7 -> 0.68841762
A7: MAU | B7: =B27+B28+B29+B30 -> 2376 | C7: =C27+C28+C29+C30 -> 2414 | D7: =D27+D28+D29+D30 -> 2449 | E7: =E27+E28+E29+E30 -> 2497 | F7: =F27+F28+F29+F30 -> 2603 | G7: =G27+G28+G29+G30 -> 2700 | H7: =H27+H28+H29+H30 -> 2740 | I7: =I27+I28+I29+I30 -> 2797 | ... Q7: =Q27+Q28+Q29+Q30 -> 2964 | R7: 2989 | S7: 3030 | T7: 3049 | U7: 3065
A8: Growth QoQ | C8: =C7-B7 -> 38 | D8: =D7-C7 -> 35 | E8: =E7-D7 -> 48 | F8: =F7-E7 -> 106 | G8: =G7-F7 -> 97 | H8: =H7-G7 -> 40 | I8: =I7-H7 -> 57 | J8: =J7-I7 -> 55 | ... U8: =U7-T7 -> 16
A10: Family of Apps
A12: DAP | B12: 2100 | C12: 2140 | D12: 2200 | E12: 2260 | F12: 2360 | G12: 2470 | H12: 2540 | I12: 2600 | J12: 2720 | K12: 2760 | L12: 2810 | M12: 2820 | N12: 2870 | O12: 2880 | P12: 2930 | Q12: 2960 | R12: 3002 | S12: 3007 | T12: 3140 | U12: 3190 | V12: 3240 | W12: 3270 | X12: 3290 | Y12: 3350
A13: Growth QoQ | C13: =C12-B12 -> 40 | D13: =D12-C12 -> 60 | E13: =E12-D12 -> 60 | F13: =F12-E12 -> 100 | G13: =G12-F12 -> 110 | H13: =H12-G12 -> 70 | I13: =I12-H12 -> 60 | J13: =J12-I12 -> 120 | ... Y13: =Y12-X12 -> 60
A14: DAP/DAU | B14: =B12/B4 -> 1.3478819 | C14: =C12/C4 -> 1.3484562 | D14: =D12/D4 -> 1.3571869 | E14: =E12/E4 -> 1.3688674 | F14: =F12/F4 -> 1.369704 | G14: =G12/G4 -> 1.3837535 | H14: =H12/H4 -> 1.394838 | I14: =I12/I4 -> 1.4092141 | ... U14: =U12/U4 -> 1.5118483
A15: DAP/MAP | B15: =B12/B16 -> 0.78066914 | C15: =C12/C16 -> 0.77536232 | D15: =D12/D16 -> 0.78014184 | E15: =E12/E16 -> 0.78200692 | F15: =F12/F16 -> 0.78929766 | G15: =G12/G16 -> 0.7866242 | H15: =H12/H16 -> 0.79127726 | I15: =I12/I16 -> 0.78787879 | ... U15: =U12/U16 -> 0.80150754
A16: MAP | B16: 2690 | C16: 2760 | D16: 2820 | E16: 2890 | F16: 2990 | G16: 3140 | H16: 3210 | I16: 3300 | J16: 3450 | K16: 3510 | L16: 3580 | M16: 3590 | N16: 3640 | O16: 3650 | P16: 3710 | Q16: 3740 | R16: 3810 | S16: 3880 | T16: 3960 | U16: 3980
A17: Implied IG+WhatsApp only DAU | B17: =B12-B4 -> 542 | C17: =C12-C4 -> 553 | D17: =D12-D4 -> 579 | E17: =E12-E4 -> 609 | F17: =F12-F4 -> 637 | G17: =G12-G4 -> 685 | H17: =H12-H4 -> 719 | I17: =I12-I4 -> 755 | ... U17: =U12-U4 -> 1080
A18: Growth QoQ | C18: =C17-B17 -> 11 | D18: =D17-C17 -> 26 | E18: =E17-D17 -> 30 | F18: =F17-E17 -> 28 | G18: =G17-F17 -> 48 | H18: =H17-G17 -> 34 | I18: =I17-H17 -> 36 | J18: =J17-I17 -> 88 | ... U18: =U17-T17 -> 25
A20: DAU Mix
A21: US & Canada | B21: 186 | C21: 187 | D21: 189 | E21: 190 | F21: 195 | G21: 198 | H21: 196 | I21: 195 | J21: 195 | K21: 195 | L21: 196 | M21: 195 | N21: 196 | O21: 197 | P21: 197 | Q21: 199 | R21: 200 | S21: 202 | T21: 203 | U21: 205
A22: Europe | B22: 282 | C22: 286 | D22: 286 | E22: 288 | F22: 294 | G22: 305 | H22: 305 | I22: 308 | J22: 309 | K22: 307 | L22: 308 | M22: 309 | N22: 307 | O22: 303 | P22: 303 | Q22: 304 | R22: 307 | S22: 307 | T22: 307 | U22: 308
A23: Asia-Pacific | B23: 600 | C23: 615 | D23: 627 | E23: 641 | F23: 678 | G23: 699 | H23: 727 | I23: 744 | J23: 760 | K23: 788 | L23: 805 | M23: 806 | N23: 827 | O23: 836 | P23: 845 | Q23: 854 | R23: 873 | S23: 891 | T23: 899 | U23: 914
A24: Rest of the World | B24: 490 | C24: 499 | D24: 519 | E24: 532 | F24: 556 | G24: 583 | H24: 593 | I24: 598 | J24: 613 | K24: 618 | L24: 622 | M24: 619 | N24: 629 | O24: 631 | P24: 638 | Q24: 643 | R24: 657 | S24: 665 | T24: 676 | U24: 683
L25: =SUM(L21:L24) -> 1931 | M25: =SUM(M21:M24) -> 1929 | N25: =SUM(N21:N24) -> 1959 | O25: =SUM(O21:O24) -> 1967 | P25: =SUM(P21:P24) -> 1983 | Q25: =SUM(Q21:Q24) -> 2000 | R25: =SUM(R21:R24) -> 2037 | S25: =SUM(S21:S24) -> 2065 | ... U25: =SUM(U21:U24) -> 2110
A26: MAU Mix
A27: =A21 -> US & Canada | B27: 243 | C27: 244 | D27: 247 | E27: 248 | F27: 253 | G27: 256 | H27: 255 | I27: 258 | J27: 259 | K27: 259 | L27: 261 | M27: 262 | N27: 263 | O27: 264 | P27: 266 | Q27: 266 | R27: 269 | S27: 270 | T27: 271 | U27: 272
A28: =A22 -> Europe | B28: 384 | C28: 385 | D28: 387 | E28: 394 | F28: 406 | G28: 410 | H28: 413 | I28: 419 | J28: 423 | K28: 420 | L28: 423 | M28: 427 | N28: 418 | O28: 407 | P28: 408 | Q28: 407 | R28: 411 | S28: 409 | T28: 408 | U28: 408
A29: =A23 -> Asia-Pacific | B29: 981 | C29: 1003 | D29: 1013 | E29: 1038 | F29: 1093 | G29: 1142 | H29: 1166 | I29: 1199 | J29: 1230 | K29: 1265 | L29: 1278 | M29: 1278 | N29: 1297 | O29: 1305 | P29: 1312 | Q29: 1312 | R29: 1324 | S29: 1349 | T29: 1357 | U29: 1367
A30: =A24 -> Rest of the World | B30: 768 | C30: 782 | D30: 802 | E30: 817 | F30: 851 | G30: 892 | H30: 906 | I30: 921 | J30: 940 | K30: 951 | L30: 949 | M30: 945 | N30: 957 | O30: 959 | P30: 971 | Q30: 979 | R30: 986 | S30: 1002 | T30: 1013 | U30: 1018
B31: =SUM(B27:B30) -> 2376 | C31: =SUM(C27:C30) -> 2414 | D31: =SUM(D27:D30) -> 2449 | E31: =SUM(E27:E30) -> 2497 | F31: =SUM(F27:F30) -> 2603 | G31: =SUM(G27:G30) -> 2700 | H31: =SUM(H27:H30) -> 2740 | I31: =SUM(I27:I30) -> 2797 | ... U31: =SUM(U27:U30) -> 3065
A32: DAU/MAU
A33: =A27 -> US & Canada | B33: =B21/B27 -> 0.7654321 | C33: =C21/C27 -> 0.76639344 | D33: =D21/D27 -> 0.76518219 | E33: =E21/E27 -> 0.76612903 | F33: =F21/F27 -> 0.77075099 | G33: =G21/G27 -> 0.7734375 | H33: =H21/H27 -> 0.76862745 | I33: =I21/I27 -> 0.75581395 | ... U33: =U21/U27 -> 0.75367647
A34: =A28 -> Europe | B34: =B22/B28 -> 0.734375 | C34: =C22/C28 -> 0.74285714 | D34: =D22/D28 -> 0.73901809 | E34: =E22/E28 -> 0.73096447 | F34: =F22/F28 -> 0.72413793 | G34: =G22/G28 -> 0.74390244 | H34: =H22/H28 -> 0.73849879 | I34: =I22/I28 -> 0.73508353 | ... U34: =U22/U28 -> 0.75490196
A35: =A29 -> Asia-Pacific | B35: =B23/B29 -> 0.6116208 | C35: =C23/C29 -> 0.61316052 | D35: =D23/D29 -> 0.6189536 | E35: =E23/E29 -> 0.61753372 | F35: =F23/F29 -> 0.62031107 | G35: =G23/G29 -> 0.61208406 | H35: =H23/H29 -> 0.62349914 | I35: =I23/I29 -> 0.6205171 | ... U35: =U23/U29 -> 0.66861741
A36: =A30 -> Rest of the World | B36: =B24/B30 -> 0.63802083 | C36: =C24/C30 -> 0.63810742 | D36: =D24/D30 -> 0.64713217 | E36: =E24/E30 -> 0.65116279 | F36: =F24/F30 -> 0.653349 | G36: =G24/G30 -> 0.65358744 | H36: =H24/H30 -> 0.65452539 | I36: =I24/I30 -> 0.64929425 | ... U36: =U24/U30 -> 0.67092338
R37: =R25/R31 -> 0.6812709 | S37: =S25/S31 -> 0.68151815 | T37: =T25/T31 -> 0.68383076 | U37: =U25/U31 -> 0.68841762
A38: FOA
A39: Ad Revenue by Geography
A40: =A21 -> US & Canada | B40: 7203 | C40: 7952 | D40: 8317 | E40: 10021 | F40: 8379 | G40: 9059 | H40: 9988 | I40: 13150 | J40: 11897 | K40: 13366 | L40: 13094 | M40: 15062 | N40: 12024 | O40: 12788 | P40: 12766 | Q40: 15005 | R40: 12710 | S40: 14131 | T40: 14956 | U40: 17784 | V40: 15451 | W40: 16593 | X40: 17389 | Y40: 20982
A41: Europe | B41: 3609 | C41: 4043 | D41: 4057 | E41: 5071 | F41: 4171 | G41: 4411 | H41: 5051 | I41: 6822 | J41: 6373 | K41: 7205 | L41: 6821 | M41: 8174 | N41: 6364 | O41: 6360 | P41: 5707 | Q41: 6904 | R41: 6269 | S41: 7268 | T41: 7721 | U41: 9159 | V41: 8327 | W41: 9135 | X41: 9358 | Y41: 11154
A42: Asia Pacific | B42: 2670 | C42: 2985 | D42: 3243 | E42: 3642 | F42: 3236 | G42: 3312 | H42: 4202 | I42: 4703 | J42: 4735 | K42: 5152 | L42: 5398 | M42: 6183 | N42: 5661 | O42: 5835 | P42: 5717 | Q42: 5968 | R42: 5893 | S42: 6435 | T42: 6829 | U42: 7316 | V42: 7338 | W42: 7721 | X42: 8050 | Y42: 9012
A43: Rest of the World | B43: 1430 | C43: 1644 | D43: 1766 | E43: 2002 | F43: 1654 | G43: 1539 | H43: 1980 | I43: 2512 | J43: 2434 | K43: 2857 | L43: 2963 | M43: 3220 | N43: 2949 | O43: 3169 | P43: 3047 | Q43: 3377 | R43: 3229 | S43: 3664 | T43: 4137 | U43: 4447 | V43: 4519 | W43: 4880 | X43: 5088 | Y43: 5635
A44: Worldwide | B44: =SUM(B40:B43) -> 14912 | C44: =SUM(C40:C43) -> 16624 | D44: =SUM(D40:D43) -> 17383 | E44: =SUM(E40:E43) -> 20736 | F44: =SUM(F40:F43) -> 17440 | G44: =SUM(G40:G43) -> 18321 | H44: =SUM(H40:H43) -> 21221 | I44: =SUM(I40:I43) -> 27187 | ... Y44: =SUM(Y40:Y43) -> 46783
A45: Ad revenue Growth YoY
A46: =A40 -> US & Canada | F46: =F40/B40-1 -> 0.16326531 | G46: =G40/C40-1 -> 0.13921026 | H46: =H40/D40-1 -> 0.20091379 | I46: =I40/E40-1 -> 0.31224429 | J46: =J40/F40-1 -> 0.41985917 | K46: =K40/G40-1 -> 0.47543879 | L46: =L40/H40-1 -> 0.31097317 | M46: =M40/I40-1 -> 0.14539924 | ... Y46: =Y40/U40-1 -> 0.17982456
A47: =A41 -> Europe | F47: =F41/B41-1 -> 0.15572181 | G47: =G41/C41-1 -> 0.091021519 | H47: =H41/D41-1 -> 0.24500863 | I47: =I41/E41-1 -> 0.34529679 | J47: =J41/F41-1 -> 0.52793095 | K47: =K41/G41-1 -> 0.63341646 | L47: =L41/H41-1 -> 0.35042566 | M47: =M41/I41-1 -> 0.19818235 | ... Y47: =Y41/U41-1 -> 0.21781854
A48: =A42 -> Asia Pacific | F48: =F42/B42-1 -> 0.21198502 | G48: =G42/C42-1 -> 0.10954774 | H48: =H42/D42-1 -> 0.29571385 | I48: =I42/E42-1 -> 0.29132345 | J48: =J42/F42-1 -> 0.46322621 | K48: =K42/G42-1 -> 0.55555556 | L48: =L42/H42-1 -> 0.28462637 | M48: =M42/I42-1 -> 0.31469275 | ... Y48: =Y42/U42-1 -> 0.23182067
A49: =A43 -> Rest of the World | F49: =F43/B43-1 -> 0.15664336 | G49: =G43/C43-1 -> -0.063868613 | H49: =H43/D43-1 -> 0.1211778 | I49: =I43/E43-1 -> 0.25474525 | J49: =J43/F43-1 -> 0.47158404 | K49: =K43/G43-1 -> 0.85640026 | L49: =L43/H43-1 -> 0.49646465 | M49: =M43/I43-1 -> 0.28184713 | ... Y49: =Y43/U43-1 -> 0.26714639
A50: =A44 -> Worldwide | F50: =F44/B44-1 -> 0.1695279 | G50: =G44/C44-1 -> 0.10208133 | H50: =H44/D44-1 -> 0.22079043 | I50: =I44/E44-1 -> 0.31110147 | J50: =J44/F44-1 -> 0.45865826 | K50: =K44/G44-1 -> 0.55995852 | L50: =L44/H44-1 -> 0.3324537 | M50: =M44/I44-1 -> 0.20053702 | ... Y50: =Y44/U44-1 -> 0.20867566
A51: Ad impression Growth YoY
A52: =A46 -> US & Canada | R52: 0.22 | S52: 0.28 | T52: 0.26 | U52: 0.16 | V52: 0.16 | W52: 0.08 | X52: 0.07 | Y52: 0.06
A53: =A47 -> Europe | R53: 0.11 | S53: 0.26 | T53: 0.25 | U53: 0.17 | V53: 0.12 | W53: 0.06 | X53: 0.05 | Y53: 0.05
A54: =A48 -> Asia Pacific | R54: 0.34 | S54: 0.42 | T54: 0.39 | U54: 0.3 | V54: 0.28 | W54: 0.15 | X54: 0.09 | Y54: 0.1
A55: =A49 -> Rest of the World | R55: 0.28 | S55: 0.31 | T55: 0.27 | U55: 0.17 | V55: 0.17 | W55: 0.08 | X55: 0.05 | Y55: 0.03
A56: Worldwide | R56: 0.26 | S56: 0.34 | T56: 0.31 | U56: 0.21 | V56: 0.2 | W56: 0.1 | X56: 0.07 | Y56: 0.06
A57: Avg. Price per Ad YoY
A58: =A52 -> US & Canada | R58: -0.13 | S58: -0.14 | T58: -0.07 | U58: 0.02 | V58: 0.05 | W58: 0.09 | X58: 0.09 | Y58: 0.12
A59: =A53 -> Europe | R59: -0.11 | S59: -0.09 | T59: 0.08 | U59: 0.14 | V59: 0.18 | W59: 0.18 | X59: 0.16 | Y59: 0.16
A60: =A54 -> Asia Pacific | R60: -0.22 | S60: -0.22 | T60: -0.14 | U60: -0.06 | V60: -0.03 | W60: 0.04 | X60: 0.08 | Y60: 0.12
A61: =A55 -> Rest of the World | R61: -0.15 | S61: -0.12 | T61: 0.07 | U61: 0.13 | V61: 0.2 | W61: 0.24 | X61: 0.17 | Y61: 0.23
A62: =A56 -> Worldwide | R62: -0.17 | S62: -0.16 | T62: -0.06 | U62: 0.02 | V62: 0.06 | W62: 0.1 | X62: 0.11 | Y62: 0.14
A64: Advertising revenue mix
A65: =A40 -> US & Canada | B65: =B40/SUM(B$40:B$43) -> 0.4830338 | C65: =C40/SUM(C$40:C$43) -> 0.47834456 | D65: =D40/SUM(D$40:D$43) -> 0.47845596 | E65: =E40/SUM(E$40:E$43) -> 0.48326582 | F65: =F40/SUM(F$40:F$43) -> 0.48044725 | G65: =G40/SUM(G$40:G$43) -> 0.49445991 | H65: =H40/SUM(H$40:H$43) -> 0.47066585 | I65: =I40/SUM(I$40:I$43) -> 0.48368706 | ... Y65: =Y40/SUM(Y$40:Y$43) -> 0.44849625
A66: =A41 -> Europe | B66: =B41/SUM(B$40:B$43) -> 0.24201985 | C66: =C41/SUM(C$40:C$43) -> 0.2432026 | D66: =D41/SUM(D$40:D$43) -> 0.23338894 | E66: =E41/SUM(E$40:E$43) -> 0.24455054 | F66: =F41/SUM(F$40:F$43) -> 0.23916284 | G66: =G41/SUM(G$40:G$43) -> 0.24076197 | H66: =H41/SUM(H$40:H$43) -> 0.23801894 | I66: =I41/SUM(I$40:I$43) -> 0.25092875 | ... Y66: =Y41/SUM(Y$40:Y$43) -> 0.23841994
A67: =A42 -> Asia Pacific | B67: =B42/SUM(B$40:B$43) -> 0.17905043 | C67: =C42/SUM(C$40:C$43) -> 0.17955967 | D67: =D42/SUM(D$40:D$43) -> 0.18656158 | E67: =E42/SUM(E$40:E$43) -> 0.17563657 | F67: =F42/SUM(F$40:F$43) -> 0.18555046 | G67: =G42/SUM(G$40:G$43) -> 0.18077616 | H67: =H42/SUM(H$40:H$43) -> 0.1980114 | I67: =I42/SUM(I$40:I$43) -> 0.17298709 | ... Y67: =Y42/SUM(Y$40:Y$43) -> 0.19263408
A68: =A43 -> Rest of the World | B68: =B43/SUM(B$40:B$43) -> 0.095895923 | C68: =C43/SUM(C$40:C$43) -> 0.098893167 | D68: =D43/SUM(D$40:D$43) -> 0.10159351 | E68: =E43/SUM(E$40:E$43) -> 0.096547068 | F68: =F43/SUM(F$40:F$43) -> 0.09483945 | G68: =G43/SUM(G$40:G$43) -> 0.084001965 | H68: =H43/SUM(H$40:H$43) -> 0.093303803 | I68: =I43/SUM(I$40:I$43) -> 0.092397102 | ... Y68: =Y43/SUM(Y$40:Y$43) -> 0.12044974
F69: =F68+F67 -> 0.28038991 | G69: =G68+G67 -> 0.26477812 | H69: =H68+H67 -> 0.29131521 | I69: =I68+I67 -> 0.26538419 | J69: =J68+J67 -> 0.28181139 | K69: =K68+K67 -> 0.28023093 | L69: =L68+L67 -> 0.29569246 | M69: =M68+M67 -> 0.28809093 | ... Y69: =Y68+Y67 -> 0.31308381
A70: Annualized ARPU
A71: =A40 -> US & Canada | E71: =E40*4/AVERAGE(B27:E27) -> 163.27495 | F71: =F40*4/AVERAGE(C27:F27) -> 135.14516 | G71: =G40*4/AVERAGE(D27:G27) -> 144.36653 | H71: =H40*4/AVERAGE(E27:H27) -> 157.91304 | I71: =I40*4/AVERAGE(F27:I27) -> 205.87084 | J71: =J40*4/AVERAGE(G27:J27) -> 185.16732 | K71: =K40*4/AVERAGE(H27:K27) -> 207.4258 | L71: =L40*4/AVERAGE(I27:L27) -> 202.02893 | ... U71: =U40*4/AVERAGE(R27:U27) -> 262.97967
A72: =A41 -> Europe | E72: =E41*4/AVERAGE(B28:E28) -> 52.345806 | F72: =F41*4/AVERAGE(C28:F28) -> 42.452926 | G72: =G41*4/AVERAGE(D28:G28) -> 44.192862 | H72: =H41*4/AVERAGE(E28:H28) -> 49.794208 | I72: =I41*4/AVERAGE(F28:I28) -> 66.23301 | J72: =J41*4/AVERAGE(G28:J28) -> 61.242042 | K72: =K41*4/AVERAGE(H28:K28) -> 68.823881 | L72: =L41*4/AVERAGE(I28:L28) -> 64.769139 | ... U72: =U41*4/AVERAGE(R28:U28) -> 89.574572
A73: =A42 -> Asia Pacific | E73: =E42*4/AVERAGE(B29:E29) -> 14.441636 | F73: =F42*4/AVERAGE(C29:F29) -> 12.48517 | G73: =G42*4/AVERAGE(D29:G29) -> 12.363976 | H73: =H42*4/AVERAGE(E29:H29) -> 15.145754 | I73: =I42*4/AVERAGE(F29:I29) -> 16.358261 | J73: =J42*4/AVERAGE(G29:J29) -> 15.993245 | K73: =K42*4/AVERAGE(H29:K29) -> 16.961317 | L73: =L42*4/AVERAGE(I29:L29) -> 17.370877 | ... U73: =U42*4/AVERAGE(R29:U29) -> 21.689087
A74: =A43 -> Rest of the World | E74: =E43*4/AVERAGE(B30:E30) -> 10.10792 | F74: =F43*4/AVERAGE(C30:F30) -> 8.1377614 | G74: =G43*4/AVERAGE(D30:G30) -> 7.3242118 | H74: =H43*4/AVERAGE(E30:H30) -> 9.1402193 | I74: =I43*4/AVERAGE(F30:I30) -> 11.258263 | J74: =J43*4/AVERAGE(G30:J30) -> 10.643345 | K74: =K43*4/AVERAGE(H30:K30) -> 12.294782 | L74: =L43*4/AVERAGE(I30:L30) -> 12.605158 | ... U74: =U43*4/AVERAGE(R30:U30) -> 17.703906
A75: Overall ARPU
A77: Annualized ARPU growth YoY
A78: =A71 -> US & Canada | I78: =I71/E71-1 -> 0.26088443 | J78: =J71/F71-1 -> 0.37013648 | K78: =K71/G71-1 -> 0.43679975 | L78: =L71/H71-1 -> 0.27936822 | M78: =M71/I71-1 -> 0.12449378 | N78: =N71/J71-1 -> -0.0057666421 | O78: =O71/K71-1 -> -0.060556779 | P78: =P71/L71-1 -> -0.041683865 | ... V78: =V71/R71-1 -> -1
A79: =A72 -> Europe | I79: =I72/E72-1 -> 0.26529734 | J79: =J72/F72-1 -> 0.44258706 | K79: =K72/G72-1 -> 0.55735289 | L79: =L72/H72-1 -> 0.30073641 | M79: =M72/I72-1 -> 0.16633462 | N79: =N72/J72-1 -> -0.015018558 | O79: =O72/K72-1 -> -0.11727967 | P79: =P72/L72-1 -> -0.15071855 | ... V79: =V72/R72-1 -> -1
A80: =A73 -> Asia Pacific | I80: =I73/E73-1 -> 0.13271524 | J80: =J73/F73-1 -> 0.28097933 | K80: =K73/G73-1 -> 0.37183356 | L80: =L73/H73-1 -> 0.14691401 | M80: =M73/I73-1 -> 0.19730482 | N80: =N73/J73-1 -> 0.10656333 | O80: =O73/K73-1 -> 0.067136409 | P80: =P73/L73-1 -> 0.014219014 | ... V80: =V73/R73-1 -> -1
A81: =A74 -> Rest of the World | I81: =I74/E74-1 -> 0.11380608 | J81: =J74/F74-1 -> 0.30789595 | K81: =K74/G74-1 -> 0.67864919 | L81: =L74/H74-1 -> 0.37908707 | M81: =M74/I74-1 -> 0.20903415 | N81: =N74/J74-1 -> 0.16601596 | O81: =O74/K74-1 -> 0.082421496 | P81: =P74/L74-1 -> 0.0092961945 | ... V81: =V74/R74-1 -> -1
A84: Buyback+Dividend | B84: 1125 | C84: 1752 | D84: 1739 | E84: 1923 | F84: 1940 | G84: 2122 | H84: 2725 | I84: 3049 | J84: 5016 | K84: 8434 | L84: 15033 | M84: 21569 | N84: 10431 | O84: 5233 | P84: 6354 | Q84: 6863 | R84: =-[2]Daloopa!AS321 -> 9365 | S84: =-[2]Daloopa!AT321 -> 898 | T84: 3570 | U84: 5942 | V84: =15008+1273 -> 16281 | W84: =6299+1266 -> 7565 | X84: =8818+1263 -> 10081 | Y84: =1269 -> 1269
A85: FCF | B85: 5346 | C85: 4840 | D85: 5631 | E85: 4842 | F85: 7343 | G85: 514 | H85: 5950 | I85: 9222 | J85: 7819 | K85: 8511 | L85: 9547 | M85: 12562 | N85: 8528 | O85: 4450 | P85: 173 | Q85: 5288 | R85: 6911 | S85: 10955 | T85: 13639 | U85: 11505 | V85: 12531 | W85: 10898 | X85: 15522 | Y85: 13152
A86: Buyback+Div as % of FCF | B86: =B84/B85 -> 0.21043771 | C86: =C84/C85 -> 0.36198347 | D86: =D84/D85 -> 0.30882614 | E86: =E84/E85 -> 0.39714994 | F86: =F84/F85 -> 0.26419719 | G86: =G84/G85 -> 4.1284047 | H86: =H84/H85 -> 0.45798319 | I86: =I84/I85 -> 0.33062242 | ... Y86: =Y84/Y85 -> 0.096487226
A87: Net Cash | B87: 45243 | C87: 48596 | D87: 52269 | E87: 54578 | F87: 60289 | G87: 58240 | H87: 55620 | I87: 61954 | J87: 64219 | K87: 64080 | L87: 58075 | M87: 47998 | N87: 43890 | O87: 40489 | P87: =14308+27468-9922 -> 31854 | Q87: =14681+26057-9923 -> 30815 | R87: =11551+25888-9925 -> 27514 | S87: =28785+24661-18382 -> 35064 | T87: =36890+24233-18383 -> 42740 | U87: =41862+23541-18385 -> 47018 | V87: =32307+25813-18387 -> 39733 | W87: =32045+26035-18389 -> 39691 | X87: =43852+27048-28823 -> 42077 | Y87: =43889+33926-28826 -> 48989
A88: Diluted share oustanding | B88: 2869 | C88: 2875 | D88: 2874 | E88: 2871 | F88: 2868 | G88: 2879 | H88: 2891 | I88: 2890 | J88: 2882 | K88: 2877 | L88: 2859 | M88: 2799 | N88: 2742 | O88: 2713 | P88: 2687 | Q88: 2640 | R88: 2596 | S88: 2612 | T88: 2641 | U88: 2630 | V88: 2625 | W88: 2610 | X88: 2600 | Y88: 2599
A89: Increase YoY | F89: =F88/B88-1 -> -0.0003485535 | G89: =G88/C88-1 -> 0.0013913043 | H89: =H88/D88-1 -> 0.0059151009 | I89: =I88/E88-1 -> 0.0066179032 | J89: =J88/F88-1 -> 0.0048814505 | K89: =K88/G88-1 -> -0.00069468565 | L89: =L88/H88-1 -> -0.011068834 | M89: =M88/I88-1 -> -0.031487889 | ... Y89: =Y88/U88-1 -> -0.011787072
A90: Increase QoQ | C90: =C88/B88-1 -> 0.002091321 | D90: =D88/C88-1 -> -0.00034782609 | E90: =E88/D88-1 -> -0.0010438413 | F90: =F88/E88-1 -> -0.0010449321 | G90: =G88/F88-1 -> 0.0038354254 | H90: =H88/G88-1 -> 0.0041681139 | I90: =I88/H88-1 -> -0.00034590107 | J90: =J88/I88-1 -> -0.0027681661 | ... Y90: =Y88/X88-1 -> -0.00038461538
A91: Headcount | B91: 37773 | C91: 39651 | D91: 43030 | E91: 44942 | F91: 48268 | G91: 52534 | H91: 56653 | I91: 58604 | J91: 60654 | K91: 63404 | L91: 68177 | M91: 71970 | N91: 77805 | O91: 83553 | P91: 87314 | Q91: 86482 | R91: 77114 | S91: 71469 | T91: 66185 | U91: 67317 | V91: 69329 | W91: 70799 | X91: 72404 | Y91: 74067
A92: Increase QoQ | C92: =C91-B91 -> 1878 | D92: =D91-C91 -> 3379 | E92: =E91-D91 -> 1912 | F92: =F91-E91 -> 3326 | G92: =G91-F91 -> 4266 | H92: =H91-G91 -> 4119 | I92: =I91-H91 -> 1951 | J92: =J91-I91 -> 2050 | ... Y92: =Y91-X91 -> 1663
A93: SBC | B93: 1010 | C93: 1303 | D93: 1249 | E93: 1273 | F93: 1335 | G93: 1695 | H93: 1722 | I93: 1784 | J93: 1830 | K93: 2548 | L93: 2379 | M93: 2406 | N93: 2498 | O93: 3351 | P93: 3134 | Q93: 3008 | R93: 3051 | S93: 4060 | T93: 3492 | U93: 3424 | V93: 3562 | W93: 4616 | X93: 4250 | Y93: 4262
A94: LTM SBC $ per employee | F94: =SUM(C93:F93)*1000000/AVERAGE(C91:F91) -> 117345.4 | G94: =SUM(D93:G93)*1000000/AVERAGE(D91:G91) -> 117643.32 | H94: =SUM(E93:H93)*1000000/AVERAGE(E91:H91) -> 119072.91 | I94: =SUM(F93:I93)*1000000/AVERAGE(F91:I91) -> 121003.99 | J94: =SUM(G93:J93)*1000000/AVERAGE(G91:J91) -> 123110.6 | K94: =SUM(H93:K93)*1000000/AVERAGE(H91:K91) -> 131776.11 | L94: =SUM(I93:L93)*1000000/AVERAGE(I91:L91) -> 136198.92 | M94: =SUM(J93:M93)*1000000/AVERAGE(J91:M91) -> 138725.61 | ... Y94: =SUM(V93:Y93)*1000000/AVERAGE(V91:Y91) -> 232938.71
A96: As % of revenue
A97: Total Opex | F97: 0.66775667 | G97: 0.68090116 | H97: 0.62552399 | I97: 0.54492021 | J97: 0.56524397 | K97: 0.57468102 | L97: 0.6407101 | M97: 0.62623623 | N97: 0.69456787 | O97: 0.71001318 | P97: 0.79562676 | Q97: 0.80105705 | R97: 0.74770466 | S97: 0.70649083 | T97: 0.59737597 | U97: 0.59153349 | V97: 0.62095734 | W97: 0.61999949 | X97: 0.57254429 | Y97: =25020/48385 -> 0.51710241
A98: Capex, including finance leases | F98: 0.20623555 | G98: 0.18001819 | H98: 0.18062413 | I98: 0.17163009 | J98: 0.16900386 | K98: 0.16284348 | L98: 0.15663564 | M98: 0.16459268 | N98: 0.19879604 | O98: 0.26878773 | P98: 0.34343653 | Q98: 0.28674025 | R98: 0.24740792 | S98: 0.19856871 | T98: 0.19806127 | U98: 0.19692852 | V98: 0.1841997 | W98: 0.21683602 | X98: 0.22671167 | Y98: =(14425+411)/48385 -> 0.30662395
